Workbook

Sheet UK_PL_EUR
A1: NetSuite Financial Report Export | B1: Helios Software Ltd — management accounts | E1: Exported 13-Jul-2026
G2: ACTUAL — posted / controller adjustments | AF2: BUDGET — approved operating plan
A3: Legal entity | B3: Department | C3: Cost centre | D3: Account code | E3: Account name | F3: Unit | G3: Jan-2024 | H3: Feb-2024 | I3: Mar-2024 | J3: Apr-2024 | K3: May-2024 | L3: Jun-2024 | M3: Jul-2024 | N3: Aug-2024 | O3: Sept-2024 | P3: Oct-2024 | Q3: Nov-2024 | R3: Dec-2024 | S3: Jan-2025 | T3: Feb-2025 | U3: Mar-2025 | V3: Apr-2025 | W3: May-2025 | X3: Jun-2025 | Y3: Jul-2025 | Z3: Aug-2025 | AA3: Sept-2025 | AB3: Oct-2025 | AC3: Nov-2025 | AD3: Dec-2025 | AF3: Jan-2024 | AG3: Feb-2024 | AH3: Mar-2024 | AI3: Apr-2024 | AJ3: May-2024 | AK3: Jun-2024 | AL3: Jul-2024 | AM3: Aug-2024 | AN3: Sept-2024 | AO3: Oct-2024 | AP3: Nov-2024 | AQ3: Dec-2024 | AR3: Jan-2025 | AS3: Feb-2025 | AT3: Mar-2025 | AU3: Apr-2025 | AV3: May-2025 | AW3: Jun-2025 | AX3: Jul-2025 | AY3: Aug-2025 | AZ3: Sept-2025 | BA3: Oct-2025 | BB3: Nov-2025 | BC3: Dec-2025
A4: Helios Software Ltd | B4: Commercial - EMEA | C4: CC-110 | D4: 4000 | E4: SaaS Recurring–EMEA | F4: EUR '000 | G4: 2352 | H4: 2429.5 | I4: 2534.3 | J4: 2565.7 | K4: 2675.9 | L4: 2762.9 | M4: 2715.4 | N4: 2720.4 | O4: 2896.3 | P4: 2990.8 | Q4: 3148 | R4: 3372.1 | S4: 3071.8 | T4: 3173 | U4: 3309.9 | V4: 3350.9 | W4: 3494.8 | X4: 3608.5 | Y4: 3546.4 | Z4: 3552.9 | AA4: 3782.7 | AB4: 3906.1 | AC4: 4111.4 | AD4: 4404.1 | AF4: 2240 | AG4: 2291.9811 | AH4: 2725.0538 | AI4: 2788.8043 | AJ4: 2454.9541 | AK4: 2511.7273 | AL4: 2858.3158 | AM4: 2894.0426 | AN4: 2706.8224 | AO4: 2769.2593 | AP4: 3459.3407 | AQ4: 3746.7778 | AR4: 2925.5238 | AS4: 2993.3962 | AT4: 3559.0323 | AU4: 3642.2826 | AV4: 3206.2385 | AW4: 3280.4545 | AX4: 3733.0526 | AY4: 3779.6809 | AZ4: 3535.2336 | BA4: 3616.7593 | BB4: 4518.022 | BC4: 4893.4444
A5: Helios Software Ltd | B5: Commercial - EMEA | C5: CC-110 | D5: 4000 | E5: SaaS Recurring–EMEA / enterprise | F5: EUR '000 | G5: 509.6 | H5: 526.4 | I5: 549.1 | J5: 555.9 | K5: 579.8 | L5: 598.6 | M5: 588.3 | N5: 589.4 | O5: 627.5 | P5: 648 | Q5: 682.1 | R5: 730.6 | S5: 665.6 | T5: 687.5 | U5: 717.2 | V5: 726 | W5: 757.2 | X5: 781.8 | Y5: 768.4 | Z5: 769.8 | AA5: 819.6 | AB5: 846.3 | AC5: 890.8 | AD5: 954.2 | AF5: 480.75472 | AG5: 491.96262 | AH5: 596.84783 | AI5: 610.87912 | AJ5: 527.09091 | AK5: 570.09524 | AL5: 625.85106 | AM5: 633.76344 | AN5: 581.01852 | AO5: 594.49541 | AP5: 757.88889 | AQ5: 769.05263 | AR5: 627.92453 | AS5: 642.52336 | AT5: 779.56522 | AU5: 797.8022 | AV5: 688.36364 | AW5: 744.57143 | AX5: 817.44681 | AY5: 827.74194 | AZ5: 758.88889 | BA5: 776.42202 | BB5: 989.77778 | BC5: 1004.4211
A6: Helios Software Ltd | B6: Commercial - EMEA | C6: CC-110 | D6: 4100 | E6: Implementation & Onboarding | F6: EUR '000 | G6: 254.8 | H6: 261.3 | I6: 270.5 | J6: 271.9 | K6: 281.5 | L6: 288.5 | M6: 281.5 | N6: 279.9 | O6: 295.8 | P6: 303.2 | Q6: 316.8 | R6: 336.9 | S6: 304.6 | T6: 312.4 | U6: 323.5 | V6: 325.1 | W6: 336.5 | X6: 344.9 | Y6: 336.5 | Z6: 334.7 | AA6: 353.7 | AB6: 362.5 | AC6: 378.8 | AD6: 402.8 | AF6: 238.13084 | AG6: 241.94444 | AH6: 297.25275 | AI6: 302.11111 | AJ6: 268.09524 | AK6: 272.16981 | AL6: 302.68817 | AM6: 304.23913 | AN6: 271.37615 | AO6: 275.63636 | AP6: 333.47368 | AQ6: 358.40426 | AR6: 284.6729 | AS6: 289.25926 | AT6: 355.49451 | AU6: 361.22222 | AV6: 320.47619 | AW6: 325.37736 | AX6: 361.82796 | AY6: 363.80435 | AZ6: 324.49541 | BA6: 329.54545 | BB6: 398.73684 | BC6: 428.51064
A7: Helios Software Ltd | B7: Commercial - EMEA | C7: -- | D7: SUB | E7: Commercial EMEA ledger subtotal | F7: EUR '000 | G7: =SUM(G4:G6) -> 3116.4 | H7: =SUM(H4:H6) -> 3217.2 | I7: =SUM(I4:I6) -> 3353.9 | J7: =SUM(J4:J6) -> 3393.5 | K7: =SUM(K4:K6) -> 3537.2 | L7: =SUM(L4:L6) -> 3650 | M7: =SUM(M4:M6) -> 3585.2 | N7: =SUM(N4:N6) -> 3589.7 | ... AD7: =SUM(AD4:AD6) -> 5761.1 | AF7: =SUM(AF4:AF6) -> 2958.8856 | AG7: =SUM(AG4:AG6) -> 3025.8882 | AH7: =SUM(AH4:AH6) -> 3619.1543 | AI7: =SUM(AI4:AI6) -> 3701.7946 | AJ7: =SUM(AJ4:AJ6) -> 3250.1403 | AK7: =SUM(AK4:AK6) -> 3353.9923 | AL7: =SUM(AL4:AL6) -> 3786.855 | AM7: =SUM(AM4:AM6) -> 3832.0451 | ... BC7: =SUM(BC4:BC6) -> 6326.3761
A9: Helios Software Ltd | B9: Commercial - Americas | C9: CC-120 | D9: 4010 | E9: SaaS Recurring–Americas | F9: EUR '000 | G9: 1097.6 | H9: 1133.7 | I9: 1182.7 | J9: 1197.3 | K9: 1248.7 | L9: 1289.4 | M9: 1267.2 | N9: 1269.5 | O9: 1351.6 | P9: 1395.7 | Q9: 1469.1 | R9: 1573.6 | S9: 1433.5 | T9: 1480.7 | U9: 1544.6 | V9: 1563.8 | W9: 1630.9 | X9: 1684 | Y9: 1655 | Z9: 1658 | AA9: 1765.2 | AB9: 1822.8 | AC9: 1918.7 | AD9: 2055.3 | AF9: 997.81818 | AG9: 1079.7143 | AH9: 1258.1915 | AI9: 1287.4194 | AJ9: 1156.2037 | AK9: 1182.9358 | AL9: 1408 | AM9: 1336.3158 | AN9: 1275.0943 | AO9: 1304.3925 | AP9: 1596.8478 | AQ9: 1729.2308 | AR9: 1303.1818 | AS9: 1410.1905 | AT9: 1643.1915 | AU9: 1681.5054 | AV9: 1510.0926 | AW9: 1544.9541 | AX9: 1838.8889 | AY9: 1745.2632 | AZ9: 1665.283 | BA9: 1703.5514 | BB9: 2085.5435 | BC9: 2258.5714
A10: Helios Software Ltd | B10: Commercial - Americas | C10: CC-120 | D10: 4010 | E10: SaaS Recurring–Americas / enterprise | F10: EUR '000 | G10: 274.4 | H10: 283.4 | I10: 295.7 | J10: 299.3 | K10: 312.2 | L10: 322.3 | M10: 316.8 | N10: 317.4 | O10: 337.9 | P10: 348.9 | Q10: 367.3 | R10: 393.4 | S10: 358.4 | T10: 370.2 | U10: 386.2 | V10: 390.9 | W10: 407.7 | X10: 421 | Y10: 413.7 | Z10: 414.5 | AA10: 441.3 | AB10: 455.7 | AC10: 479.7 | AD10: 513.8 | AF10: 261.33333 | AG10: 267.35849 | AH10: 317.95699 | AI10: 325.32609 | AJ10: 286.42202 | AK10: 293 | AL10: 333.47368 | AM10: 337.65957 | AN10: 315.79439 | AO10: 323.05556 | AP10: 403.62637 | AQ10: 437.11111 | AR10: 341.33333 | AS10: 349.24528 | AT10: 415.26882 | AU10: 424.8913 | AV10: 374.0367 | AW10: 382.72727 | AX10: 435.47368 | AY10: 440.95745 | AZ10: 412.42991 | BA10: 421.94444 | BB10: 527.14286 | BC10: 570.88889
A11: Helios Software Ltd | B11: Commercial - Americas | C11: CC-120 | D11: 4100 | E11: Implementation & Onboarding / Americas | F11: EUR '000 | G11: 93.1 | H11: 95.5 | I11: 98.9 | J11: 99.3 | K11: 102.8 | L11: 105.4 | M11: 102.8 | N11: 102.3 | O11: 108.1 | P11: 110.8 | Q11: 115.8 | R11: 123.1 | S11: 111.3 | T11: 114.1 | U11: 118.2 | V11: 118.8 | W11: 123 | X11: 126 | Y11: 123 | Z11: 122.3 | AA11: 129.2 | AB11: 132.5 | AC11: 138.4 | AD11: 147.2 | AF11: 87.830189 | AG11: 89.252336 | AH11: 107.5 | AI11: 109.12088 | AJ11: 93.454545 | AK11: 100.38095 | AL11: 109.3617 | AM11: 110 | AN11: 100.09259 | AO11: 101.65138 | AP11: 128.66667 | AQ11: 129.57895 | AR11: 105 | AS11: 106.63551 | AT11: 128.47826 | AU11: 130.54945 | AV11: 111.81818 | AW11: 120 | AX11: 130.85106 | AY11: 131.50538 | AZ11: 119.62963 | BA11: 121.55963 | BB11: 153.77778 | BC11: 154.94737
A12: Helios Software Ltd | B12: Commercial - Americas | C12: -- | D12: SUB | E12: Commercial Americas ledger subtotal | F12: EUR '000 | G12: =SUM(G9:G11) -> 1465.1 | H12: =SUM(H9:H11) -> 1512.6 | I12: =SUM(I9:I11) -> 1577.3 | J12: =SUM(J9:J11) -> 1595.9 | K12: =SUM(K9:K11) -> 1663.7 | L12: =SUM(L9:L11) -> 1717.1 | M12: =SUM(M9:M11) -> 1686.8 | N12: =SUM(N9:N11) -> 1689.2 | ... AD12: =SUM(AD9:AD11) -> 2716.3 | AF12: =SUM(AF9:AF11) -> 1346.9817 | AG12: =SUM(AG9:AG11) -> 1436.3251 | AH12: =SUM(AH9:AH11) -> 1683.6485 | AI12: =SUM(AI9:AI11) -> 1721.8663 | AJ12: =SUM(AJ9:AJ11) -> 1536.0803 | AK12: =SUM(AK9:AK11) -> 1576.3167 | AL12: =SUM(AL9:AL11) -> 1850.8354 | AM12: =SUM(AM9:AM11) -> 1783.9754 | ... BC12: =SUM(BC9:BC11) -> 2984.4077
A14: Helios Software Ltd | B14: Commercial - APAC | C14: CC-130 | D14: 4020 | E14: SaaS Recurring–APAC | F14: EUR '000 | G14: 421.4 | H14: 435.3 | I14: 454.1 | J14: 459.7 | K14: 479.4 | L14: 495 | M14: 486.5 | N14: 487.4 | O14: 518.9 | P14: 535.8 | Q14: 564 | R14: 604.2 | S14: 550.4 | T14: 568.5 | U14: 593 | V14: 600.4 | W14: 626.2 | X14: 646.5 | Y14: 635.4 | Z14: 636.6 | AA14: 677.7 | AB14: 699.8 | AC14: 736.6 | AD14: 789.1 | AF14: 386.6055 | AG14: 395.72727 | AH14: 478 | AI14: 489.04255 | AJ14: 448.03738 | AK14: 458.33333 | AL14: 534.61538 | AM14: 541.55556 | AN14: 494.19048 | AO14: 505.4717 | AP14: 606.45161 | AQ14: 656.73913 | AR14: 504.95413 | AS14: 516.81818 | AT14: 624.21053 | AU14: 638.7234 | AV14: 585.23364 | AW14: 598.61111 | AX14: 698.24176 | AY14: 707.33333 | AZ14: 645.42857 | BA14: 660.18868 | BB14: 792.04301 | BC14: 857.71739
A15: Helios Software Ltd | B15: Commercial - APAC | C15: CC-130 | D15: 4100 | E15: Implementation & Onboarding / APAC | F15: EUR '000 | G15: 44.1 | H15: 45.2 | I15: 46.8 | J15: 47.1 | K15: 48.7 | L15: 49.9 | M15: 48.7 | N15: 48.4 | O15: 51.2 | P15: 52.5 | Q15: 54.8 | R15: 58.3 | S15: 52.7 | T15: 54.1 | U15: 56 | V15: 56.3 | W15: 58.2 | X15: 59.7 | Y15: 58.2 | Z15: 57.9 | AA15: 61.2 | AB15: 62.7 | AC15: 65.6 | AD15: 69.7 | AF15: 40.090909 | AG15: 43.047619 | AH15: 49.787234 | AI15: 50.645161 | AJ15: 45.092593 | AK15: 45.779817 | AL15: 54.111111 | AM15: 50.947368 | AN15: 48.301887 | AO15: 49.065421 | AP15: 59.565217 | AQ15: 64.065934 | AR15: 47.909091 | AS15: 51.52381 | AT15: 59.574468 | AU15: 60.537634 | AV15: 53.888889 | AW15: 54.770642 | AX15: 64.666667 | AY15: 60.947368 | AZ15: 57.735849 | BA15: 58.598131 | BB15: 71.304348 | BC15: 76.593407
A16: Helios Software Ltd | B16: Commercial - APAC | C16: -- | D16: SUB | E16: Commercial APAC ledger subtotal | F16: EUR '000 | G16: =SUM(G14:G15) -> 465.5 | H16: =SUM(H14:H15) -> 480.5 | I16: =SUM(I14:I15) -> 500.9 | J16: =SUM(J14:J15) -> 506.8 | K16: =SUM(K14:K15) -> 528.1 | L16: =SUM(L14:L15) -> 544.9 | M16: =SUM(M14:M15) -> 535.2 | N16: =SUM(N14:N15) -> 535.8 | ... AD16: =SUM(AD14:AD15) -> 858.8 | AF16: =SUM(AF14:AF15) -> 426.69641 | AG16: =SUM(AG14:AG15) -> 438.77489 | AH16: =SUM(AH14:AH15) -> 527.78723 | AI16: =SUM(AI14:AI15) -> 539.68771 | AJ16: =SUM(AJ14:AJ15) -> 493.12998 | AK16: =SUM(AK14:AK15) -> 504.11315 | AL16: =SUM(AL14:AL15) -> 588.7265 | AM16: =SUM(AM14:AM15) -> 592.50292 | ... BC16: =SUM(BC14:BC15) -> 934.3108
A18: Helios Software Ltd | B18: Customer Operations | C18: CC-210 | D18: 4110 | E18: Managed Services | F18: EUR '000 | G18: 220.5 | H18: 226.1 | I18: 234.1 | J18: 235.3 | K18: 243.6 | L18: 249.7 | M18: 243.6 | N18: 242.2 | O18: 256 | P18: 262.4 | Q18: 274.2 | R18: 291.5 | S18: 263.6 | T18: 270.3 | U18: 279.9 | V18: 281.3 | W18: 291.2 | X18: 298.5 | Y18: 291.2 | Z18: 289.6 | AA18: 306.1 | AB18: 313.7 | AC18: 327.8 | AD18: 348.6 | AF18: 206.07477 | AG18: 209.35185 | AH18: 257.25275 | AI18: 261.44444 | AJ18: 232 | AK18: 235.56604 | AL18: 261.93548 | AM18: 263.26087 | AN18: 234.86239 | AO18: 238.54545 | AP18: 288.63158 | AQ18: 310.10638 | AR18: 246.35514 | AS18: 250.27778 | AT18: 307.58242 | AU18: 312.55556 | AV18: 277.33333 | AW18: 281.60377 | AX18: 313.11828 | AY18: 314.78261 | AZ18: 280.82569 | BA18: 285.18182 | BB18: 345.05263 | BC18: 370.85106
A19: Helios Software Ltd | B19: Customer Operations | C19: CC-210 | D19: 4200 | E19: Training & Certification | F19: EUR '000 | G19: 60.8 | H19: 62.3 | I19: 64.5 | J19: 64.8 | K19: 67.1 | L19: 68.8 | M19: 67.1 | N19: 66.7 | O19: 70.5 | P19: 72.3 | Q19: 75.6 | R19: 80.3 | S19: 72.6 | T19: 74.5 | U19: 77.1 | V19: 77.5 | W19: 80.3 | X19: 82.3 | Y19: 80.2 | Z19: 79.8 | AA19: 84.3 | AB19: 86.5 | AC19: 90.3 | AD19: 96.1 | AF19: 56.296296 | AG19: 57.155963 | AH19: 71.666667 | AI19: 68.210526 | AJ19: 63.301887 | AK19: 64.299065 | AL19: 72.934783 | AM19: 73.296703 | AN19: 64.090909 | AO19: 68.857143 | AP19: 80.425532 | AQ19: 86.344086 | AR19: 67.222222 | AS19: 68.348624 | AT19: 85.666667 | AU19: 81.578947 | AV19: 75.754717 | AW19: 76.915888 | AX19: 87.173913 | AY19: 87.692308 | AZ19: 76.636364 | BA19: 82.380952 | BB19: 96.06383 | BC19: 103.33333
A20: Helios Software Ltd | B20: Customer Operations | C20: CC-210 | D20: 5200 | E20: Support salaries | F20: EUR '000 | G20: -360 | H20: -366.5 | I20: -373.1 | J20: -379.8 | K20: -386.6 | L20: -393.6 | M20: -400.7 | N20: -407.9 | O20: -415.2 | P20: -422.7 | Q20: -430.3 | R20: -438.1 | S20: -445.9 | T20: -454 | U20: -462.1 | V20: -470.5 | W20: -478.9 | X20: -487.5 | Y20: -496.3 | Z20: -505.3 | AA20: -514.3 | AB20: -523.6 | AC20: -533 | AD20: -542.6 | AF20: -330.27523 | AG20: -333.18182 | AH20: -392.73684 | AI20: -404.04255 | AJ20: -361.30841 | AK20: -364.44444 | AL20: -440.32967 | AM20: -453.22222 | AN20: -395.42857 | AO20: -398.77358 | AP20: -462.68817 | AQ20: -476.19565 | AR20: -409.08257 | AS20: -412.72727 | AT20: -486.42105 | AU20: -500.53191 | AV20: -447.57009 | AW20: -451.38889 | AX20: -545.38462 | AY20: -561.44444 | AZ20: -489.80952 | BA20: -493.96226 | BB20: -573.11828 | BC20: -589.78261
A21: Helios Software Ltd | B21: Customer Operations | C21: CC-210 | D21: 5210 | E21: Support contractors | F21: EUR '000 | G21: -82 | H21: -83 | I21: -84 | J21: -85 | K21: -86 | L21: -87 | M21: -88.1 | N21: -89.1 | O21: -90.2 | P21: -91.3 | Q21: -92.4 | R21: -93.5 | S21: -94.6 | T21: -95.8 | U21: -96.9 | V21: -98.1 | W21: -99.2 | X21: -100.4 | Y21: -101.6 | Z21: -102.9 | AA21: -104.1 | AB21: -105.3 | AC21: -106.6 | AD21: -107.9 | AF21: -74.545455 | AG21: -79.047619 | AH21: -89.361702 | AI21: -91.397849 | AJ21: -79.62963 | AK21: -79.816514 | AL21: -97.888889 | AM21: -93.789474 | AN21: -85.09434 | AO21: -85.327103 | AP21: -100.43478 | AQ21: -102.74725 | AR21: -86 | AS21: -91.238095 | AT21: -103.08511 | AU21: -105.48387 | AV21: -91.851852 | AW21: -92.110092 | AX21: -112.88889 | AY21: -108.31579 | AZ21: -98.207547 | BA21: -98.411215 | BB21: -115.86957 | BC21: -118.57143
A22: Helios Software Ltd | B22: Customer Operations | C22: CC-210 | D22: 5220 | E22: Support tooling & telephony | F22: EUR '000 | G22: -36 | H22: -36.4 | I22: -36.9 | J22: -37.3 | K22: -37.8 | L22: -38.2 | M22: -38.7 | N22: -39.1 | O22: -39.6 | P22: -40.1 | Q22: -40.6 | R22: -41 | S22: -41.5 | T22: -42 | U22: -42.5 | V22: -43.1 | W22: -43.6 | X22: -44.1 | Y22: -44.6 | Z22: -45.2 | AA22: -45.7 | AB22: -46.2 | AC22: -46.8 | AD22: -47.4 | AF22: -34.285714 | AG22: -34.339623 | AH22: -39.677419 | AI22: -40.543478 | AJ22: -34.678899 | AK22: -34.727273 | AL22: -40.736842 | AM22: -41.595745 | AN22: -37.009346 | AO22: -37.12963 | AP22: -44.615385 | AQ22: -45.555556 | AR22: -39.52381 | AS22: -39.622642 | AT22: -45.698925 | AU22: -46.847826 | AV22: -40 | AW22: -40.090909 | AX22: -46.947368 | AY22: -48.085106 | AZ22: -42.71028 | BA22: -42.777778 | BB22: -51.428571 | BC22: -52.666667
A23: Helios Software Ltd | B23: Customer Operations | C23: -- | D23: SUB | E23: Customer Operations ledger subtotal | F23: EUR '000 | G23: =SUM(G18:G22) -> -196.7 | H23: =SUM(H18:H22) -> -197.5 | I23: =SUM(I18:I22) -> -195.4 | J23: =SUM(J18:J22) -> -202 | K23: =SUM(K18:K22) -> -199.7 | L23: =SUM(L18:L22) -> -200.3 | M23: =SUM(M18:M22) -> -216.8 | N23: =SUM(N18:N22) -> -227.2 | ... AD23: =SUM(AD18:AD22) -> -253.2 | AF23: =SUM(AF18:AF22) -> -176.73534 | AG23: =SUM(AG18:AG22) -> -180.06124 | AH23: =SUM(AH18:AH22) -> -192.85655 | AI23: =SUM(AI18:AI22) -> -206.32891 | AJ23: =SUM(AJ18:AJ22) -> -180.31505 | AK23: =SUM(AK18:AK22) -> -179.12313 | AL23: =SUM(AL18:AL22) -> -244.08513 | AM23: =SUM(AM18:AM22) -> -252.04987 | ... BC23: =SUM(BC18:BC22) -> -286.83631
A25: Helios Software Ltd | B25: Alliances | C25: CC-140 | D25: 4300 | E25: Partner/Reseller | F25: EUR '000 | G25: 186.2 | H25: 190.9 | I25: 197.7 | J25: 198.7 | K25: 205.7 | L25: 210.8 | M25: 205.7 | N25: 204.5 | O25: 216.2 | P25: 221.6 | Q25: 231.5 | R25: 246.2 | S25: 222.6 | T25: 228.3 | U25: 236.4 | V25: 237.5 | W25: 245.9 | X25: 252.1 | Y25: 245.9 | Z25: 244.6 | AA25: 258.5 | AB25: 264.9 | AC25: 276.8 | AD25: 294.4 | AF25: 172.40741 | AG25: 175.13761 | AH25: 219.66667 | AI25: 209.15789 | AJ25: 194.0566 | AK25: 197.00935 | AL25: 223.58696 | AM25: 224.72527 | AN25: 196.54545 | AO25: 211.04762 | AP25: 246.2766 | AQ25: 264.73118 | AR25: 206.11111 | AS25: 209.44954 | AT25: 262.66667 | AU25: 250 | AV25: 231.98113 | AW25: 235.60748 | AX25: 267.28261 | AY25: 268.79121 | AZ25: 235 | BA25: 252.28571 | BB25: 294.46809 | BC25: 316.55914
A26: Helios Software Ltd | B26: Alliances | C26: CC-140 | D26: 4900 | E26: Other income | F26: EUR '000 | G26: 28 | H26: 28.1 | I26: 28.2 | J26: 28.3 | K26: 28.5 | L26: 28.6 | M26: 28.7 | N26: 28.8 | O26: 28.9 | P26: 29 | Q26: 29.1 | R26: 29.3 | S26: 29.4 | T26: 29.5 | U26: 29.6 | V26: 29.7 | W26: 29.8 | X26: 30 | Y26: 30.1 | Z26: 30.2 | AA26: 30.3 | AB26: 30.4 | AC26: 30.6 | AD26: 30.7 | AF26: 25.688073 | AG26: 25.545455 | AH26: 29.684211 | AI26: 30.106383 | AJ26: 26.635514 | AK26: 26.481481 | AL26: 31.538462 | AM26: 32 | AN26: 27.52381 | AO26: 27.358491 | AP26: 31.290323 | AQ26: 31.847826 | AR26: 26.972477 | AS26: 26.818182 | AT26: 31.157895 | AU26: 31.595745 | AV26: 27.850467 | AW26: 27.777778 | AX26: 33.076923 | AY26: 33.555556 | AZ26: 28.857143 | BA26: 28.679245 | BB26: 32.903226 | BC26: 33.369565
A27: Helios Software Ltd | B27: Alliances | C27: CC-140 | D27: 6010 | E27: Sales commissions / channel | F27: EUR '000 | G27: -48 | H27: -48.6 | I27: -49.2 | J27: -49.7 | K27: -50.3 | L27: -50.9 | M27: -51.6 | N27: -52.2 | O27: -52.8 | P27: -53.4 | Q27: -54.1 | R27: -54.7 | S27: -55.4 | T27: -56.1 | U27: -56.7 | V27: -57.4 | W27: -58.1 | X27: -58.8 | Y27: -59.5 | Z27: -60.2 | AA27: -60.9 | AB27: -61.7 | AC27: -62.4 | AD27: -63.2 | AF27: -43.636364 | AG27: -46.285714 | AH27: -52.340426 | AI27: -53.44086 | AJ27: -46.574074 | AK27: -46.697248 | AL27: -57.333333 | AM27: -54.947368 | AN27: -49.811321 | AO27: -49.906542 | AP27: -58.804348 | AQ27: -60.10989 | AR27: -50.363636 | AS27: -53.428571 | AT27: -60.319149 | AU27: -61.72043 | AV27: -53.796296 | AW27: -53.944954 | AX27: -66.111111 | AY27: -63.368421 | AZ27: -57.45283 | BA27: -57.663551 | BB27: -67.826087 | BC27: -69.450549
A28: Helios Software Ltd | B28: Alliances | C28: -- | D28: SUB | E28: Alliances ledger subtotal | F28: EUR '000 | G28: =SUM(G25:G27) -> 166.2 | H28: =SUM(H25:H27) -> 170.4 | I28: =SUM(I25:I27) -> 176.7 | J28: =SUM(J25:J27) -> 177.3 | K28: =SUM(K25:K27) -> 183.9 | L28: =SUM(L25:L27) -> 188.5 | M28: =SUM(M25:M27) -> 182.8 | N28: =SUM(N25:N27) -> 181.1 | ... AD28: =SUM(AD25:AD27) -> 261.9 | AF28: =SUM(AF25:AF27) -> 154.45912 | AG28: =SUM(AG25:AG27) -> 154.39735 | AH28: =SUM(AH25:AH27) -> 197.01045 | AI28: =SUM(AI25:AI27) -> 185.82342 | AJ28: =SUM(AJ25:AJ27) -> 174.11804 | AK28: =SUM(AK25:AK27) -> 176.79358 | AL28: =SUM(AL25:AL27) -> 197.79208 | AM28: =SUM(AM25:AM27) -> 201.77791 | ... BC28: =SUM(BC25:BC27) -> 280.47816
A30: Helios Software Ltd | B30: Cloud Operations | C30: CC-220 | D30: 5000 | E30: Cloud hosting–AWS | F30: EUR '000 | G30: -420 | H30: -428.8 | I30: -437.8 | J30: -447 | K30: -456.4 | L30: -466 | M30: -475.8 | N30: -485.8 | O30: -496 | P30: -506.4 | Q30: -517 | R30: -527.9 | S30: -539 | T30: -550.3 | U30: -561.8 | V30: -573.6 | W30: -585.7 | X30: -598 | Y30: -610.5 | Z30: -623.4 | AA30: -636.4 | AB30: -649.8 | AC30: -663.5 | AD30: -677.4 | AF30: -392.52336 | AG30: -397.03704 | AH30: -481.0989 | AI30: -496.66667 | AJ30: -434.66667 | AK30: -439.62264 | AL30: -511.6129 | AM30: -528.04348 | AN30: -455.04587 | AO30: -460.36364 | AP30: -544.21053 | AQ30: -561.59574 | AR30: -503.73832 | AS30: -509.53704 | AT30: -617.36264 | AU30: -637.33333 | AV30: -557.80952 | AW30: -564.15094 | AX30: -656.45161 | AY30: -677.6087 | AZ30: -583.85321 | BA30: -590.72727 | BB30: -698.42105 | BC30: -720.6383
A31: Helios Software Ltd | B31: Cloud Operations | C31: CC-220 | D31: 5010 | E31: Cloud hosting–Azure | F31: EUR '000 | G31: -138 | H31: -140.9 | I31: -143.9 | J31: -146.9 | K31: -150 | L31: -153.1 | M31: -156.3 | N31: -159.6 | O31: -163 | P31: -166.4 | Q31: -169.9 | R31: -173.4 | S31: -177.1 | T31: -180.8 | U31: -184.6 | V31: -188.5 | W31: -192.4 | X31: -196.5 | Y31: -200.6 | Z31: -204.8 | AA31: -209.1 | AB31: -213.5 | AC31: -218 | AD31: -222.6 | AF31: -127.77778 | AG31: -129.26606 | AH31: -159.88889 | AI31: -154.63158 | AJ31: -141.50943 | AK31: -143.08411 | AL31: -169.8913 | AM31: -175.38462 | AN31: -148.18182 | AO31: -158.47619 | AP31: -180.74468 | AQ31: -186.45161 | AR31: -163.98148 | AS31: -165.87156 | AT31: -205.11111 | AU31: -198.42105 | AV31: -181.50943 | AW31: -183.64486 | AX31: -218.04348 | AY31: -225.05495 | AZ31: -190.09091 | BA31: -203.33333 | BB31: -231.91489 | BC31: -239.35484
A32: Helios Software Ltd | B32: Cloud Operations | C32: CC-220 | D32: 5100 | E32: 3rd-party licences | F32: EUR '000 | G32: -172 | H32: -175.6 | I32: -179.3 | J32: -183.1 | K32: -186.9 | L32: -190.8 | M32: -194.8 | N32: -198.9 | O32: -203.1 | P32: -207.4 | Q32: -211.7 | R32: -216.2 | S32: -220.7 | T32: -225.4 | U32: -230.1 | V32: -234.9 | W32: -239.9 | X32: -244.9 | Y32: -250 | Z32: -255.3 | AA32: -260.6 | AB32: -266.1 | AC32: -271.7 | AD32: -277.4 | AF32: -157.79817 | AG32: -159.63636 | AH32: -188.73684 | AI32: -194.78723 | AJ32: -174.6729 | AK32: -176.66667 | AL32: -214.06593 | AM32: -221 | AN32: -193.42857 | AO32: -195.66038 | AP32: -227.63441 | AQ32: -235 | AR32: -202.47706 | AS32: -204.90909 | AT32: -242.21053 | AU32: -249.89362 | AV32: -224.20561 | AW32: -226.75926 | AX32: -274.72527 | AY32: -283.66667 | AZ32: -248.19048 | BA32: -251.03774 | BB32: -292.15054 | BC32: -301.52174
A33: Helios Software Ltd | B33: Cloud Operations | C33: CC-220 | D33: 5110 | E33: Observability & data transfer | F33: EUR '000 | G33: -74 | H33: -75.6 | I33: -77.1 | J33: -78.8 | K33: -80.4 | L33: -82.1 | M33: -83.8 | N33: -85.6 | O33: -87.4 | P33: -89.2 | Q33: -91.1 | R33: -93 | S33: -95 | T33: -97 | U33: -99 | V33: -101.1 | W33: -103.2 | X33: -105.4 | Y33: -107.6 | Z33: -109.8 | AA33: -112.1 | AB33: -114.5 | AC33: -116.9 | AD33: -119.4 | AF33: -67.272727 | AG33: -72 | AH33: -82.021277 | AI33: -84.731183 | AJ33: -74.444444 | AK33: -75.321101 | AL33: -93.111111 | AM33: -90.105263 | AN33: -82.45283 | AO33: -83.364486 | AP33: -99.021739 | AQ33: -102.1978 | AR33: -86.363636 | AS33: -92.380952 | AT33: -105.31915 | AU33: -108.70968 | AV33: -95.555556 | AW33: -96.697248 | AX33: -119.55556 | AY33: -115.57895 | AZ33: -105.75472 | BA33: -107.00935 | BB33: -127.06522 | BC33: -131.20879
A34: Helios Software Ltd | B34: Cloud Operations | C34: CC-220 | D34: 5120 | E34: Security scanning subscriptions | F34: EUR '000 | G34: -31 | H34: -31.7 | I34: -32.3 | J34: -33 | K34: -33.7 | L34: -34.4 | M34: -35.1 | N34: -35.9 | O34: -36.6 | P34: -37.4 | Q34: -38.2 | R34: -39 | S34: -39.8 | T34: -40.6 | U34: -41.5 | V34: -42.3 | W34: -43.2 | X34: -44.1 | Y34: -45.1 | Z34: -46 | AA34: -47 | AB34: -48 | AC34: -49 | AD34: -50 | AF34: -29.52381 | AG34: -29.90566 | AH34: -34.731183 | AI34: -35.869565 | AJ34: -30.917431 | AK34: -31.272727 | AL34: -36.947368 | AM34: -38.191489 | AN34: -34.205607 | AO34: -34.62963 | AP34: -41.978022 | AQ34: -43.333333 | AR34: -37.904762 | AS34: -38.301887 | AT34: -44.623656 | AU34: -45.978261 | AV34: -39.633028 | AW34: -40.090909 | AX34: -47.473684 | AY34: -48.93617 | AZ34: -43.925234 | BA34: -44.444444 | BB34: -53.846154 | BC34: -55.555556
A35: Helios Software Ltd | B35: Cloud Operations | C35: -- | D35: SUB | E35: Cloud Operations ledger subtotal | F35: EUR '000 | G35: =SUM(G30:G34) -> -835 | H35: =SUM(H30:H34) -> -852.6 | I35: =SUM(I30:I34) -> -870.4 | J35: =SUM(J30:J34) -> -888.8 | K35: =SUM(K30:K34) -> -907.4 | L35: =SUM(L30:L34) -> -926.4 | M35: =SUM(M30:M34) -> -945.8 | N35: =SUM(N30:N34) -> -965.8 | ... AD35: =SUM(AD30:AD34) -> -1346.8 | AF35: =SUM(AF30:AF34) -> -774.89584 | AG35: =SUM(AG30:AG34) -> -787.84512 | AH35: =SUM(AH30:AH34) -> -946.47709 | AI35: =SUM(AI30:AI34) -> -966.68623 | AJ35: =SUM(AJ30:AJ34) -> -856.21087 | AK35: =SUM(AK30:AK34) -> -865.96725 | AL35: =SUM(AL30:AL34) -> -1025.6286 | AM35: =SUM(AM30:AM34) -> -1052.7248 | ... BC35: =SUM(BC30:BC34) -> -1448.2792
A37: Helios Software Ltd | B37: Professional Services | C37: CC-230 | D37: 5300 | E37: PS delivery cost | F37: EUR '000 | G37: -218 | H37: -220.6 | I37: -223.3 | J37: -225.9 | K37: -228.7 | L37: -231.4 | M37: -234.2 | N37: -237 | O37: -239.8 | P37: -242.7 | Q37: -245.6 | R37: -248.6 | S37: -251.5 | T37: -254.6 | U37: -257.6 | V37: -260.7 | W37: -263.8 | X37: -267 | Y37: -270.2 | Z37: -273.5 | AA37: -276.7 | AB37: -280.1 | AC37: -283.4 | AD37: -286.8 | AF37: -201.85185 | AG37: -202.38532 | AH37: -248.11111 | AI37: -237.78947 | AJ37: -215.75472 | AK37: -216.26168 | AL37: -254.56522 | AM37: -260.43956 | AN37: -218 | AO37: -231.14286 | AP37: -261.2766 | AQ37: -267.31183 | AR37: -232.87037 | AS37: -233.57798 | AT37: -286.22222 | AU37: -274.42105 | AV37: -248.86792 | AW37: -249.53271 | AX37: -293.69565 | AY37: -300.54945 | AZ37: -251.54545 | BA37: -266.7619 | BB37: -301.48936 | BC37: -308.3871
A38: Helios Software Ltd | B38: Professional Services | C38: CC-230 | D38: 5310 | E38: PS delivery subcontractors | F38: EUR '000 | G38: -96 | H38: -97.2 | I38: -98.3 | J38: -99.5 | K38: -100.7 | L38: -101.9 | M38: -103.1 | N38: -104.4 | O38: -105.6 | P38: -106.9 | Q38: -108.2 | R38: -109.5 | S38: -110.8 | T38: -112.1 | U38: -113.4 | V38: -114.8 | W38: -116.2 | X38: -117.6 | Y38: -119 | Z38: -120.4 | AA38: -121.9 | AB38: -123.3 | AC38: -124.8 | AD38: -126.3 | AF38: -88.073394 | AG38: -88.363636 | AH38: -103.47368 | AI38: -105.85106 | AJ38: -94.11215 | AK38: -94.351852 | AL38: -113.2967 | AM38: -116 | AN38: -100.57143 | AO38: -100.84906 | AP38: -116.34409 | AQ38: -119.02174 | AR38: -101.65138 | AS38: -101.90909 | AT38: -119.36842 | AU38: -122.12766 | AV38: -108.59813 | AW38: -108.88889 | AX38: -130.76923 | AY38: -133.77778 | AZ38: -116.09524 | BA38: -116.32075 | BB38: -134.19355 | BC38: -137.28261
A39: Helios Software Ltd | B39: Professional Services | C39: CC-230 | D39: 5320 | E39: PS travel & project expenses | F39: EUR '000 | G39: -34 | H39: -34.4 | I39: -34.8 | J39: -35.2 | K39: -35.7 | L39: -36.1 | M39: -36.5 | N39: -37 | O39: -37.4 | P39: -37.9 | Q39: -38.3 | R39: -38.8 | S39: -39.2 | T39: -39.7 | U39: -40.2 | V39: -40.7 | W39: -41.1 | X39: -41.6 | Y39: -42.1 | Z39: -42.6 | AA39: -43.2 | AB39: -43.7 | AC39: -44.2 | AD39: -44.7 | AF39: -30.909091 | AG39: -32.761905 | AH39: -37.021277 | AI39: -37.849462 | AJ39: -33.055556 | AK39: -33.119266 | AL39: -40.555556 | AM39: -38.947368 | AN39: -35.283019 | AO39: -35.420561 | AP39: -41.630435 | AQ39: -42.637363 | AR39: -35.636364 | AS39: -37.809524 | AT39: -42.765957 | AU39: -43.763441 | AV39: -38.055556 | AW39: -38.165138 | AX39: -46.777778 | AY39: -44.842105 | AZ39: -40.754717 | BA39: -40.841121 | BB39: -48.043478 | BC39: -49.120879
A40: Helios Software Ltd | B40: Professional Services | C40: -- | D40: SUB | E40: Professional Services ledger subtotal | F40: EUR '000 | G40: =SUM(G37:G39) -> -348 | H40: =SUM(H37:H39) -> -352.2 | I40: =SUM(I37:I39) -> -356.4 | J40: =SUM(J37:J39) -> -360.6 | K40: =SUM(K37:K39) -> -365.1 | L40: =SUM(L37:L39) -> -369.4 | M40: =SUM(M37:M39) -> -373.8 | N40: =SUM(N37:N39) -> -378.4 | ... AD40: =SUM(AD37:AD39) -> -457.8 | AF40: =SUM(AF37:AF39) -> -320.83434 | AG40: =SUM(AG37:AG39) -> -323.51086 | AH40: =SUM(AH37:AH39) -> -388.60607 | AI40: =SUM(AI37:AI39) -> -381.49 | AJ40: =SUM(AJ37:AJ39) -> -342.92242 | AK40: =SUM(AK37:AK39) -> -343.7328 | AL40: =SUM(AL37:AL39) -> -408.41748 | AM40: =SUM(AM37:AM39) -> -415.38693 | ... BC40: =SUM(BC37:BC39) -> -494.79058
A42: Helios Software Ltd | B42: Field Sales - EMEA | C42: CC-310 | D42: 6000 | E42: Sales salaries / EMEA | F42: EUR '000 | G42: -445 | H42: -453 | I42: -461.2 | J42: -469.5 | K42: -477.9 | L42: -486.5 | M42: -495.3 | N42: -504.2 | O42: -513.3 | P42: -522.5 | Q42: -531.9 | R42: -541.5 | S42: -551.2 | T42: -561.2 | U42: -571.3 | V42: -581.5 | W42: -592 | X42: -602.7 | Y42: -613.5 | Z42: -624.6 | AA42: -635.8 | AB42: -647.2 | AC42: -658.9 | AD42: -670.7 | AF42: -415.88785 | AG42: -419.44444 | AH42: -506.81319 | AI42: -521.66667 | AJ42: -455.14286 | AK42: -458.96226 | AL42: -532.58065 | AM42: -548.04348 | AN42: -470.91743 | AO42: -475 | AP42: -559.89474 | AQ42: -576.06383 | AR42: -515.14019 | AS42: -519.62963 | AT42: -627.8022 | AU42: -646.11111 | AV42: -563.80952 | AW42: -568.58491 | AX42: -659.67742 | AY42: -678.91304 | AZ42: -583.30275 | BA42: -588.36364 | BB42: -693.57895 | BC42: -713.51064
A43: Helios Software Ltd | B43: Field Sales - EMEA | C43: CC-310 | D43: 6010 | E43: Sales commissions / EMEA | F43: EUR '000 | G43: -175 | H43: -177.1 | I43: -179.2 | J43: -181.4 | K43: -183.6 | L43: -185.8 | M43: -188 | N43: -190.2 | O43: -192.5 | P43: -194.8 | Q43: -197.2 | R43: -199.5 | S43: -201.9 | T43: -204.4 | U43: -206.8 | V43: -209.3 | W43: -211.8 | X43: -214.3 | Y43: -216.9 | Z43: -219.5 | AA43: -222.2 | AB43: -224.8 | AC43: -227.5 | AD43: -230.2 | AF43: -162.03704 | AG43: -162.47706 | AH43: -199.11111 | AI43: -190.94737 | AJ43: -173.20755 | AK43: -173.64486 | AL43: -204.34783 | AM43: -209.01099 | AN43: -175 | AO43: -185.52381 | AP43: -209.78723 | AQ43: -214.51613 | AR43: -186.94444 | AS43: -187.52294 | AT43: -229.77778 | AU43: -220.31579 | AV43: -199.81132 | AW43: -200.28037 | AX43: -235.76087 | AY43: -241.20879 | AZ43: -202 | BA43: -214.09524 | BB43: -242.02128 | BC43: -247.52688
A44: Helios Software Ltd | B44: Field Sales - EMEA | C44: CC-310 | D44: 6050 | E44: Sales travel & entertainment / EMEA | F44: EUR '000 | G44: -58 | H44: -58.7 | I44: -59.4 | J44: -60.1 | K44: -60.8 | L44: -61.6 | M44: -62.3 | N44: -63.1 | O44: -63.8 | P44: -64.6 | Q44: -65.3 | R44: -66.1 | S44: -66.9 | T44: -67.7 | U44: -68.5 | V44: -69.4 | W44: -70.2 | X44: -71 | Y44: -71.9 | Z44: -72.8 | AA44: -73.6 | AB44: -74.5 | AC44: -75.4 | AD44: -76.3 | AF44: -53.211009 | AG44: -53.363636 | AH44: -62.526316 | AI44: -63.93617 | AJ44: -56.82243 | AK44: -57.037037 | AL44: -68.461538 | AM44: -70.111111 | AN44: -60.761905 | AO44: -60.943396 | AP44: -70.215054 | AQ44: -71.847826 | AR44: -61.376147 | AS44: -61.545455 | AT44: -72.105263 | AU44: -73.829787 | AV44: -65.607477 | AW44: -65.740741 | AX44: -79.010989 | AY44: -80.888889 | AZ44: -70.095238 | BA44: -70.283019 | BB44: -81.075269 | BC44: -82.934783
A45: Helios Software Ltd | B45: Field Sales - EMEA | C45: -- | D45: SUB | E45: Field Sales EMEA ledger subtotal | F45: EUR '000 | G45: =SUM(G42:G44) -> -678 | H45: =SUM(H42:H44) -> -688.8 | I45: =SUM(I42:I44) -> -699.8 | J45: =SUM(J42:J44) -> -711 | K45: =SUM(K42:K44) -> -722.3 | L45: =SUM(L42:L44) -> -733.9 | M45: =SUM(M42:M44) -> -745.6 | N45: =SUM(N42:N44) -> -757.5 | ... AD45: =SUM(AD42:AD44) -> -977.2 | AF45: =SUM(AF42:AF44) -> -631.1359 | AG45: =SUM(AG42:AG44) -> -635.28515 | AH45: =SUM(AH42:AH44) -> -768.45061 | AI45: =SUM(AI42:AI44) -> -776.55021 | AJ45: =SUM(AJ42:AJ44) -> -685.17283 | AK45: =SUM(AK42:AK44) -> -689.64416 | AL45: =SUM(AL42:AL44) -> -805.39001 | AM45: =SUM(AM42:AM44) -> -827.16558 | ... BC45: =SUM(BC42:BC44) -> -1043.9723
A47: Helios Software Ltd | B47: Field Sales - Americas | C47: CC-320 | D47: 6000 | E47: Sales salaries / Americas | F47: EUR '000 | G47: -325 | H47: -330.8 | I47: -336.8 | J47: -342.9 | K47: -349 | L47: -355.3 | M47: -361.7 | N47: -368.2 | O47: -374.9 | P47: -381.6 | Q47: -388.5 | R47: -395.5 | S47: -402.6 | T47: -409.8 | U47: -417.2 | V47: -424.7 | W47: -432.4 | X47: -440.1 | Y47: -448.1 | Z47: -456.1 | AA47: -464.3 | AB47: -472.7 | AC47: -481.2 | AD47: -489.9 | AF47: -306.60377 | AG47: -309.15888 | AH47: -366.08696 | AI47: -376.81319 | AJ47: -317.27273 | AK47: -338.38095 | AL47: -384.78723 | AM47: -395.91398 | AN47: -347.12963 | AO47: -350.09174 | AP47: -431.66667 | AQ47: -416.31579 | AR47: -379.81132 | AS47: -382.99065 | AT47: -453.47826 | AU47: -466.7033 | AV47: -393.09091 | AW47: -419.14286 | AX47: -476.70213 | AY47: -490.43011 | AZ47: -429.90741 | BA47: -433.66972 | BB47: -534.66667 | BC47: -515.68421
A48: Helios Software Ltd | B48: Field Sales - Americas | C48: CC-320 | D48: 6010 | E48: Sales commissions / Americas | F48: EUR '000 | G48: -122 | H48: -123.5 | I48: -124.9 | J48: -126.4 | K48: -128 | L48: -129.5 | M48: -131.1 | N48: -132.6 | O48: -134.2 | P48: -135.8 | Q48: -137.5 | R48: -139.1 | S48: -140.8 | T48: -142.5 | U48: -144.2 | V48: -145.9 | W48: -147.7 | X48: -149.4 | Y48: -151.2 | Z48: -153 | AA48: -154.9 | AB48: -156.7 | AC48: -158.6 | AD48: -160.5 | AF48: -114.01869 | AG48: -114.35185 | AH48: -137.25275 | AI48: -140.44444 | AJ48: -121.90476 | AK48: -122.16981 | AL48: -140.96774 | AM48: -144.13043 | AN48: -123.11927 | AO48: -123.45455 | AP48: -144.73684 | AQ48: -147.97872 | AR48: -131.58879 | AS48: -131.94444 | AT48: -158.46154 | AU48: -162.11111 | AV48: -140.66667 | AW48: -140.9434 | AX48: -162.58065 | AY48: -166.30435 | AZ48: -142.11009 | BA48: -142.45455 | BB48: -166.94737 | BC48: -170.74468
A49: Helios Software Ltd | B49: Field Sales - Americas | C49: CC-320 | D49: 6050 | E49: Sales travel & entertainment / Americas | F49: EUR '000 | G49: -42 | H49: -42.5 | I49: -43 | J49: -43.5 | K49: -44.1 | L49: -44.6 | M49: -45.1 | N49: -45.7 | O49: -46.2 | P49: -46.8 | Q49: -47.3 | R49: -47.9 | S49: -48.5 | T49: -49 | U49: -49.6 | V49: -50.2 | W49: -50.8 | X49: -51.4 | Y49: -52.1 | Z49: -52.7 | AA49: -53.3 | AB49: -54 | AC49: -54.6 | AD49: -55.3 | AF49: -38.888889 | AG49: -38.990826 | AH49: -47.777778 | AI49: -45.789474 | AJ49: -41.603774 | AK49: -41.682243 | AL49: -49.021739 | AM49: -50.21978 | AN49: -42 | AO49: -44.571429 | AP49: -50.319149 | AQ49: -51.505376 | AR49: -44.907407 | AS49: -44.954128 | AT49: -55.111111 | AU49: -52.842105 | AV49: -47.924528 | AW49: -48.037383 | AX49: -56.630435 | AY49: -57.912088 | AZ49: -48.454545 | BA49: -51.428571 | BB49: -58.085106 | BC49: -59.462366
A50: Helios Software Ltd | B50: Field Sales - Americas | C50: -- | D50: SUB | E50: Field Sales Americas ledger subtotal | F50: EUR '000 | G50: =SUM(G47:G49) -> -489 | H50: =SUM(H47:H49) -> -496.8 | I50: =SUM(I47:I49) -> -504.7 | J50: =SUM(J47:J49) -> -512.8 | K50: =SUM(K47:K49) -> -521.1 | L50: =SUM(L47:L49) -> -529.4 | M50: =SUM(M47:M49) -> -537.9 | N50: =SUM(N47:N49) -> -546.5 | ... AD50: =SUM(AD47:AD49) -> -705.7 | AF50: =SUM(AF47:AF49) -> -459.51135 | AG50: =SUM(AG47:AG49) -> -462.50156 | AH50: =SUM(AH47:AH49) -> -551.11748 | AI50: =SUM(AI47:AI49) -> -563.0471 | AJ50: =SUM(AJ47:AJ49) -> -480.78126 | AK50: =SUM(AK47:AK49) -> -502.23301 | AL50: =SUM(AL47:AL49) -> -574.77672 | AM50: =SUM(AM47:AM49) -> -590.26419 | ... BC50: =SUM(BC47:BC49) -> -745.89126
A52: Helios Software Ltd | B52: Field Sales - APAC | C52: CC-330 | D52: 6000 | E52: Sales salaries / APAC | F52: EUR '000 | G52: -150 | H52: -152.7 | I52: -155.4 | J52: -158.2 | K52: -161.1 | L52: -164 | M52: -166.9 | N52: -170 | O52: -173 | P52: -176.1 | Q52: -179.3 | R52: -182.5 | S52: -185.8 | T52: -189.2 | U52: -192.6 | V52: -196 | W52: -199.6 | X52: -203.1 | Y52: -206.8 | Z52: -210.5 | AA52: -214.3 | AB52: -218.2 | AC52: -222.1 | AD52: -226.1 | AF52: -142.85714 | AG52: -144.0566 | AH52: -167.09677 | AI52: -171.95652 | AJ52: -147.79817 | AK52: -149.09091 | AL52: -175.68421 | AM52: -180.85106 | AN52: -161.68224 | AO52: -163.05556 | AP52: -197.03297 | AQ52: -202.77778 | AR52: -176.95238 | AS52: -178.49057 | AT52: -207.09677 | AU52: -213.04348 | AV52: -183.11927 | AW52: -184.63636 | AX52: -217.68421 | AY52: -223.93617 | AZ52: -200.28037 | BA52: -202.03704 | BB52: -244.06593 | BC52: -251.22222
A53: Helios Software Ltd | B53: Field Sales - APAC | C53: CC-330 | D53: 6010 | E53: Sales commissions / APAC | F53: EUR '000 | G53: -49 | H53: -49.6 | I53: -50.2 | J53: -50.8 | K53: -51.4 | L53: -52 | M53: -52.6 | N53: -53.3 | O53: -53.9 | P53: -54.6 | Q53: -55.2 | R53: -55.9 | S53: -56.5 | T53: -57.2 | U53: -57.9 | V53: -58.6 | W53: -59.3 | X53: -60 | Y53: -60.7 | Z53: -61.5 | AA53: -62.2 | AB53: -62.9 | AC53: -63.7 | AD53: -64.5 | AF53: -46.226415 | AG53: -46.35514 | AH53: -54.565217 | AI53: -55.824176 | AJ53: -46.727273 | AK53: -49.52381 | AL53: -55.957447 | AM53: -57.311828 | AN53: -49.907407 | AO53: -50.091743 | AP53: -61.333333 | AQ53: -58.842105 | AR53: -53.301887 | AS53: -53.457944 | AT53: -62.934783 | AU53: -64.395604 | AV53: -53.909091 | AW53: -57.142857 | AX53: -64.574468 | AY53: -66.129032 | AZ53: -57.592593 | BA53: -57.706422 | BB53: -70.777778 | BC53: -67.894737
A54: Helios Software Ltd | B54: Field Sales - APAC | C54: CC-330 | D54: 6050 | E54: Sales travel & entertainment / APAC | F54: EUR '000 | G54: -20 | H54: -20.2 | I54: -20.5 | J54: -20.7 | K54: -21 | L54: -21.2 | M54: -21.5 | N54: -21.7 | O54: -22 | P54: -22.3 | Q54: -22.5 | R54: -22.8 | S54: -23.1 | T54: -23.4 | U54: -23.6 | V54: -23.9 | W54: -24.2 | X54: -24.5 | Y54: -24.8 | Z54: -25.1 | AA54: -25.4 | AB54: -25.7 | AC54: -26 | AD54: -26.3 | AF54: -18.691589 | AG54: -18.703704 | AH54: -22.527473 | AI54: -23 | AJ54: -20 | AK54: -20 | AL54: -23.11828 | AM54: -23.586957 | AN54: -20.183486 | AO54: -20.272727 | AP54: -23.684211 | AQ54: -24.255319 | AR54: -21.588785 | AS54: -21.666667 | AT54: -25.934066 | AU54: -26.555556 | AV54: -23.047619 | AW54: -23.113208 | AX54: -26.666667 | AY54: -27.282609 | AZ54: -23.302752 | BA54: -23.363636 | BB54: -27.368421 | BC54: -27.978723
A55: Helios Software Ltd | B55: Field Sales - APAC | C55: -- | D55: SUB | E55: Field Sales APAC ledger subtotal | F55: EUR '000 | G55: =SUM(G52:G54) -> -219 | H55: =SUM(H52:H54) -> -222.5 | I55: =SUM(I52:I54) -> -226.1 | J55: =SUM(J52:J54) -> -229.7 | K55: =SUM(K52:K54) -> -233.5 | L55: =SUM(L52:L54) -> -237.2 | M55: =SUM(M52:M54) -> -241 | N55: =SUM(N52:N54) -> -245 | ... AD55: =SUM(AD52:AD54) -> -316.9 | AF55: =SUM(AF52:AF54) -> -207.77515 | AG55: =SUM(AG52:AG54) -> -209.11545 | AH55: =SUM(AH52:AH54) -> -244.18946 | AI55: =SUM(AI52:AI54) -> -250.7807 | AJ55: =SUM(AJ52:AJ54) -> -214.52544 | AK55: =SUM(AK52:AK54) -> -218.61472 | AL55: =SUM(AL52:AL54) -> -254.75994 | AM55: =SUM(AM52:AM54) -> -261.74985 | ... BC55: =SUM(BC52:BC54) -> -347.09568
A57: Helios Software Ltd | B57: Marketing | C57: CC-340 | D57: 6020 | E57: Marketing programs | F57: EUR '000 | G57: -240.1 | H57: -245.5 | I57: -253.4 | J57: -253.9 | K57: -262.1 | L57: -267.9 | M57: -260.5 | N57: -258.3 | O57: -272.2 | P57: -278.2 | Q57: -289.8 | R57: -307.3 | S57: -277.1 | T57: -283.2 | U57: -292.4 | V57: -293 | W57: -302.5 | X57: -309.1 | Y57: -300.6 | Z57: -298.1 | AA57: -314.1 | AB57: -321 | AC57: -334.4 | AD57: -354.6 | AF57: -218.27273 | AG57: -233.80952 | AH57: -269.57447 | AI57: -273.01075 | AJ57: -242.68519 | AK57: -245.77982 | AL57: -289.44444 | AM57: -271.89474 | AN57: -256.79245 | AO57: -260 | AP57: -315 | AQ57: -337.69231 | AR57: -251.90909 | AS57: -269.71429 | AT57: -311.06383 | AU57: -315.05376 | AV57: -280.09259 | AW57: -283.57798 | AX57: -334 | AY57: -313.78947 | AZ57: -296.32075 | BA57: -300 | BB57: -363.47826 | BC57: -389.67033
A58: Helios Software Ltd | B58: Marketing | C58: CC-340 | D58: 6030 | E58: Marketing salaries | F58: EUR '000 | G58: -205 | H58: -208.7 | I58: -212.4 | J58: -216.3 | K58: -220.2 | L58: -224.1 | M58: -228.2 | N58: -232.3 | O58: -236.4 | P58: -240.7 | Q58: -245 | R58: -249.4 | S58: -253.9 | T58: -258.5 | U58: -263.2 | V58: -267.9 | W58: -272.7 | X58: -277.6 | Y58: -282.6 | Z58: -287.7 | AA58: -292.9 | AB58: -298.2 | AC58: -303.5 | AD58: -309 | AF58: -195.2381 | AG58: -196.88679 | AH58: -228.3871 | AI58: -235.1087 | AJ58: -202.01835 | AK58: -203.72727 | AL58: -240.21053 | AM58: -247.12766 | AN58: -220.93458 | AO58: -222.87037 | AP58: -269.23077 | AQ58: -277.11111 | AR58: -241.80952 | AS58: -243.86792 | AT58: -283.01075 | AU58: -291.19565 | AV58: -250.18349 | AW58: -252.36364 | AX58: -297.47368 | AY58: -306.06383 | AZ58: -273.73832 | BA58: -276.11111 | BB58: -333.51648 | BC58: -343.33333
A59: Helios Software Ltd | B59: Marketing | C59: CC-340 | D59: 6040 | E59: Events, content & analyst relations | F59: EUR '000 | G59: -109.8 | H59: -112.2 | I59: -115.9 | J59: -116.1 | K59: -119.8 | L59: -122.4 | M59: -119.1 | N59: -118.1 | O59: -124.4 | P59: -127.2 | Q59: -132.5 | R59: -140.5 | S59: -126.7 | T59: -129.5 | U59: -133.7 | V59: -133.9 | W59: -138.3 | X59: -141.3 | Y59: -137.4 | Z59: -136.3 | AA59: -143.6 | AB59: -146.8 | AC59: -152.9 | AD59: -162.1 | AF59: -103.58491 | AG59: -104.85981 | AH59: -125.97826 | AI59: -127.58242 | AJ59: -108.90909 | AK59: -116.57143 | AL59: -126.70213 | AM59: -126.98925 | AN59: -115.18519 | AO59: -116.69725 | AP59: -147.22222 | AQ59: -147.89474 | AR59: -119.5283 | AS59: -121.02804 | AT59: -145.32609 | AU59: -147.14286 | AV59: -125.72727 | AW59: -134.57143 | AX59: -146.17021 | AY59: -146.55914 | AZ59: -132.96296 | BA59: -134.6789 | BB59: -169.88889 | BC59: -170.63158
A60: Helios Software Ltd | B60: Marketing | C60: CC-340 | D60: 6060 | E60: Digital demand generation | F60: EUR '000 | G60: -86.2 | H60: -88.2 | I60: -91 | J60: -91.2 | K60: -94.1 | L60: -96.2 | M60: -93.6 | N60: -92.8 | O60: -97.8 | P60: -99.9 | Q60: -104.1 | R60: -110.4 | S60: -99.5 | T60: -101.7 | U60: -105 | V60: -105.2 | W60: -108.6 | X60: -111 | Y60: -108 | Z60: -107.1 | AA60: -112.8 | AB60: -115.3 | AC60: -120.1 | AD60: -127.4 | AF60: -80.560748 | AG60: -81.666667 | AH60: -100 | AI60: -101.33333 | AJ60: -89.619048 | AK60: -90.754717 | AL60: -100.64516 | AM60: -100.86957 | AN60: -89.724771 | AO60: -90.818182 | AP60: -109.57895 | AQ60: -117.44681 | AR60: -92.990654 | AS60: -94.166667 | AT60: -115.38462 | AU60: -116.88889 | AV60: -103.42857 | AW60: -104.71698 | AX60: -116.12903 | AY60: -116.41304 | AZ60: -103.48624 | BA60: -104.81818 | BB60: -126.42105 | BC60: -135.53191
A61: Helios Software Ltd | B61: Marketing | C61: -- | D61: SUB | E61: Marketing ledger subtotal | F61: EUR '000 | G61: =SUM(G57:G60) -> -641.1 | H61: =SUM(H57:H60) -> -654.6 | I61: =SUM(I57:I60) -> -672.7 | J61: =SUM(J57:J60) -> -677.5 | K61: =SUM(K57:K60) -> -696.2 | L61: =SUM(L57:L60) -> -710.6 | M61: =SUM(M57:M60) -> -701.4 | N61: =SUM(N57:N60) -> -701.5 | ... AD61: =SUM(AD57:AD60) -> -953.1 | AF61: =SUM(AF57:AF60) -> -597.65648 | AG61: =SUM(AG57:AG60) -> -617.2228 | AH61: =SUM(AH57:AH60) -> -723.93983 | AI61: =SUM(AI57:AI60) -> -737.0352 | AJ61: =SUM(AJ57:AJ60) -> -643.23167 | AK61: =SUM(AK57:AK60) -> -656.83323 | AL61: =SUM(AL57:AL60) -> -757.00226 | AM61: =SUM(AM57:AM60) -> -746.88121 | ... BC61: =SUM(BC57:BC60) -> -1039.1672
A63: Helios Software Ltd | B63: Engineering | C63: CC-410 | D63: 6100 | E63: Engineering salaries | F63: EUR '000 | G63: -805 | H63: -819.5 | I63: -834.2 | J63: -849.3 | K63: -864.5 | L63: -880.1 | M63: -895.9 | N63: -912.1 | O63: -928.5 | P63: -945.2 | Q63: -962.2 | R63: -979.5 | S63: -997.2 | T63: -1015.1 | U63: -1033.4 | V63: -1052 | W63: -1070.9 | X63: -1090.2 | Y63: -1109.8 | Z63: -1129.8 | AA63: -1150.1 | AB63: -1170.8 | AC63: -1191.9 | AD63: -1213.4 | AF63: -731.81818 | AG63: -780.47619 | AH63: -887.44681 | AI63: -913.22581 | AJ63: -800.46296 | AK63: -807.43119 | AL63: -995.44444 | AM63: -960.10526 | AN63: -875.9434 | AO63: -883.36449 | AP63: -1045.8696 | AQ63: -1076.3736 | AR63: -906.54545 | AS63: -966.7619 | AT63: -1099.3617 | AU63: -1131.1828 | AV63: -991.57407 | AW63: -1000.1835 | AX63: -1233.1111 | AY63: -1189.2632 | AZ63: -1085 | BA63: -1094.2056 | BB63: -1295.5435 | BC63: -1333.4066
A64: Helios Software Ltd | B64: Engineering | C64: CC-410 | D64: 6120 | E64: Engineering contractors | F64: EUR '000 | G64: -142 | H64: -143.7 | I64: -145.4 | J64: -147.2 | K64: -148.9 | L64: -150.7 | M64: -152.5 | N64: -154.4 | O64: -156.2 | P64: -158.1 | Q64: -160 | R64: -161.9 | S64: -163.9 | T64: -165.8 | U64: -167.8 | V64: -169.8 | W64: -171.9 | X64: -173.9 | Y64: -176 | Z64: -178.1 | AA64: -180.3 | AB64: -182.4 | AC64: -184.6 | AD64: -186.8 | AF64: -135.2381 | AG64: -135.56604 | AH64: -156.34409 | AI64: -160 | AJ64: -136.6055 | AK64: -137 | AL64: -160.52632 | AM64: -164.25532 | AN64: -145.98131 | AO64: -146.38889 | AP64: -175.82418 | AQ64: -179.88889 | AR64: -156.09524 | AS64: -156.41509 | AT64: -180.43011 | AU64: -184.56522 | AV64: -157.70642 | AW64: -158.09091 | AX64: -185.26316 | AY64: -189.46809 | AZ64: -168.50467 | BA64: -168.88889 | BB64: -202.85714 | BC64: -207.55556
A65: Helios Software Ltd | B65: Engineering | C65: CC-410 | D65: 6130 | E65: Engineering software & tooling | F65: EUR '000 | G65: -92 | H65: -93.1 | I65: -94.2 | J65: -95.4 | K65: -96.5 | L65: -97.7 | M65: -98.8 | N65: -100 | O65: -101.2 | P65: -102.4 | Q65: -103.7 | R65: -104.9 | S65: -106.2 | T65: -107.4 | U65: -108.7 | V65: -110 | W65: -111.3 | X65: -112.7 | Y65: -114 | Z65: -115.4 | AA65: -116.8 | AB65: -118.2 | AC65: -119.6 | AD65: -121 | AF65: -86.792453 | AG65: -87.009346 | AH65: -102.3913 | AI65: -104.83516 | AJ65: -87.727273 | AK65: -93.047619 | AL65: -105.10638 | AM65: -107.52688 | AN65: -93.703704 | AO65: -93.944954 | AP65: -115.22222 | AQ65: -110.42105 | AR65: -100.18868 | AS65: -100.37383 | AT65: -118.15217 | AU65: -120.87912 | AV65: -101.18182 | AW65: -107.33333 | AX65: -121.2766 | AY65: -124.08602 | AZ65: -108.14815 | BA65: -108.44037 | BB65: -132.88889 | BC65: -127.36842
A66: Helios Software Ltd | B66: Engineering | C66: CC-410 | D66: 6140 | E66: Engineering recruitment & travel | F66: EUR '000 | G66: -40.2 | H66: -41.1 | I66: -42.4 | J66: -42.5 | K66: -43.9 | L66: -44.8 | M66: -43.6 | N66: -43.2 | O66: -45.6 | P66: -46.6 | Q66: -48.5 | R66: -51.4 | S66: -46.4 | T66: -47.4 | U66: -48.9 | V66: -49 | W66: -50.6 | X66: -51.7 | Y66: -50.3 | Z66: -49.9 | AA66: -52.6 | AB66: -53.7 | AC66: -56 | AD66: -59.3 | AF66: -37.570093 | AG66: -38.055556 | AH66: -46.593407 | AI66: -47.222222 | AJ66: -41.809524 | AK66: -42.264151 | AL66: -46.88172 | AM66: -46.956522 | AN66: -41.834862 | AO66: -42.363636 | AP66: -51.052632 | AQ66: -54.680851 | AR66: -43.364486 | AS66: -43.888889 | AT66: -53.736264 | AU66: -54.444444 | AV66: -48.190476 | AW66: -48.773585 | AX66: -54.086022 | AY66: -54.23913 | AZ66: -48.256881 | BA66: -48.818182 | BB66: -58.947368 | BC66: -63.085106
A67: Helios Software Ltd | B67: Engineering | C67: -- | D67: SUB | E67: Engineering ledger subtotal | F67: EUR '000 | G67: =SUM(G63:G66) -> -1079.2 | H67: =SUM(H63:H66) -> -1097.4 | I67: =SUM(I63:I66) -> -1116.2 | J67: =SUM(J63:J66) -> -1134.4 | K67: =SUM(K63:K66) -> -1153.8 | L67: =SUM(L63:L66) -> -1173.3 | M67: =SUM(M63:M66) -> -1190.8 | N67: =SUM(N63:N66) -> -1209.7 | ... AD67: =SUM(AD63:AD66) -> -1580.5 | AF67: =SUM(AF63:AF66) -> -991.41882 | AG67: =SUM(AG63:AG66) -> -1041.1071 | AH67: =SUM(AH63:AH66) -> -1192.7756 | AI67: =SUM(AI63:AI66) -> -1225.2832 | AJ67: =SUM(AJ63:AJ66) -> -1066.6053 | AK67: =SUM(AK63:AK66) -> -1079.743 | AL67: =SUM(AL63:AL66) -> -1307.9589 | AM67: =SUM(AM63:AM66) -> -1278.844 | ... BC67: =SUM(BC63:BC66) -> -1731.4157
A69: Helios Software Ltd | B69: Product | C69: CC-420 | D69: 6110 | E69: Product salaries | F69: EUR '000 | G69: -248 | H69: -252.5 | I69: -257 | J69: -261.6 | K69: -266.3 | L69: -271.1 | M69: -276 | N69: -281 | O69: -286 | P69: -291.2 | Q69: -296.4 | R69: -301.8 | S69: -307.2 | T69: -312.7 | U69: -318.4 | V69: -324.1 | W69: -329.9 | X69: -335.9 | Y69: -341.9 | Z69: -348.1 | AA69: -354.3 | AB69: -360.7 | AC69: -367.2 | AD69: -373.8 | AF69: -225.45455 | AG69: -240.47619 | AH69: -273.40426 | AI69: -281.29032 | AJ69: -246.57407 | AK69: -248.7156 | AL69: -306.66667 | AM69: -295.78947 | AN69: -269.81132 | AO69: -272.14953 | AP69: -322.17391 | AQ69: -331.64835 | AR69: -279.27273 | AS69: -297.80952 | AT69: -338.7234 | AU69: -348.49462 | AV69: -305.46296 | AW69: -308.16514 | AX69: -379.88889 | AY69: -366.42105 | AZ69: -334.24528 | BA69: -337.1028 | BB69: -399.13043 | BC69: -410.76923
A70: Helios Software Ltd | B70: Product | C70: CC-420 | D70: 6150 | E70: Product research & design | F70: EUR '000 | G70: -52.9 | H70: -54.1 | I70: -55.9 | J70: -56 | K70: -57.8 | L70: -59 | M70: -57.4 | N70: -56.9 | O70: -60 | P70: -61.3 | Q70: -63.9 | R70: -67.7 | S70: -61.1 | T70: -62.4 | U70: -64.5 | V70: -64.6 | W70: -66.7 | X70: -68.1 | Y70: -66.3 | Z70: -65.7 | AA70: -69.2 | AB70: -70.8 | AC70: -73.7 | AD70: -78.2 | AF70: -50.380952 | AG70: -51.037736 | AH70: -60.107527 | AI70: -60.869565 | AJ70: -53.027523 | AK70: -53.636364 | AL70: -60.421053 | AM70: -60.531915 | AN70: -56.074766 | AO70: -56.759259 | AP70: -70.21978 | AQ70: -75.222222 | AR70: -58.190476 | AS70: -58.867925 | AT70: -69.354839 | AU70: -70.217391 | AV70: -61.192661 | AW70: -61.909091 | AX70: -69.789474 | AY70: -69.893617 | AZ70: -64.672897 | BA70: -65.555556 | BB70: -80.989011 | BC70: -86.888889
A71: Helios Software Ltd | B71: Product | C71: CC-420 | D71: 6160 | E71: Product data subscriptions | F71: EUR '000 | G71: -18 | H71: -18.2 | I71: -18.4 | J71: -18.7 | K71: -18.9 | L71: -19.1 | M71: -19.3 | N71: -19.6 | O71: -19.8 | P71: -20 | Q71: -20.3 | R71: -20.5 | S71: -20.8 | T71: -21 | U71: -21.3 | V71: -21.5 | W71: -21.8 | X71: -22 | Y71: -22.3 | Z71: -22.6 | AA71: -22.8 | AB71: -23.1 | AC71: -23.4 | AD71: -23.7 | AF71: -16.981132 | AG71: -17.009346 | AH71: -20 | AI71: -20.549451 | AJ71: -17.181818 | AK71: -18.190476 | AL71: -20.531915 | AM71: -21.075269 | AN71: -18.333333 | AO71: -18.348624 | AP71: -22.555556 | AQ71: -21.578947 | AR71: -19.622642 | AS71: -19.626168 | AT71: -23.152174 | AU71: -23.626374 | AV71: -19.818182 | AW71: -20.952381 | AX71: -23.723404 | AY71: -24.301075 | AZ71: -21.111111 | BA71: -21.192661 | BB71: -26 | BC71: -24.947368
A72: Helios Software Ltd | B72: Product | C72: -- | D72: SUB | E72: Product ledger subtotal | F72: EUR '000 | G72: =SUM(G69:G71) -> -318.9 | H72: =SUM(H69:H71) -> -324.8 | I72: =SUM(I69:I71) -> -331.3 | J72: =SUM(J69:J71) -> -336.3 | K72: =SUM(K69:K71) -> -343 | L72: =SUM(L69:L71) -> -349.2 | M72: =SUM(M69:M71) -> -352.7 | N72: =SUM(N69:N71) -> -357.5 | ... AD72: =SUM(AD69:AD71) -> -475.7 | AF72: =SUM(AF69:AF71) -> -292.81663 | AG72: =SUM(AG69:AG71) -> -308.52327 | AH72: =SUM(AH69:AH71) -> -353.51178 | AI72: =SUM(AI69:AI71) -> -362.70934 | AJ72: =SUM(AJ69:AJ71) -> -316.78342 | AK72: =SUM(AK69:AK71) -> -320.54244 | AL72: =SUM(AL69:AL71) -> -387.61963 | AM72: =SUM(AM69:AM71) -> -377.39666 | ... BC72: =SUM(BC69:BC71) -> -522.60549
A74: Helios Software Ltd | B74: Corporate Services | C74: CC-500 | D74: 6200 | E74: Finance | F74: EUR '000 | G74: -210 | H74: -213.8 | I74: -217.6 | J74: -221.5 | K74: -225.5 | L74: -229.6 | M74: -233.7 | N74: -237.9 | O74: -242.2 | P74: -246.6 | Q74: -251 | R74: -255.5 | S74: -260.1 | T74: -264.8 | U74: -269.6 | V74: -274.4 | W74: -279.4 | X74: -284.4 | Y74: -289.5 | Z74: -294.7 | AA74: -300 | AB74: -305.4 | AC74: -310.9 | AD74: -316.5 | AF74: -192.66055 | AG74: -194.36364 | AH74: -229.05263 | AI74: -235.6383 | AJ74: -210.74766 | AK74: -212.59259 | AL74: -256.81319 | AM74: -264.33333 | AN74: -230.66667 | AO74: -232.64151 | AP74: -269.89247 | AQ74: -277.71739 | AR74: -238.62385 | AS74: -240.72727 | AT74: -283.78947 | AU74: -291.91489 | AV74: -261.1215 | AW74: -263.33333 | AX74: -318.13187 | AY74: -327.44444 | AZ74: -285.71429 | BA74: -288.11321 | BB74: -334.30108 | BC74: -344.02174
A75: Helios Software Ltd | B75: Corporate Services | C75: CC-500 | D75: 6210 | E75: People/HR | F75: EUR '000 | G75: -138 | H75: -140.5 | I75: -143 | J75: -145.6 | K75: -148.2 | L75: -150.9 | M75: -153.6 | N75: -156.4 | O75: -159.2 | P75: -162 | Q75: -165 | R75: -167.9 | S75: -170.9 | T75: -174 | U75: -177.2 | V75: -180.3 | W75: -183.6 | X75: -186.9 | Y75: -190.3 | Z75: -193.7 | AA75: -197.2 | AB75: -200.7 | AC75: -204.3 | AD75: -208 | AF75: -125.45455 | AG75: -133.80952 | AH75: -152.12766 | AI75: -156.55914 | AJ75: -137.22222 | AK75: -138.44037 | AL75: -170.66667 | AM75: -164.63158 | AN75: -150.18868 | AO75: -151.40187 | AP75: -179.34783 | AQ75: -184.50549 | AR75: -155.36364 | AS75: -165.71429 | AT75: -188.51064 | AU75: -193.87097 | AV75: -170 | AW75: -171.46789 | AX75: -211.44444 | AY75: -203.89474 | AZ75: -186.03774 | BA75: -187.57009 | BB75: -222.06522 | BC75: -228.57143
A76: Helios Software Ltd | B76: Corporate Services | C76: CC-500 | D76: 6220 | E76: IT & facilities | F76: EUR '000 | G76: -185 | H76: -187.2 | I76: -189.5 | J76: -191.7 | K76: -194 | L76: -196.4 | M76: -198.7 | N76: -201.1 | O76: -203.5 | P76: -206 | Q76: -208.4 | R76: -210.9 | S76: -213.5 | T76: -216 | U76: -218.6 | V76: -221.2 | W76: -223.9 | X76: -226.6 | Y76: -229.3 | Z76: -232.1 | AA76: -234.8 | AB76: -237.7 | AC76: -240.5 | AD76: -243.4 | AF76: -176.19048 | AG76: -176.60377 | AH76: -203.76344 | AI76: -208.36957 | AJ76: -177.98165 | AK76: -178.54545 | AL76: -209.15789 | AM76: -213.93617 | AN76: -190.18692 | AO76: -190.74074 | AP76: -229.01099 | AQ76: -234.33333 | AR76: -203.33333 | AS76: -203.77358 | AT76: -235.05376 | AU76: -240.43478 | AV76: -205.41284 | AW76: -206 | AX76: -241.36842 | AY76: -246.91489 | AZ76: -219.43925 | BA76: -220.09259 | BB76: -264.28571 | BC76: -270.44444
A77: Helios Software Ltd | B77: Corporate Services | C77: CC-500 | D77: 6230 | E77: Legal & compliance | F77: EUR '000 | G77: -113.7 | H77: -116.2 | I77: -120 | J77: -120.2 | K77: -124.1 | L77: -126.8 | M77: -123.4 | N77: -122.3 | O77: -128.9 | P77: -131.7 | Q77: -137.2 | R77: -145.5 | S77: -131.2 | T77: -134.1 | U77: -138.5 | V77: -138.7 | W77: -143.2 | X77: -146.3 | Y77: -142.3 | Z77: -141.1 | AA77: -148.7 | AB77: -152 | AC77: -158.4 | AD77: -167.9 | AF77: -107.26415 | AG77: -108.59813 | AH77: -130.43478 | AI77: -132.08791 | AJ77: -112.81818 | AK77: -120.7619 | AL77: -131.2766 | AM77: -131.50538 | AN77: -119.35185 | AO77: -120.82569 | AP77: -152.44444 | AQ77: -153.15789 | AR77: -123.77358 | AS77: -125.3271 | AT77: -150.54348 | AU77: -152.41758 | AV77: -130.18182 | AW77: -139.33333 | AX77: -151.38298 | AY77: -151.72043 | AZ77: -137.68519 | BA77: -139.44954 | BB77: -176 | BC77: -176.73684
A78: Helios Software Ltd | B78: Corporate Services | C78: CC-500 | D78: 6240 | E78: Executive | F78: EUR '000 | G78: -225 | H78: -229 | I78: -233.2 | J78: -237.4 | K78: -241.6 | L78: -246 | M78: -250.4 | N78: -254.9 | O78: -259.5 | P78: -264.2 | Q78: -268.9 | R78: -273.8 | S78: -278.7 | T78: -283.7 | U78: -288.8 | V78: -294 | W78: -299.3 | X78: -304.7 | Y78: -310.2 | Z78: -315.8 | AA78: -321.5 | AB78: -327.3 | AC78: -333.1 | AD78: -339.1 | AF78: -210.28037 | AG78: -212.03704 | AH78: -256.26374 | AI78: -263.77778 | AJ78: -230.09524 | AK78: -232.07547 | AL78: -269.24731 | AM78: -277.06522 | AN78: -238.07339 | AO78: -240.18182 | AP78: -283.05263 | AQ78: -291.2766 | AR78: -260.46729 | AS78: -262.68519 | AT78: -317.36264 | AU78: -326.66667 | AV78: -285.04762 | AW78: -287.45283 | AX78: -333.54839 | AY78: -343.26087 | AZ78: -294.95413 | BA78: -297.54545 | BB78: -350.63158 | BC78: -360.74468
A79: Helios Software Ltd | B79: Corporate Services | C79: CC-500 | D79: 6250 | E79: Audit, tax & insurance | F79: EUR '000 | G79: -66.6 | H79: -68.1 | I79: -70.3 | J79: -70.5 | K79: -72.7 | L79: -74.3 | M79: -72.3 | N79: -71.7 | O79: -75.6 | P79: -77.2 | Q79: -80.4 | R79: -85.3 | S79: -76.9 | T79: -78.6 | U79: -81.2 | V79: -81.3 | W79: -83.9 | X79: -85.8 | Y79: -83.4 | Z79: -82.7 | AA79: -87.2 | AB79: -89.1 | AC79: -92.8 | AD79: -98.4 | AF79: -61.666667 | AG79: -62.477064 | AH79: -78.111111 | AI79: -74.210526 | AJ79: -68.584906 | AK79: -69.439252 | AL79: -78.586957 | AM79: -78.791209 | AN79: -68.727273 | AO79: -73.52381 | AP79: -85.531915 | AQ79: -91.72043 | AR79: -71.203704 | AS79: -72.110092 | AT79: -90.222222 | AU79: -85.578947 | AV79: -79.150943 | AW79: -80.186916 | AX79: -90.652174 | AY79: -90.879121 | AZ79: -79.272727 | BA79: -84.857143 | BB79: -98.723404 | BC79: -105.80645
A80: Helios Software Ltd | B80: Corporate Services | C80: CC-500 | D80: 6260 | E80: Office rent & utilities | F80: EUR '000 | G80: -92 | H80: -92.4 | I80: -92.7 | J80: -93.1 | K80: -93.5 | L80: -93.9 | M80: -94.2 | N80: -94.6 | O80: -95 | P80: -95.4 | Q80: -95.7 | R80: -96.1 | S80: -96.5 | T80: -96.9 | U80: -97.3 | V80: -97.7 | W80: -98.1 | X80: -98.5 | Y80: -98.9 | Z80: -99.2 | AA80: -99.6 | AB80: -100 | AC80: -100.4 | AD80: -100.8 | AF80: -84.40367 | AG80: -84 | AH80: -97.578947 | AI80: -99.042553 | AJ80: -87.383178 | AK80: -86.944444 | AL80: -103.51648 | AM80: -105.11111 | AN80: -90.47619 | AO80: -90 | AP80: -102.90323 | AQ80: -104.45652 | AR80: -88.53211 | AS80: -88.090909 | AT80: -102.42105 | AU80: -103.93617 | AV80: -91.682243 | AW80: -91.203704 | AX80: -108.68132 | AY80: -110.22222 | AZ80: -94.857143 | BA80: -94.339623 | BB80: -107.95699 | BC80: -109.56522
A81: Helios Software Ltd | B81: Corporate Services | C81: -- | D81: SUB | E81: Corporate Services ledger subtotal | F81: EUR '000 | G81: =SUM(G74:G80) -> -1030.3 | H81: =SUM(H74:H80) -> -1047.2 | I81: =SUM(I74:I80) -> -1066.3 | J81: =SUM(J74:J80) -> -1080 | K81: =SUM(K74:K80) -> -1099.6 | L81: =SUM(L74:L80) -> -1117.9 | M81: =SUM(M74:M80) -> -1126.3 | N81: =SUM(N74:N80) -> -1138.9 | ... AD81: =SUM(AD74:AD80) -> -1474.1 | AF81: =SUM(AF74:AF80) -> -957.92043 | AG81: =SUM(AG74:AG80) -> -971.88917 | AH81: =SUM(AH74:AH80) -> -1147.3323 | AI81: =SUM(AI74:AI80) -> -1169.6858 | AJ81: =SUM(AJ74:AJ80) -> -1024.833 | AK81: =SUM(AK74:AK80) -> -1038.7995 | AL81: =SUM(AL74:AL80) -> -1219.2651 | AM81: =SUM(AM74:AM80) -> -1235.374 | ... BC81: =SUM(BC74:BC80) -> -1595.8908
A83: Helios Software Ltd | B83: Fixed Assets | C83: CC-900 | D83: 7000 | E83: Deprec–equipment | F83: EUR '000 | G83: -72 | H83: -72.7 | I83: -73.4 | J83: -74.2 | K83: -74.9 | L83: -75.7 | M83: -76.4 | N83: -77.2 | O83: -78 | P83: -78.7 | Q83: -79.5 | R83: -80.3 | S83: -81.1 | T83: -81.9 | U83: -82.8 | V83: -83.6 | W83: -84.4 | X83: -85.3 | Y83: -86.1 | Z83: -87 | AA83: -87.9 | AB83: -88.7 | AC83: -89.6 | AD83: -90.5 | AF83: -67.924528 | AG83: -67.943925 | AH83: -79.782609 | AI83: -81.538462 | AJ83: -68.090909 | AK83: -72.095238 | AL83: -81.276596 | AM83: -83.010753 | AN83: -72.222222 | AO83: -72.201835 | AP83: -88.333333 | AQ83: -84.526316 | AR83: -76.509434 | AS83: -76.542056 | AT83: -90 | AU83: -91.868132 | AV83: -76.727273 | AW83: -81.238095 | AX83: -91.595745 | AY83: -93.548387 | AZ83: -81.388889 | BA83: -81.376147 | BB83: -99.555556 | BC83: -95.263158
A84: Helios Software Ltd | B84: Fixed Assets | C84: CC-900 | D84: 7010 | E84: Deprec–leasehold | F84: EUR '000 | G84: -24 | H84: -24.2 | I84: -24.5 | J84: -24.7 | K84: -25 | L84: -25.2 | M84: -25.5 | N84: -25.7 | O84: -26 | P84: -26.2 | Q84: -26.5 | R84: -26.8 | S84: -27 | T84: -27.3 | U84: -27.6 | V84: -27.9 | W84: -28.1 | X84: -28.4 | Y84: -28.7 | Z84: -29 | AA84: -29.3 | AB84: -29.6 | AC84: -29.9 | AD84: -30.2 | AF84: -22.429907 | AG84: -22.407407 | AH84: -26.923077 | AI84: -27.444444 | AJ84: -23.809524 | AK84: -23.773585 | AL84: -27.419355 | AM84: -27.934783 | AN84: -23.853211 | AO84: -23.818182 | AP84: -27.894737 | AQ84: -28.510638 | AR84: -25.233645 | AS84: -25.277778 | AT84: -30.32967 | AU84: -31 | AV84: -26.761905 | AW84: -26.792453 | AX84: -30.860215 | AY84: -31.521739 | AZ84: -26.880734 | BA84: -26.909091 | BB84: -31.473684 | BC84: -32.12766
A85: Helios Software Ltd | B85: Fixed Assets | C85: CC-900 | D85: 7100 | E85: Amort–intangibles | F85: EUR '000 | G85: -38 | H85: -38.4 | I85: -38.8 | J85: -39.2 | K85: -39.5 | L85: -39.9 | M85: -40.3 | N85: -40.7 | O85: -41.1 | P85: -41.6 | Q85: -42 | R85: -42.4 | S85: -42.8 | T85: -43.2 | U85: -43.7 | V85: -44.1 | W85: -44.6 | X85: -45 | Y85: -45.5 | Z85: -45.9 | AA85: -46.4 | AB85: -46.8 | AC85: -47.3 | AD85: -47.8 | AF85: -35.185185 | AG85: -35.229358 | AH85: -43.111111 | AI85: -41.263158 | AJ85: -37.264151 | AK85: -37.28972 | AL85: -43.804348 | AM85: -44.725275 | AN85: -37.363636 | AO85: -39.619048 | AP85: -44.680851 | AQ85: -45.591398 | AR85: -39.62963 | AS85: -39.633028 | AT85: -48.555556 | AU85: -46.421053 | AV85: -42.075472 | AW85: -42.056075 | AX85: -49.456522 | AY85: -50.43956 | AZ85: -42.181818 | BA85: -44.571429 | BB85: -50.319149 | BC85: -51.397849
A86: Helios Software Ltd | B86: Fixed Assets | C86: CC-900 | D86: 7110 | E86: Amort–capitalised dev | F86: EUR '000 | G86: -96 | H86: -97 | I86: -97.9 | J86: -98.9 | K86: -99.9 | L86: -100.9 | M86: -101.9 | N86: -102.9 | O86: -104 | P86: -105 | Q86: -106 | R86: -107.1 | S86: -108.2 | T86: -109.3 | U86: -110.3 | V86: -111.5 | W86: -112.6 | X86: -113.7 | Y86: -114.8 | Z86: -116 | AA86: -117.1 | AB86: -118.3 | AC86: -119.5 | AD86: -120.7 | AF86: -88.073394 | AG86: -88.181818 | AH86: -103.05263 | AI86: -105.21277 | AJ86: -93.364486 | AK86: -93.425926 | AL86: -111.97802 | AM86: -114.33333 | AN86: -99.047619 | AO86: -99.056604 | AP86: -113.97849 | AQ86: -116.41304 | AR86: -99.266055 | AS86: -99.363636 | AT86: -116.10526 | AU86: -118.61702 | AV86: -105.23364 | AW86: -105.27778 | AX86: -126.15385 | AY86: -128.88889 | AZ86: -111.52381 | BA86: -111.60377 | BB86: -128.49462 | BC86: -131.19565
A87: Helios Software Ltd | B87: Fixed Assets | C87: -- | D87: SUB | E87: Fixed Assets ledger subtotal | F87: EUR '000 | G87: =SUM(G83:G86) -> -230 | H87: =SUM(H83:H86) -> -232.3 | I87: =SUM(I83:I86) -> -234.6 | J87: =SUM(J83:J86) -> -237 | K87: =SUM(K83:K86) -> -239.3 | L87: =SUM(L83:L86) -> -241.7 | M87: =SUM(M83:M86) -> -244.1 | N87: =SUM(N83:N86) -> -246.5 | ... AD87: =SUM(AD83:AD86) -> -289.2 | AF87: =SUM(AF83:AF86) -> -213.61301 | AG87: =SUM(AG83:AG86) -> -213.76251 | AH87: =SUM(AH83:AH86) -> -252.86943 | AI87: =SUM(AI83:AI86) -> -255.45883 | AJ87: =SUM(AJ83:AJ86) -> -222.52907 | AK87: =SUM(AK83:AK86) -> -226.58447 | AL87: =SUM(AL83:AL86) -> -264.47832 | AM87: =SUM(AM83:AM86) -> -270.00414 | ... BC87: =SUM(BC83:BC86) -> -309.98432
A89: Helios Software Ltd | B89: Treasury & Tax | C89: CC-910 | D89: 7500 | E89: Net interest–senior | F89: EUR '000 | G89: -248 | H89: -247 | I89: -246 | J89: -245 | K89: -244.1 | L89: -243.1 | M89: -242.1 | N89: -241.1 | O89: -240.2 | P89: -239.2 | Q89: -238.3 | R89: -237.3 | S89: -236.4 | T89: -235.4 | U89: -234.5 | V89: -233.5 | W89: -232.6 | X89: -231.7 | Y89: -230.7 | Z89: -229.8 | AA89: -228.9 | AB89: -228 | AC89: -227.1 | AD89: -226.2 | AF89: -233.96226 | AG89: -230.84112 | AH89: -267.3913 | AI89: -269.23077 | AJ89: -221.90909 | AK89: -231.52381 | AL89: -257.55319 | AM89: -259.24731 | AN89: -222.40741 | AO89: -219.44954 | AP89: -264.77778 | AQ89: -249.78947 | AR89: -223.01887 | AS89: -220 | AT89: -254.8913 | AU89: -256.59341 | AV89: -211.45455 | AW89: -220.66667 | AX89: -245.42553 | AY89: -247.09677 | AZ89: -211.94444 | BA89: -209.17431 | BB89: -252.33333 | BC89: -238.10526
A90: Helios Software Ltd | B90: Treasury & Tax | C90: CC-910 | D90: 7510 | E90: Net interest–shareholder loan | F90: EUR '000 | G90: -64 | H90: -64.8 | I90: -65.5 | J90: -66.3 | K90: -67.1 | L90: -67.9 | M90: -68.7 | N90: -69.6 | O90: -70.4 | P90: -71.3 | Q90: -72.1 | R90: -73 | S90: -73.8 | T90: -74.7 | U90: -75.6 | V90: -76.5 | W90: -77.5 | X90: -78.4 | Y90: -79.3 | Z90: -80.3 | AA90: -81.2 | AB90: -82.2 | AC90: -83.2 | AD90: -84.2 | AF90: -59.813084 | AG90: -60 | AH90: -71.978022 | AI90: -73.666667 | AJ90: -63.904762 | AK90: -64.056604 | AL90: -73.870968 | AM90: -75.652174 | AN90: -64.587156 | AO90: -64.818182 | AP90: -75.894737 | AQ90: -77.659574 | AR90: -68.971963 | AS90: -69.166667 | AT90: -83.076923 | AU90: -85 | AV90: -73.809524 | AW90: -73.962264 | AX90: -85.268817 | AY90: -87.282609 | AZ90: -74.495413 | BA90: -74.727273 | BB90: -87.578947 | BC90: -89.574468
A91: Helios Software Ltd | B91: Treasury & Tax | C91: CC-910 | D91: 8000 | E91: Corporation tax | F91: EUR '000 | G91: -22 | H91: -22.3 | I91: -22.5 | J91: -22.8 | K91: -23.1 | L91: -23.4 | M91: -23.6 | N91: -23.9 | O91: -24.2 | P91: -24.5 | Q91: -24.8 | R91: -25.1 | S91: -25.4 | T91: -25.7 | U91: -26 | V91: -26.3 | W91: -26.6 | X91: -26.9 | Y91: -27.3 | Z91: -27.6 | AA91: -27.9 | AB91: -28.3 | AC91: -28.6 | AD91: -28.9 | AF91: -20.37037 | AG91: -20.458716 | AH91: -25 | AI91: -24 | AJ91: -21.792453 | AK91: -21.869159 | AL91: -25.652174 | AM91: -26.263736 | AN91: -22 | AO91: -23.333333 | AP91: -26.382979 | AQ91: -26.989247 | AR91: -23.518519 | AS91: -23.577982 | AT91: -28.888889 | AU91: -27.684211 | AV91: -25.09434 | AW91: -25.140187 | AX91: -29.673913 | AY91: -30.32967 | AZ91: -25.363636 | BA91: -26.952381 | BB91: -30.425532 | BC91: -31.075269
A92: Helios Software Ltd | B92: Treasury & Tax | C92: CC-910 | D92: 8010 | E92: Deferred tax | F92: EUR '000 | G92: 8 | H92: 8.1 | I92: 8.2 | J92: 8.3 | K92: 8.4 | L92: 8.5 | M92: 8.6 | N92: 8.7 | O92: 8.8 | P92: 8.9 | Q92: 9 | R92: 9.1 | S92: 9.2 | T92: 9.3 | U92: 9.5 | V92: 9.6 | W92: 9.7 | X92: 9.8 | Y92: 9.9 | Z92: 10 | AA92: 10.2 | AB92: 10.3 | AC92: 10.4 | AD92: 10.5 | AF92: 7.3394495 | AG92: 7.3636364 | AH92: 8.6315789 | AI92: 8.8297872 | AJ92: 7.8504673 | AK92: 7.8703704 | AL92: 9.4505495 | AM92: 9.6666667 | AN92: 8.3809524 | AO92: 8.3962264 | AP92: 9.6774194 | AQ92: 9.8913043 | AR92: 8.440367 | AS92: 8.4545455 | AT92: 10 | AU92: 10.212766 | AV92: 9.0654206 | AW92: 9.0740741 | AX92: 10.879121 | AY92: 11.111111 | AZ92: 9.7142857 | BA92: 9.7169811 | BB92: 11.182796 | BC92: 11.413043
A93: Helios Software Ltd | B93: Treasury & Tax | C93: -- | D93: SUB | E93: Treasury & Tax ledger subtotal | F93: EUR '000 | G93: =SUM(G89:G92) -> -326 | H93: =SUM(H89:H92) -> -326 | I93: =SUM(I89:I92) -> -325.8 | J93: =SUM(J89:J92) -> -325.8 | K93: =SUM(K89:K92) -> -325.9 | L93: =SUM(L89:L92) -> -325.9 | M93: =SUM(M89:M92) -> -325.8 | N93: =SUM(N89:N92) -> -325.9 | ... AD93: =SUM(AD89:AD92) -> -328.8 | AF93: =SUM(AF89:AF92) -> -306.80627 | AG93: =SUM(AG89:AG92) -> -303.9362 | AH93: =SUM(AH89:AH92) -> -355.73775 | AI93: =SUM(AI89:AI92) -> -358.06765 | AJ93: =SUM(AJ89:AJ92) -> -299.75584 | AK93: =SUM(AK89:AK92) -> -309.5792 | AL93: =SUM(AL89:AL92) -> -347.62578 | AM93: =SUM(AM89:AM92) -> -351.49656 | ... BC93: =SUM(BC89:BC92) -> -347.34196
A95: Helios Software Ltd | B95: Controller review | C95: CC-999 | D95: CHK | E95: UK ledger movement incl. tax | F95: EUR '000 | G95: =G7+G12+G16+G23+G28+G35+G40+G45+G50+G55+G61+G67+G72+G81+G87+G93 -> -1178 | H95: =H7+H12+H16+H23+H28+H35+H40+H45+H50+H55+H61+H67+H72+H81+H87+H93 -> -1112 | I95: =I7+I12+I16+I23+I28+I35+I40+I45+I50+I55+I61+I67+I72+I81+I87+I93 -> -990.9 | J95: =J7+J12+J16+J23+J28+J35+J40+J45+J50+J55+J61+J67+J72+J81+J87+J93 -> -1022.4 | K95: =K7+K12+K16+K23+K28+K35+K40+K45+K50+K55+K61+K67+K72+K81+K87+K93 -> -894 | L95: =L7+L12+L16+L23+L28+L35+L40+L45+L50+L55+L61+L67+L72+L81+L87+L93 -> -814.7 | M95: =M7+M12+M16+M23+M28+M35+M40+M45+M50+M55+M61+M67+M72+M81+M87+M93 -> -1012 | N95: =N7+N12+N16+N23+N28+N35+N40+N45+N50+N55+N61+N67+N72+N81+N87+N93 -> -1104.6 | ... AD95: =AD7+AD12+AD16+AD23+AD28+AD35+AD40+AD45+AD50+AD55+AD61+AD67+AD72+AD81+AD87+AD93 -> 439.1 | AF95: =AF7+AF12+AF16+AF23+AF28+AF35+AF40+AF45+AF50+AF55+AF61+AF67+AF72+AF81+AF87+AF93 -> -1044.0968 | AG95: =AG7+AG12+AG16+AG23+AG28+AG35+AG40+AG45+AG50+AG55+AG61+AG67+AG72+AG81+AG87+AG93 -> -999.37489 | AH95: =AH7+AH12+AH16+AH23+AH28+AH35+AH40+AH45+AH50+AH55+AH61+AH67+AH72+AH81+AH87+AH93 -> -1090.2635 | AI95: =AI7+AI12+AI16+AI23+AI28+AI35+AI40+AI45+AI50+AI55+AI61+AI67+AI72+AI81+AI87+AI93 -> -1103.9511 | AJ95: =AJ7+AJ12+AJ16+AJ23+AJ28+AJ35+AJ40+AJ45+AJ50+AJ55+AJ61+AJ67+AJ72+AJ81+AJ87+AJ93 -> -880.19762 | AK95: =AK7+AK12+AK16+AK23+AK28+AK35+AK40+AK45+AK50+AK55+AK61+AK67+AK72+AK81+AK87+AK93 -> -820.18107 | AL95: =AL7+AL12+AL16+AL23+AL28+AL35+AL40+AL45+AL50+AL55+AL61+AL67+AL72+AL81+AL87+AL93 -> -1172.7989 | AM95: =AM7+AM12+AM16+AM23+AM28+AM35+AM40+AM45+AM50+AM55+AM61+AM67+AM72+AM81+AM87+AM93 -> -1249.0365 | ... BC95: =BC7+BC12+BC16+BC23+BC28+BC35+BC40+BC45+BC50+BC55+BC61+BC67+BC72+BC81+BC87+BC93 -> 612.30202

Sheet Group_BS_EUR
A1: NetSuite Balance Sheet Export | B1: Helios Software Group — consolidation ledger | E1: Reporting currency: EUR
G2: ACTUAL — month end closing balances | AF2: BUDGET — month end plan balances
A3: Legal entity | B3: Department | C3: Cost centre | D3: Account code | E3: Account name | F3: Unit | G3: Jan-2024 | H3: Feb-2024 | I3: Mar-2024 | J3: Apr-2024 | K3: May-2024 | L3: Jun-2024 | M3: Jul-2024 | N3: Aug-2024 | O3: Sept-2024 | P3: Oct-2024 | Q3: Nov-2024 | R3: Dec-2024 | S3: Jan-2025 | T3: Feb-2025 | U3: Mar-2025 | V3: Apr-2025 | W3: May-2025 | X3: Jun-2025 | Y3: Jul-2025 | Z3: Aug-2025 | AA3: Sept-2025 | AB3: Oct-2025 | AC3: Nov-2025 | AD3: Dec-2025 | AF3: Jan-2024 | AG3: Feb-2024 | AH3: Mar-2024 | AI3: Apr-2024 | AJ3: May-2024 | AK3: Jun-2024 | AL3: Jul-2024 | AM3: Aug-2024 | AN3: Sept-2024 | AO3: Oct-2024 | AP3: Nov-2024 | AQ3: Dec-2024 | AR3: Jan-2025 | AS3: Feb-2025 | AT3: Mar-2025 | AU3: Apr-2025 | AV3: May-2025 | AW3: Jun-2025 | AX3: Jul-2025 | AY3: Aug-2025 | AZ3: Sept-2025 | BA3: Oct-2025 | BB3: Nov-2025 | BC3: Dec-2025
A4: Helios Software Ltd | B4: Treasury | C4: CC-910 | D4: 1000 | E4: Cash | F4: EUR '000 | G4: 12400 | H4: 12833.7 | I4: 13202.8 | J4: 13458.6 | K4: 13580.1 | L4: 13579.2 | M4: 13497.6 | N4: 13397.1 | O4: 13343.8 | P4: 13392.4 | Q4: 13572.6 | R4: 13882 | S4: 14286.3 | T4: 14728.3 | U4: 15141.3 | V4: 15465.9 | W4: 15664.1 | X4: 15729.2 | Y4: 15686.7 | Z4: 15588.7 | AA4: 15500.8 | AB4: 15486.2 | AC4: 15590 | AD4: 15828.5 | AF4: 11780 | AG4: 13603.7 | AH4: 12278.6 | AI4: 14535.3 | AJ4: 12357.9 | AK4: 14937.1 | AL4: 12822.7 | AM4: 14200.9 | AN4: 12409.7 | AO4: 14463.7 | AP4: 12351.1 | AQ4: 15270.1 | AR4: 13572 | AS4: 15612 | AT4: 14081.4 | AU4: 16703.2 | AV4: 14254.4 | AW4: 17302.1 | AX4: 14902.3 | AY4: 16524 | AZ4: 14415.7 | BA4: 16725.1 | BB4: 14186.9 | BC4: 17411.4
A5: Helios Software Ltd | B5: Treasury | C5: CC-910 | D5: 1010 | E5: Restricted cash | F5: EUR '000 | G5: 920 | H5: 920 | I5: 920 | J5: 920 | K5: 920 | L5: 920 | M5: 920 | N5: 920 | O5: 920 | P5: 920 | Q5: 920 | R5: 920 | S5: 920 | T5: 920 | U5: 920 | V5: 920 | W5: 920 | X5: 920 | Y5: 920 | Z5: 920 | AA5: 920 | AB5: 920 | AC5: 920 | AD5: 920 | AF5: 864.8 | AG5: 984.4 | AH5: 846.4 | AI5: 1002.8 | AJ5: 828 | AK5: 966 | AL5: 864.8 | AM5: 984.4 | AN5: 846.4 | AO5: 1002.8 | AP5: 828 | AQ5: 966 | AR5: 864.8 | AS5: 984.4 | AT5: 846.4 | AU5: 1002.8 | AV5: 828 | AW5: 966 | AX5: 864.8 | AY5: 984.4 | AZ5: 846.4 | BA5: 1002.8 | BB5: 828 | BC5: 966
A6: Helios Software Ltd | B6: Treasury | C6: CC-910 | D6: 1020 | E6: Payment processor clearing | F6: EUR '000 | G6: 180 | H6: 183.1 | I6: 186.2 | J6: 189.3 | K6: 192.6 | L6: 195.8 | M6: 199.2 | N6: 202.5 | O6: 206 | P6: 209.5 | Q6: 213.1 | R6: 216.7 | S6: 220.4 | T6: 224.1 | U6: 227.9 | V6: 231.8 | W6: 235.7 | X6: 239.7 | Y6: 243.8 | Z6: 248 | AA6: 252.2 | AB6: 256.5 | AC6: 260.8 | AD6: 265.2 | AF6: 167.4 | AG6: 197.7 | AH6: 169.4 | AI6: 208.3 | AJ6: 182.9 | AK6: 207.6 | AL6: 185.2 | AM6: 218.7 | AN6: 187.4 | AO6: 230.4 | AP6: 202.4 | AQ6: 229.7 | AR6: 204.9 | AS6: 242 | AT6: 207.4 | AU6: 255 | AV6: 223.9 | AW6: 254.1 | AX6: 226.7 | AY6: 267.8 | AZ6: 229.5 | BA6: 282.1 | BB6: 247.8 | BC6: 281.2
A7: Helios Software Ltd | B7: Treasury | C7: -- | D7: SUB | E7: Treasury ledger subtotal | F7: EUR '000 | G7: =SUM(G4:G6) -> 13500 | H7: =SUM(H4:H6) -> 13936.8 | I7: =SUM(I4:I6) -> 14309 | J7: =SUM(J4:J6) -> 14567.9 | K7: =SUM(K4:K6) -> 14692.7 | L7: =SUM(L4:L6) -> 14695 | M7: =SUM(M4:M6) -> 14616.8 | N7: =SUM(N4:N6) -> 14519.6 | ... AD7: =SUM(AD4:AD6) -> 17013.7 | AF7: =SUM(AF4:AF6) -> 12812.2 | AG7: =SUM(AG4:AG6) -> 14785.8 | AH7: =SUM(AH4:AH6) -> 13294.4 | AI7: =SUM(AI4:AI6) -> 15746.4 | AJ7: =SUM(AJ4:AJ6) -> 13368.8 | AK7: =SUM(AK4:AK6) -> 16110.7 | AL7: =SUM(AL4:AL6) -> 13872.7 | AM7: =SUM(AM4:AM6) -> 15404 | ... BC7: =SUM(BC4:BC6) -> 18658.6
A9: Helios Software Ltd | B9: Customer Billing | C9: CC-215 | D9: 1100 | E9: Trade receivables | F9: EUR '000 | G9: 6900 | H9: 7044.9 | I9: 7192.8 | J9: 7343.9 | K9: 7498.1 | L9: 7655.6 | M9: 7816.3 | N9: 7980.5 | O9: 8148.1 | P9: 8319.2 | Q9: 8493.9 | R9: 8672.3 | S9: 8854.4 | T9: 9040.3 | U9: 9230.2 | V9: 9424 | W9: 9621.9 | X9: 9824 | Y9: 10030.3 | Z9: 10240.9 | AA9: 10456 | AB9: 10675.5 | AC9: 10899.7 | AD9: 11128.6 | AF9: 6210 | AG9: 7397.1 | AH9: 6761.3 | AI9: 7858 | AJ9: 6898.3 | AK9: 8344.6 | AL9: 7034.7 | AM9: 8379.5 | AN9: 7659.2 | AO9: 8901.5 | AP9: 7814.4 | AQ9: 9452.8 | AR9: 7968.9 | AS9: 9492.3 | AT9: 8676.4 | AU9: 10083.7 | AV9: 8852.2 | AW9: 10708.1 | AX9: 9027.2 | AY9: 10752.9 | AZ9: 9828.6 | BA9: 11422.8 | BB9: 10027.7 | BC9: 12130.2
A10: Helios Software Ltd | B10: Customer Billing | C10: CC-215 | D10: 1110 | E10: Accrued subscription income | F10: EUR '000 | G10: 1450 | H10: 1480.4 | I10: 1511.5 | J10: 1543.3 | K10: 1575.7 | L10: 1608.8 | M10: 1642.6 | N10: 1677.1 | O10: 1712.3 | P10: 1748.2 | Q10: 1784.9 | R10: 1822.4 | S10: 1860.7 | T10: 1899.8 | U10: 1939.7 | V10: 1980.4 | W10: 2022 | X10: 2064.5 | Y10: 2107.8 | Z10: 2152.1 | AA10: 2197.3 | AB10: 2243.4 | AC10: 2290.5 | AD10: 2338.6 | AF10: 1377.5 | AG10: 1569.3 | AH10: 1405.7 | AI10: 1666.7 | AJ10: 1433.9 | AK10: 1769.7 | AL10: 1560.4 | AM10: 1777.7 | AN10: 1592.4 | AO10: 1888.1 | AP10: 1624.3 | AQ10: 2004.7 | AR10: 1767.7 | AS10: 2013.8 | AT10: 1803.9 | AU10: 2138.8 | AV10: 1840 | AW10: 2270.9 | AX10: 2002.4 | AY10: 2281.2 | AZ10: 2043.5 | BA10: 2422.9 | BB10: 2084.4 | BC10: 2572.5
A11: Helios Software Ltd | B11: Customer Billing | C11: CC-215 | D11: 1120 | E11: Contract assets | F11: EUR '000 | G11: 780 | H11: 796.4 | I11: 813.1 | J11: 830.2 | K11: 847.6 | L11: 865.4 | M11: 883.6 | N11: 902.1 | O11: 921.1 | P11: 940.4 | Q11: 960.2 | R11: 980.3 | S11: 1000.9 | T11: 1021.9 | U11: 1043.4 | V11: 1065.3 | W11: 1087.7 | X11: 1110.5 | Y11: 1133.9 | Z11: 1157.7 | AA11: 1182 | AB11: 1206.8 | AC11: 1232.1 | AD11: 1258 | AF11: 733.2 | AG11: 852.1 | AH11: 748.1 | AI11: 904.9 | AJ11: 762.9 | AK11: 908.7 | AL11: 830.6 | AM11: 965.3 | AN11: 847.4 | AO11: 1025.1 | AP11: 864.2 | AQ11: 1029.4 | AR11: 940.9 | AS11: 1093.5 | AT11: 959.9 | AU11: 1161.2 | AV11: 978.9 | AW11: 1166.1 | AX11: 1065.8 | AY11: 1238.7 | AZ11: 1087.4 | BA11: 1315.4 | BB11: 1108.9 | BC11: 1320.9
A12: Helios Software Ltd | B12: Customer Billing | C12: CC-215 | D12: 1130 | E12: Allowance for doubtful accounts | F12: EUR '000 | G12: -210 | H12: -214.4 | I12: -218.9 | J12: -223.5 | K12: -228.2 | L12: -233 | M12: -237.9 | N12: -242.9 | O12: -248 | P12: -253.2 | Q12: -258.5 | R12: -263.9 | S12: -269.5 | T12: -275.1 | U12: -280.9 | V12: -286.8 | W12: -292.8 | X12: -299 | Y12: -305.3 | Z12: -311.7 | AA12: -318.2 | AB12: -324.9 | AC12: -331.7 | AD12: -338.7 | AF12: -195.3 | AG12: -231.6 | AH12: -199.2 | AI12: -245.9 | AJ12: -216.8 | AK12: -247 | AL12: -221.2 | AM12: -262.3 | AN12: -225.7 | AO12: -278.5 | AP12: -245.6 | AQ12: -279.8 | AR12: -250.6 | AS12: -297.2 | AT12: -255.6 | AU12: -315.5 | AV12: -278.2 | AW12: -316.9 | AX12: -283.9 | AY12: -336.6 | AZ12: -289.6 | BA12: -357.4 | BB12: -315.1 | BC12: -359
A13: Helios Software Ltd | B13: Customer Billing | C13: -- | D13: SUB | E13: Customer Billing ledger subtotal | F13: EUR '000 | G13: =SUM(G9:G12) -> 8920 | H13: =SUM(H9:H12) -> 9107.3 | I13: =SUM(I9:I12) -> 9298.5 | J13: =SUM(J9:J12) -> 9493.9 | K13: =SUM(K9:K12) -> 9693.2 | L13: =SUM(L9:L12) -> 9896.8 | M13: =SUM(M9:M12) -> 10104.6 | N13: =SUM(N9:N12) -> 10316.8 | ... AD13: =SUM(AD9:AD12) -> 14386.5 | AF13: =SUM(AF9:AF12) -> 8125.4 | AG13: =SUM(AG9:AG12) -> 9586.9 | AH13: =SUM(AH9:AH12) -> 8715.9 | AI13: =SUM(AI9:AI12) -> 10183.7 | AJ13: =SUM(AJ9:AJ12) -> 8878.3 | AK13: =SUM(AK9:AK12) -> 10776 | AL13: =SUM(AL9:AL12) -> 9204.5 | AM13: =SUM(AM9:AM12) -> 10860.2 | ... BC13: =SUM(BC9:BC12) -> 15664.6
A15: Helios Software Ltd | B15: Procurement | C15: CC-505 | D15: 1200 | E15: Prepayments | F15: EUR '000 | G15: 1150 | H15: 1169.6 | I15: 1189.4 | J15: 1209.7 | K15: 1230.2 | L15: 1251.1 | M15: 1272.4 | N15: 1294 | O15: 1316 | P15: 1338.4 | Q15: 1361.2 | R15: 1384.3 | S15: 1407.8 | T15: 1431.8 | U15: 1456.1 | V15: 1480.9 | W15: 1506 | X15: 1531.6 | Y15: 1557.7 | Z15: 1584.1 | AA15: 1611.1 | AB15: 1638.5 | AC15: 1666.3 | AD15: 1694.6 | AF15: 1035 | AG15: 1228 | AH15: 1118.1 | AI15: 1294.3 | AJ15: 1131.8 | AK15: 1363.7 | AL15: 1145.2 | AM15: 1358.7 | AN15: 1237.1 | AO15: 1432.1 | AP15: 1252.3 | AQ15: 1508.9 | AR15: 1267 | AS15: 1503.3 | AT15: 1368.7 | AU15: 1584.5 | AV15: 1385.5 | AW15: 1669.5 | AX15: 1401.9 | AY15: 1663.4 | AZ15: 1514.4 | BA15: 1753.2 | BB15: 1533 | BC15: 1847.2
A16: Helios Software Ltd | B16: Procurement | C16: CC-505 | D16: 1210 | E16: Supplier deposits | F16: EUR '000 | G16: 320 | H16: 325.4 | I16: 331 | J16: 336.6 | K16: 342.3 | L16: 348.1 | M16: 354.1 | N16: 360.1 | O16: 366.2 | P16: 372.4 | Q16: 378.8 | R16: 385.2 | S16: 391.7 | T16: 398.4 | U16: 405.2 | V16: 412.1 | W16: 419.1 | X16: 426.2 | Y16: 433.4 | Z16: 440.8 | AA16: 448.3 | AB16: 455.9 | AC16: 463.7 | AD16: 471.6 | AF16: 304 | AG16: 345 | AH16: 307.8 | AI16: 363.5 | AJ16: 311.5 | AK16: 383 | AL16: 336.4 | AM16: 381.7 | AN16: 340.6 | AO16: 402.2 | AP16: 344.7 | AQ16: 423.7 | AR16: 372.2 | AS16: 422.3 | AT16: 376.8 | AU16: 445 | AV16: 381.4 | AW16: 468.8 | AX16: 411.8 | AY16: 467.3 | AZ16: 416.9 | BA16: 492.4 | BB16: 421.9 | BC16: 518.7
A17: Helios Software Ltd | B17: Procurement | C17: CC-505 | D17: 1220 | E17: Inventory/WIP | F17: EUR '000 | G17: 460 | H17: 467.8 | I17: 475.8 | J17: 483.9 | K17: 492.1 | L17: 500.5 | M17: 509 | N17: 517.6 | O17: 526.4 | P17: 535.4 | Q17: 544.5 | R17: 553.7 | S17: 563.1 | T17: 572.7 | U17: 582.4 | V17: 592.3 | W17: 602.4 | X17: 612.7 | Y17: 623.1 | Z17: 633.7 | AA17: 644.4 | AB17: 655.4 | AC17: 666.5 | AD17: 677.9 | AF17: 432.4 | AG17: 500.6 | AH17: 437.7 | AI17: 527.4 | AJ17: 442.9 | AK17: 525.5 | AL17: 478.4 | AM17: 553.8 | AN17: 484.3 | AO17: 583.5 | AP17: 490 | AQ17: 581.4 | AR17: 529.3 | AS17: 612.8 | AT17: 535.8 | AU17: 645.7 | AV17: 542.2 | AW17: 643.3 | AX17: 585.7 | AY17: 678 | AZ17: 592.9 | BA17: 714.4 | BB17: 599.9 | BC17: 711.8
A18: Helios Software Ltd | B18: Procurement | C18: CC-505 | D18: 1230 | E18: VAT & sales tax receivable | F18: EUR '000 | G18: 270 | H18: 274.6 | I18: 279.3 | J18: 284 | K18: 288.8 | L18: 293.7 | M18: 298.7 | N18: 303.8 | O18: 309 | P18: 314.2 | Q18: 319.6 | R18: 325 | S18: 330.5 | T18: 336.2 | U18: 341.9 | V18: 347.7 | W18: 353.6 | X18: 359.6 | Y18: 365.7 | Z18: 371.9 | AA18: 378.3 | AB18: 384.7 | AC18: 391.2 | AD18: 397.9 | AF18: 251.1 | AG18: 296.6 | AH18: 254.1 | AI18: 312.4 | AJ18: 274.4 | AK18: 311.4 | AL18: 277.8 | AM18: 328.1 | AN18: 281.2 | AO18: 345.7 | AP18: 303.6 | AQ18: 344.5 | AR18: 307.4 | AS18: 363 | AT18: 311.1 | AU18: 382.4 | AV18: 335.9 | AW18: 381.2 | AX18: 340.1 | AY18: 401.7 | AZ18: 344.2 | BA18: 423.2 | BB18: 371.7 | BC18: 421.7
A19: Helios Software Ltd | B19: Procurement | C19: -- | D19: SUB | E19: Procurement debit-balance subtotal | F19: EUR '000 | G19: =SUM(G15:G18) -> 2200 | H19: =SUM(H15:H18) -> 2237.4 | I19: =SUM(I15:I18) -> 2275.5 | J19: =SUM(J15:J18) -> 2314.2 | K19: =SUM(K15:K18) -> 2353.4 | L19: =SUM(L15:L18) -> 2393.4 | M19: =SUM(M15:M18) -> 2434.2 | N19: =SUM(N15:N18) -> 2475.5 | ... AD19: =SUM(AD15:AD18) -> 3242 | AF19: =SUM(AF15:AF18) -> 2022.5 | AG19: =SUM(AG15:AG18) -> 2370.2 | AH19: =SUM(AH15:AH18) -> 2117.7 | AI19: =SUM(AI15:AI18) -> 2497.6 | AJ19: =SUM(AJ15:AJ18) -> 2160.6 | AK19: =SUM(AK15:AK18) -> 2583.6 | AL19: =SUM(AL15:AL18) -> 2237.8 | AM19: =SUM(AM15:AM18) -> 2622.3 | ... BC19: =SUM(BC15:BC18) -> 3499.4
A21: Helios Software Ltd | B21: Fixed Assets | C21: CC-900 | D21: 1300 | E21: Computer equipment at cost | F21: EUR '000 | G21: 6200 | H21: 6335 | I21: 6470 | J21: 6605 | K21: 6740 | L21: 6875 | M21: 7010 | N21: 7145 | O21: 7280 | P21: 7415 | Q21: 7550 | R21: 7685 | S21: 7820 | T21: 7955 | U21: 8090 | V21: 8225 | W21: 8360 | X21: 8495 | Y21: 8630 | Z21: 8765 | AA21: 8900 | AB21: 9035 | AC21: 9170 | AD21: 9305 | AF21: 5580 | AG21: 6651.8 | AH21: 6081.8 | AI21: 7067.4 | AJ21: 6200.8 | AK21: 7493.8 | AL21: 6309 | AM21: 7502.3 | AN21: 6843.2 | AO21: 7934.1 | AP21: 6946 | AQ21: 8376.7 | AR21: 7038 | AS21: 8352.8 | AT21: 7604.6 | AU21: 8800.8 | AV21: 7691.2 | AW21: 9259.6 | AX21: 7767 | AY21: 9203.3 | AZ21: 8366 | BA21: 9667.5 | BB21: 8436.4 | BC21: 10142.5
A22: Helios Software Ltd | B22: Fixed Assets | C22: CC-900 | D22: 1310 | E22: Accumulated deprec–equipment | F22: EUR '000 | G22: -2650 | H22: -2725 | I22: -2800 | J22: -2875 | K22: -2950 | L22: -3025 | M22: -3100 | N22: -3175 | O22: -3250 | P22: -3325 | Q22: -3400 | R22: -3475 | S22: -3550 | T22: -3625 | U22: -3700 | V22: -3775 | W22: -3850 | X22: -3925 | Y22: -4000 | Z22: -4075 | AA22: -4150 | AB22: -4225 | AC22: -4300 | AD22: -4375 | AF22: -2517.5 | AG22: -2888.5 | AH22: -2604 | AI22: -3105 | AJ22: -2684.5 | AK22: -3327.5 | AL22: -2945 | AM22: -3365.5 | AN22: -3022.5 | AO22: -3591 | AP22: -3094 | AQ22: -3822.5 | AR22: -3372.5 | AS22: -3842.5 | AT22: -3441 | AU22: -4077 | AV22: -3503.5 | AW22: -4317.5 | AX22: -3800 | AY22: -4319.5 | AZ22: -3859.5 | BA22: -4563 | BB22: -3913 | BC22: -4812.5
A23: Helios Software Ltd | B23: Fixed Assets | C23: CC-900 | D23: 1320 | E23: Leasehold improvements at cost | F23: EUR '000 | G23: 1780 | H23: 1915 | I23: 2050 | J23: 2185 | K23: 2320 | L23: 2455 | M23: 2590 | N23: 2725 | O23: 2860 | P23: 2995 | Q23: 3130 | R23: 3265 | S23: 3400 | T23: 3535 | U23: 3670 | V23: 3805 | W23: 3940 | X23: 4075 | Y23: 4210 | Z23: 4345 | AA23: 4480 | AB23: 4615 | AC23: 4750 | AD23: 4885 | AF23: 1673.2 | AG23: 2049.1 | AH23: 1886 | AI23: 2381.7 | AJ23: 2088 | AK23: 2577.8 | AL23: 2434.6 | AM23: 2915.8 | AN23: 2631.2 | AO23: 3264.6 | AP23: 2817 | AQ23: 3428.3 | AR23: 3196 | AS23: 3782.5 | AT23: 3376.4 | AU23: 4147.5 | AV23: 3546 | AW23: 4278.8 | AX23: 3957.4 | AY23: 4649.2 | AZ23: 4121.6 | BA23: 5030.4 | BB23: 4275 | BC23: 5129.3
A24: Helios Software Ltd | B24: Fixed Assets | C24: CC-900 | D24: 1330 | E24: Accumulated deprec–leasehold | F24: EUR '000 | G24: -640 | H24: -715 | I24: -790 | J24: -865 | K24: -940 | L24: -1015 | M24: -1090 | N24: -1165 | O24: -1240 | P24: -1315 | Q24: -1390 | R24: -1465 | S24: -1540 | T24: -1615 | U24: -1690 | V24: -1765 | W24: -1840 | X24: -1915 | Y24: -1990 | Z24: -2065 | AA24: -2140 | AB24: -2215 | AC24: -2290 | AD24: -2365 | AF24: -595.2 | AG24: -772.2 | AH24: -718.9 | AI24: -951.5 | AJ24: -893 | AK24: -1075.9 | AL24: -1013.7 | AM24: -1258.2 | AN24: -1128.4 | AO24: -1446.5 | AP24: -1320.5 | AQ24: -1552.9 | AR24: -1432.2 | AS24: -1744.2 | AT24: -1537.9 | AU24: -1941.5 | AV24: -1748 | AW24: -2029.9 | AX24: -1850.7 | AY24: -2230.2 | AZ24: -1947.4 | BA24: -2436.5 | BB24: -2175.5 | BC24: -2506.9
A25: Helios Software Ltd | B25: Fixed Assets | C25: CC-900 | D25: 1400 | E25: Purchased intangibles at cost | F25: EUR '000 | G25: 3100 | H25: 3235 | I25: 3370 | J25: 3505 | K25: 3640 | L25: 3775 | M25: 3910 | N25: 4045 | O25: 4180 | P25: 4315 | Q25: 4450 | R25: 4585 | S25: 4720 | T25: 4855 | U25: 4990 | V25: 5125 | W25: 5260 | X25: 5395 | Y25: 5530 | Z25: 5665 | AA25: 5800 | AB25: 5935 | AC25: 6070 | AD25: 6205 | AF25: 2852 | AG25: 3526.2 | AH25: 3033 | AI25: 3680.3 | AJ25: 3421.6 | AK25: 4039.3 | AL25: 3597.2 | AM25: 4409.1 | AN25: 3762 | AO25: 4530.8 | AP25: 4183 | AQ25: 4906 | AR25: 4342.4 | AS25: 5292 | AT25: 4491 | AU25: 5381.3 | AV25: 4944.4 | AW25: 5772.7 | AX25: 5087.6 | AY25: 6174.9 | AZ25: 5220 | BA25: 6231.8 | BB25: 5705.8 | BC25: 6639.4
A26: Helios Software Ltd | B26: Fixed Assets | C26: CC-900 | D26: 1410 | E26: Accumulated amort–intangibles | F26: EUR '000 | G26: -1480 | H26: -1555 | I26: -1630 | J26: -1705 | K26: -1780 | L26: -1855 | M26: -1930 | N26: -2005 | O26: -2080 | P26: -2155 | Q26: -2230 | R26: -2305 | S26: -2380 | T26: -2455 | U26: -2530 | V26: -2605 | W26: -2680 | X26: -2755 | Y26: -2830 | Z26: -2905 | AA26: -2980 | AB26: -3055 | AC26: -3130 | AD26: -3205 | AF26: -1346.8 | AG26: -1710.5 | AH26: -1548.5 | AI26: -1807.3 | AJ26: -1655.4 | AK26: -2003.4 | AL26: -1756.3 | AM26: -2205.5 | AN26: -1976 | AO26: -2284.3 | AP26: -2073.9 | AQ26: -2489.4 | AR26: -2165.8 | AS26: -2700.5 | AT26: -2403.5 | AU26: -2761.3 | AV26: -2492.4 | AW26: -2975.4 | AX26: -2575.3 | AY26: -3195.5 | AZ26: -2831 | BA26: -3238.3 | BB26: -2910.9 | BC26: -3461.4
A27: Helios Software Ltd | B27: Fixed Assets | C27: CC-900 | D27: 1420 | E27: Capitalised development cost | F27: EUR '000 | G27: 7600 | H27: 7735 | I27: 7870 | J27: 8005 | K27: 8140 | L27: 8275 | M27: 8410 | N27: 8545 | O27: 8680 | P27: 8815 | Q27: 8950 | R27: 9085 | S27: 9220 | T27: 9355 | U27: 9490 | V27: 9625 | W27: 9760 | X27: 9895 | Y27: 10030 | Z27: 10165 | AA27: 10300 | AB27: 10435 | AC27: 10570 | AD27: 10705 | AF27: 6840 | AG27: 8121.8 | AH27: 7397.8 | AI27: 8565.4 | AJ27: 7488.8 | AK27: 9019.8 | AL27: 7569 | AM27: 8972.3 | AN27: 8159.2 | AO27: 9432.1 | AP27: 8234 | AQ27: 9902.7 | AR27: 8298 | AS27: 9822.8 | AT27: 8920.6 | AU27: 10298.8 | AV27: 8979.2 | AW27: 10785.6 | AX27: 9027 | AY27: 10673.3 | AZ27: 9682 | BA27: 11165.5 | BB27: 9724.4 | BC27: 11668.5
A28: Helios Software Ltd | B28: Fixed Assets | C28: CC-900 | D28: 1430 | E28: Accumulated amort–capitalised dev | F28: EUR '000 | G28: -2890 | H28: -2965 | I28: -3040 | J28: -3115 | K28: -3190 | L28: -3265 | M28: -3340 | N28: -3415 | O28: -3490 | P28: -3565 | Q28: -3640 | R28: -3715 | S28: -3790 | T28: -3865 | U28: -3940 | V28: -4015 | W28: -4090 | X28: -4165 | Y28: -4240 | Z28: -4315 | AA28: -4390 | AB28: -4465 | AC28: -4540 | AD28: -4615 | AF28: -2745.5 | AG28: -3142.9 | AH28: -2827.2 | AI28: -3364.2 | AJ28: -2902.9 | AK28: -3591.5 | AL28: -3173 | AM28: -3619.9 | AN28: -3245.7 | AO28: -3850.2 | AP28: -3312.4 | AQ28: -4086.5 | AR28: -3600.5 | AS28: -4096.9 | AT28: -3664.2 | AU28: -4336.2 | AV28: -3721.9 | AW28: -4581.5 | AX28: -4028 | AY28: -4573.9 | AZ28: -4082.7 | BA28: -4822.2 | BB28: -4131.4 | BC28: -5076.5
A29: Helios Software Ltd | B29: Fixed Assets | C29: -- | D29: SUB | E29: Fixed Assets register subtotal | F29: EUR '000 | G29: =SUM(G21:G28) -> 11020 | H29: =SUM(H21:H28) -> 11260 | I29: =SUM(I21:I28) -> 11500 | J29: =SUM(J21:J28) -> 11740 | K29: =SUM(K21:K28) -> 11980 | L29: =SUM(L21:L28) -> 12220 | M29: =SUM(M21:M28) -> 12460 | N29: =SUM(N21:N28) -> 12700 | ... AD29: =SUM(AD21:AD28) -> 16540 | AF29: =SUM(AF21:AF28) -> 9740.2 | AG29: =SUM(AG21:AG28) -> 11834.8 | AH29: =SUM(AH21:AH28) -> 10700 | AI29: =SUM(AI21:AI28) -> 12466.8 | AJ29: =SUM(AJ21:AJ28) -> 11063.4 | AK29: =SUM(AK21:AK28) -> 13132.4 | AL29: =SUM(AL21:AL28) -> 11021.8 | AM29: =SUM(AM21:AM28) -> 13350.4 | ... BC29: =SUM(BC21:BC28) -> 17722.4
A31: Helios Software Inc. | B31: US Working Capital | C31: CC-US1 | D31: 1500 | E31: US cash translated to EUR | F31: EUR '000 | G31: 2850 | H31: 3283.7 | I31: 3652.8 | J31: 3908.6 | K31: 4030.1 | L31: 4029.2 | M31: 3947.6 | N31: 3847.1 | O31: 3793.8 | P31: 3842.4 | Q31: 4022.6 | R31: 4332 | S31: 4736.3 | T31: 5178.3 | U31: 5591.3 | V31: 5915.9 | W31: 6114.1 | X31: 6179.2 | Y31: 6136.7 | Z31: 6038.7 | AA31: 5950.8 | AB31: 5936.2 | AC31: 6040 | AD31: 6278.5 | AF31: 2622 | AG31: 3579.2 | AH31: 3287.5 | AI31: 4104.1 | AJ31: 3788.3 | AK31: 4311.2 | AL31: 3631.8 | AM31: 4193.3 | AN31: 3414.4 | AO31: 4034.5 | AP31: 3781.2 | AQ31: 4635.2 | AR31: 4357.4 | AS31: 5644.4 | AT31: 5032.2 | AU31: 6211.7 | AV31: 5747.3 | AW31: 6611.7 | AX31: 5645.7 | AY31: 6582.1 | AZ31: 5355.7 | BA31: 6233 | BB31: 5677.6 | BC31: 6718
A32: Helios Software Inc. | B32: US Working Capital | C32: CC-US1 | D32: 1510 | E32: US trade receivables translated | F32: EUR '000 | G32: 1850 | H32: 1888.9 | I32: 1928.5 | J32: 1969 | K32: 2010.4 | L32: 2052.6 | M32: 2095.7 | N32: 2139.7 | O32: 2184.6 | P32: 2230.5 | Q32: 2277.3 | R32: 2325.2 | S32: 2374 | T32: 2423.9 | U32: 2474.8 | V32: 2526.7 | W32: 2579.8 | X32: 2634 | Y32: 2689.3 | Z32: 2745.7 | AA32: 2803.4 | AB32: 2862.3 | AC32: 2922.4 | AD32: 2983.8 | AF32: 1683.5 | AG32: 2077.7 | AH32: 1832.1 | AI32: 2087.2 | AJ32: 1869.6 | AK32: 2216.8 | AL32: 1907.1 | AM32: 2353.7 | AN32: 2075.4 | AO32: 2364.3 | AP32: 2117.9 | AQ32: 2511.2 | AR32: 2160.3 | AS32: 2666.2 | AT32: 2351 | AU32: 2678.3 | AV32: 2399.2 | AW32: 2844.7 | AX32: 2447.2 | AY32: 3020.3 | AZ32: 2663.2 | BA32: 3034 | BB32: 2717.8 | BC32: 3222.5
A33: Helios Software Inc. | B33: US Working Capital | C33: CC-US1 | D33: 1520 | E33: US intercompany receivable | F33: EUR '000 | G33: 1120 | H33: 1120 | I33: 1120 | J33: 1120 | K33: 1120 | L33: 1120 | M33: 1120 | N33: 1120 | O33: 1120 | P33: 1120 | Q33: 1120 | R33: 1120 | S33: 1120 | T33: 1120 | U33: 1120 | V33: 1120 | W33: 1120 | X33: 1120 | Y33: 1120 | Z33: 1120 | AA33: 1120 | AB33: 1120 | AC33: 1120 | AD33: 1120 | AF33: 1008 | AG33: 1176 | AH33: 1052.8 | AI33: 1198.4 | AJ33: 1030.4 | AK33: 1220.8 | AL33: 1008 | AM33: 1176 | AN33: 1052.8 | AO33: 1198.4 | AP33: 1030.4 | AQ33: 1220.8 | AR33: 1008 | AS33: 1176 | AT33: 1052.8 | AU33: 1198.4 | AV33: 1030.4 | AW33: 1220.8 | AX33: 1008 | AY33: 1176 | AZ33: 1052.8 | BA33: 1198.4 | BB33: 1030.4 | BC33: 1220.8
A34: Helios Software Inc. | B34: US Working Capital | C34: CC-US1 | D34: 1530 | E34: US lease right-of-use asset | F34: EUR '000 | G34: 940 | H34: 895 | I34: 850 | J34: 805 | K34: 760 | L34: 715 | M34: 670 | N34: 625 | O34: 580 | P34: 535 | Q34: 490 | R34: 445 | S34: 400 | T34: 355 | U34: 310 | V34: 265 | W34: 220 | X34: 175 | Y34: 130 | Z34: 85 | AA34: 40 | AB34: -5 | AC34: -50 | AD34: -95 | AF34: 893 | AG34: 948.7 | AH34: 790.5 | AI34: 869.4 | AJ34: 691.6 | AK34: 786.5 | AL34: 636.5 | AM34: 662.5 | AN34: 539.4 | AO34: 577.8 | AP34: 445.9 | AQ34: 489.5 | AR34: 380 | AS34: 376.3 | AT34: 288.3 | AU34: 286.2 | AV34: 200.2 | AW34: 192.5 | AX34: 123.5 | AY34: 90.1 | AZ34: 37.2 | BA34: -5.4 | BB34: -45.5 | BC34: -104.5
A35: Helios Software Inc. | B35: US Working Capital | C35: -- | D35: SUB | E35: US consolidation debit subtotal | F35: EUR '000 | G35: =SUM(G31:G34) -> 6760 | H35: =SUM(H31:H34) -> 7187.6 | I35: =SUM(I31:I34) -> 7551.3 | J35: =SUM(J31:J34) -> 7802.6 | K35: =SUM(K31:K34) -> 7920.5 | L35: =SUM(L31:L34) -> 7916.8 | M35: =SUM(M31:M34) -> 7833.3 | N35: =SUM(N31:N34) -> 7731.8 | ... AD35: =SUM(AD31:AD34) -> 10287.3 | AF35: =SUM(AF31:AF34) -> 6206.5 | AG35: =SUM(AG31:AG34) -> 7781.6 | AH35: =SUM(AH31:AH34) -> 6962.9 | AI35: =SUM(AI31:AI34) -> 8259.1 | AJ35: =SUM(AJ31:AJ34) -> 7379.9 | AK35: =SUM(AK31:AK34) -> 8535.3 | AL35: =SUM(AL31:AL34) -> 7183.4 | AM35: =SUM(AM31:AM34) -> 8385.5 | ... BC35: =SUM(BC31:BC34) -> 11056.8
A37: Helios Software Ltd | B37: Accounts Payable | C37: CC-506 | D37: 2000 | E37: Trade payables | F37: EUR '000 | G37: -3480 | H37: -3539.2 | I37: -3599.3 | J37: -3660.5 | K37: -3722.7 | L37: -3786 | M37: -3850.4 | N37: -3915.8 | O37: -3982.4 | P37: -4050.1 | Q37: -4119 | R37: -4189 | S37: -4260.2 | T37: -4332.6 | U37: -4406.3 | V37: -4481.2 | W37: -4557.4 | X37: -4634.8 | Y37: -4713.6 | Z37: -4793.8 | AA37: -4875.3 | AB37: -4958.1 | AC37: -5042.4 | AD37: -5128.2 | AF37: -3201.6 | AG37: -3857.7 | AH37: -3239.4 | AI37: -3843.5 | AJ37: -3499.4 | AK37: -4051.1 | AL37: -3542.4 | AM37: -4268.3 | AN37: -3584.2 | AO37: -4252.6 | AP37: -3871.8 | AQ37: -4482.2 | AR37: -3919.4 | AS37: -4722.6 | AT37: -3965.7 | AU37: -4705.3 | AV37: -4283.9 | AW37: -4959.3 | AX37: -4336.5 | AY37: -5225.2 | AZ37: -4387.7 | BA37: -5206.1 | BB37: -4739.9 | BC37: -5487.1
A38: Helios Software Ltd | B38: Accounts Payable | C38: CC-506 | D38: 2010 | E38: Accrued hosting costs | F38: EUR '000 | G38: -1280 | H38: -1301.8 | I38: -1323.9 | J38: -1346.4 | K38: -1369.3 | L38: -1392.6 | M38: -1416.2 | N38: -1440.3 | O38: -1464.8 | P38: -1489.7 | Q38: -1515 | R38: -1540.8 | S38: -1567 | T38: -1593.6 | U38: -1620.7 | V38: -1648.3 | W38: -1676.3 | X38: -1704.8 | Y38: -1733.8 | Z38: -1763.2 | AA38: -1793.2 | AB38: -1823.7 | AC38: -1854.7 | AD38: -1886.2 | AF38: -1164.8 | AG38: -1431.9 | AH38: -1257.7 | AI38: -1427.2 | AJ38: -1273.4 | AK38: -1504 | AL38: -1288.8 | AM38: -1584.3 | AN38: -1391.6 | AO38: -1579.1 | AP38: -1409 | AQ38: -1664 | AR38: -1425.9 | AS38: -1753 | AT38: -1539.7 | AU38: -1747.1 | AV38: -1558.9 | AW38: -1841.2 | AX38: -1577.7 | AY38: -1939.5 | AZ38: -1703.5 | BA38: -1933.1 | BB38: -1724.9 | BC38: -2037.1
A39: Helios Software Ltd | B39: Accounts Payable | C39: CC-506 | D39: 2020 | E39: Payroll & commission accruals | F39: EUR '000 | G39: -2380 | H39: -2420.5 | I39: -2461.6 | J39: -2503.5 | K39: -2546 | L39: -2589.3 | M39: -2633.3 | N39: -2678.1 | O39: -2723.6 | P39: -2769.9 | Q39: -2817 | R39: -2864.9 | S39: -2913.6 | T39: -2963.1 | U39: -3013.5 | V39: -3064.7 | W39: -3116.8 | X39: -3169.8 | Y39: -3223.7 | Z39: -3278.5 | AA39: -3334.2 | AB39: -3390.9 | AC39: -3448.6 | AD39: -3507.2 | AF39: -2142 | AG39: -2541.5 | AH39: -2313.9 | AI39: -2678.7 | AJ39: -2342.3 | AK39: -2822.3 | AL39: -2370 | AM39: -2812 | AN39: -2560.2 | AO39: -2963.8 | AP39: -2591.6 | AQ39: -3122.7 | AR39: -2622.2 | AS39: -3111.3 | AT39: -2832.7 | AU39: -3279.3 | AV39: -2867.5 | AW39: -3455.1 | AX39: -2901.3 | AY39: -3442.4 | AZ39: -3134.2 | BA39: -3628.3 | BB39: -3172.7 | BC39: -3822.8
A40: Helios Software Ltd | B40: Accounts Payable | C40: CC-506 | D40: 2030 | E40: VAT & payroll taxes payable | F40: EUR '000 | G40: -620 | H40: -630.5 | I40: -641.3 | J40: -652.2 | K40: -663.2 | L40: -674.5 | M40: -686 | N40: -697.7 | O40: -709.5 | P40: -721.6 | Q40: -733.8 | R40: -746.3 | S40: -759 | T40: -771.9 | U40: -785 | V40: -798.4 | W40: -811.9 | X40: -825.7 | Y40: -839.8 | Z40: -854.1 | AA40: -868.6 | AB40: -883.3 | AC40: -898.4 | AD40: -913.6 | AF40: -589 | AG40: -668.4 | AH40: -596.4 | AI40: -704.3 | AJ40: -603.6 | AK40: -742 | AL40: -651.7 | AM40: -739.5 | AN40: -659.8 | AO40: -779.3 | AP40: -667.8 | AQ40: -820.9 | AR40: -721.1 | AS40: -818.2 | AT40: -730.1 | AU40: -862.2 | AV40: -738.9 | AW40: -908.3 | AX40: -797.8 | AY40: -905.3 | AZ40: -807.8 | BA40: -954 | BB40: -817.5 | BC40: -1005
A41: Helios Software Ltd | B41: Accounts Payable | C41: CC-506 | D41: 2040 | E41: Deferred subscription billings | F41: EUR '000 | G41: -7850 | H41: -7983.4 | I41: -8119.2 | J41: -8257.2 | K41: -8397.6 | L41: -8540.3 | M41: -8685.5 | N41: -8833.2 | O41: -8983.3 | P41: -9136 | Q41: -9291.4 | R41: -9449.3 | S41: -9609.9 | T41: -9773.3 | U41: -9939.5 | V41: -10108.4 | W41: -10280.3 | X41: -10455 | Y41: -10632.8 | Z41: -10813.5 | AA41: -10997.4 | AB41: -11184.3 | AC41: -11374.5 | AD41: -11567.8 | AF41: -7379 | AG41: -8542.3 | AH41: -7469.6 | AI41: -9000.3 | AJ41: -7557.8 | AK41: -8967.3 | AL41: -8164.4 | AM41: -9451.5 | AN41: -8264.7 | AO41: -9958.3 | AP41: -8362.2 | AQ41: -9921.8 | AR41: -9033.4 | AS41: -10457.5 | AT41: -9144.3 | AU41: -11018.2 | AV41: -9252.3 | AW41: -10977.8 | AX41: -9994.8 | AY41: -11570.5 | AZ41: -10117.6 | BA41: -12190.9 | BB41: -10237 | BC41: -12146.2
A42: Helios Software Ltd | B42: Accounts Payable | C42: CC-506 | D42: 2050 | E42: Other accruals | F42: EUR '000 | G42: -940 | H42: -956 | I42: -972.2 | J42: -988.8 | K42: -1005.6 | L42: -1022.7 | M42: -1040 | N42: -1057.7 | O42: -1075.7 | P42: -1094 | Q42: -1112.6 | R42: -1131.5 | S42: -1150.7 | T42: -1170.3 | U42: -1190.2 | V42: -1210.4 | W42: -1231 | X42: -1251.9 | Y42: -1273.2 | Z42: -1294.9 | AA42: -1316.9 | AB42: -1339.3 | AC42: -1362 | AD42: -1385.2 | AF42: -874.2 | AG42: -1032.5 | AH42: -884.7 | AI42: -1087.6 | AJ42: -955.3 | AK42: -1084 | AL42: -967.2 | AM42: -1142.3 | AN42: -978.9 | AO42: -1203.4 | AP42: -1057 | AQ42: -1199.4 | AR42: -1070.2 | AS42: -1263.9 | AT42: -1083.1 | AU42: -1331.5 | AV42: -1169.5 | AW42: -1327.1 | AX42: -1184.1 | AY42: -1398.5 | AZ42: -1198.4 | BA42: -1473.2 | BB42: -1293.9 | BC42: -1468.3
A43: Helios Software Ltd | B43: Accounts Payable | C43: -- | D43: SUB | E43: Accounts Payable ledger subtotal | F43: EUR '000 | G43: =SUM(G37:G42) -> -16550 | H43: =SUM(H37:H42) -> -16831.4 | I43: =SUM(I37:I42) -> -17117.5 | J43: =SUM(J37:J42) -> -17408.6 | K43: =SUM(K37:K42) -> -17704.4 | L43: =SUM(L37:L42) -> -18005.4 | M43: =SUM(M37:M42) -> -18311.4 | N43: =SUM(N37:N42) -> -18622.8 | ... AD43: =SUM(AD37:AD42) -> -24388.2 | AF43: =SUM(AF37:AF42) -> -15350.6 | AG43: =SUM(AG37:AG42) -> -18074.3 | AH43: =SUM(AH37:AH42) -> -15761.7 | AI43: =SUM(AI37:AI42) -> -18741.6 | AJ43: =SUM(AJ37:AJ42) -> -16231.8 | AK43: =SUM(AK37:AK42) -> -19170.7 | AL43: =SUM(AL37:AL42) -> -16984.5 | AM43: =SUM(AM37:AM42) -> -19997.9 | ... BC43: =SUM(BC37:BC42) -> -25966.5
A45: Helios Software Ltd | B45: Facilities & Tax | C45: CC-500 | D45: 2100 | E45: Current lease liabilities | F45: EUR '000 | G45: -520 | H45: -524.2 | I45: -528.4 | J45: -532.6 | K45: -536.8 | L45: -541.1 | M45: -545.5 | N45: -549.8 | O45: -554.2 | P45: -558.7 | Q45: -563.1 | R45: -567.6 | S45: -572.2 | T45: -576.8 | U45: -581.4 | V45: -586 | W45: -590.7 | X45: -595.4 | Y45: -600.2 | Z45: -605 | AA45: -609.8 | AB45: -614.7 | AC45: -619.6 | AD45: -624.6 | AF45: -468 | AG45: -550.4 | AH45: -496.7 | AI45: -569.9 | AJ45: -493.9 | AK45: -589.8 | AL45: -490.9 | AM45: -577.3 | AN45: -521 | AO45: -597.8 | AP45: -518.1 | AQ45: -618.7 | AR45: -515 | AS45: -605.6 | AT45: -546.5 | AU45: -627 | AV45: -543.5 | AW45: -649 | AX45: -540.2 | AY45: -635.2 | AZ45: -573.2 | BA45: -657.7 | BB45: -570.1 | BC45: -680.8
A46: Helios Software Ltd | B46: Facilities & Tax | C46: CC-500 | D46: 2110 | E46: Non-current lease liabilities | F46: EUR '000 | G46: -1180 | H46: -1189.4 | I46: -1199 | J46: -1208.5 | K46: -1218.2 | L46: -1228 | M46: -1237.8 | N46: -1247.7 | O46: -1257.7 | P46: -1267.7 | Q46: -1277.9 | R46: -1288.1 | S46: -1298.4 | T46: -1308.8 | U46: -1319.3 | V46: -1329.8 | W46: -1340.4 | X46: -1351.2 | Y46: -1362 | Z46: -1372.9 | AA46: -1383.9 | AB46: -1394.9 | AC46: -1406.1 | AD46: -1417.3 | AF46: -1121 | AG46: -1260.8 | AH46: -1115 | AI46: -1305.2 | AJ46: -1108.6 | AK46: -1350.8 | AL46: -1175.9 | AM46: -1322.5 | AN46: -1169.6 | AO46: -1369.1 | AP46: -1162.9 | AQ46: -1416.9 | AR46: -1233.5 | AS46: -1387.3 | AT46: -1226.9 | AU46: -1436.2 | AV46: -1219.8 | AW46: -1486.3 | AX46: -1293.9 | AY46: -1455.3 | AZ46: -1287 | BA46: -1506.5 | BB46: -1279.5 | BC46: -1559.1
A47: Helios Software Ltd | B47: Facilities & Tax | C47: CC-500 | D47: 2120 | E47: Corporation tax payable | F47: EUR '000 | G47: -360 | H47: -362.9 | I47: -365.8 | J47: -368.7 | K47: -371.7 | L47: -374.6 | M47: -377.6 | N47: -380.7 | O47: -383.7 | P47: -386.8 | Q47: -389.9 | R47: -393 | S47: -396.1 | T47: -399.3 | U47: -402.5 | V47: -405.7 | W47: -409 | X47: -412.2 | Y47: -415.5 | Z47: -418.8 | AA47: -422.2 | AB47: -425.6 | AC47: -429 | AD47: -432.4 | AF47: -338.4 | AG47: -388.3 | AH47: -336.5 | AI47: -401.9 | AJ47: -334.5 | AK47: -393.4 | AL47: -355 | AM47: -407.3 | AN47: -353 | AO47: -421.6 | AP47: -350.9 | AQ47: -412.6 | AR47: -372.4 | AS47: -427.2 | AT47: -370.3 | AU47: -442.2 | AV47: -368.1 | AW47: -432.8 | AX47: -390.6 | AY47: -448.2 | AZ47: -388.4 | BA47: -463.9 | BB47: -386.1 | BC47: -454
A48: Helios Software Ltd | B48: Facilities & Tax | C48: CC-500 | D48: 2130 | E48: Deferred tax liability | F48: EUR '000 | G48: -610 | H48: -614.9 | I48: -619.8 | J48: -624.8 | K48: -629.8 | L48: -634.8 | M48: -639.9 | N48: -645 | O48: -650.2 | P48: -655.4 | Q48: -660.6 | R48: -665.9 | S48: -671.2 | T48: -676.6 | U48: -682 | V48: -687.4 | W48: -692.9 | X48: -698.5 | Y48: -704.1 | Z48: -709.7 | AA48: -715.4 | AB48: -721.1 | AC48: -726.9 | AD48: -732.7 | AF48: -567.3 | AG48: -664.1 | AH48: -564 | AI48: -687.2 | AJ48: -598.3 | AK48: -672.9 | AL48: -595.1 | AM48: -696.6 | AN48: -591.6 | AO48: -720.9 | AP48: -627.6 | AQ48: -705.8 | AR48: -624.2 | AS48: -730.7 | AT48: -620.6 | AU48: -756.2 | AV48: -658.3 | AW48: -740.4 | AX48: -654.8 | AY48: -766.5 | AZ48: -651 | BA48: -793.2 | BB48: -690.5 | BC48: -776.7
A49: Helios Software Ltd | B49: Facilities & Tax | C49: CC-500 | D49: 2140 | E49: Employee leave provision | F49: EUR '000 | G49: -430 | H49: -433.4 | I49: -436.9 | J49: -440.4 | K49: -443.9 | L49: -447.5 | M49: -451.1 | N49: -454.7 | O49: -458.3 | P49: -462 | Q49: -465.7 | R49: -469.4 | S49: -473.1 | T49: -476.9 | U49: -480.7 | V49: -484.6 | W49: -488.5 | X49: -492.4 | Y49: -496.3 | Z49: -500.3 | AA49: -504.3 | AB49: -508.3 | AC49: -512.4 | AD49: -516.5 | AF49: -395.6 | AG49: -472.4 | AH49: -393.2 | AI49: -462.4 | AJ49: -417.3 | AK49: -478.8 | AL49: -415 | AM49: -495.6 | AN49: -412.5 | AO49: -485.1 | AP49: -437.7 | AQ49: -502.2 | AR49: -435.3 | AS49: -519.9 | AT49: -432.7 | AU49: -508.8 | AV49: -459.2 | AW49: -526.8 | AX49: -456.6 | AY49: -545.3 | AZ49: -453.9 | BA49: -533.7 | BB49: -481.6 | BC49: -552.6
A50: Helios Software Ltd | B50: Facilities & Tax | C50: -- | D50: SUB | E50: Facilities & Tax ledger subtotal | F50: EUR '000 | G50: =SUM(G45:G49) -> -3100 | H50: =SUM(H45:H49) -> -3124.8 | I50: =SUM(I45:I49) -> -3149.9 | J50: =SUM(J45:J49) -> -3175 | K50: =SUM(K45:K49) -> -3200.4 | L50: =SUM(L45:L49) -> -3226 | M50: =SUM(M45:M49) -> -3251.9 | N50: =SUM(N45:N49) -> -3277.9 | ... AD50: =SUM(AD45:AD49) -> -3723.5 | AF50: =SUM(AF45:AF49) -> -2890.3 | AG50: =SUM(AG45:AG49) -> -3336 | AH50: =SUM(AH45:AH49) -> -2905.4 | AI50: =SUM(AI45:AI49) -> -3426.6 | AJ50: =SUM(AJ45:AJ49) -> -2952.6 | AK50: =SUM(AK45:AK49) -> -3485.7 | AL50: =SUM(AL45:AL49) -> -3031.9 | AM50: =SUM(AM45:AM49) -> -3499.3 | ... BC50: =SUM(BC45:BC49) -> -4023.2
A52: Helios Software Inc. | B52: US Working Capital | C52: CC-US1 | D52: 2200 | E52: US trade payables translated | F52: EUR '000 | G52: -930 | H52: -945.8 | I52: -961.9 | J52: -978.2 | K52: -994.9 | L52: -1011.8 | M52: -1029 | N52: -1046.5 | O52: -1064.3 | P52: -1082.4 | Q52: -1100.8 | R52: -1119.5 | S52: -1138.5 | T52: -1157.9 | U52: -1177.5 | V52: -1197.6 | W52: -1217.9 | X52: -1238.6 | Y52: -1259.7 | Z52: -1281.1 | AA52: -1302.9 | AB52: -1325 | AC52: -1347.5 | AD52: -1370.5 | AF52: -883.5 | AG52: -1002.6 | AH52: -894.6 | AI52: -1056.5 | AJ52: -905.3 | AK52: -1113 | AL52: -977.5 | AM52: -1109.3 | AN52: -989.8 | AO52: -1168.9 | AP52: -1001.7 | AQ52: -1231.4 | AR52: -1081.6 | AS52: -1227.3 | AT52: -1095.1 | AU52: -1293.4 | AV52: -1108.3 | AW52: -1362.5 | AX52: -1196.7 | AY52: -1358 | AZ52: -1211.7 | BA52: -1431 | BB52: -1226.3 | BC52: -1507.5
A53: Helios Software Inc. | B53: US Working Capital | C53: CC-US1 | D53: 2210 | E53: US payroll accrual translated | F53: EUR '000 | G53: -680 | H53: -691.6 | I53: -703.3 | J53: -715.3 | K53: -727.4 | L53: -739.8 | M53: -752.4 | N53: -765.2 | O53: -778.2 | P53: -791.4 | Q53: -804.9 | R53: -818.5 | S53: -832.5 | T53: -846.6 | U53: -861 | V53: -875.6 | W53: -890.5 | X53: -905.7 | Y53: -921.1 | Z53: -936.7 | AA53: -952.6 | AB53: -968.8 | AC53: -985.3 | AD53: -1002.1 | AF53: -639.2 | AG53: -740 | AH53: -647.1 | AI53: -779.6 | AJ53: -654.7 | AK53: -776.8 | AL53: -707.2 | AM53: -818.7 | AN53: -715.9 | AO53: -862.6 | AP53: -724.4 | AQ53: -859.5 | AR53: -782.5 | AS53: -905.9 | AT53: -792.1 | AU53: -954.4 | AV53: -801.5 | AW53: -950.9 | AX53: -865.8 | AY53: -1002.3 | AZ53: -876.4 | BA53: -1056 | BB53: -886.8 | BC53: -1052.2
A54: Helios Software Inc. | B54: US Working Capital | C54: CC-US1 | D54: 2220 | E54: US intercompany payable | F54: EUR '000 | G54: -1120 | H54: -1120 | I54: -1120 | J54: -1120 | K54: -1120 | L54: -1120 | M54: -1120 | N54: -1120 | O54: -1120 | P54: -1120 | Q54: -1120 | R54: -1120 | S54: -1120 | T54: -1120 | U54: -1120 | V54: -1120 | W54: -1120 | X54: -1120 | Y54: -1120 | Z54: -1120 | AA54: -1120 | AB54: -1120 | AC54: -1120 | AD54: -1120 | AF54: -1041.6 | AG54: -1209.6 | AH54: -1019.2 | AI54: -1232 | AJ54: -1064 | AK54: -1187.2 | AL54: -1041.6 | AM54: -1209.6 | AN54: -1019.2 | AO54: -1232 | AP54: -1064 | AQ54: -1187.2 | AR54: -1041.6 | AS54: -1209.6 | AT54: -1019.2 | AU54: -1232 | AV54: -1064 | AW54: -1187.2 | AX54: -1041.6 | AY54: -1209.6 | AZ54: -1019.2 | BA54: -1232 | BB54: -1064 | BC54: -1187.2
A55: Helios Software Inc. | B55: US Working Capital | C55: CC-US1 | D55: 2230 | E55: US deferred billings translated | F55: EUR '000 | G55: -1640 | H55: -1667.9 | I55: -1696.2 | J55: -1725.1 | K55: -1754.4 | L55: -1784.2 | M55: -1814.6 | N55: -1845.4 | O55: -1876.8 | P55: -1908.7 | Q55: -1941.1 | R55: -1974.1 | S55: -2007.7 | T55: -2041.8 | U55: -2076.5 | V55: -2111.8 | W55: -2147.7 | X55: -2184.2 | Y55: -2221.4 | Z55: -2259.1 | AA55: -2297.5 | AB55: -2336.6 | AC55: -2376.3 | AD55: -2416.7 | AF55: -1508.8 | AG55: -1818 | AH55: -1526.6 | AI55: -1811.3 | AJ55: -1649.1 | AK55: -1909.1 | AL55: -1669.4 | AM55: -2011.5 | AN55: -1689.1 | AO55: -2004.1 | AP55: -1824.7 | AQ55: -2112.3 | AR55: -1847.1 | AS55: -2225.6 | AT55: -1868.9 | AU55: -2217.4 | AV55: -2018.9 | AW55: -2337.1 | AX55: -2043.7 | AY55: -2462.5 | AZ55: -2067.8 | BA55: -2453.4 | BB55: -2233.7 | BC55: -2585.9
A56: Helios Software Inc. | B56: US Working Capital | C56: -- | D56: SUB | E56: US consolidation credit subtotal | F56: EUR '000 | G56: =SUM(G52:G55) -> -4370 | H56: =SUM(H52:H55) -> -4425.3 | I56: =SUM(I52:I55) -> -4481.4 | J56: =SUM(J52:J55) -> -4538.6 | K56: =SUM(K52:K55) -> -4596.7 | L56: =SUM(L52:L55) -> -4655.8 | M56: =SUM(M52:M55) -> -4716 | N56: =SUM(N52:N55) -> -4777.1 | ... AD56: =SUM(AD52:AD55) -> -5909.3 | AF56: =SUM(AF52:AF55) -> -4073.1 | AG56: =SUM(AG52:AG55) -> -4770.2 | AH56: =SUM(AH52:AH55) -> -4087.5 | AI56: =SUM(AI52:AI55) -> -4879.4 | AJ56: =SUM(AJ52:AJ55) -> -4273.1 | AK56: =SUM(AK52:AK55) -> -4986.1 | AL56: =SUM(AL52:AL55) -> -4395.7 | AM56: =SUM(AM52:AM55) -> -5149.1 | ... BC56: =SUM(BC52:BC55) -> -6332.8
A58: Helios Holdings Ltd | B58: Group Financing | C58: CC-920 | D58: 2500 | E58: Senior facility–Term Loan A | F58: EUR '000 | G58: -42000 | H58: -41500 | I58: -41000 | J58: -40500 | K58: -40000 | L58: -39500 | M58: -39000 | N58: -38500 | O58: -38000 | P58: -37500 | Q58: -37000 | R58: -36500 | S58: -36000 | T58: -35500 | U58: -35000 | V58: -34500 | W58: -34000 | X58: -33500 | Y58: -33000 | Z58: -32500 | AA58: -32000 | AB58: -31500 | AC58: -31000 | AD58: -30500 | AF58: -39900 | AG58: -43990 | AH58: -38130 | AI58: -43740 | AJ58: -36400 | AK58: -43450 | AL58: -37050 | AM58: -40810 | AN58: -35340 | AO58: -40500 | AP58: -33670 | AQ58: -40150 | AR58: -34200 | AS58: -37630 | AT58: -32550 | AU58: -37260 | AV58: -30940 | AW58: -36850 | AX58: -31350 | AY58: -34450 | AZ58: -29760 | BA58: -34020 | BB58: -28210 | BC58: -33550
A59: Helios Holdings Ltd | B59: Group Financing | C59: CC-920 | D59: 2510 | E59: Senior facility–Term Loan B | F59: EUR '000 | G59: -28000 | H59: -28000 | I59: -28000 | J59: -28000 | K59: -28000 | L59: -28000 | M59: -28000 | N59: -28000 | O59: -28000 | P59: -28000 | Q59: -28000 | R59: -28000 | S59: -27750 | T59: -27500 | U59: -27250 | V59: -27000 | W59: -26750 | X59: -26500 | Y59: -26250 | Z59: -26000 | AA59: -25750 | AB59: -25500 | AC59: -25250 | AD59: -25000 | AF59: -26320 | AG59: -29960 | AH59: -25760 | AI59: -30520 | AJ59: -25200 | AK59: -29400 | AL59: -26320 | AM59: -29960 | AN59: -25760 | AO59: -30520 | AP59: -25200 | AQ59: -29400 | AR59: -26085 | AS59: -29425 | AT59: -25070 | AU59: -29430 | AV59: -24075 | AW59: -27825 | AX59: -24675 | AY59: -27820 | AZ59: -23690 | BA59: -27795 | BB59: -22725 | BC59: -26250
A60: Helios Holdings Ltd | B60: Group Financing | C60: CC-920 | D60: 2520 | E60: Second lien notes | F60: EUR '000 | G60: -25000 | H60: -25000 | I60: -25000 | J60: -25000 | K60: -25000 | L60: -25000 | M60: -25000 | N60: -25000 | O60: -25000 | P60: -25000 | Q60: -25000 | R60: -25000 | S60: -25000 | T60: -25000 | U60: -25000 | V60: -25000 | W60: -25000 | X60: -25000 | Y60: -25000 | Z60: -25000 | AA60: -25000 | AB60: -25000 | AC60: -25000 | AD60: -25000 | AF60: -23250 | AG60: -27000 | AH60: -22750 | AI60: -27500 | AJ60: -23750 | AK60: -26500 | AL60: -23250 | AM60: -27000 | AN60: -22750 | AO60: -27500 | AP60: -23750 | AQ60: -26500 | AR60: -23250 | AS60: -27000 | AT60: -22750 | AU60: -27500 | AV60: -23750 | AW60: -26500 | AX60: -23250 | AY60: -27000 | AZ60: -22750 | BA60: -27500 | BB60: -23750 | BC60: -26500
A61: Helios Holdings Ltd | B61: Group Financing | C61: CC-920 | D61: 2530 | E61: Shareholder loan notes | F61: EUR '000 | G61: -18000 | H61: -18000 | I61: -18000 | J61: -18000 | K61: -18000 | L61: -18000 | M61: -18000 | N61: -18000 | O61: -18000 | P61: -18000 | Q61: -18000 | R61: -18000 | S61: -18000 | T61: -18000 | U61: -18000 | V61: -18000 | W61: -18000 | X61: -18000 | Y61: -18000 | Z61: -18000 | AA61: -18000 | AB61: -18000 | AC61: -18000 | AD61: -18000 | AF61: -16560 | AG61: -19620 | AH61: -16200 | AI61: -18900 | AJ61: -16920 | AK61: -19260 | AL61: -16560 | AM61: -19620 | AN61: -16200 | AO61: -18900 | AP61: -16920 | AQ61: -19260 | AR61: -16560 | AS61: -19620 | AT61: -16200 | AU61: -18900 | AV61: -16920 | AW61: -19260 | AX61: -16560 | AY61: -19620 | AZ61: -16200 | BA61: -18900 | BB61: -16920 | BC61: -19260
A62: Helios Holdings Ltd | B62: Group Financing | C62: CC-920 | D62: 2540 | E62: Accrued PIK interest | F62: EUR '000 | G62: -1350 | H62: -1366.2 | I62: -1382.6 | J62: -1399.2 | K62: -1416 | L62: -1433 | M62: -1450.2 | N62: -1467.6 | O62: -1485.2 | P62: -1503 | Q62: -1521 | R62: -1539.3 | S62: -1557.8 | T62: -1576.5 | U62: -1595.4 | V62: -1614.5 | W62: -1633.9 | X62: -1653.5 | Y62: -1673.3 | Z62: -1693.4 | AA62: -1713.7 | AB62: -1734.3 | AC62: -1755.1 | AD62: -1776.2 | AF62: -1228.5 | AG62: -1502.8 | AH62: -1313.5 | AI62: -1483.1 | AJ62: -1316.9 | AK62: -1547.6 | AL62: -1319.6 | AM62: -1614.3 | AN62: -1410.9 | AO62: -1593.2 | AP62: -1414.6 | AQ62: -1662.4 | AR62: -1417.6 | AS62: -1734.1 | AT62: -1515.6 | AU62: -1711.4 | AV62: -1519.5 | AW62: -1785.8 | AX62: -1522.7 | AY62: -1862.8 | AZ62: -1628 | BA62: -1838.4 | BB62: -1632.3 | BC62: -1918.3
A63: Helios Holdings Ltd | B63: Group Financing | C63: CC-920 | D63: 2550 | E63: Debt issue costs | F63: EUR '000 | G63: 1850 | H63: 1805 | I63: 1760 | J63: 1715 | K63: 1670 | L63: 1625 | M63: 1580 | N63: 1535 | O63: 1490 | P63: 1445 | Q63: 1400 | R63: 1355 | S63: 1310 | T63: 1265 | U63: 1220 | V63: 1175 | W63: 1130 | X63: 1085 | Y63: 1040 | Z63: 995 | AA63: 950 | AB63: 905 | AC63: 860 | AD63: 815 | AF63: 1665 | AG63: 1895.3 | AH63: 1654.4 | AI63: 1835.1 | AJ63: 1536.4 | AK63: 1771.3 | AL63: 1422 | AM63: 1611.8 | AN63: 1400.6 | AO63: 1546.2 | AP63: 1288 | AQ63: 1477 | AR63: 1179 | AS63: 1328.3 | AT63: 1146.8 | AU63: 1257.3 | AV63: 1039.6 | AW63: 1182.7 | AX63: 936 | AY63: 1044.8 | AZ63: 893 | BA63: 968.4 | BB63: 791.2 | BC63: 888.4
A64: Helios Holdings Ltd | B64: Group Financing | C64: -- | D64: SUB | E64: Group Financing ledger subtotal | F64: EUR '000 | G64: =SUM(G58:G63) -> -112500 | H64: =SUM(H58:H63) -> -112061.2 | I64: =SUM(I58:I63) -> -111622.6 | J64: =SUM(J58:J63) -> -111184.2 | K64: =SUM(K58:K63) -> -110746 | L64: =SUM(L58:L63) -> -110308 | M64: =SUM(M58:M63) -> -109870.2 | N64: =SUM(N58:N63) -> -109432.6 | ... AD64: =SUM(AD58:AD63) -> -99461.2 | AF64: =SUM(AF58:AF63) -> -105593.5 | AG64: =SUM(AG58:AG63) -> -120177.5 | AH64: =SUM(AH58:AH63) -> -102499.1 | AI64: =SUM(AI58:AI63) -> -120308 | AJ64: =SUM(AJ58:AJ63) -> -102050.5 | AK64: =SUM(AK58:AK63) -> -118386.3 | AL64: =SUM(AL58:AL63) -> -103077.6 | AM64: =SUM(AM58:AM63) -> -117392.5 | ... BC64: =SUM(BC58:BC63) -> -106589.9
A66: Helios Holdings Ltd | B66: Equity & Reserves | C66: CC-930 | D66: 3000 | E66: Ordinary share capital | F66: EUR '000 | G66: -120 | H66: -120 | I66: -120 | J66: -120 | K66: -120 | L66: -120 | M66: -120 | N66: -120 | O66: -120 | P66: -120 | Q66: -120 | R66: -120 | S66: -120 | T66: -120 | U66: -120 | V66: -120 | W66: -120 | X66: -120 | Y66: -120 | Z66: -120 | AA66: -120 | AB66: -120 | AC66: -120 | AD66: -120 | AF66: -111.6 | AG66: -129.6 | AH66: -109.2 | AI66: -132 | AJ66: -114 | AK66: -127.2 | AL66: -111.6 | AM66: -129.6 | AN66: -109.2 | AO66: -132 | AP66: -114 | AQ66: -127.2 | AR66: -111.6 | AS66: -129.6 | AT66: -109.2 | AU66: -132 | AV66: -114 | AW66: -127.2 | AX66: -111.6 | AY66: -129.6 | AZ66: -109.2 | BA66: -132 | BB66: -114 | BC66: -127.2
A67: Helios Holdings Ltd | B67: Equity & Reserves | C67: CC-930 | D67: 3010 | E67: Share premium | F67: EUR '000 | G67: -18400 | H67: -18400 | I67: -18400 | J67: -18400 | K67: -18400 | L67: -18400 | M67: -18400 | N67: -18400 | O67: -18400 | P67: -18400 | Q67: -18400 | R67: -18400 | S67: -18400 | T67: -18400 | U67: -18400 | V67: -18400 | W67: -18400 | X67: -18400 | Y67: -18400 | Z67: -18400 | AA67: -18400 | AB67: -18400 | AC67: -18400 | AD67: -18400 | AF67: -16928 | AG67: -20056 | AH67: -16560 | AI67: -19320 | AJ67: -17296 | AK67: -19688 | AL67: -16928 | AM67: -20056 | AN67: -16560 | AO67: -19320 | AP67: -17296 | AQ67: -19688 | AR67: -16928 | AS67: -20056 | AT67: -16560 | AU67: -19320 | AV67: -17296 | AW67: -19688 | AX67: -16928 | AY67: -20056 | AZ67: -16560 | BA67: -19320 | BB67: -17296 | BC67: -19688
A68: Helios Holdings Ltd | B68: Equity & Reserves | C68: CC-930 | D68: 3020 | E68: Share-based payment reserve | F68: EUR '000 | G68: -2350 | H68: -2445 | I68: -2540 | J68: -2635 | K68: -2730 | L68: -2825 | M68: -2920 | N68: -3015 | O68: -3110 | P68: -3205 | Q68: -3300 | R68: -3395 | S68: -3490 | T68: -3585 | U68: -3680 | V68: -3775 | W68: -3870 | X68: -3965 | Y68: -4060 | Z68: -4155 | AA68: -4250 | AB68: -4345 | AC68: -4440 | AD68: -4535 | AF68: -2138.5 | AG68: -2689.5 | AH68: -2413 | AI68: -2793.1 | AJ68: -2538.9 | AK68: -3051 | AL68: -2657.2 | AM68: -3316.5 | AN68: -2954.5 | AO68: -3397.3 | AP68: -3069 | AQ68: -3666.6 | AR68: -3175.9 | AS68: -3943.5 | AT68: -3496 | AU68: -4001.5 | AV68: -3599.1 | AW68: -4282.2 | AX68: -3694.6 | AY68: -4570.5 | AZ68: -4037.5 | BA68: -4605.7 | BB68: -4129.2 | BC68: -4897.8
A69: Helios Holdings Ltd | B69: Equity & Reserves | C69: CC-930 | D69: 3030 | E69: Foreign currency translation reserve | F69: EUR '000 | G69: 180 | H69: 201.4 | I69: 219.5 | J69: 231.3 | K69: 235 | L69: 230 | M69: 217.2 | N69: 198.4 | O69: 176.8 | P69: 155.7 | Q69: 138.4 | R69: 127.7 | S69: 125.2 | T69: 131.4 | U69: 145.3 | V69: 164.6 | W69: 186.4 | X69: 207.2 | Y69: 223.7 | Z69: 233.2 | AA69: 234.4 | AB69: 227 | AC69: 212.2 | AD69: 192.3 | AF69: 162 | AG69: 211.5 | AH69: 206.3 | AI69: 247.5 | AJ69: 216.2 | AK69: 250.7 | AL69: 195.4 | AM69: 208.3 | AN69: 166.2 | AO69: 166.6 | AP69: 127.3 | AQ69: 139.2 | AR69: 112.7 | AS69: 138 | AT69: 136.6 | AU69: 176.2 | AV69: 171.5 | AW69: 225.8 | AX69: 201.3 | AY69: 244.9 | AZ69: 220.3 | BA69: 242.9 | BB69: 195.2 | BC69: 209.6
A70: Helios Holdings Ltd | B70: Equity & Reserves | C70: CC-930 | D70: 3040 | E70: Retained earnings / consolidation reserve | F70: EUR '000 | G70: =-(G7+G13+G19+G29+G35+G43+G50+G56+G64+G65+G66+G67+G68+G69+G71) -> 113632 | H70: =-(H7+H13+H19+H29+H35+H43+H50+H56+H64+H65+H66+H67+H68+H69+H71) -> 111187.2 | I70: =-(I7+I13+I19+I29+I35+I43+I50+I56+I64+I65+I66+I67+I68+I69+I71) -> 108996.7 | J70: =-(J7+J13+J19+J29+J35+J43+J50+J56+J64+J65+J66+J67+J68+J69+J71) -> 107008.2 | K70: =-(K7+K13+K19+K29+K35+K43+K50+K56+K64+K65+K66+K67+K68+K69+K71) -> 105425.4 | L70: =-(L7+L13+L19+L29+L35+L43+L50+L56+L64+L65+L66+L67+L68+L69+L71) -> 104176.2 | M70: =-(M7+M13+M19+M29+M35+M43+M50+M56+M64+M65+M66+M67+M68+M69+M71) -> 102899.4 | N70: =-(N7+N13+N19+N29+N35+N43+N50+N56+N64+N65+N66+N67+N68+N69+N71) -> 101574.7 | ... AD70: =-(AD7+AD13+AD19+AD29+AD35+AD43+AD50+AD56+AD64+AD65+AD66+AD67+AD68+AD69+AD71) -> 78555 | AF70: =-(AF7+AF13+AF19+AF29+AF35+AF43+AF50+AF56+AF64+AF65+AF66+AF67+AF68+AF69+AF71) -> 106972.7 | AG70: =-(AG7+AG13+AG19+AG29+AG35+AG43+AG50+AG56+AG64+AG65+AG66+AG67+AG68+AG69+AG71) -> 120618.83 | AH70: =-(AH7+AH13+AH19+AH29+AH35+AH43+AH50+AH56+AH64+AH65+AH66+AH67+AH68+AH69+AH71) -> 99204.965 | AI70: =-(AI7+AI13+AI19+AI29+AI35+AI43+AI50+AI56+AI64+AI65+AI66+AI67+AI68+AI69+AI71) -> 115961.91 | AJ70: =-(AJ7+AJ13+AJ19+AJ29+AJ35+AJ43+AJ50+AJ56+AJ64+AJ65+AJ66+AJ67+AJ68+AJ69+AJ71) -> 97271.816 | AK70: =-(AK7+AK13+AK19+AK29+AK35+AK43+AK50+AK56+AK64+AK65+AK66+AK67+AK68+AK69+AK71) -> 111568.24 | AL70: =-(AL7+AL13+AL19+AL29+AL35+AL43+AL50+AL56+AL64+AL65+AL66+AL67+AL68+AL69+AL71) -> 96360.036 | AM70: =-(AM7+AM13+AM19+AM29+AM35+AM43+AM50+AM56+AM64+AM65+AM66+AM67+AM68+AM69+AM71) -> 110350.3 | ... BC70: =-(BC7+BC13+BC19+BC29+BC35+BC43+BC50+BC56+BC64+BC65+BC66+BC67+BC68+BC69+BC71) -> 84581.044
A71: Helios Holdings Ltd | B71: Equity & Reserves | C71: CC-930 | D71: 3995 | E71: Current period ledger result | F71: EUR '000 | G71: =-SUM(UK_PL_EUR!$G$95:G95) -> 1178 | H71: =-SUM(UK_PL_EUR!$G$95:H95) -> 2290 | I71: =-SUM(UK_PL_EUR!$G$95:I95) -> 3280.9 | J71: =-SUM(UK_PL_EUR!$G$95:J95) -> 4303.3 | K71: =-SUM(UK_PL_EUR!$G$95:K95) -> 5197.3 | L71: =-SUM(UK_PL_EUR!$G$95:L95) -> 6012 | M71: =-SUM(UK_PL_EUR!$G$95:M95) -> 7024 | N71: =-SUM(UK_PL_EUR!$G$95:N95) -> 8128.6 | ... AD71: =-SUM(UK_PL_EUR!$G$95:AD95) -> 16320.4 | AF71: =-SUM(UK_PL_EUR!$AF$95:AF95) -> 1044.0968 | AG71: =-SUM(UK_PL_EUR!$AF$95:AG95) -> 2043.4717 | AH71: =-SUM(UK_PL_EUR!$AF$95:AH95) -> 3133.7351 | AI71: =-SUM(UK_PL_EUR!$AF$95:AI95) -> 4237.6862 | AJ71: =-SUM(UK_PL_EUR!$AF$95:AJ95) -> 5117.8838 | AK71: =-SUM(UK_PL_EUR!$AF$95:AK95) -> 5938.0649 | AL71: =-SUM(UK_PL_EUR!$AF$95:AL95) -> 7110.8638 | AM71: =-SUM(UK_PL_EUR!$AF$95:AM95) -> 8359.9003 | ... BC71: =-SUM(UK_PL_EUR!$AF$95:BC95) -> 16232.956
A72: Helios Holdings Ltd | B72: Equity & Reserves | C72: -- | D72: SUB | E72: Equity & Reserves ledger subtotal | F72: EUR '000 | G72: =SUM(G66:G71) -> 94120 | H72: =SUM(H66:H71) -> 92713.6 | I72: =SUM(I66:I71) -> 91437.1 | J72: =SUM(J66:J71) -> 90387.8 | K72: =SUM(K66:K71) -> 89607.7 | L72: =SUM(L66:L71) -> 89073.2 | M72: =SUM(M66:M71) -> 88700.6 | N72: =SUM(N66:N71) -> 88366.7 | ... AD72: =SUM(AD66:AD71) -> 72012.7 | AF72: =SUM(AF66:AF71) -> 89000.7 | AG72: =SUM(AG66:AG71) -> 99998.7 | AH72: =SUM(AH66:AH71) -> 83462.8 | AI72: =SUM(AI66:AI71) -> 98202 | AJ72: =SUM(AJ66:AJ71) -> 82657 | AK72: =SUM(AK66:AK71) -> 94890.8 | AL72: =SUM(AL66:AL71) -> 83969.5 | AM72: =SUM(AM66:AM71) -> 95416.4 | ... BC72: =SUM(BC66:BC71) -> 76310.6
A74: Helios Holdings Ltd | B74: Group Consolidation | C74: CC-999 | D74: CHK | E74: Monthly ledger control difference | F74: EUR '000 | G74: =ROUND(G7+G13+G19+G29+G35+G43+G50+G56+G64+G72,6) -> 0 | H74: =ROUND(H7+H13+H19+H29+H35+H43+H50+H56+H64+H72,6) -> 0 | I74: =ROUND(I7+I13+I19+I29+I35+I43+I50+I56+I64+I72,6) -> 0 | J74: =ROUND(J7+J13+J19+J29+J35+J43+J50+J56+J64+J72,6) -> 0 | K74: =ROUND(K7+K13+K19+K29+K35+K43+K50+K56+K64+K72,6) -> 0 | L74: =ROUND(L7+L13+L19+L29+L35+L43+L50+L56+L64+L72,6) -> 0 | M74: =ROUND(M7+M13+M19+M29+M35+M43+M50+M56+M64+M72,6) -> 0 | N74: =ROUND(N7+N13+N19+N29+N35+N43+N50+N56+N64+N72,6) -> 0 | ... AD74: =ROUND(AD7+AD13+AD19+AD29+AD35+AD43+AD50+AD56+AD64+AD72,6) -> 0 | AF74: =ROUND(AF7+AF13+AF19+AF29+AF35+AF43+AF50+AF56+AF64+AF72,6) -> 0 | AG74: =ROUND(AG7+AG13+AG19+AG29+AG35+AG43+AG50+AG56+AG64+AG72,6) -> 0 | AH74: =ROUND(AH7+AH13+AH19+AH29+AH35+AH43+AH50+AH56+AH64+AH72,6) -> 0 | AI74: =ROUND(AI7+AI13+AI19+AI29+AI35+AI43+AI50+AI56+AI64+AI72,6) -> 0 | AJ74: =ROUND(AJ7+AJ13+AJ19+AJ29+AJ35+AJ43+AJ50+AJ56+AJ64+AJ72,6) -> 0 | AK74: =ROUND(AK7+AK13+AK19+AK29+AK35+AK43+AK50+AK56+AK64+AK72,6) -> 0 | AL74: =ROUND(AL7+AL13+AL19+AL29+AL35+AL43+AL50+AL56+AL64+AL72,6) -> 0 | AM74: =ROUND(AM7+AM13+AM19+AM29+AM35+AM43+AM50+AM56+AM64+AM72,6) -> 0 | ... BC74: =ROUND(BC7+BC13+BC19+BC29+BC35+BC43+BC50+BC56+BC64+BC72,6) -> 0

Sheet KPI_Operational
A1: NetSuite Operational Metrics Export | B1: Helios Software Group — controller KPI load | E1: Units vary by metric
G2: ACTUAL — monthly operating statistics | AF2: BUDGET — approved operating plan
A3: Legal entity | B3: Department | C3: Cost centre | D3: Metric code | E3: Metric name | F3: Unit | G3: Jan-2024 | H3: Feb-2024 | I3: Mar-2024 | J3: Apr-2024 | K3: May-2024 | L3: Jun-2024 | M3: Jul-2024 | N3: Aug-2024 | O3: Sept-2024 | P3: Oct-2024 | Q3: Nov-2024 | R3: Dec-2024 | S3: Jan-2025 | T3: Feb-2025 | U3: Mar-2025 | V3: Apr-2025 | W3: May-2025 | X3: Jun-2025 | Y3: Jul-2025 | Z3: Aug-2025 | AA3: Sept-2025 | AB3: Oct-2025 | AC3: Nov-2025 | AD3: Dec-2025 | AF3: Jan-2024 | AG3: Feb-2024 | AH3: Mar-2024 | AI3: Apr-2024 | AJ3: May-2024 | AK3: Jun-2024 | AL3: Jul-2024 | AM3: Aug-2024 | AN3: Sept-2024 | AO3: Oct-2024 | AP3: Nov-2024 | AQ3: Dec-2024 | AR3: Jan-2025 | AS3: Feb-2025 | AT3: Mar-2025 | AU3: Apr-2025 | AV3: May-2025 | AW3: Jun-2025 | AX3: Jul-2025 | AY3: Aug-2025 | AZ3: Sept-2025 | BA3: Oct-2025 | BB3: Nov-2025 | BC3: Dec-2025
A4: Helios Software Group | B4: Commercial Operations | C4: CC-100 | D4: KPI-001 | E4: ARR | F4: €m | G4: 57.2 | H4: 58.733 | I4: 60.075 | J4: 61.192 | K4: 62.288 | L4: 63.625 | M4: 65.278 | N4: 67.06 | O4: 68.682 | P4: 70.026 | Q4: 71.26 | R4: 72.697 | S4: 74.506 | T4: 76.547 | U4: 78.493 | V4: 80.123 | W4: 81.542 | X4: 83.096 | Y4: 85.055 | Z4: 87.362 | AA4: 89.669 | AB4: 91.651 | AC4: 93.319 | AD4: 95.019 | AF4: 60.211 | AG4: 55.409 | AH4: 64.597 | AI4: 56.659 | AJ4: 68.448 | AK4: 57.841 | AL4: 68.714 | AM4: 63.264 | AN4: 73.852 | AO4: 64.839 | AP4: 78.308 | AQ4: 66.088 | AR4: 78.427 | AS4: 72.215 | AT4: 84.401 | AU4: 74.188 | AV4: 89.607 | AW4: 75.542 | AX4: 89.532 | AY4: 82.417 | AZ4: 96.418 | BA4: 84.862 | BB4: 102.548 | BC4: 86.381
A5: Helios Software Group | B5: Commercial Operations | C5: CC-100 | D5: KPI-002 | E5: Net new ARR | F5: €m | G5: 1.15 | H5: 1.285 | I5: 1.386 | J5: 1.432 | K5: 1.418 | L5: 1.361 | M5: 1.292 | N5: 1.246 | O5: 1.25 | P5: 1.315 | Q5: 1.43 | R5: 1.569 | S5: 1.696 | T5: 1.781 | U5: 1.807 | V5: 1.777 | W5: 1.712 | X5: 1.647 | Y5: 1.615 | Z5: 1.638 | AA5: 1.721 | AB5: 1.847 | AC5: 1.986 | AD5: 2.103 | AF5: 1.223 | AG5: 1.201 | AH5: 1.507 | AI5: 1.313 | AJ5: 1.575 | AK5: 1.296 | AL5: 1.374 | AM5: 1.164 | AN5: 1.359 | AO5: 1.206 | AP5: 1.589 | AQ5: 1.494 | AR5: 1.804 | AS5: 1.665 | AT5: 1.964 | AU5: 1.63 | AV5: 1.903 | AW5: 1.569 | AX5: 1.718 | AY5: 1.531 | AZ5: 1.87 | BA5: 1.694 | BB5: 2.207 | BC5: 2.003
A6: Helios Software Group | B6: Commercial Operations | C6: CC-100 | D6: KPI-003 | E6: Bookings | F6: €m | G6: 5.336 | H6: 5.62 | I6: 6.517 | J6: 6.155 | K6: 6.404 | L6: 6.788 | M6: 5.879 | N6: 5.863 | O6: 7.067 | P6: 6.932 | Q6: 7.919 | R6: 9.231 | S6: 6.767 | T6: 7.128 | U6: 8.265 | V6: 7.806 | W6: 8.121 | X6: 8.609 | Y6: 7.455 | Z6: 7.436 | AA6: 8.963 | AB6: 8.791 | AC6: 10.043 | AD6: 11.707 | AF6: 5.738 | AG6: 5.204 | AH6: 7.162 | AI6: 5.595 | AJ6: 6.741 | AK6: 6.404 | AL6: 6.321 | AM6: 5.429 | AN6: 7.766 | AO6: 6.301 | AP6: 8.335 | AQ6: 8.708 | AR6: 7.277 | AS6: 6.6 | AT6: 9.083 | AU6: 7.096 | AV6: 8.549 | AW6: 8.121 | AX6: 8.017 | AY6: 6.885 | AZ6: 9.85 | BA6: 7.992 | BB6: 10.571 | BC6: 11.044
A7: Helios Software Group | B7: Commercial Operations | C7: CC-100 | D7: KPI-004 | E7: Pipeline coverage | F7: x | G7: 3.1 | H7: 3.298 | I7: 3.455 | J7: 3.54 | K7: 3.536 | L7: 3.444 | M7: 3.281 | N7: 3.082 | O7: 2.886 | P7: 2.734 | Q7: 2.656 | R7: 2.668 | S7: 2.768 | T7: 2.936 | U7: 3.136 | V7: 3.329 | W7: 3.476 | X7: 3.546 | Y7: 3.526 | Z7: 3.419 | AA7: 3.247 | AB7: 3.046 | AC7: 2.855 | AD7: 2.714 | AF7: 3.37 | AG7: 3.025 | AH7: 3.839 | AI7: 3.372 | AJ7: 3.762 | AK7: 3.218 | AL7: 3.566 | AM7: 2.827 | AN7: 3.207 | AO7: 2.604 | AP7: 2.826 | AQ7: 2.494 | AR7: 3.009 | AS7: 2.693 | AT7: 3.485 | AU7: 3.171 | AV7: 3.698 | AW7: 3.314 | AX7: 3.833 | AY7: 3.137 | AZ7: 3.608 | BA7: 2.901 | BB7: 3.037 | BC7: 2.537
A8: Helios Software Group | B8: Commercial Operations | C8: CC-100 | D8: KPI-005 | E8: CAC | F8: €k | G8: 43 | H8: 45.138 | I8: 46.924 | J8: 48.092 | K8: 48.528 | L8: 48.295 | M8: 47.623 | N8: 46.848 | O8: 46.33 | P8: 46.367 | Q8: 47.123 | R8: 48.583 | S8: 50.562 | T8: 52.745 | U8: 54.771 | V8: 56.314 | W8: 57.168 | X8: 57.295 | Y8: 56.836 | Z8: 56.075 | AA8: 55.368 | AB8: 55.061 | AC8: 55.4 | AD8: 56.474 | AF8: 47.253 | AG8: 41.035 | AH8: 49.394 | AI8: 45.37 | AJ8: 52.181 | AK8: 44.718 | AL8: 52.333 | AM8: 42.589 | AN8: 48.768 | AO8: 43.743 | AP8: 50.67 | AQ8: 44.985 | AR8: 55.562 | AS8: 47.95 | AT8: 57.654 | AU8: 53.126 | AV8: 61.471 | AW8: 53.051 | AX8: 62.458 | AY8: 50.977 | AZ8: 58.282 | BA8: 51.944 | BB8: 59.57 | BC8: 52.29
A9: Helios Software Group | B9: Commercial Operations | C9: CC-100 | D9: KPI-006 | E9: LTV | F9: €k | G9: 310 | H9: 319.408 | I9: 328.276 | J9: 336.122 | K9: 342.579 | L9: 347.431 | M9: 350.639 | N9: 352.346 | O9: 352.859 | P9: 352.617 | Q9: 352.141 | R9: 351.981 | S9: 352.648 | T9: 354.565 | U9: 358.016 | V9: 363.116 | W9: 369.8 | X9: 377.827 | Y9: 386.809 | Z9: 396.252 | AA9: 405.612 | AB9: 414.355 | AC9: 422.012 | AD9: 428.238 | AF9: 344.444 | AG9: 304.198 | AH9: 349.229 | AI9: 314.133 | AJ9: 372.369 | AK9: 318.744 | AL9: 389.599 | AM9: 335.568 | AN9: 375.382 | AO9: 329.548 | AP9: 382.762 | AQ9: 322.918 | AR9: 391.831 | AS9: 337.681 | AT9: 380.868 | AU9: 339.361 | AV9: 401.957 | AW9: 346.63 | AX9: 429.788 | AY9: 377.383 | AZ9: 431.502 | BA9: 387.247 | BB9: 458.709 | BC9: 392.879
A10: Helios Software Group | B10: Commercial Operations | C10: CC-100 | D10: KPI-007 | E10: Magic number | F10: x | G10: 0.72 | H10: 0.764 | I10: 0.803 | J10: 0.832 | K10: 0.848 | L10: 0.85 | M10: 0.84 | N10: 0.822 | O10: 0.801 | P10: 0.782 | Q10: 0.772 | R10: 0.773 | S10: 0.787 | T10: 0.815 | U10: 0.853 | V10: 0.897 | W10: 0.942 | X10: 0.981 | Y10: 1.011 | Z10: 1.028 | AA10: 1.031 | AB10: 1.022 | AC10: 1.004 | AD10: 0.983 | AF10: 0.758 | AG10: 0.721 | AH10: 0.864 | AI10: 0.77 | AJ10: 0.931 | AK10: 0.772 | AL10: 0.884 | AM10: 0.775 | AN10: 0.861 | AO10: 0.724 | AP10: 0.848 | AQ10: 0.702 | AR10: 0.829 | AS10: 0.769 | AT10: 0.917 | AU10: 0.831 | AV10: 1.035 | AW10: 0.892 | AX10: 1.064 | AY10: 0.97 | AZ10: 1.109 | BA10: 0.946 | BB10: 1.104 | BC10: 0.894
A12: Helios Software Group | B12: Customer Operations | C12: CC-210 | D12: KPI-010 | E12: Gross churn (logo) % | F12: % | G12: 0.021 | H12: 0.023 | I12: 0.025 | J12: 0.025 | K12: 0.024 | L12: 0.022 | M12: 0.02 | N12: 0.018 | O12: 0.017 | P12: 0.017 | Q12: 0.018 | R12: 0.02 | S12: 0.022 | T12: 0.024 | U12: 0.025 | V12: 0.025 | W12: 0.023 | X12: 0.021 | Y12: 0.019 | Z12: 0.017 | AA12: 0.017 | AB12: 0.018 | AC12: 0.02 | AD12: 0.022 | AF12: 0.023 | AG12: 0.021 | AH12: 0.027 | AI12: 0.023 | AJ12: 0.025 | AK12: 0.021 | AL12: 0.022 | AM12: 0.017 | AN12: 0.019 | AO12: 0.016 | AP12: 0.019 | AQ12: 0.019 | AR12: 0.024 | AS12: 0.022 | AT12: 0.027 | AU12: 0.022 | AV12: 0.024 | AW12: 0.02 | AX12: 0.02 | AY12: 0.016 | AZ12: 0.019 | BA12: 0.016 | BB12: 0.021 | BC12: 0.021
A13: Helios Software Group | B13: Customer Operations | C13: CC-210 | D13: KPI-011 | E13: Gross churn (revenue) % | F13: % | G13: 0.021 | H13: 0.02 | I13: 0.019 | J13: 0.017 | K13: 0.016 | L13: 0.014 | M13: 0.014 | N13: 0.014 | O13: 0.015 | P13: 0.016 | Q13: 0.018 | R13: 0.019 | S13: 0.02 | T13: 0.02 | U13: 0.02 | V13: 0.018 | W13: 0.016 | X13: 0.015 | Y13: 0.014 | Z13: 0.014 | AA13: 0.014 | AB13: 0.015 | AC13: 0.017 | AD13: 0.019 | AF13: 0.022 | AG13: 0.018 | AH13: 0.021 | AI13: 0.016 | AJ13: 0.017 | AK13: 0.013 | AL13: 0.015 | AM13: 0.013 | AN13: 0.016 | AO13: 0.015 | AP13: 0.019 | AQ13: 0.018 | AR13: 0.022 | AS13: 0.019 | AT13: 0.022 | AU13: 0.017 | AV13: 0.018 | AW13: 0.014 | AX13: 0.015 | AY13: 0.012 | AZ13: 0.016 | BA13: 0.015 | BB13: 0.018 | BC13: 0.017
A14: Helios Software Group | B14: Customer Operations | C14: CC-210 | D14: KPI-012 | E14: Net revenue retention % | F14: % | G14: 1.018 | H14: 1.02 | I14: 1.022 | J14: 1.024 | K14: 1.024 | L14: 1.023 | M14: 1.022 | N14: 1.02 | O14: 1.018 | P14: 1.015 | Q14: 1.013 | R14: 1.012 | S14: 1.012 | T14: 1.013 | U14: 1.014 | V14: 1.016 | W14: 1.019 | X14: 1.021 | Y14: 1.023 | Z14: 1.024 | AA14: 1.024 | AB14: 1.023 | AC14: 1.022 | AD14: 1.019 | AF14: 1.119 | AG14: 0.928 | AH14: 1.076 | AI14: 0.966 | AJ14: 1.101 | AK14: 0.948 | AL14: 1.123 | AM14: 0.927 | AN14: 1.071 | AO14: 0.958 | AP14: 1.09 | AQ14: 0.937 | AR14: 1.112 | AS14: 0.921 | AT14: 1.068 | AU14: 0.959 | AV14: 1.095 | AW14: 0.945 | AX14: 1.124 | AY14: 0.931 | AZ14: 1.078 | BA14: 0.965 | BB14: 1.098 | BC14: 0.944
A16: Helios Software Group | B16: Field Sales | C16: CC-310 | D16: FTE-310 | E16: Sales FTE | F16: FTE | G16: 34 | H16: 35 | I16: 36 | J16: 37 | K16: 38 | L16: 39 | M16: 41 | N16: 42 | O16: 43 | P16: 44 | Q16: 45 | R16: 46 | S16: 48 | T16: 49 | U16: 50 | V16: 51 | W16: 52 | X16: 53 | Y16: 55 | Z16: 56 | AA16: 57 | AB16: 58 | AC16: 59 | AD16: 60 | AF16: 36 | AG16: 33 | AH16: 38 | AI16: 35 | AJ16: 41 | AK16: 38 | AL16: 43 | AM16: 40 | AN16: 46 | AO16: 42 | AP16: 48 | AQ16: 44 | AR16: 50 | AS16: 46 | AT16: 53 | AU16: 48 | AV16: 55 | AW16: 51 | AX16: 58 | AY16: 53 | AZ16: 60 | BA16: 55 | BB16: 63 | BC16: 57
A17: Helios Software Group | B17: Marketing | C17: CC-340 | D17: FTE-340 | E17: Marketing FTE | F17: FTE | G17: 18 | H17: 18 | I17: 19 | J17: 19 | K17: 20 | L17: 21 | M17: 21 | N17: 22 | O17: 22 | P17: 23 | Q17: 24 | R17: 24 | S17: 25 | T17: 25 | U17: 26 | V17: 27 | W17: 27 | X17: 28 | Y17: 29 | Z17: 29 | AA17: 30 | AB17: 30 | AC17: 31 | AD17: 32 | AF17: 19 | AG17: 17 | AH17: 20 | AI17: 18 | AJ17: 21 | AK17: 20 | AL17: 23 | AM17: 21 | AN17: 24 | AO17: 22 | AP17: 25 | AQ17: 23 | AR17: 26 | AS17: 24 | AT17: 28 | AU17: 25 | AV17: 29 | AW17: 26 | AX17: 30 | AY17: 28 | AZ17: 32 | BA17: 29 | BB17: 33 | BC17: 30
... A26: Helios Software Group | B26: Executive | C26: CC-550 | D26: FTE-550 | E26: Executive FTE | F26: FTE | G26: 8 | H26: 9 | I26: 9 | J26: 12 | K26: 7 | L26: 8 | M26: 9 | N26: 9 | O26: 10 | P26: 10 | Q26: 10 | R26: 10 | S26: 10 | T26: 10 | U26: 11 | V26: 10 | W26: 11 | X26: 10 | Y26: 10 | Z26: 12 | AA26: 9 | AB26: 12 | AC26: 12 | AD26: 11 | AF26: 8 | AG26: 9 | AH26: 7 | AI26: 10 | AJ26: 9 | AK26: 4 | AL26: 9 | AM26: 8 | AN26: 9 | AO26: 9 | AP26: 10 | AQ26: 10 | AR26: 10 | AS26: 9 | AT26: 9 | AU26: 11 | AV26: 11 | AW26: 10 | AX26: 11 | AY26: 9 | AZ26: 11 | BA26: 11 | BB26: 12 | BC26: 10
A27: Helios Software Group | B27: People/HR | C27: CC-520 | D27: FTE-SUB | E27: Workforce register total | F27: FTE | G27: =SUM(G16:G26) -> 180 | H27: =SUM(H16:H26) -> 186 | I27: =SUM(I16:I26) -> 192 | J27: =SUM(J16:J26) -> 198 | K27: =SUM(K16:K26) -> 204 | L27: =SUM(L16:L26) -> 210 | M27: =SUM(M16:M26) -> 217 | N27: =SUM(N16:N26) -> 223 | ... AD27: =SUM(AD16:AD26) -> 320 | AF27: =SUM(AF16:AF26) -> 191 | AG27: =SUM(AG16:AG26) -> 177 | AH27: =SUM(AH16:AH26) -> 204 | AI27: =SUM(AI16:AI26) -> 188 | AJ27: =SUM(AJ16:AJ26) -> 216 | AK27: =SUM(AK16:AK26) -> 200 | AL27: =SUM(AL16:AL26) -> 230 | AM27: =SUM(AM16:AM26) -> 212 | ... BC27: =SUM(BC16:BC26) -> 304
A28: Helios Software Group | B28: People/HR | C28: CC-520 | D28: CTR-001 | E28: Contractors | F28: FTE | G28: 28 | H28: 30 | I28: 31 | J28: 33 | K28: 33 | L28: 33 | M28: 33 | N28: 33 | O28: 33 | P28: 34 | Q28: 35 | R28: 36 | S28: 38 | T28: 39 | U28: 41 | V28: 43 | W28: 44 | X28: 44 | Y28: 44 | Z28: 44 | AA28: 44 | AB28: 44 | AC28: 45 | AD28: 46 | AF28: 29.474 | AG28: 28.302 | AH28: 33.333 | AI28: 30.556 | AJ28: 36.264 | AK28: 30 | AL28: 34.737 | AM28: 31.132 | AN28: 35.484 | AO28: 31.481 | AP28: 38.462 | AQ28: 32.727 | AR28: 40 | AS28: 36.792 | AT28: 44.086 | AU28: 39.815 | AV28: 48.352 | AW28: 40 | AX28: 46.316 | AY28: 41.509 | AZ28: 47.312 | BA28: 40.741 | BB28: 49.451 | BC28: 41.818

Sheet EBITDA_Normalisation
A1: NetSuite Management Adjustment Export | B1: Helios Software Group — EBITDA normalisation register | E1: Positive values increase adjusted result
G2: ACTUAL — controller approved | AF2: BUDGET — approved operating plan
A3: Legal entity | B3: Department | C3: Cost centre | D3: Account code | E3: Account name | F3: Unit | G3: Jan-2024 | H3: Feb-2024 | I3: Mar-2024 | J3: Apr-2024 | K3: May-2024 | L3: Jun-2024 | M3: Jul-2024 | N3: Aug-2024 | O3: Sept-2024 | P3: Oct-2024 | Q3: Nov-2024 | R3: Dec-2024 | S3: Jan-2025 | T3: Feb-2025 | U3: Mar-2025 | V3: Apr-2025 | W3: May-2025 | X3: Jun-2025 | Y3: Jul-2025 | Z3: Aug-2025 | AA3: Sept-2025 | AB3: Oct-2025 | AC3: Nov-2025 | AD3: Dec-2025 | AF3: Jan-2024 | AG3: Feb-2024 | AH3: Mar-2024 | AI3: Apr-2024 | AJ3: May-2024 | AK3: Jun-2024 | AL3: Jul-2024 | AM3: Aug-2024 | AN3: Sept-2024 | AO3: Oct-2024 | AP3: Nov-2024 | AQ3: Dec-2024 | AR3: Jan-2025 | AS3: Feb-2025 | AT3: Mar-2025 | AU3: Apr-2025 | AV3: May-2025 | AW3: Jun-2025 | AX3: Jul-2025 | AY3: Aug-2025 | AZ3: Sept-2025 | BA3: Oct-2025 | BB3: Nov-2025 | BC3: Dec-2025
A4: Helios Software Ltd | B4: People/HR | C4: CC-520 | D4: 9000 | E4: Restructuring & redundancy | F4: EUR '000 | G4: 0 | H4: 0 | I4: 180 | J4: 95 | K4: 0 | L4: 0 | M4: 0 | N4: 0 | O4: 0 | P4: 0 | Q4: 0 | R4: 0 | S4: 0 | T4: 0 | U4: 0 | V4: 420 | W4: 165 | X4: 0 | Y4: 0 | Z4: 0 | AA4: 0 | AB4: 0 | AC4: 0 | AD4: 0 | AF4: 0 | AG4: 0 | AH4: 150 | AI4: 80 | AJ4: 0 | AK4: 0 | AL4: 0 | AM4: 0 | AN4: 0 | AO4: 0 | AP4: 0 | AQ4: 0 | AR4: 0 | AS4: 0 | AT4: 0 | AU4: 350 | AV4: 140 | AW4: 0 | AX4: 0 | AY4: 0 | AZ4: 0 | BA4: 0 | BB4: 0 | BC4: 0
A5: Helios Software Ltd | B5: People/HR | C5: CC-520 | D5: 9020 | E5: Share-based payments (IFRS 2) | F5: EUR '000 | G5: 118 | H5: 123 | I5: 128 | J5: 133 | K5: 138 | L5: 143 | M5: 148 | N5: 153 | O5: 158 | P5: 163 | Q5: 168 | R5: 173 | S5: 178 | T5: 183 | U5: 188 | V5: 193 | W5: 198 | X5: 203 | Y5: 208 | Z5: 213 | AA5: 218 | AB5: 223 | AC5: 228 | AD5: 233 | AF5: 110.3 | AG5: 115 | AH5: 119.6 | AI5: 124.3 | AJ5: 129 | AK5: 133.6 | AL5: 138.3 | AM5: 143 | AN5: 147.7 | AO5: 152.3 | AP5: 157 | AQ5: 161.7 | AR5: 166.4 | AS5: 171 | AT5: 175.7 | AU5: 180.4 | AV5: 185 | AW5: 189.7 | AX5: 194.4 | AY5: 199.1 | AZ5: 203.7 | BA5: 208.4 | BB5: 213.1 | BC5: 217.8
A6: Helios Software Ltd | B6: People/HR | C6: -- | D6: SUB | E6: People/HR adjustment register subtotal | F6: EUR '000 | G6: =SUM(G4:G5) -> 118 | H6: =SUM(H4:H5) -> 123 | I6: =SUM(I4:I5) -> 308 | J6: =SUM(J4:J5) -> 228 | K6: =SUM(K4:K5) -> 138 | L6: =SUM(L4:L5) -> 143 | M6: =SUM(M4:M5) -> 148 | N6: =SUM(N4:N5) -> 153 | ... AD6: =SUM(AD4:AD5) -> 233 | AF6: =SUM(AF4:AF5) -> 110.3 | AG6: =SUM(AG4:AG5) -> 115 | AH6: =SUM(AH4:AH5) -> 269.6 | AI6: =SUM(AI4:AI5) -> 204.3 | AJ6: =SUM(AJ4:AJ5) -> 129 | AK6: =SUM(AK4:AK5) -> 133.6 | AL6: =SUM(AL4:AL5) -> 138.3 | AM6: =SUM(AM4:AM5) -> 143 | ... BC6: =SUM(BC4:BC5) -> 217.8
A8: Helios Holdings Ltd | B8: Corporate Development | C8: CC-940 | D8: 9010 | E8: M&A/transaction fees | F8: EUR '000 | G8: 0 | H8: 65 | I8: 210 | J8: 340 | K8: 125 | L8: 0 | M8: 0 | N8: 85 | O8: 190 | P8: 0 | Q8: 0 | R8: 0 | S8: 0 | T8: 0 | U8: 0 | V8: 0 | W8: 75 | X8: 260 | Y8: 410 | Z8: 140 | AA8: 0 | AB8: 0 | AC8: 0 | AD8: 0 | AF8: 0 | AG8: 0 | AH8: 0 | AI8: 0 | AJ8: 0 | AK8: 0 | AL8: 0 | AM8: 0 | AN8: 0 | AO8: 0 | AP8: 0 | AQ8: 0 | AR8: 0 | AS8: 0 | AT8: 0 | AU8: 0 | AV8: 0 | AW8: 0 | AX8: 0 | AY8: 0 | AZ8: 0 | BA8: 0 | BB8: 0 | BC8: 0
A9: Helios Holdings Ltd | B9: Corporate Development | C9: CC-940 | D9: 9030 | E9: Sponsor monitoring fee | F9: EUR '000 | G9: 42 | H9: 42 | I9: 42 | J9: 42 | K9: 42 | L9: 42 | M9: 42 | N9: 42 | O9: 42 | P9: 42 | Q9: 42 | R9: 42 | S9: 42 | T9: 42 | U9: 42 | V9: 42 | W9: 42 | X9: 42 | Y9: 42 | Z9: 42 | AA9: 42 | AB9: 42 | AC9: 42 | AD9: 42 | AF9: 40 | AG9: 40 | AH9: 40 | AI9: 40 | AJ9: 40 | AK9: 40 | AL9: 40 | AM9: 40 | AN9: 40 | AO9: 40 | AP9: 40 | AQ9: 40 | AR9: 40 | AS9: 40 | AT9: 40 | AU9: 40 | AV9: 40 | AW9: 40 | AX9: 40 | AY9: 40 | AZ9: 40 | BA9: 40 | BB9: 40 | BC9: 40
A10: Helios Holdings Ltd | B10: Corporate Development | C10: -- | D10: SUB | E10: Corporate Development adjustment register subtotal | F10: EUR '000 | G10: =SUM(G8:G9) -> 42 | H10: =SUM(H8:H9) -> 107 | I10: =SUM(I8:I9) -> 252 | J10: =SUM(J8:J9) -> 382 | K10: =SUM(K8:K9) -> 167 | L10: =SUM(L8:L9) -> 42 | M10: =SUM(M8:M9) -> 42 | N10: =SUM(N8:N9) -> 127 | ... AD10: =SUM(AD8:AD9) -> 42 | AF10: =SUM(AF8:AF9) -> 40 | AG10: =SUM(AG8:AG9) -> 40 | AH10: =SUM(AH8:AH9) -> 40 | AI10: =SUM(AI8:AI9) -> 40 | AJ10: =SUM(AJ8:AJ9) -> 40 | AK10: =SUM(AK8:AK9) -> 40 | AL10: =SUM(AL8:AL9) -> 40 | AM10: =SUM(AM8:AM9) -> 40 | ... BC10: =SUM(BC8:BC9) -> 40
A12: Helios Software Ltd | B12: Legal & Compliance | C12: CC-540 | D12: 9040 | E12: Legal settlement (one-off) | F12: EUR '000 | G12: 0 | H12: 0 | I12: 0 | J12: 0 | K12: 0 | L12: 0 | M12: 0 | N12: 0 | O12: 0 | P12: 780 | Q12: 120 | R12: 0 | S12: 0 | T12: 0 | U12: 0 | V12: 0 | W12: 0 | X12: 0 | Y12: 0 | Z12: 0 | AA12: 0 | AB12: 0 | AC12: 0 | AD12: 0 | AF12: 0 | AG12: 0 | AH12: 0 | AI12: 0 | AJ12: 0 | AK12: 0 | AL12: 0 | AM12: 0 | AN12: 0 | AO12: 0 | AP12: 0 | AQ12: 0 | AR12: 0 | AS12: 0 | AT12: 0 | AU12: 0 | AV12: 0 | AW12: 0 | AX12: 0 | AY12: 0 | AZ12: 0 | BA12: 0 | BB12: 0 | BC12: 0
A13: Helios Software Ltd | B13: Legal & Compliance | C13: CC-540 | D13: 9070 | E13: Lease exit & dilapidation provision | F13: EUR '000 | G13: 0 | H13: 0 | I13: 0 | J13: 0 | K13: 0 | L13: 0 | M13: 0 | N13: 0 | O13: 0 | P13: 0 | Q13: 0 | R13: 0 | S13: 0 | T13: 0 | U13: 0 | V13: 210 | W13: 0 | X13: 0 | Y13: 0 | Z13: 0 | AA13: 0 | AB13: 0 | AC13: 0 | AD13: 0 | AF13: 0 | AG13: 0 | AH13: 0 | AI13: 0 | AJ13: 0 | AK13: 0 | AL13: 0 | AM13: 0 | AN13: 0 | AO13: 0 | AP13: 0 | AQ13: 0 | AR13: 0 | AS13: 0 | AT13: 0 | AU13: 190 | AV13: 0 | AW13: 0 | AX13: 0 | AY13: 0 | AZ13: 0 | BA13: 0 | BB13: 0 | BC13: 0
A14: Helios Software Ltd | B14: Legal & Compliance | C14: -- | D14: SUB | E14: Legal & Compliance adjustment register subtotal | F14: EUR '000 | G14: =SUM(G12:G13) -> 0 | H14: =SUM(H12:H13) -> 0 | I14: =SUM(I12:I13) -> 0 | J14: =SUM(J12:J13) -> 0 | K14: =SUM(K12:K13) -> 0 | L14: =SUM(L12:L13) -> 0 | M14: =SUM(M12:M13) -> 0 | N14: =SUM(N12:N13) -> 0 | ... AD14: =SUM(AD12:AD13) -> 0 | AF14: =SUM(AF12:AF13) -> 0 | AG14: =SUM(AG12:AG13) -> 0 | AH14: =SUM(AH12:AH13) -> 0 | AI14: =SUM(AI12:AI13) -> 0 | AJ14: =SUM(AJ12:AJ13) -> 0 | AK14: =SUM(AK12:AK13) -> 0 | AL14: =SUM(AL12:AL13) -> 0 | AM14: =SUM(AM12:AM13) -> 0 | ... BC14: =SUM(BC12:BC13) -> 0
A16: Helios Software Ltd | B16: IT & Facilities | C16: CC-530 | D16: 9050 | E16: ERP implementation costs | F16: EUR '000 | G16: 85 | H16: 88 | I16: 91 | J16: 94 | K16: 97 | L16: 100 | M16: 103 | N16: 106 | O16: 109 | P16: 112 | Q16: 115 | R16: 118 | S16: 121 | T16: 124 | U16: 127 | V16: 130 | W16: 35 | X16: 35 | Y16: 35 | Z16: 35 | AA16: 35 | AB16: 35 | AC16: 35 | AD16: 35 | AF16: 80.2 | AG16: 83 | AH16: 85.8 | AI16: 88.7 | AJ16: 91.5 | AK16: 94.3 | AL16: 97.2 | AM16: 100 | AN16: 102.8 | AO16: 105.7 | AP16: 108.5 | AQ16: 111.3 | AR16: 114.2 | AS16: 117 | AT16: 119.8 | AU16: 122.6 | AV16: 33 | AW16: 33 | AX16: 33 | AY16: 33 | AZ16: 33 | BA16: 33 | BB16: 33 | BC16: 33
A17: Helios Software Ltd | B17: IT & Facilities | C17: CC-530 | D17: 9080 | E17: Cyber incident response | F17: EUR '000 | G17: 0 | H17: 0 | I17: 0 | J17: 0 | K17: 0 | L17: 0 | M17: 145 | N17: 62 | O17: 0 | P17: 0 | Q17: 0 | R17: 0 | S17: 0 | T17: 0 | U17: 0 | V17: 0 | W17: 0 | X17: 0 | Y17: 0 | Z17: 0 | AA17: 0 | AB17: 0 | AC17: 0 | AD17: 0 | AF17: 0 | AG17: 0 | AH17: 0 | AI17: 0 | AJ17: 0 | AK17: 0 | AL17: 0 | AM17: 0 | AN17: 0 | AO17: 0 | AP17: 0 | AQ17: 0 | AR17: 0 | AS17: 0 | AT17: 0 | AU17: 0 | AV17: 0 | AW17: 0 | AX17: 0 | AY17: 0 | AZ17: 0 | BA17: 0 | BB17: 0 | BC17: 0
A18: Helios Software Ltd | B18: IT & Facilities | C18: -- | D18: SUB | E18: IT & Facilities adjustment register subtotal | F18: EUR '000 | G18: =SUM(G16:G17) -> 85 | H18: =SUM(H16:H17) -> 88 | I18: =SUM(I16:I17) -> 91 | J18: =SUM(J16:J17) -> 94 | K18: =SUM(K16:K17) -> 97 | L18: =SUM(L16:L17) -> 100 | M18: =SUM(M16:M17) -> 248 | N18: =SUM(N16:N17) -> 168 | ... AD18: =SUM(AD16:AD17) -> 35 | AF18: =SUM(AF16:AF17) -> 80.2 | AG18: =SUM(AG16:AG17) -> 83 | AH18: =SUM(AH16:AH17) -> 85.8 | AI18: =SUM(AI16:AI17) -> 88.7 | AJ18: =SUM(AJ16:AJ17) -> 91.5 | AK18: =SUM(AK16:AK17) -> 94.3 | AL18: =SUM(AL16:AL17) -> 97.2 | AM18: =SUM(AM16:AM17) -> 100 | ... BC18: =SUM(BC16:BC17) -> 33
A20: Helios Holdings Ltd | B20: Treasury | C20: CC-910 | D20: 9060 | E20: FX revaluation (non-cash) | F20: EUR '000 | G20: -25 | H20: 68.6 | I20: 6.8 | J20: -107.8 | K20: -85 | L20: 37.4 | M20: 56.2 | N20: -59.8 | O20: -118 | P20: -21.8 | Q20: 69.1 | R20: 3.8 | S20: -109.3 | T20: -82.5 | U20: 39.8 | V20: 54.5 | W20: -62.8 | X20: -117.3 | Y20: -18.6 | Z20: 69.5 | AA20: 0.7 | AB20: -110.7 | AC20: -79.9 | AD20: 42.1 | AF20: 0 | AG20: 0 | AH20: 0 | AI20: 0 | AJ20: 0 | AK20: 0 | AL20: 0 | AM20: 0 | AN20: 0 | AO20: 0 | AP20: 0 | AQ20: 0 | AR20: 0 | AS20: 0 | AT20: 0 | AU20: 0 | AV20: 0 | AW20: 0 | AX20: 0 | AY20: 0 | AZ20: 0 | BA20: 0 | BB20: 0 | BC20: 0
A21: Helios Holdings Ltd | B21: Treasury | C21: -- | D21: SUB | E21: Treasury adjustment register subtotal | F21: EUR '000 | G21: =SUM(G20:G20) -> -25 | H21: =SUM(H20:H20) -> 68.6 | I21: =SUM(I20:I20) -> 6.8 | J21: =SUM(J20:J20) -> -107.8 | K21: =SUM(K20:K20) -> -85 | L21: =SUM(L20:L20) -> 37.4 | M21: =SUM(M20:M20) -> 56.2 | N21: =SUM(N20:N20) -> -59.8 | ... AD21: =SUM(AD20:AD20) -> 42.1 | AF21: =SUM(AF20:AF20) -> 0 | AG21: =SUM(AG20:AG20) -> 0 | AH21: =SUM(AH20:AH20) -> 0 | AI21: =SUM(AI20:AI20) -> 0 | AJ21: =SUM(AJ20:AJ20) -> 0 | AK21: =SUM(AK20:AK20) -> 0 | AL21: =SUM(AL20:AL20) -> 0 | AM21: =SUM(AM20:AM20) -> 0 | ... BC21: =SUM(BC20:BC20) -> 0
A23: Helios Software Group | B23: Controller Review | C23: CC-999 | D23: CHK | E23: Controller-approved adjustment register total | F23: EUR '000 | G23: =G6+G10+G14+G18+G21 -> 220 | H23: =H6+H10+H14+H18+H21 -> 386.6 | I23: =I6+I10+I14+I18+I21 -> 657.8 | J23: =J6+J10+J14+J18+J21 -> 596.2 | K23: =K6+K10+K14+K18+K21 -> 317 | L23: =L6+L10+L14+L18+L21 -> 322.4 | M23: =M6+M10+M14+M18+M21 -> 494.2 | N23: =N6+N10+N14+N18+N21 -> 388.2 | ... AD23: =AD6+AD10+AD14+AD18+AD21 -> 352.1 | AF23: =AF6+AF10+AF14+AF18+AF21 -> 230.5 | AG23: =AG6+AG10+AG14+AG18+AG21 -> 238 | AH23: =AH6+AH10+AH14+AH18+AH21 -> 395.4 | AI23: =AI6+AI10+AI14+AI18+AI21 -> 333 | AJ23: =AJ6+AJ10+AJ14+AJ18+AJ21 -> 260.5 | AK23: =AK6+AK10+AK14+AK18+AK21 -> 267.9 | AL23: =AL6+AL10+AL14+AL18+AL21 -> 275.5 | AM23: =AM6+AM10+AM14+AM18+AM21 -> 283 | ... BC23: =BC6+BC10+BC14+BC18+BC21 -> 290.8

Sheet US_Entity_USD
A1: NetSuite Financial Report Export | B1: Helios Software Inc. — standalone ledger | E1: Reporting currency: USD
G2: ACTUAL — posted / controller adjustments | AF2: BUDGET — approved operating plan
A3: Legal entity | B3: Department | C3: Cost centre | D3: Account code | E3: Account name | F3: Unit | G3: Jan-2024 | H3: Feb-2024 | I3: Mar-2024 | J3: Apr-2024 | K3: May-2024 | L3: Jun-2024 | M3: Jul-2024 | N3: Aug-2024 | O3: Sept-2024 | P3: Oct-2024 | Q3: Nov-2024 | R3: Dec-2024 | S3: Jan-2025 | T3: Feb-2025 | U3: Mar-2025 | V3: Apr-2025 | W3: May-2025 | X3: Jun-2025 | Y3: Jul-2025 | Z3: Aug-2025 | AA3: Sept-2025 | AB3: Oct-2025 | AC3: Nov-2025 | AD3: Dec-2025 | AF3: Jan-2024 | AG3: Feb-2024 | AH3: Mar-2024 | AI3: Apr-2024 | AJ3: May-2024 | AK3: Jun-2024 | AL3: Jul-2024 | AM3: Aug-2024 | AN3: Sept-2024 | AO3: Oct-2024 | AP3: Nov-2024 | AQ3: Dec-2024 | AR3: Jan-2025 | AS3: Feb-2025 | AT3: Mar-2025 | AU3: Apr-2025 | AV3: May-2025 | AW3: Jun-2025 | AX3: Jul-2025 | AY3: Aug-2025 | AZ3: Sept-2025 | BA3: Oct-2025 | BB3: Nov-2025 | BC3: Dec-2025
A4: Helios Software Inc. | B4: Commercial - Americas | C4: CC-US120 | D4: 4010 | E4: SaaS Recurring–Americas | F4: USD $'000 | G4: 1430.8 | H4: 1480.1 | I4: 1546.2 | J4: 1567.7 | K4: 1637.4 | L4: 1693.1 | M4: 1666.4 | N4: 1672 | O4: 1782.7 | P4: 1843.5 | Q4: 1943.3 | R4: 2084.7 | S4: 1901.9 | T4: 1967.4 | U4: 2055.3 | V4: 2083.8 | W4: 2176.5 | X4: 2250.6 | Y4: 2215.1 | Z4: 2222.4 | AA4: 2369.6 | AB4: 2450.5 | AC4: 2583.1 | AD4: 2771.1 | AF4: 1362.6667 | AG4: 1396.3208 | AH4: 1662.5806 | AI4: 1704.0217 | AJ4: 1502.2018 | AK4: 1539.1818 | AL4: 1754.1053 | AM4: 1778.7234 | AN4: 1666.0748 | AO4: 1706.9444 | AP4: 2135.4945 | AQ4: 2316.3333 | AR4: 1811.3333 | AS4: 1856.0377 | AT4: 2210 | AU4: 2265 | AV4: 1996.789 | AW4: 2046 | AX4: 2331.6842 | AY4: 2364.2553 | AZ4: 2214.5794 | BA4: 2268.9815 | BB4: 2838.5714 | BC4: 3079
A5: Helios Software Inc. | B5: Commercial - Americas | C5: CC-US120 | D5: 4010 | E5: SaaS Recurring–Americas / mid-market | F5: USD $'000 | G5: 401.8 | H5: 415.6 | I5: 434.2 | J5: 440.2 | K5: 459.8 | L5: 475.5 | M5: 468 | N5: 469.5 | O5: 500.6 | P5: 517.7 | Q5: 545.7 | R5: 585.4 | S5: 534.1 | T5: 552.5 | U5: 577.2 | V5: 585.2 | W5: 611.2 | X5: 632 | Y5: 622 | Z5: 624.1 | AA5: 665.4 | AB5: 688.2 | AC5: 725.4 | AD5: 778.2 | AF5: 379.0566 | AG5: 388.41121 | AH5: 471.95652 | AI5: 483.73626 | AJ5: 418 | AK5: 452.85714 | AL5: 497.87234 | AM5: 504.83871 | AN5: 463.51852 | AO5: 474.95413 | AP5: 606.33333 | AQ5: 616.21053 | AR5: 503.86792 | AS5: 516.35514 | AT5: 627.3913 | AU5: 643.07692 | AV5: 555.63636 | AW5: 601.90476 | AX5: 661.70213 | AY5: 671.07527 | AZ5: 616.11111 | BA5: 631.37615 | BB5: 806 | BC5: 819.15789
A6: Helios Software Inc. | B6: Commercial - Americas | C6: CC-US120 | D6: 4100 | E6: Implementation & Onboarding / US | F6: USD $'000 | G6: 132.3 | H6: 135.8 | I6: 140.7 | J6: 141.6 | K6: 146.7 | L6: 150.5 | M6: 147 | N6: 146.3 | O6: 154.8 | P6: 158.8 | Q6: 166.1 | R6: 176.8 | S6: 160.1 | T6: 164.3 | U6: 170.3 | V6: 171.3 | W6: 177.5 | X6: 182.1 | Y6: 177.9 | Z6: 177 | AA6: 187.3 | AB6: 192.2 | AC6: 201 | AD6: 213.9 | AF6: 123.64486 | AG6: 125.74074 | AH6: 154.61538 | AI6: 157.33333 | AJ6: 139.71429 | AK6: 141.98113 | AL6: 158.06452 | AM6: 159.02174 | AN6: 142.01835 | AO6: 144.36364 | AP6: 174.84211 | AQ6: 188.08511 | AR6: 149.62617 | AS6: 152.12963 | AT6: 187.14286 | AU6: 190.33333 | AV6: 169.04762 | AW6: 171.79245 | AX6: 191.29032 | AY6: 192.3913 | AZ6: 171.83486 | BA6: 174.72727 | BB6: 211.57895 | BC6: 227.55319
A7: Helios Software Inc. | B7: Commercial - Americas | C7: CC-US120 | D7: 4110 | E7: Managed Services / US | F7: USD $'000 | G7: 86.2 | H7: 88.5 | I7: 91.7 | J7: 92.3 | K7: 95.6 | L7: 98.1 | M7: 95.8 | N7: 95.4 | O7: 100.9 | P7: 103.5 | Q7: 108.3 | R7: 115.3 | S7: 104.3 | T7: 107.1 | U7: 111 | V7: 111.7 | W7: 115.7 | X7: 118.7 | Y7: 115.9 | Z7: 115.4 | AA7: 122.1 | AB7: 125.3 | AC7: 131 | AD7: 139.5 | AF7: 79.814815 | AG7: 81.192661 | AH7: 101.88889 | AI7: 97.157895 | AJ7: 90.188679 | AK7: 91.682243 | AL7: 104.13043 | AM7: 104.83516 | AN7: 91.727273 | AO7: 98.571429 | AP7: 115.21277 | AQ7: 123.97849 | AR7: 96.574074 | AS7: 98.256881 | AT7: 123.33333 | AU7: 117.57895 | AV7: 109.15094 | AW7: 110.93458 | AX7: 125.97826 | AY7: 126.81319 | AZ7: 111 | BA7: 119.33333 | BB7: 139.3617 | BC7: 150
A8: Helios Software Inc. | B8: Commercial - Americas | C8: -- | D8: SUB | E8: US Commercial ledger subtotal | F8: USD $'000 | G8: =SUM(G4:G7) -> 2051.1 | H8: =SUM(H4:H7) -> 2120 | I8: =SUM(I4:I7) -> 2212.8 | J8: =SUM(J4:J7) -> 2241.8 | K8: =SUM(K4:K7) -> 2339.5 | L8: =SUM(L4:L7) -> 2417.2 | M8: =SUM(M4:M7) -> 2377.2 | N8: =SUM(N4:N7) -> 2383.2 | ... AD8: =SUM(AD4:AD7) -> 3902.7 | AF8: =SUM(AF4:AF7) -> 1945.1829 | AG8: =SUM(AG4:AG7) -> 1991.6654 | AH8: =SUM(AH4:AH7) -> 2391.0414 | AI8: =SUM(AI4:AI7) -> 2442.2492 | AJ8: =SUM(AJ4:AJ7) -> 2150.1048 | AK8: =SUM(AK4:AK7) -> 2225.7023 | AL8: =SUM(AL4:AL7) -> 2514.1726 | AM8: =SUM(AM4:AM7) -> 2547.419 | ... BC8: =SUM(BC4:BC7) -> 4275.7111
A10: Helios Software Inc. | B10: Cloud & Customer Operations | C10: CC-US220 | D10: 5000 | E10: Cloud hosting–AWS / US | F10: USD $'000 | G10: -285 | H10: -291.3 | I10: -297.7 | J10: -304.2 | K10: -310.9 | L10: -317.8 | M10: -324.8 | N10: -331.9 | O10: -339.2 | P10: -346.7 | Q10: -354.3 | R10: -362.1 | S10: -370 | T10: -378.2 | U10: -386.5 | V10: -395 | W10: -403.7 | X10: -412.6 | Y10: -421.7 | Z10: -430.9 | AA10: -440.4 | AB10: -450.1 | AC10: -460 | AD10: -470.1 | AF10: -271.42857 | AG10: -274.81132 | AH10: -320.10753 | AI10: -330.65217 | AJ10: -285.22936 | AK10: -288.90909 | AL10: -341.89474 | AM10: -353.08511 | AN10: -317.00935 | AO10: -321.01852 | AP10: -389.34066 | AQ10: -402.33333 | AR10: -352.38095 | AS10: -356.79245 | AT10: -415.5914 | AU10: -429.34783 | AV10: -370.36697 | AW10: -375.09091 | AX10: -443.89474 | AY10: -458.40426 | AZ10: -411.58879 | BA10: -416.75926 | BB10: -505.49451 | BC10: -522.33333
A11: Helios Software Inc. | B11: Cloud & Customer Operations | C11: CC-US220 | D11: 5010 | E11: Cloud hosting–Azure / US | F11: USD $'000 | G11: -74 | H11: -75.6 | I11: -77.3 | J11: -79 | K11: -80.7 | L11: -82.5 | M11: -84.3 | N11: -86.2 | O11: -88.1 | P11: -90 | Q11: -92 | R11: -94 | S11: -96.1 | T11: -98.2 | U11: -100.4 | V11: -102.6 | W11: -104.8 | X11: -107.1 | Y11: -109.5 | Z11: -111.9 | AA11: -114.4 | AB11: -116.9 | AC11: -119.4 | AD11: -122.1 | AF11: -69.811321 | AG11: -70.654206 | AH11: -84.021739 | AI11: -86.813187 | AJ11: -73.363636 | AK11: -78.571429 | AL11: -89.680851 | AM11: -92.688172 | AN11: -81.574074 | AO11: -82.568807 | AP11: -102.22222 | AQ11: -98.947368 | AR11: -90.660377 | AS11: -91.775701 | AT11: -109.13043 | AU11: -112.74725 | AV11: -95.272727 | AW11: -102 | AX11: -116.48936 | AY11: -120.32258 | AZ11: -105.92593 | BA11: -107.24771 | BB11: -132.66667 | BC11: -128.52632
A12: Helios Software Inc. | B12: Cloud & Customer Operations | C12: CC-US220 | D12: 5100 | E12: 3rd-party licences / US | F12: USD $'000 | G12: -92 | H12: -94 | I12: -96.1 | J12: -98.2 | K12: -100.4 | L12: -102.6 | M12: -104.8 | N12: -107.1 | O12: -109.5 | P12: -111.9 | Q12: -114.4 | R12: -116.9 | S12: -119.5 | T12: -122.1 | U12: -124.8 | V12: -127.5 | W12: -130.3 | X12: -133.2 | Y12: -136.1 | Z12: -139.1 | AA12: -142.2 | AB12: -145.3 | AC12: -148.5 | AD12: -151.8 | AF12: -85.981308 | AG12: -87.037037 | AH12: -105.6044 | AI12: -109.11111 | AJ12: -95.619048 | AK12: -96.792453 | AL12: -112.68817 | AM12: -116.41304 | AN12: -100.45872 | AO12: -101.72727 | AP12: -120.42105 | AQ12: -124.3617 | AR12: -111.68224 | AS12: -113.05556 | AT12: -137.14286 | AU12: -141.66667 | AV12: -124.09524 | AW12: -125.66038 | AX12: -146.34409 | AY12: -151.19565 | AZ12: -130.45872 | BA12: -132.09091 | BB12: -156.31579 | BC12: -161.48936
A13: Helios Software Inc. | B13: Cloud & Customer Operations | C13: CC-US220 | D13: 5200 | E13: Support salaries / US | F13: USD $'000 | G13: -215 | H13: -219.1 | I13: -223.2 | J13: -227.5 | K13: -231.8 | L13: -236.2 | M13: -240.7 | N13: -245.3 | O13: -249.9 | P13: -254.7 | Q13: -259.5 | R13: -264.5 | S13: -269.5 | T13: -274.6 | U13: -279.8 | V13: -285.1 | W13: -290.6 | X13: -296.1 | Y13: -301.7 | Z13: -307.4 | AA13: -313.3 | AB13: -319.2 | AC13: -325.3 | AD13: -331.5 | AF13: -199.07407 | AG13: -201.00917 | AH13: -248 | AI13: -239.47368 | AJ13: -218.67925 | AK13: -220.74766 | AL13: -261.63043 | AM13: -269.56044 | AN13: -227.18182 | AO13: -242.57143 | AP13: -276.06383 | AQ13: -284.4086 | AR13: -249.53704 | AS13: -251.92661 | AT13: -310.88889 | AU13: -300.10526 | AV13: -274.15094 | AW13: -276.72897 | AX13: -327.93478 | AY13: -337.8022 | AZ13: -284.81818 | BA13: -304 | BB13: -346.06383 | BC13: -356.45161
A14: Helios Software Inc. | B14: Cloud & Customer Operations | C14: CC-US220 | D14: 5210 | E14: Support contractors / US | F14: USD $'000 | G14: -38 | H14: -38.5 | I14: -38.9 | J14: -39.4 | K14: -39.9 | L14: -40.3 | M14: -40.8 | N14: -41.3 | O14: -41.8 | P14: -42.3 | Q14: -42.8 | R14: -43.3 | S14: -43.8 | T14: -44.4 | U14: -44.9 | V14: -45.4 | W14: -46 | X14: -46.5 | Y14: -47.1 | Z14: -47.7 | AA14: -48.2 | AB14: -48.8 | AC14: -49.4 | AD14: -50 | AF14: -34.862385 | AG14: -35 | AH14: -40.947368 | AI14: -41.914894 | AJ14: -37.28972 | AK14: -37.314815 | AL14: -44.835165 | AM14: -45.888889 | AN14: -39.809524 | AO14: -39.90566 | AP14: -46.021505 | AQ14: -47.065217 | AR14: -40.183486 | AS14: -40.363636 | AT14: -47.263158 | AU14: -48.297872 | AV14: -42.990654 | AW14: -43.055556 | AX14: -51.758242 | AY14: -53 | AZ14: -45.904762 | BA14: -46.037736 | BB14: -53.11828 | BC14: -54.347826
A15: Helios Software Inc. | B15: Cloud & Customer Operations | C15: -- | D15: SUB | E15: US Cloud & Customer Ops ledger subtotal | F15: USD $'000 | G15: =SUM(G10:G14) -> -704 | H15: =SUM(H10:H14) -> -718.5 | I15: =SUM(I10:I14) -> -733.2 | J15: =SUM(J10:J14) -> -748.3 | K15: =SUM(K10:K14) -> -763.7 | L15: =SUM(L10:L14) -> -779.4 | M15: =SUM(M10:M14) -> -795.4 | N15: =SUM(N10:N14) -> -811.8 | ... AD15: =SUM(AD10:AD14) -> -1125.5 | AF15: =SUM(AF10:AF14) -> -661.15766 | AG15: =SUM(AG10:AG14) -> -668.51174 | AH15: =SUM(AH10:AH14) -> -798.68103 | AI15: =SUM(AI10:AI14) -> -807.96505 | AJ15: =SUM(AJ10:AJ14) -> -710.18101 | AK15: =SUM(AK10:AK14) -> -722.33545 | AL15: =SUM(AL10:AL14) -> -850.72936 | AM15: =SUM(AM10:AM14) -> -877.63565 | ... BC15: =SUM(BC10:BC14) -> -1223.1484
A17: Helios Software Inc. | B17: Field Sales - Americas | C17: CC-US320 | D17: 6000 | E17: Sales salaries / US | F17: USD $'000 | G17: -395 | H17: -402.5 | I17: -410.2 | J17: -417.9 | K17: -425.9 | L17: -434 | M17: -442.2 | N17: -450.6 | O17: -459.2 | P17: -467.9 | Q17: -476.8 | R17: -485.9 | S17: -495.1 | T17: -504.5 | U17: -514.1 | V17: -523.9 | W17: -533.8 | X17: -543.9 | Y17: -554.3 | Z17: -564.8 | AA17: -575.5 | AB17: -586.5 | AC17: -597.6 | AD17: -609 | AF17: -372.64151 | AG17: -376.16822 | AH17: -445.86957 | AI17: -459.23077 | AJ17: -387.18182 | AK17: -413.33333 | AL17: -470.42553 | AM17: -484.51613 | AN17: -425.18519 | AO17: -429.26606 | AP17: -529.77778 | AQ17: -511.47368 | AR17: -467.07547 | AS17: -471.49533 | AT17: -558.80435 | AU17: -575.71429 | AV17: -485.27273 | AW17: -518 | AX17: -589.68085 | AY17: -607.31183 | AZ17: -532.87037 | BA17: -538.07339 | BB17: -664 | BC17: -641.05263
A18: Helios Software Inc. | B18: Field Sales - Americas | C18: CC-US320 | D18: 6010 | E18: Sales commissions / US | F18: USD $'000 | G18: -142 | H18: -143.7 | I18: -145.4 | J18: -147.2 | K18: -148.9 | L18: -150.7 | M18: -152.5 | N18: -154.4 | O18: -156.2 | P18: -158.1 | Q18: -160 | R18: -161.9 | S18: -163.9 | T18: -165.8 | U18: -167.8 | V18: -169.8 | W18: -171.9 | X18: -173.9 | Y18: -176 | Z18: -178.1 | AA18: -180.3 | AB18: -182.4 | AC18: -184.6 | AD18: -186.8 | AF18: -132.71028 | AG18: -133.05556 | AH18: -159.78022 | AI18: -163.55556 | AJ18: -141.80952 | AK18: -142.16981 | AL18: -163.97849 | AM18: -167.82609 | AN18: -143.30275 | AO18: -143.72727 | AP18: -168.42105 | AQ18: -172.23404 | AR18: -153.17757 | AS18: -153.51852 | AT18: -184.3956 | AU18: -188.66667 | AV18: -163.71429 | AW18: -164.0566 | AX18: -189.24731 | AY18: -193.58696 | AZ18: -165.41284 | BA18: -165.81818 | BB18: -194.31579 | BC18: -198.7234
A19: Helios Software Inc. | B19: Field Sales - Americas | C19: CC-US320 | D19: 6020 | E19: Marketing programs / US | F19: USD $'000 | G19: -112.7 | H19: -115.2 | I19: -119 | J19: -119.2 | K19: -123 | L19: -125.7 | M19: -122.3 | N19: -121.3 | O19: -127.8 | P19: -130.6 | Q19: -136 | R19: -144.2 | S19: -130 | T19: -132.9 | U19: -137.3 | V19: -137.5 | W19: -142 | X19: -145.1 | Y19: -141.1 | Z19: -139.9 | AA19: -147.4 | AB19: -150.7 | AC19: -157 | AD19: -166.4 | AF19: -104.35185 | AG19: -105.68807 | AH19: -132.22222 | AI19: -125.47368 | AJ19: -116.03774 | AK19: -117.47664 | AL19: -132.93478 | AM19: -133.2967 | AN19: -116.18182 | AO19: -124.38095 | AP19: -144.68085 | AQ19: -155.05376 | AR19: -120.37037 | AS19: -121.92661 | AT19: -152.55556 | AU19: -144.73684 | AV19: -133.96226 | AW19: -135.60748 | AX19: -153.36957 | AY19: -153.73626 | AZ19: -134 | BA19: -143.52381 | BB19: -167.02128 | BC19: -178.92473
A20: Helios Software Inc. | B20: Field Sales - Americas | C20: CC-US320 | D20: 6030 | E20: Marketing salaries / US | F20: USD $'000 | G20: -98 | H20: -99.9 | I20: -101.8 | J20: -103.7 | K20: -105.7 | L20: -107.7 | M20: -109.7 | N20: -111.8 | O20: -113.9 | P20: -116.1 | Q20: -118.3 | R20: -120.5 | S20: -122.8 | T20: -125.2 | U20: -127.5 | V20: -130 | W20: -132.4 | X20: -135 | Y20: -137.5 | Z20: -140.1 | AA20: -142.8 | AB20: -145.5 | AC20: -148.3 | AD20: -151.1 | AF20: -89.908257 | AG20: -90.818182 | AH20: -107.15789 | AI20: -110.31915 | AJ20: -98.785047 | AK20: -99.722222 | AL20: -120.54945 | AM20: -124.22222 | AN20: -108.47619 | AO20: -109.5283 | AP20: -127.2043 | AQ20: -130.97826 | AR20: -112.66055 | AS20: -113.81818 | AT20: -134.21053 | AU20: -138.29787 | AV20: -123.73832 | AW20: -125 | AX20: -151.0989 | AY20: -155.66667 | AZ20: -136 | BA20: -137.26415 | BB20: -159.46237 | BC20: -164.23913
A21: Helios Software Inc. | B21: Field Sales - Americas | C21: CC-US320 | D21: 6050 | E21: Sales travel & entertainment / US | F21: USD $'000 | G21: -43.1 | H21: -44.1 | I21: -45.5 | J21: -45.6 | K21: -47.1 | L21: -48.1 | M21: -46.8 | N21: -46.4 | O21: -48.9 | P21: -50 | Q21: -52.1 | R21: -55.2 | S21: -49.8 | T21: -50.9 | U21: -52.5 | V21: -52.6 | W21: -54.3 | X21: -55.5 | Y21: -54 | Z21: -53.5 | AA21: -56.4 | AB21: -57.7 | AC21: -60.1 | AD21: -63.7 | AF21: -39.181818 | AG21: -42 | AH21: -48.404255 | AI21: -49.032258 | AJ21: -43.611111 | AK21: -44.12844 | AL21: -52 | AM21: -48.842105 | AN21: -46.132075 | AO21: -46.728972 | AP21: -56.630435 | AQ21: -60.659341 | AR21: -45.272727 | AS21: -48.47619 | AT21: -55.851064 | AU21: -56.55914 | AV21: -50.277778 | AW21: -50.917431 | AX21: -60 | AY21: -56.315789 | AZ21: -53.207547 | BA21: -53.925234 | BB21: -65.326087 | BC21: -70
A22: Helios Software Inc. | B22: Field Sales - Americas | C22: -- | D22: SUB | E22: US Go-to-market ledger subtotal | F22: USD $'000 | G22: =SUM(G17:G21) -> -790.8 | H22: =SUM(H17:H21) -> -805.4 | I22: =SUM(I17:I21) -> -821.9 | J22: =SUM(J17:J21) -> -833.6 | K22: =SUM(K17:K21) -> -850.6 | L22: =SUM(L17:L21) -> -866.2 | M22: =SUM(M17:M21) -> -873.5 | N22: =SUM(N17:N21) -> -884.5 | ... AD22: =SUM(AD17:AD21) -> -1177 | AF22: =SUM(AF17:AF21) -> -738.79372 | AG22: =SUM(AG17:AG21) -> -747.73004 | AH22: =SUM(AH17:AH21) -> -893.43416 | AI22: =SUM(AI17:AI21) -> -907.61142 | AJ22: =SUM(AJ17:AJ21) -> -787.42524 | AK22: =SUM(AK17:AK21) -> -816.83044 | AL22: =SUM(AL17:AL21) -> -939.88826 | AM22: =SUM(AM17:AM21) -> -958.70325 | ... BC22: =SUM(BC17:BC21) -> -1252.9399
A24: Helios Software Inc. | B24: Engineering - Americas | C24: CC-US410 | D24: 6100 | E24: Engineering salaries / US | F24: USD $'000 | G24: -220 | H24: -224.2 | I24: -228.4 | J24: -232.8 | K24: -237.2 | L24: -241.7 | M24: -246.3 | N24: -251 | O24: -255.8 | P24: -260.6 | Q24: -265.6 | R24: -270.6 | S24: -275.7 | T24: -281 | U24: -286.3 | V24: -291.8 | W24: -297.3 | X24: -303 | Y24: -308.7 | Z24: -314.6 | AA24: -320.6 | AB24: -326.6 | AC24: -332.9 | AD24: -339.2 | AF24: -205.60748 | AG24: -207.59259 | AH24: -250.98901 | AI24: -258.66667 | AJ24: -225.90476 | AK24: -228.01887 | AL24: -264.83871 | AM24: -272.82609 | AN24: -234.6789 | AO24: -236.90909 | AP24: -279.57895 | AQ24: -287.87234 | AR24: -257.66355 | AS24: -260.18519 | AT24: -314.61538 | AU24: -324.22222 | AV24: -283.14286 | AW24: -285.84906 | AX24: -331.93548 | AY24: -341.95652 | AZ24: -294.12844 | BA24: -296.90909 | BB24: -350.42105 | BC24: -360.85106
A25: Helios Software Inc. | B25: Engineering - Americas | C25: CC-US410 | D25: 6110 | E25: Product salaries / US | F25: USD $'000 | G25: -84 | H25: -85.6 | I25: -87.2 | J25: -88.9 | K25: -90.6 | L25: -92.3 | M25: -94 | N25: -95.8 | O25: -97.7 | P25: -99.5 | Q25: -101.4 | R25: -103.3 | S25: -105.3 | T25: -107.3 | U25: -109.3 | V25: -111.4 | W25: -113.5 | X25: -115.7 | Y25: -117.9 | Z25: -120.1 | AA25: -122.4 | AB25: -124.7 | AC25: -127.1 | AD25: -129.5 | AF25: -77.777778 | AG25: -78.53211 | AH25: -96.888889 | AI25: -93.578947 | AJ25: -85.471698 | AK25: -86.261682 | AL25: -102.17391 | AM25: -105.27473 | AN25: -88.818182 | AO25: -94.761905 | AP25: -107.87234 | AQ25: -111.07527 | AR25: -97.5 | AS25: -98.440367 | AT25: -121.44444 | AU25: -117.26316 | AV25: -107.07547 | AW25: -108.13084 | AX25: -128.15217 | AY25: -131.97802 | AZ25: -111.27273 | BA25: -118.7619 | BB25: -135.21277 | BC25: -139.24731
A26: Helios Software Inc. | B26: Engineering - Americas | C26: CC-US410 | D26: 6130 | E26: Engineering software & tooling / US | F26: USD $'000 | G26: -31 | H26: -31.4 | I26: -31.7 | J26: -32.1 | K26: -32.5 | L26: -32.9 | M26: -33.3 | N26: -33.7 | O26: -34.1 | P26: -34.5 | Q26: -34.9 | R26: -35.3 | S26: -35.8 | T26: -36.2 | U26: -36.6 | V26: -37.1 | W26: -37.5 | X26: -38 | Y26: -38.4 | Z26: -38.9 | AA26: -39.4 | AB26: -39.8 | AC26: -40.3 | AD26: -40.8 | AF26: -28.440367 | AG26: -28.545455 | AH26: -33.368421 | AI26: -34.148936 | AJ26: -30.373832 | AK26: -30.462963 | AL26: -36.593407 | AM26: -37.444444 | AN26: -32.47619 | AO26: -32.54717 | AP26: -37.526882 | AQ26: -38.369565 | AR26: -32.844037 | AS26: -32.909091 | AT26: -38.526316 | AU26: -39.468085 | AV26: -35.046729 | AW26: -35.185185 | AX26: -42.197802 | AY26: -43.222222 | AZ26: -37.52381 | BA26: -37.54717 | BB26: -43.333333 | BC26: -44.347826
A27: Helios Software Inc. | B27: Engineering - Americas | C27: -- | D27: SUB | E27: US Engineering ledger subtotal | F27: USD $'000 | G27: =SUM(G24:G26) -> -335 | H27: =SUM(H24:H26) -> -341.2 | I27: =SUM(I24:I26) -> -347.3 | J27: =SUM(J24:J26) -> -353.8 | K27: =SUM(K24:K26) -> -360.3 | L27: =SUM(L24:L26) -> -366.9 | M27: =SUM(M24:M26) -> -373.6 | N27: =SUM(N24:N26) -> -380.5 | ... AD27: =SUM(AD24:AD26) -> -509.5 | AF27: =SUM(AF24:AF26) -> -311.82562 | AG27: =SUM(AG24:AG26) -> -314.67016 | AH27: =SUM(AH24:AH26) -> -381.24632 | AI27: =SUM(AI24:AI26) -> -386.39455 | AJ27: =SUM(AJ24:AJ26) -> -341.75029 | AK27: =SUM(AK24:AK26) -> -344.74351 | AL27: =SUM(AL24:AL26) -> -403.60603 | AM27: =SUM(AM24:AM26) -> -415.54526 | ... BC27: =SUM(BC24:BC26) -> -544.4462
A29: Helios Software Inc. | B29: Corporate Services - US | C29: CC-US500 | D29: 6200 | E29: Finance / US | F29: USD $'000 | G29: -76 | H29: -77.4 | I29: -78.9 | J29: -80.4 | K29: -81.9 | L29: -83.5 | M29: -85.1 | N29: -86.7 | O29: -88.4 | P29: -90 | Q29: -91.7 | R29: -93.5 | S29: -95.3 | T29: -97.1 | U29: -98.9 | V29: -100.8 | W29: -102.7 | X29: -104.7 | Y29: -106.6 | Z29: -108.7 | AA29: -110.7 | AB29: -112.8 | AC29: -115 | AD29: -117.2 | AF29: -71.698113 | AG29: -72.336449 | AH29: -85.76087 | AI29: -88.351648 | AJ29: -74.454545 | AK29: -79.52381 | AL29: -90.531915 | AM29: -93.225806 | AN29: -81.851852 | AO29: -82.568807 | AP29: -101.88889 | AQ29: -98.421053 | AR29: -89.90566 | AS29: -90.747664 | AT29: -107.5 | AU29: -110.76923 | AV29: -93.363636 | AW29: -99.714286 | AX29: -113.40426 | AY29: -116.88172 | AZ29: -102.5 | BA29: -103.48624 | BB29: -127.77778 | BC29: -123.36842
A30: Helios Software Inc. | B30: Corporate Services - US | C30: CC-US500 | D30: 6210 | E30: People/HR / US | F30: USD $'000 | G30: -43 | H30: -43.8 | I30: -44.6 | J30: -45.5 | K30: -46.4 | L30: -47.2 | M30: -48.1 | N30: -49.1 | O30: -50 | P30: -50.9 | Q30: -51.9 | R30: -52.9 | S30: -53.9 | T30: -54.9 | U30: -56 | V30: -57 | W30: -58.1 | X30: -59.2 | Y30: -60.3 | Z30: -61.5 | AA30: -62.7 | AB30: -63.8 | AC30: -65.1 | AD30: -66.3 | AF30: -40.186916 | AG30: -40.555556 | AH30: -49.010989 | AI30: -50.555556 | AJ30: -44.190476 | AK30: -44.528302 | AL30: -51.72043 | AM30: -53.369565 | AN30: -45.87156 | AO30: -46.272727 | AP30: -54.631579 | AQ30: -56.276596 | AR30: -50.373832 | AS30: -50.833333 | AT30: -61.538462 | AU30: -63.333333 | AV30: -55.333333 | AW30: -55.849057 | AX30: -64.83871 | AY30: -66.847826 | AZ30: -57.522936 | BA30: -58 | BB30: -68.526316 | BC30: -70.531915
A31: Helios Software Inc. | B31: Corporate Services - US | C31: CC-US500 | D31: 6220 | E31: IT & facilities / US | F31: USD $'000 | G31: -58 | H31: -58.7 | I31: -59.4 | J31: -60.1 | K31: -60.8 | L31: -61.6 | M31: -62.3 | N31: -63.1 | O31: -63.8 | P31: -64.6 | Q31: -65.3 | R31: -66.1 | S31: -66.9 | T31: -67.7 | U31: -68.5 | V31: -69.4 | W31: -70.2 | X31: -71 | Y31: -71.9 | Z31: -72.8 | AA31: -73.6 | AB31: -74.5 | AC31: -75.4 | AD31: -76.3 | AF31: -53.703704 | AG31: -53.853211 | AH31: -66 | AI31: -63.263158 | AJ31: -57.358491 | AK31: -57.570093 | AL31: -67.717391 | AM31: -69.340659 | AN31: -58 | AO31: -61.52381 | AP31: -69.468085 | AQ31: -71.075269 | AR31: -61.944444 | AS31: -62.110092 | AT31: -76.111111 | AU31: -73.052632 | AV31: -66.226415 | AW31: -66.35514 | AX31: -78.152174 | AY31: -80 | AZ31: -66.909091 | BA31: -70.952381 | BB31: -80.212766 | BC31: -82.043011
A32: Helios Software Inc. | B32: Corporate Services - US | C32: CC-US500 | D32: 6230 | E32: Legal & compliance / US | F32: USD $'000 | G32: -28.4 | H32: -29.1 | I32: -30 | J32: -30.1 | K32: -31 | L32: -31.7 | M32: -30.8 | N32: -30.6 | O32: -32.2 | P32: -32.9 | Q32: -34.3 | R32: -36.4 | S32: -32.8 | T32: -33.5 | U32: -34.6 | V32: -34.7 | W32: -35.8 | X32: -36.6 | Y32: -35.6 | Z32: -35.3 | AA32: -37.2 | AB32: -38 | AC32: -39.6 | AD32: -42 | AF32: -26.055046 | AG32: -26.454545 | AH32: -31.578947 | AI32: -32.021277 | AJ32: -28.971963 | AK32: -29.351852 | AL32: -33.846154 | AM32: -34 | AN32: -30.666667 | AO32: -31.037736 | AP32: -36.88172 | AQ32: -39.565217 | AR32: -30.091743 | AS32: -30.454545 | AT32: -36.421053 | AU32: -36.914894 | AV32: -33.457944 | AW32: -33.888889 | AX32: -39.120879 | AY32: -39.222222 | AZ32: -35.428571 | BA32: -35.849057 | BB32: -42.580645 | BC32: -45.652174
A33: Helios Software Inc. | B33: Corporate Services - US | C33: CC-US500 | D33: 6240 | E33: Executive / US | F33: USD $'000 | G33: -66 | H33: -67.3 | I33: -68.5 | J33: -69.8 | K33: -71.2 | L33: -72.5 | M33: -73.9 | N33: -75.3 | O33: -76.7 | P33: -78.2 | Q33: -79.7 | R33: -81.2 | S33: -82.7 | T33: -84.3 | U33: -85.9 | V33: -87.5 | W33: -89.2 | X33: -90.9 | Y33: -92.6 | Z33: -94.4 | AA33: -96.2 | AB33: -98 | AC33: -99.9 | AD33: -101.8 | AF33: -60 | AG33: -64.095238 | AH33: -72.87234 | AI33: -75.053763 | AJ33: -65.925926 | AK33: -66.513761 | AL33: -82.111111 | AM33: -79.263158 | AN33: -72.358491 | AO33: -73.084112 | AP33: -86.630435 | AQ33: -89.230769 | AR33: -75.181818 | AS33: -80.285714 | AT33: -91.382979 | AU33: -94.086022 | AV33: -82.592593 | AW33: -83.394495 | AX33: -102.88889 | AY33: -99.368421 | AZ33: -90.754717 | BA33: -91.588785 | BB33: -108.58696 | BC33: -111.86813
A34: Helios Software Inc. | B34: Corporate Services - US | C34: -- | D34: SUB | E34: US Corporate Services ledger subtotal | F34: USD $'000 | G34: =SUM(G29:G33) -> -271.4 | H34: =SUM(H29:H33) -> -276.3 | I34: =SUM(I29:I33) -> -281.4 | J34: =SUM(J29:J33) -> -285.9 | K34: =SUM(K29:K33) -> -291.3 | L34: =SUM(L29:L33) -> -296.5 | M34: =SUM(M29:M33) -> -300.2 | N34: =SUM(N29:N33) -> -304.8 | ... AD34: =SUM(AD29:AD33) -> -403.6 | AF34: =SUM(AF29:AF33) -> -251.64378 | AG34: =SUM(AG29:AG33) -> -257.295 | AH34: =SUM(AH29:AH33) -> -305.22315 | AI34: =SUM(AI29:AI33) -> -309.2454 | AJ34: =SUM(AJ29:AJ33) -> -270.9014 | AK34: =SUM(AK29:AK33) -> -277.48782 | AL34: =SUM(AL29:AL33) -> -325.927 | AM34: =SUM(AM29:AM33) -> -329.19919 | ... BC34: =SUM(BC29:BC33) -> -433.46365
A36: Helios Software Inc. | B36: Fixed Assets & Tax - US | C36: CC-US900 | D36: 7000 | E36: Deprec–equipment / US | F36: USD $'000 | G36: -18 | H36: -18.2 | I36: -18.4 | J36: -18.5 | K36: -18.7 | L36: -18.9 | M36: -19.1 | N36: -19.3 | O36: -19.5 | P36: -19.7 | Q36: -19.9 | R36: -20.1 | S36: -20.3 | T36: -20.5 | U36: -20.7 | V36: -20.9 | W36: -21.1 | X36: -21.3 | Y36: -21.5 | Z36: -21.7 | AA36: -22 | AB36: -22.2 | AC36: -22.4 | AD36: -22.6 | AF36: -16.82243 | AG36: -16.851852 | AH36: -20.21978 | AI36: -20.555556 | AJ36: -17.809524 | AK36: -17.830189 | AL36: -20.537634 | AM36: -20.978261 | AN36: -17.889908 | AO36: -17.909091 | AP36: -20.947368 | AQ36: -21.382979 | AR36: -18.971963 | AS36: -18.981481 | AT36: -22.747253 | AU36: -23.222222 | AV36: -20.095238 | AW36: -20.09434 | AX36: -23.11828 | AY36: -23.586957 | AZ36: -20.183486 | BA36: -20.181818 | BB36: -23.578947 | BC36: -24.042553
A37: Helios Software Inc. | B37: Fixed Assets & Tax - US | C37: CC-US900 | D37: 7100 | E37: Amort–intangibles / US | F37: USD $'000 | G37: -11 | H37: -11.1 | I37: -11.2 | J37: -11.3 | K37: -11.4 | L37: -11.6 | M37: -11.7 | N37: -11.8 | O37: -11.9 | P37: -12 | Q37: -12.2 | R37: -12.3 | S37: -12.4 | T37: -12.5 | U37: -12.6 | V37: -12.8 | W37: -12.9 | X37: -13 | Y37: -13.2 | Z37: -13.3 | AA37: -13.4 | AB37: -13.6 | AC37: -13.7 | AD37: -13.8 | AF37: -10.185185 | AG37: -10.183486 | AH37: -12.444444 | AI37: -11.894737 | AJ37: -10.754717 | AK37: -10.841121 | AL37: -12.717391 | AM37: -12.967033 | AN37: -10.818182 | AO37: -11.428571 | AP37: -12.978723 | AQ37: -13.225806 | AR37: -11.481481 | AS37: -11.46789 | AT37: -14 | AU37: -13.473684 | AV37: -12.169811 | AW37: -12.149533 | AX37: -14.347826 | AY37: -14.615385 | AZ37: -12.181818 | BA37: -12.952381 | BB37: -14.574468 | BC37: -14.83871
A38: Helios Software Inc. | B38: Fixed Assets & Tax - US | C38: CC-US900 | D38: 7500 | E38: Net interest–senior / US allocation | F38: USD $'000 | G38: -24 | H38: -23.9 | I38: -23.9 | J38: -23.8 | K38: -23.7 | L38: -23.6 | M38: -23.6 | N38: -23.5 | O38: -23.4 | P38: -23.4 | Q38: -23.3 | R38: -23.2 | S38: -23.2 | T38: -23.1 | U38: -23 | V38: -22.9 | W38: -22.9 | X38: -22.8 | Y38: -22.7 | Z38: -22.7 | AA38: -22.6 | AB38: -22.5 | AC38: -22.5 | AD38: -22.4 | AF38: -22.018349 | AG38: -21.727273 | AH38: -25.157895 | AI38: -25.319149 | AJ38: -22.149533 | AK38: -21.851852 | AL38: -25.934066 | AM38: -26.111111 | AN38: -22.285714 | AO38: -22.075472 | AP38: -25.053763 | AQ38: -25.217391 | AR38: -21.284404 | AS38: -21 | AT38: -24.210526 | AU38: -24.361702 | AV38: -21.401869 | AW38: -21.111111 | AX38: -24.945055 | AY38: -25.222222 | AZ38: -21.52381 | BA38: -21.226415 | BB38: -24.193548 | BC38: -24.347826
A39: Helios Software Inc. | B39: Fixed Assets & Tax - US | C39: CC-US900 | D39: 8000 | E39: Corporation tax / US | F39: USD $'000 | G39: -8 | H39: -8.1 | I39: -8.2 | J39: -8.3 | K39: -8.4 | L39: -8.5 | M39: -8.6 | N39: -8.7 | O39: -8.8 | P39: -8.9 | Q39: -9 | R39: -9.1 | S39: -9.2 | T39: -9.3 | U39: -9.5 | V39: -9.6 | W39: -9.7 | X39: -9.8 | Y39: -9.9 | Z39: -10 | AA39: -10.2 | AB39: -10.3 | AC39: -10.4 | AD39: -10.5 | AF39: -7.2727273 | AG39: -7.7142857 | AH39: -8.7234043 | AI39: -8.9247312 | AJ39: -7.7777778 | AK39: -7.7981651 | AL39: -9.5555556 | AM39: -9.1578947 | AN39: -8.3018868 | AO39: -8.317757 | AP39: -9.7826087 | AQ39: -10 | AR39: -8.3636364 | AS39: -8.8571429 | AT39: -10.106383 | AU39: -10.322581 | AV39: -8.9814815 | AW39: -8.9908257 | AX39: -11 | AY39: -10.526316 | AZ39: -9.6226415 | BA39: -9.6261682 | BB39: -11.304348 | BC39: -11.538462
A40: Helios Software Inc. | B40: Fixed Assets & Tax - US | C40: CC-US900 | D40: 8010 | E40: Deferred tax / US | F40: USD $'000 | G40: 3 | H40: 3 | I40: 3.1 | J40: 3.1 | K40: 3.1 | L40: 3.2 | M40: 3.2 | N40: 3.3 | O40: 3.3 | P40: 3.3 | Q40: 3.4 | R40: 3.4 | S40: 3.5 | T40: 3.5 | U40: 3.5 | V40: 3.6 | W40: 3.6 | X40: 3.7 | Y40: 3.7 | Z40: 3.8 | AA40: 3.8 | AB40: 3.9 | AC40: 3.9 | AD40: 3.9 | AF40: 2.8571429 | AG40: 2.8301887 | AH40: 3.3333333 | AI40: 3.3695652 | AJ40: 2.8440367 | AK40: 2.9090909 | AL40: 3.3684211 | AM40: 3.5106383 | AN40: 3.0841121 | AO40: 3.0555556 | AP40: 3.7362637 | AQ40: 3.7777778 | AR40: 3.3333333 | AS40: 3.3018868 | AT40: 3.7634409 | AU40: 3.9130435 | AV40: 3.3027523 | AW40: 3.3636364 | AX40: 3.8947368 | AY40: 4.0425532 | AZ40: 3.5514019 | BA40: 3.6111111 | BB40: 4.2857143 | BC40: 4.3333333
A41: Helios Software Inc. | B41: Fixed Assets & Tax - US | C41: -- | D41: SUB | E41: US Fixed Assets & Tax ledger subtotal | F41: USD $'000 | G41: =SUM(G36:G40) -> -58 | H41: =SUM(H36:H40) -> -58.3 | I41: =SUM(I36:I40) -> -58.6 | J41: =SUM(J36:J40) -> -58.8 | K41: =SUM(K36:K40) -> -59.1 | L41: =SUM(L36:L40) -> -59.4 | M41: =SUM(M36:M40) -> -59.8 | N41: =SUM(N36:N40) -> -60 | ... AD41: =SUM(AD36:AD40) -> -65.4 | AF41: =SUM(AF36:AF40) -> -53.441548 | AG41: =SUM(AG36:AG40) -> -53.646708 | AH41: =SUM(AH36:AH40) -> -63.21219 | AI41: =SUM(AI36:AI40) -> -63.324607 | AJ41: =SUM(AJ36:AJ40) -> -55.647515 | AK41: =SUM(AK36:AK40) -> -55.412236 | AL41: =SUM(AL36:AL40) -> -65.376226 | AM41: =SUM(AM36:AM40) -> -65.703661 | ... BC41: =SUM(BC36:BC40) -> -70.434217
A43: Helios Software Inc. | B43: US Controller Review | C43: CC-US999 | D43: CHK | E43: US entity ledger movement incl. tax | F43: USD $'000 | G43: =G8+G15+G22+G27+G34+G41 -> -108.1 | H43: =H8+H15+H22+H27+H34+H41 -> -79.7 | I43: =I8+I15+I22+I27+I34+I41 -> -29.6 | J43: =J8+J15+J22+J27+J34+J41 -> -38.6 | K43: =K8+K15+K22+K27+K34+K41 -> 14.5 | L43: =L8+L15+L22+L27+L34+L41 -> 48.8 | M43: =M8+M15+M22+M27+M34+M41 -> -25.3 | N43: =N8+N15+N22+N27+N34+N41 -> -58.4 | ... AD43: =AD8+AD15+AD22+AD27+AD34+AD41 -> 621.7 | AF43: =AF8+AF15+AF22+AF27+AF34+AF41 -> -71.67938 | AG43: =AG8+AG15+AG22+AG27+AG34+AG41 -> -50.188266 | AH43: =AH8+AH15+AH22+AH27+AH34+AH41 -> -50.755405 | AI43: =AI8+AI15+AI22+AI27+AI34+AI41 -> -32.291794 | AJ43: =AJ8+AJ15+AJ22+AJ27+AJ34+AJ41 -> -15.80065 | AK43: =AK8+AK15+AK22+AK27+AK34+AK41 -> 8.8928751 | AL43: =AL8+AL15+AL22+AL27+AL34+AL41 -> -71.354321 | AM43: =AM8+AM15+AM22+AM27+AM34+AM41 -> -99.367986 | ... BC43: =BC8+BC15+BC22+BC27+BC34+BC41 -> 751.27867

Sheet Footnotes_FX
A1: NetSuite Translation Rate Export | B1: Helios Software Group — controller rate table | E1: Rates approved for monthly close
G2: ACTUAL — monthly rate | AF2: BUDGET — planning rate
A3: Legal entity | B3: Department | C3: Cost centre | D3: Rate code | E3: Rate description | F3: Unit | G3: Jan-2024 | H3: Feb-2024 | I3: Mar-2024 | J3: Apr-2024 | K3: May-2024 | L3: Jun-2024 | M3: Jul-2024 | N3: Aug-2024 | O3: Sept-2024 | P3: Oct-2024 | Q3: Nov-2024 | R3: Dec-2024 | S3: Jan-2025 | T3: Feb-2025 | U3: Mar-2025 | V3: Apr-2025 | W3: May-2025 | X3: Jun-2025 | Y3: Jul-2025 | Z3: Aug-2025 | AA3: Sept-2025 | AB3: Oct-2025 | AC3: Nov-2025 | AD3: Dec-2025 | AF3: Jan-2024 | AG3: Feb-2024 | AH3: Mar-2024 | AI3: Apr-2024 | AJ3: May-2024 | AK3: Jun-2024 | AL3: Jul-2024 | AM3: Aug-2024 | AN3: Sept-2024 | AO3: Oct-2024 | AP3: Nov-2024 | AQ3: Dec-2024 | AR3: Jan-2025 | AS3: Feb-2025 | AT3: Mar-2025 | AU3: Apr-2025 | AV3: May-2025 | AW3: Jun-2025 | AX3: Jul-2025 | AY3: Aug-2025 | AZ3: Sept-2025 | BA3: Oct-2025 | BB3: Nov-2025 | BC3: Dec-2025
A4: Helios Software Group | B4: Treasury | C4: CC-910 | D4: FX-USD-AVG | E4: USD average rate | F4: EUR per USD | G4: 0.92 | H4: 0.9315 | I4: 0.9404 | J4: 0.9447 | K4: 0.9436 | L4: 0.9372 | M4: 0.927 | N4: 0.9152 | O4: 0.9045 | P4: 0.8972 | Q4: 0.895 | R4: 0.8984 | S4: 0.9065 | T4: 0.9177 | U4: 0.9294 | V4: 0.9389 | W4: 0.9443 | X4: 0.9443 | Y4: 0.9388 | Z4: 0.9292 | AA4: 0.9175 | AB4: 0.9064 | AC4: 0.8983 | AD4: 0.895 | AF4: 0.925 | AG4: 0.925 | AH4: 0.925 | AI4: 0.925 | AJ4: 0.925 | AK4: 0.925 | AL4: 0.925 | AM4: 0.925 | AN4: 0.925 | AO4: 0.925 | AP4: 0.925 | AQ4: 0.925 | AR4: 0.925 | AS4: 0.925 | AT4: 0.925 | AU4: 0.925 | AV4: 0.925 | AW4: 0.925 | AX4: 0.925 | AY4: 0.925 | AZ4: 0.925 | BA4: 0.925 | BB4: 0.925 | BC4: 0.925
A5: Helios Software Group | B5: Treasury | C5: CC-910 | D5: FX-USD-CLOSE | E5: USD closing rate | F5: EUR per USD | G5: 0.918 | H5: 0.9258 | I5: 0.927 | J5: 0.9268 | K5: 0.9284 | L5: 0.9295 | M5: 0.9247 | N5: 0.9113 | O5: 0.8934 | P5: 0.88 | Q5: 0.8783 | R5: 0.8884 | S5: 0.9033 | T5: 0.9149 | U5: 0.9204 | V5: 0.9229 | W5: 0.9267 | X5: 0.9321 | Y5: 0.9341 | Z5: 0.9271 | AA5: 0.9108 | AB5: 0.892 | AC5: 0.8803 | AD5: 0.8808 | AF5: 0.925 | AG5: 0.925 | AH5: 0.925 | AI5: 0.925 | AJ5: 0.925 | AK5: 0.925 | AL5: 0.925 | AM5: 0.925 | AN5: 0.925 | AO5: 0.925 | AP5: 0.925 | AQ5: 0.925 | AR5: 0.925 | AS5: 0.925 | AT5: 0.925 | AU5: 0.925 | AV5: 0.925 | AW5: 0.925 | AX5: 0.925 | AY5: 0.925 | AZ5: 0.925 | BA5: 0.925 | BB5: 0.925 | BC5: 0.925
A6: Helios Software Group | B6: Treasury | C6: CC-910 | D6: FX-GBP-AVG | E6: GBP average rate | F6: EUR per GBP | G6: 1.17 | H6: 1.1763 | I6: 1.1818 | J6: 1.1858 | K6: 1.1878 | L6: 1.1876 | M6: 1.1851 | N6: 1.1808 | O6: 1.1751 | P6: 1.1687 | Q6: 1.1625 | R6: 1.1573 | S6: 1.1536 | T6: 1.152 | U6: 1.1527 | V6: 1.1556 | W6: 1.1603 | X6: 1.1662 | Y6: 1.1726 | Z6: 1.1787 | AA6: 1.1836 | AB6: 1.1869 | AC6: 1.188 | AD6: 1.1868 | AF6: 1.175 | AG6: 1.175 | AH6: 1.175 | AI6: 1.175 | AJ6: 1.175 | AK6: 1.175 | AL6: 1.175 | AM6: 1.175 | AN6: 1.175 | AO6: 1.175 | AP6: 1.175 | AQ6: 1.175 | AR6: 1.175 | AS6: 1.175 | AT6: 1.175 | AU6: 1.175 | AV6: 1.175 | AW6: 1.175 | AX6: 1.175 | AY6: 1.175 | AZ6: 1.175 | BA6: 1.175 | BB6: 1.175 | BC6: 1.175
A7: Helios Software Group | B7: Treasury | C7: CC-910 | D7: FX-GBP-CLOSE | E7: GBP closing rate | F7: EUR per GBP | G7: 1.166 | H7: 1.1695 | I7: 1.1693 | J7: 1.1699 | K7: 1.1739 | L7: 1.1793 | M7: 1.1809 | N7: 1.1753 | O7: 1.1642 | P7: 1.1532 | Q7: 1.1475 | R7: 1.1473 | S7: 1.1487 | T7: 1.1475 | U7: 1.1436 | V7: 1.1411 | W7: 1.1446 | X7: 1.1546 | Y7: 1.1666 | Z7: 1.1746 | AA7: 1.1761 | AB7: 1.1736 | AC7: 1.172 | AD7: 1.1736 | AF7: 1.175 | AG7: 1.175 | AH7: 1.175 | AI7: 1.175 | AJ7: 1.175 | AK7: 1.175 | AL7: 1.175 | AM7: 1.175 | AN7: 1.175 | AO7: 1.175 | AP7: 1.175 | AQ7: 1.175 | AR7: 1.175 | AS7: 1.175 | AT7: 1.175 | AU7: 1.175 | AV7: 1.175 | AW7: 1.175 | AX7: 1.175 | AY7: 1.175 | AZ7: 1.175 | BA7: 1.175 | BB7: 1.175 | BC7: 1.175
A8: Helios Software Group | B8: Treasury | C8: CC-910 | D8: FX-AUD-AVG | E8: AUD average rate | F8: EUR per AUD | G8: 0.6 | H8: 0.6093 | I8: 0.6168 | J8: 0.6212 | K8: 0.6217 | L8: 0.6181 | M8: 0.6112 | N8: 0.6022 | O8: 0.5927 | P8: 0.5847 | Q8: 0.5794 | R8: 0.5781 | S8: 0.5807 | T8: 0.587 | U8: 0.5957 | V8: 0.6052 | W8: 0.6137 | X8: 0.6197 | Y8: 0.622 | Z8: 0.6202 | AA8: 0.6147 | AB8: 0.6064 | AC8: 0.5969 | AD8: 0.588 | AF8: 0.61 | AG8: 0.61 | AH8: 0.61 | AI8: 0.61 | AJ8: 0.61 | AK8: 0.61 | AL8: 0.61 | AM8: 0.61 | AN8: 0.61 | AO8: 0.61 | AP8: 0.61 | AQ8: 0.61 | AR8: 0.61 | AS8: 0.61 | AT8: 0.61 | AU8: 0.61 | AV8: 0.61 | AW8: 0.61 | AX8: 0.61 | AY8: 0.61 | AZ8: 0.61 | BA8: 0.61 | BB8: 0.61 | BC8: 0.61
A9: Helios Software Group | B9: Treasury | C9: CC-910 | D9: FX-AUD-CLOSE | E9: AUD closing rate | F9: EUR per AUD | G9: 0.612 | H9: 0.618 | I9: 0.6189 | J9: 0.6193 | K9: 0.6221 | L9: 0.6251 | M9: 0.6229 | N9: 0.6124 | O9: 0.5967 | P9: 0.5833 | Q9: 0.5786 | R9: 0.5831 | S9: 0.5917 | T9: 0.5984 | U9: 0.6017 | V9: 0.6049 | W9: 0.612 | X9: 0.6228 | Y9: 0.6316 | Z9: 0.6321 | AA9: 0.6225 | AB9: 0.6075 | AC9: 0.5949 | AD9: 0.5893 | AF9: 0.61 | AG9: 0.61 | AH9: 0.61 | AI9: 0.61 | AJ9: 0.61 | AK9: 0.61 | AL9: 0.61 | AM9: 0.61 | AN9: 0.61 | AO9: 0.61 | AP9: 0.61 | AQ9: 0.61 | AR9: 0.61 | AS9: 0.61 | AT9: 0.61 | AU9: 0.61 | AV9: 0.61 | AW9: 0.61 | AX9: 0.61 | AY9: 0.61 | AZ9: 0.61 | BA9: 0.61 | BB9: 0.61 | BC9: 0.61
A12: Controller footnotes
A13: Note ID | B13: Applies to | C13: Controller note | D13: Owner | E13: Last updated
A14: FN-01 | B14: UK_PL_EUR | C14: Recurring subscriptions recognised ratably over the contracted service period; implementation fees recognised as delivered. | D14: Financial Controller | E14: 31-Dec-2025
A15: FN-02 | B15: UK_PL_EUR | C15: Capitalised development payroll is excluded from engineering expense only after technical-feasibility approval; amortisation remains in account 7110. | D15: Financial Controller | E15: 31-Dec-2025
A16: FN-03 | B16: Group_BS_EUR | C16: Foreign subsidiaries are translated using closing rates for balance sheet accounts and monthly average rates for monthly activity. | D16: Group Reporting | E16: 31-Dec-2025
A17: FN-04 | B17: US_Entity_USD | C17: The US entity tab is standalone USD and is not additive to the consolidated EUR balance sheet without translation and eliminations. | D17: Group Reporting | E17: 31-Dec-2025
A18: FN-05 | B18: All data tabs | C18: A dash represents a true zero balance or no activity, not missing data. Negative values are displayed in parentheses. | D18: Financial Controller | E18: 31-Dec-2025
A19: FN-06 | B19: All data tabs | C19: Budget block contains the same Jan-2024 to Dec-2025 periods as actuals; variances reflect the approved operating plan. | D19: FP&A | E19: 31-Dec-2025
A20: FN-07 | B20: EBITDA_Normalisation | C20: Positive entries increase the controller-adjusted result. FX revaluation may reverse sign and is retained as a non-cash reconciling item. | D20: Financial Controller | E20: 31-Dec-2025
A21: FN-08 | B21: Group_BS_EUR | C21: Retained earnings / consolidation reserve is the ledger balancing reserve after current-period activity and translation entries. | D21: Group Reporting | E21: 31-Dec-2025
A22: FN-09 | B22: KPI_Operational | C22: ARR is shown in EUR millions; headcount and contractors are FTE; churn and NRR are percentages; CAC and LTV are EUR thousands. | D22: Revenue Operations | E22: 31-Dec-2025
