Workbook
Name AsOfDate: Cover!$C$7
Name ReportingEntity: Cover!$C$6

Sheet EVAL LEGEND
B1: Classification eval — 2026-07-13-saas-financial-model
B2: Every cell you marked (1/2) is coloured by what the system did with it:
B4: GREEN | C4: agreement — system fills this marked cell | E4: 636
B5: RED | C5: MISSED — invisible to the system (no fact, no region) | E5: 28
B6: ORANGE | C6: marked but holds a FORMULA — system never writes formulas | E6: 74
B7: BLUE | C7: recognized as extensible-region slot (add-line path) | E7: 78
B8: PURPLE | C8: seen but classified config/staging (control/placeholder) | E8: 0
B9: YELLOW | C9: NOT marked by you, but the system would fill it | E9: 6
B11: Note: YELLOW skips cells whose marking collides with a placeholder value (CLASSIFIED == NORMAL == 1/2) — ground truth is ambiguous there.
B12: Marked cells scored: 816

Sheet Cover
B2: MONTHLY FLASH REPORTING PACK
B3: Portfolio Company Monthly Reporting Template
B6: Reporting Entity | C6: Group (Consolidated)
B7: As-of Date | C7: 46203
B8: Currency | C8: €m
B9: Prepared by
B10: Version | C10: v1.0
B13: INSTRUCTIONS
B14: 1. Set the Reporting Entity and As-of Date above. All month headers across the pack are driven by the As-of Date (via Config).
B15: 2. Blue cells are inputs — populate Actual and Budget months on the Monthly Flash, Balance Sheet and KPI Dashboard sheets.
B16: 3. Sheets are protected: only input cells are unlocked. Totals, subtotals and the Covenants sheet are formula-driven — do not overwrite.
B17: 4. The EBITDA bridge add-backs feed Adjusted EBITDA, which drives LTM Adjusted EBITDA and covenant ratios on the Covenants sheet.
B18: 5. Custom KPIs: use the six unlocked label rows at the bottom of the KPI Dashboard (dropdown or free text) and enter values by month.
B19: 6. The Checks sheet must show ALL CHECKS PASS = TRUE before circulating this pack.
B21: All figures in €m unless stated otherwise. | CVC Capital Partners — Portfolio Monitoring

Sheet Monthly_Flash
B2: MONTHLY FLASH — P&L
B3: =ReportingEntity&" | As of "&TEXT(AsOfDate,"dd mmm yyyy")&" | "&Cover!C8 -> Group (Consolidated) | As of 30 Jun 2026 | €m
C4: ACTUAL | P4: BUDGET
C5: {=Config!$C$6} -> 45839 | D5: =EDATE(C5,1) -> 45870 | E5: =EDATE(D5,1) -> 45901 | F5: =EDATE(E5,1) -> 45931 | G5: =EDATE(F5,1) -> 45962 | H5: =EDATE(G5,1) -> 45992 | I5: =EDATE(H5,1) -> 46023 | J5: =EDATE(I5,1) -> 46054 | K5: =EDATE(J5,1) -> 46082 | ... N5: =EDATE(M5,1) -> 46174 | P5: {=C5} -> 45839 | Q5: =EDATE(P5,1) -> 45870 | R5: =EDATE(Q5,1) -> 45901 | S5: =EDATE(R5,1) -> 45931 | T5: =EDATE(S5,1) -> 45962 | U5: =EDATE(T5,1) -> 45992 | V5: =EDATE(U5,1) -> 46023 | W5: =EDATE(V5,1) -> 46054 | X5: =EDATE(W5,1) -> 46082 | ... AA5: =EDATE(Z5,1) -> 46174
B6: REVENUE
B7: Subscription | C7: 1 | D7: 1 | E7: 1 | F7: 1 | G7: 1 | H7: 1 | I7: 1 | J7: 1 | K7: 1 | L7: 1 | M7: 1 | N7: 1 | O7: 1 | P7: 1 | Q7: 1 | R7: 1 | S7: 1 | T7: 1 | U7: 1 | V7: 1 | W7: 1 | X7: 1 | Y7: 1 | Z7: 1 | AA7: 1
B8: Professional Services | C8: 1 | D8: 1 | E8: 1 | F8: 1 | G8: 1 | H8: 1 | I8: 1 | J8: 1 | K8: 1 | L8: 1 | M8: 1 | N8: 1 | O8: 1 | P8: 1 | Q8: 1 | R8: 1 | S8: 1 | T8: 1 | U8: 1 | V8: 1 | W8: 1 | X8: 1 | Y8: 1 | Z8: 1 | AA8: 1
B9: Other Revenue | C9: 1 | D9: 1 | E9: 1 | F9: 1 | G9: 1 | H9: 1 | I9: 1 | J9: 1 | K9: 1 | L9: 1 | M9: 1 | N9: 1 | O9: 1 | P9: 1 | Q9: 1 | R9: 1 | S9: 1 | T9: 1 | U9: 1 | V9: 1 | W9: 1 | X9: 1 | Y9: 1 | Z9: 1 | AA9: 1
B10: Total Revenue | C10: =SUM(C7:C9) -> 3 | D10: =SUM(D7:D9) -> 3 | E10: =SUM(E7:E9) -> 3 | F10: =SUM(F7:F9) -> 3 | G10: =SUM(G7:G9) -> 3 | H10: =SUM(H7:H9) -> 3 | I10: =SUM(I7:I9) -> 3 | J10: =SUM(J7:J9) -> 3 | ... N10: =SUM(N7:N9) -> 3 | P10: =SUM(P7:P9) -> 3 | Q10: =SUM(Q7:Q9) -> 3 | R10: =SUM(R7:R9) -> 3 | S10: =SUM(S7:S9) -> 3 | T10: =SUM(T7:T9) -> 3 | U10: =SUM(U7:U9) -> 3 | V10: =SUM(V7:V9) -> 3 | W10: =SUM(W7:W9) -> 3 | ... AA10: =SUM(AA7:AA9) -> 3
B11: COST OF GOODS SOLD
B12: Hosting & Infrastructure | C12: 1 | D12: 1 | E12: 1 | F12: 1 | G12: 1 | H12: 1 | I12: 1 | J12: 1 | K12: 1 | L12: 1 | M12: 1 | N12: 1 | O12: 1 | P12: 1 | Q12: 1 | R12: 1 | S12: 1 | T12: 1 | U12: 1 | V12: 1 | W12: 1 | X12: 1 | Y12: 1 | Z12: 1 | AA12: 1
B13: Customer Support | C13: 1 | D13: 1 | E13: 1 | F13: 1 | G13: 1 | H13: 1 | I13: 1 | J13: 1 | K13: 1 | L13: 1 | M13: 1 | N13: 1 | O13: 1 | P13: 1 | Q13: 1 | R13: 1 | S13: 1 | T13: 1 | U13: 1 | V13: 1 | W13: 1 | X13: 1 | Y13: 1 | Z13: 1 | AA13: 1
B14: Third-party Licences | C14: 1 | D14: 1 | E14: 1 | F14: 1 | G14: 1 | H14: 1 | I14: 1 | J14: 1 | K14: 1 | L14: 1 | M14: 1 | N14: 1 | O14: 1 | P14: 1 | Q14: 1 | R14: 1 | S14: 1 | T14: 1 | U14: 1 | V14: 1 | W14: 1 | X14: 1 | Y14: 1 | Z14: 1 | AA14: 1
B15: Total COGS | C15: =SUM(C12:C14) -> 3 | D15: =SUM(D12:D14) -> 3 | E15: =SUM(E12:E14) -> 3 | F15: =SUM(F12:F14) -> 3 | G15: =SUM(G12:G14) -> 3 | H15: =SUM(H12:H14) -> 3 | I15: =SUM(I12:I14) -> 3 | J15: =SUM(J12:J14) -> 3 | ... N15: =SUM(N12:N14) -> 3 | P15: =SUM(P12:P14) -> 3 | Q15: =SUM(Q12:Q14) -> 3 | R15: =SUM(R12:R14) -> 3 | S15: =SUM(S12:S14) -> 3 | T15: =SUM(T12:T14) -> 3 | U15: =SUM(U12:U14) -> 3 | V15: =SUM(V12:V14) -> 3 | W15: =SUM(W12:W14) -> 3 | ... AA15: =SUM(AA12:AA14) -> 3
B16: Gross Profit | C16: =C10-C15 -> 0 | D16: =D10-D15 -> 0 | E16: =E10-E15 -> 0 | F16: =F10-F15 -> 0 | G16: =G10-G15 -> 0 | H16: =H10-H15 -> 0 | I16: =I10-I15 -> 0 | J16: =J10-J15 -> 0 | ... N16: =N10-N15 -> 0 | P16: =P10-P15 -> 0 | Q16: =Q10-Q15 -> 0 | R16: =R10-R15 -> 0 | S16: =S10-S15 -> 0 | T16: =T10-T15 -> 0 | U16: =U10-U15 -> 0 | V16: =V10-V15 -> 0 | W16: =W10-W15 -> 0 | ... AA16: =AA10-AA15 -> 0
B17: OPERATING EXPENSES
B18: Sales & Marketing | C18: 1 | D18: 1 | E18: 1 | F18: 1 | G18: 1 | H18: 1 | I18: 1 | J18: 1 | K18: 1 | L18: 1 | M18: 1 | N18: 1 | O18: 1 | P18: 1 | Q18: 1 | R18: 1 | S18: 1 | T18: 1 | U18: 1 | V18: 1 | W18: 1 | X18: 1 | Y18: 1 | Z18: 1 | AA18: 1
B19: General & Admin | C19: 1 | D19: 1 | E19: 1 | F19: 1 | G19: 1 | H19: 1 | I19: 1 | J19: 1 | K19: 1 | L19: 1 | M19: 1 | N19: 1 | O19: 1 | P19: 1 | Q19: 1 | R19: 1 | S19: 1 | T19: 1 | U19: 1 | V19: 1 | W19: 1 | X19: 1 | Y19: 1 | Z19: 1 | AA19: 1
B20: Research & Development | C20: 1 | D20: 1 | E20: 1 | F20: 1 | G20: 1 | H20: 1 | I20: 1 | J20: 1 | K20: 1 | L20: 1 | M20: 1 | N20: 1 | O20: 1 | P20: 1 | Q20: 1 | R20: 1 | S20: 1 | T20: 1 | U20: 1 | V20: 1 | W20: 1 | X20: 1 | Y20: 1 | Z20: 1 | AA20: 1
B21: Total Opex | C21: =SUM(C18:C20) -> 3 | D21: =SUM(D18:D20) -> 3 | E21: =SUM(E18:E20) -> 3 | F21: =SUM(F18:F20) -> 3 | G21: =SUM(G18:G20) -> 3 | H21: =SUM(H18:H20) -> 3 | I21: =SUM(I18:I20) -> 3 | J21: =SUM(J18:J20) -> 3 | ... N21: =SUM(N18:N20) -> 3 | P21: =SUM(P18:P20) -> 3 | Q21: =SUM(Q18:Q20) -> 3 | R21: =SUM(R18:R20) -> 3 | S21: =SUM(S18:S20) -> 3 | T21: =SUM(T18:T20) -> 3 | U21: =SUM(U18:U20) -> 3 | V21: =SUM(V18:V20) -> 3 | W21: =SUM(W18:W20) -> 3 | ... AA21: =SUM(AA18:AA20) -> 3
B22: EBITDA | C22: =C16-C21 -> -3 | D22: =D16-D21 -> -3 | E22: =E16-E21 -> -3 | F22: =F16-F21 -> -3 | G22: =G16-G21 -> -3 | H22: =H16-H21 -> -3 | I22: =I16-I21 -> -3 | J22: =J16-J21 -> -3 | ... N22: =N16-N21 -> -3 | P22: =P16-P21 -> -3 | Q22: =Q16-Q21 -> -3 | R22: =R16-R21 -> -3 | S22: =S16-S21 -> -3 | T22: =T16-T21 -> -3 | U22: =U16-U21 -> -3 | V22: =V16-V21 -> -3 | W22: =W16-W21 -> -3 | ... AA22: =AA16-AA21 -> -3
B24: EBITDA BRIDGE
B25: Reported EBITDA | C25: {=C22} -> -3 | D25: {=D22} -> -3 | E25: {=E22} -> -3 | F25: {=F22} -> -3 | G25: {=G22} -> -3 | H25: {=H22} -> -3 | I25: {=I22} -> -3 | J25: {=J22} -> -3 | ... N25: {=N22} -> -3 | P25: {=P22} -> -3 | Q25: {=Q22} -> -3 | R25: {=R22} -> -3 | S25: {=S22} -> -3 | T25: {=T22} -> -3 | U25: {=U22} -> -3 | V25: {=V22} -> -3 | W25: {=W22} -> -3 | ... AA25: {=AA22} -> -3
B26: 2 | C26: 1 | D26: 1 | E26: 1 | F26: 1 | G26: 1 | H26: 1 | I26: 1 | J26: 1 | K26: 1 | L26: 1 | M26: 1 | N26: 1 | O26: 1 | P26: 1 | Q26: 1 | R26: 1 | S26: 1 | T26: 1 | U26: 1 | V26: 1 | W26: 1 | X26: 1 | Y26: 1 | Z26: 1 | AA26: 1
B27: 2 | C27: 1 | D27: 1 | E27: 1 | F27: 1 | G27: 1 | H27: 1 | I27: 1 | J27: 1 | K27: 1 | L27: 1 | M27: 1 | N27: 1 | O27: 1 | P27: 1 | Q27: 1 | R27: 1 | S27: 1 | T27: 1 | U27: 1 | V27: 1 | W27: 1 | X27: 1 | Y27: 1 | Z27: 1 | AA27: 1
B28: 2 | C28: 1 | D28: 1 | E28: 1 | F28: 1 | G28: 1 | H28: 1 | I28: 1 | J28: 1 | K28: 1 | L28: 1 | M28: 1 | N28: 1 | O28: 1 | P28: 1 | Q28: 1 | R28: 1 | S28: 1 | T28: 1 | U28: 1 | V28: 1 | W28: 1 | X28: 1 | Y28: 1 | Z28: 1 | AA28: 1
B29: 2 | C29: 1 | D29: 1 | E29: 1 | F29: 1 | G29: 1 | H29: 1 | I29: 1 | J29: 1 | K29: 1 | L29: 1 | M29: 1 | N29: 1 | O29: 1 | P29: 1 | Q29: 1 | R29: 1 | S29: 1 | T29: 1 | U29: 1 | V29: 1 | W29: 1 | X29: 1 | Y29: 1 | Z29: 1 | AA29: 1
B30: 2 | C30: 1 | D30: 1 | E30: 1 | F30: 1 | G30: 1 | H30: 1 | I30: 1 | J30: 1 | K30: 1 | L30: 1 | M30: 1 | N30: 1 | O30: 1 | P30: 1 | Q30: 1 | R30: 1 | S30: 1 | T30: 1 | U30: 1 | V30: 1 | W30: 1 | X30: 1 | Y30: 1 | Z30: 1 | AA30: 1
B31: Adjusted EBITDA | C31: =C25+SUM(C26:C30) -> 2 | D31: =D25+SUM(D26:D30) -> 2 | E31: =E25+SUM(E26:E30) -> 2 | F31: =F25+SUM(F26:F30) -> 2 | G31: =G25+SUM(G26:G30) -> 2 | H31: =H25+SUM(H26:H30) -> 2 | I31: =I25+SUM(I26:I30) -> 2 | J31: =J25+SUM(J26:J30) -> 2 | ... N31: =N25+SUM(N26:N30) -> 2 | P31: =P25+SUM(P26:P30) -> 2 | Q31: =Q25+SUM(Q26:Q30) -> 2 | R31: =R25+SUM(R26:R30) -> 2 | S31: =S25+SUM(S26:S30) -> 2 | T31: =T25+SUM(T26:T30) -> 2 | U31: =U25+SUM(U26:U30) -> 2 | V31: =V25+SUM(V26:V30) -> 2 | W31: =W25+SUM(W26:W30) -> 2 | ... AA31: =AA25+SUM(AA26:AA30) -> 2
B33: Depreciation & Amortisation | C33: 1 | D33: 1 | E33: 1 | F33: 1 | G33: 1 | H33: 1 | I33: 1 | J33: 1 | K33: 1 | L33: 1 | M33: 1 | N33: 1 | O33: 1 | P33: 1 | Q33: 1 | R33: 1 | S33: 1 | T33: 1 | U33: 1 | V33: 1 | W33: 1 | X33: 1 | Y33: 1 | Z33: 1 | AA33: 1
B34: EBIT | C34: =C22-C33 -> -4 | D34: =D22-D33 -> -4 | E34: =E22-E33 -> -4 | F34: =F22-F33 -> -4 | G34: =G22-G33 -> -4 | H34: =H22-H33 -> -4 | I34: =I22-I33 -> -4 | J34: =J22-J33 -> -4 | ... N34: =N22-N33 -> -4 | P34: =P22-P33 -> -4 | Q34: =Q22-Q33 -> -4 | R34: =R22-R33 -> -4 | S34: =S22-S33 -> -4 | T34: =T22-T33 -> -4 | U34: =U22-U33 -> -4 | V34: =V22-V33 -> -4 | W34: =W22-W33 -> -4 | ... AA34: =AA22-AA33 -> -4
B35: Interest | C35: 1 | D35: 1 | E35: 1 | F35: 1 | G35: 1 | H35: 1 | I35: 1 | J35: 1 | K35: 1 | L35: 1 | M35: 1 | N35: 1 | O35: 1 | P35: 1 | Q35: 1 | R35: 1 | S35: 1 | T35: 1 | U35: 1 | V35: 1 | W35: 1 | X35: 1 | Y35: 1 | Z35: 1 | AA35: 1
B36: PBT | C36: =C34-C35 -> -5 | D36: =D34-D35 -> -5 | E36: =E34-E35 -> -5 | F36: =F34-F35 -> -5 | G36: =G34-G35 -> -5 | H36: =H34-H35 -> -5 | I36: =I34-I35 -> -5 | J36: =J34-J35 -> -5 | ... N36: =N34-N35 -> -5 | P36: =P34-P35 -> -5 | Q36: =Q34-Q35 -> -5 | R36: =R34-R35 -> -5 | S36: =S34-S35 -> -5 | T36: =T34-T35 -> -5 | U36: =U34-U35 -> -5 | V36: =V34-V35 -> -5 | W36: =W34-W35 -> -5 | ... AA36: =AA34-AA35 -> -5
B37: Tax | C37: 1 | D37: 1 | E37: 1 | F37: 1 | G37: 1 | H37: 1 | I37: 1 | J37: 1 | K37: 1 | L37: 1 | M37: 1 | N37: 1 | O37: 1 | P37: 1 | Q37: 1 | R37: 1 | S37: 1 | T37: 1 | U37: 1 | V37: 1 | W37: 1 | X37: 1 | Y37: 1 | Z37: 1 | AA37: 1
B38: Net Income | C38: =C36-C37 -> -6 | D38: =D36-D37 -> -6 | E38: =E36-E37 -> -6 | F38: =F36-F37 -> -6 | G38: =G36-G37 -> -6 | H38: =H36-H37 -> -6 | I38: =I36-I37 -> -6 | J38: =J36-J37 -> -6 | ... N38: =N36-N37 -> -6 | P38: =P36-P37 -> -6 | Q38: =Q36-Q37 -> -6 | R38: =R36-R37 -> -6 | S38: =S36-S37 -> -6 | T38: =T36-T37 -> -6 | U38: =U36-U37 -> -6 | V38: =V36-V37 -> -6 | W38: =W36-W37 -> -6 | ... AA38: =AA36-AA37 -> -6
B40: OPERATIONAL KPIs
B41: 2 | C41: 1 | D41: 1 | E41: 1 | F41: 1 | G41: 1 | H41: 1 | I41: 1 | J41: 1 | K41: 1 | L41: 1 | M41: 1 | N41: 1 | O41: 1 | P41: 1 | Q41: 1 | R41: 1 | S41: 1 | T41: 1 | U41: 1 | V41: 1 | W41: 1 | X41: 1 | Y41: 1 | Z41: 1 | AA41: 1
B42: 2 | C42: 1 | D42: 1 | E42: 1 | F42: 1 | G42: 1 | H42: 1 | I42: 1 | J42: 1 | K42: 1 | L42: 1 | M42: 1 | N42: 1 | O42: 1 | P42: 1 | Q42: 1 | R42: 1 | S42: 1 | T42: 1 | U42: 1 | V42: 1 | W42: 1 | X42: 1 | Y42: 1 | Z42: 1 | AA42: 1
B43: 2 | C43: 1 | D43: 1 | E43: 1 | F43: 1 | G43: 1 | H43: 1 | I43: 1 | J43: 1 | K43: 1 | L43: 1 | M43: 1 | N43: 1 | O43: 1 | P43: 1 | Q43: 1 | R43: 1 | S43: 1 | T43: 1 | U43: 1 | V43: 1 | W43: 1 | X43: 1 | Y43: 1 | Z43: 1 | AA43: 1

Sheet Balance_Sheet
B2: BALANCE SHEET
B3: =ReportingEntity&" | As of "&TEXT(AsOfDate,"dd mmm yyyy")&" | "&Cover!C8 -> Group (Consolidated) | As of 30 Jun 2026 | €m
C5: {=Monthly_Flash!C5} -> 45839 | D5: {=Monthly_Flash!D5} -> 45870 | E5: {=Monthly_Flash!E5} -> 45901 | F5: {=Monthly_Flash!F5} -> 45931 | G5: {=Monthly_Flash!G5} -> 45962 | H5: {=Monthly_Flash!H5} -> 45992 | I5: {=Monthly_Flash!I5} -> 46023 | J5: {=Monthly_Flash!J5} -> 46054 | ... N5: {=Monthly_Flash!N5} -> 46174
B6: ASSETS
B7: Cash & Equivalents | C7: 1 | D7: 1 | E7: 1 | F7: 1 | G7: 1 | H7: 1 | I7: 1 | J7: 1 | K7: 1 | L7: 1 | M7: 1 | N7: 1
B8: Receivables | C8: 1 | D8: 1 | E8: 1 | F8: 1 | G8: 1 | H8: 1 | I8: 1 | J8: 1 | K8: 1 | L8: 1 | M8: 1 | N8: 1
B9: Inventory | C9: 1 | D9: 1 | E9: 1 | F9: 1 | G9: 1 | H9: 1 | I9: 1 | J9: 1 | K9: 1 | L9: 1 | M9: 1 | N9: 1
B10: Other Assets | C10: 1 | D10: 1 | E10: 1 | F10: 1 | G10: 1 | H10: 1 | I10: 1 | J10: 1 | K10: 1 | L10: 1 | M10: 1 | N10: 1
B11: Total Assets | C11: =SUM(C7:C10) -> 4 | D11: =SUM(D7:D10) -> 4 | E11: =SUM(E7:E10) -> 4 | F11: =SUM(F7:F10) -> 4 | G11: =SUM(G7:G10) -> 4 | H11: =SUM(H7:H10) -> 4 | I11: =SUM(I7:I10) -> 4 | J11: =SUM(J7:J10) -> 4 | ... N11: =SUM(N7:N10) -> 4
B13: LIABILITIES & EQUITY
B14: Payables | C14: 1 | D14: 1 | E14: 1 | F14: 1 | G14: 1 | H14: 1 | I14: 1 | J14: 1 | K14: 1 | L14: 1 | M14: 1 | N14: 1
B15: Senior Debt | C15: 1 | D15: 1 | E15: 1 | F15: 1 | G15: 1 | H15: 1 | I15: 1 | J15: 1 | K15: 1 | L15: 1 | M15: 1 | N15: 1
B16: Revolving Credit Facility | C16: 1 | D16: 1 | E16: 1 | F16: 1 | G16: 1 | H16: 1 | I16: 1 | J16: 1 | K16: 1 | L16: 1 | M16: 1 | N16: 1
B17: Shareholder Loan | C17: 1 | D17: 1 | E17: 1 | F17: 1 | G17: 1 | H17: 1 | I17: 1 | J17: 1 | K17: 1 | L17: 1 | M17: 1 | N17: 1
B18: Total Debt | C18: =SUM(C15:C17) -> 3 | D18: =SUM(D15:D17) -> 3 | E18: =SUM(E15:E17) -> 3 | F18: =SUM(F15:F17) -> 3 | G18: =SUM(G15:G17) -> 3 | H18: =SUM(H15:H17) -> 3 | I18: =SUM(I15:I17) -> 3 | J18: =SUM(J15:J17) -> 3 | ... N18: =SUM(N15:N17) -> 3
B19: Other Liabilities | C19: 1 | D19: 1 | E19: 1 | F19: 1 | G19: 1 | H19: 1 | I19: 1 | J19: 1 | K19: 1 | L19: 1 | M19: 1 | N19: 1
B20: Equity | C20: 1 | D20: 1 | E20: 1 | F20: 1 | G20: 1 | H20: 1 | I20: 1 | J20: 1 | K20: 1 | L20: 1 | M20: 1 | N20: 1
B21: Total Liabilities & Equity | C21: =C14+C18+C19+C20 -> 6 | D21: =D14+D18+D19+D20 -> 6 | E21: =E14+E18+E19+E20 -> 6 | F21: =F14+F18+F19+F20 -> 6 | G21: =G14+G18+G19+G20 -> 6 | H21: =H14+H18+H19+H20 -> 6 | I21: =I14+I18+I19+I20 -> 6 | J21: =J14+J18+J19+J20 -> 6 | ... N21: =N14+N18+N19+N20 -> 6
B23: KEY METRICS
B24: Net Debt | C24: =C18-C7 -> 2 | D24: =D18-D7 -> 2 | E24: =E18-E7 -> 2 | F24: =F18-F7 -> 2 | G24: =G18-G7 -> 2 | H24: =H18-H7 -> 2 | I24: =I18-I7 -> 2 | J24: =J18-J7 -> 2 | ... N24: =N18-N7 -> 2
B25: Net Working Capital | C25: =C8+C9-C14 -> 1 | D25: =D8+D9-D14 -> 1 | E25: =E8+E9-E14 -> 1 | F25: =F8+F9-F14 -> 1 | G25: =G8+G9-G14 -> 1 | H25: =H8+H9-H14 -> 1 | I25: =I8+I9-I14 -> 1 | J25: =J8+J9-J14 -> 1 | ... N25: =N8+N9-N14 -> 1

Sheet Covenants
B2: COVENANTS
B3: =ReportingEntity&" | Test date: "&TEXT(AsOfDate,"dd mmm yyyy")&" | LTM basis" -> Group (Consolidated) | Test date: 30 Jun 2026 | LTM basis
B5: BUILDING BLOCKS
B6: LTM Adjusted EBITDA (€m) | C6: =SUM(Monthly_Flash!C31:N31) -> 24
B7: LTM Interest (€m) | C7: =SUM(Monthly_Flash!C35:N35) -> 12
B8: Net Debt (€m) | C8: {=Balance_Sheet!N24} -> 2
B10: COVENANT TESTS
B11: Metric | C11: Value | D11: Threshold | E11: Headroom | F11: Status
B12: Net Leverage (Net Debt / LTM Adj. EBITDA) | C12: =IF($C$6=0,"n/a",$C$8/$C$6) -> 0.083333333 | D12: {=Config!C31} -> 4.5 | E12: =IF($C$12="n/a","n/a",D12-C12) -> 4.4166667 | F12: =IF($C$12="n/a","n/a",IF(C12<=D12,"OK","ERROR")) -> OK
B13: Interest Cover (LTM Adj. EBITDA / LTM Interest) | C13: =IF($C$7=0,"n/a",$C$6/$C$7) -> 2 | D13: {=Config!C32} -> 3 | E13: =IF($C$13="n/a","n/a",C13-D13) -> -1 | F13: =IF($C$13="n/a","n/a",IF(C13>=D13,"OK","ERROR")) -> ERROR
B15: This sheet is fully formula-driven — no manual inputs. Thresholds are maintained on Config.

Sheet KPI_Dashboard
B2: KPI DASHBOARD
B3: =ReportingEntity&" | As of "&TEXT(AsOfDate,"dd mmm yyyy") -> Group (Consolidated) | As of 30 Jun 2026
C5: {=Monthly_Flash!C5} -> 45839 | D5: {=Monthly_Flash!D5} -> 45870 | E5: {=Monthly_Flash!E5} -> 45901 | F5: {=Monthly_Flash!F5} -> 45931 | G5: {=Monthly_Flash!G5} -> 45962 | H5: {=Monthly_Flash!H5} -> 45992 | I5: {=Monthly_Flash!I5} -> 46023 | J5: {=Monthly_Flash!J5} -> 46054 | ... N5: {=Monthly_Flash!N5} -> 46174
B6: CORE KPIs
B7: ARR (€m) | C7: {=Monthly_Flash!C42} -> 1 | D7: {=Monthly_Flash!D42} -> 1 | E7: {=Monthly_Flash!E42} -> 1 | F7: {=Monthly_Flash!F42} -> 1 | G7: {=Monthly_Flash!G42} -> 1 | H7: {=Monthly_Flash!H42} -> 1 | I7: {=Monthly_Flash!I42} -> 1 | J7: {=Monthly_Flash!J42} -> 1 | ... N7: {=Monthly_Flash!N42} -> 1
B8: Net Revenue Retention % | C8: 1 | D8: 1 | E8: 1 | F8: 1 | G8: 1 | H8: 1 | I8: 1 | J8: 1 | K8: 1 | L8: 1 | M8: 1 | N8: 1
B9: Headcount (FTE) | C9: {=Monthly_Flash!C41} -> 1 | D9: {=Monthly_Flash!D41} -> 1 | E9: {=Monthly_Flash!E41} -> 1 | F9: {=Monthly_Flash!F41} -> 1 | G9: {=Monthly_Flash!G41} -> 1 | H9: {=Monthly_Flash!H41} -> 1 | I9: {=Monthly_Flash!I41} -> 1 | J9: {=Monthly_Flash!J41} -> 1 | ... N9: {=Monthly_Flash!N41} -> 1
B10: Revenue per FTE (€'000) | C10: =IF(Monthly_Flash!C41=0,"",Monthly_Flash!C10*12*1000/Monthly_Flash!C41) -> 36000 | D10: =IF(Monthly_Flash!D41=0,"",Monthly_Flash!D10*12*1000/Monthly_Flash!D41) -> 36000 | E10: =IF(Monthly_Flash!E41=0,"",Monthly_Flash!E10*12*1000/Monthly_Flash!E41) -> 36000 | F10: =IF(Monthly_Flash!F41=0,"",Monthly_Flash!F10*12*1000/Monthly_Flash!F41) -> 36000 | G10: =IF(Monthly_Flash!G41=0,"",Monthly_Flash!G10*12*1000/Monthly_Flash!G41) -> 36000 | H10: =IF(Monthly_Flash!H41=0,"",Monthly_Flash!H10*12*1000/Monthly_Flash!H41) -> 36000 | I10: =IF(Monthly_Flash!I41=0,"",Monthly_Flash!I10*12*1000/Monthly_Flash!I41) -> 36000 | J10: =IF(Monthly_Flash!J41=0,"",Monthly_Flash!J10*12*1000/Monthly_Flash!J41) -> 36000 | ... N10: =IF(Monthly_Flash!N41=0,"",Monthly_Flash!N10*12*1000/Monthly_Flash!N41) -> 36000
B11: CAC Payback (months) | C11: 1 | D11: 1 | E11: 1 | F11: 1 | G11: 1 | H11: 1 | I11: 1 | J11: 1 | K11: 1 | L11: 1 | M11: 1 | N11: 1
B12: Revenue Growth % (YoY) | C12: 1 | D12: 1 | E12: 1 | F12: 1 | G12: 1 | H12: 1 | I12: 1 | J12: 1 | K12: 1 | L12: 1 | M12: 1 | N12: 1
B13: EBITDA Margin % | C13: =IF(Monthly_Flash!C10=0,"",Monthly_Flash!C22/Monthly_Flash!C10) -> -1 | D13: =IF(Monthly_Flash!D10=0,"",Monthly_Flash!D22/Monthly_Flash!D10) -> -1 | E13: =IF(Monthly_Flash!E10=0,"",Monthly_Flash!E22/Monthly_Flash!E10) -> -1 | F13: =IF(Monthly_Flash!F10=0,"",Monthly_Flash!F22/Monthly_Flash!F10) -> -1 | G13: =IF(Monthly_Flash!G10=0,"",Monthly_Flash!G22/Monthly_Flash!G10) -> -1 | H13: =IF(Monthly_Flash!H10=0,"",Monthly_Flash!H22/Monthly_Flash!H10) -> -1 | I13: =IF(Monthly_Flash!I10=0,"",Monthly_Flash!I22/Monthly_Flash!I10) -> -1 | J13: =IF(Monthly_Flash!J10=0,"",Monthly_Flash!J22/Monthly_Flash!J10) -> -1 | ... N13: =IF(Monthly_Flash!N10=0,"",Monthly_Flash!N22/Monthly_Flash!N10) -> -1
B14: Rule of 40 % | C14: =IF(OR(C12="",C13=""),"",C12+C13) -> 0 | D14: =IF(OR(D12="",D13=""),"",D12+D13) -> 0 | E14: =IF(OR(E12="",E13=""),"",E12+E13) -> 0 | F14: =IF(OR(F12="",F13=""),"",F12+F13) -> 0 | G14: =IF(OR(G12="",G13=""),"",G12+G13) -> 0 | H14: =IF(OR(H12="",H13=""),"",H12+H13) -> 0 | I14: =IF(OR(I12="",I13=""),"",I12+I13) -> 0 | J14: =IF(OR(J12="",J13=""),"",J12+J13) -> 0 | ... N14: =IF(OR(N12="",N13=""),"",N12+N13) -> 0
B16: CUSTOM KPIs
B17: 2 | C17: 1 | D17: 1 | E17: 1 | F17: 1 | G17: 1 | H17: 1 | I17: 1 | J17: 1 | K17: 1 | L17: 1 | M17: 1 | N17: 1
B18: 2 | C18: 1 | D18: 1 | E18: 1 | F18: 1 | G18: 1 | H18: 1 | I18: 1 | J18: 1 | K18: 1 | L18: 1 | M18: 1 | N18: 1
B19: 2 | C19: 1 | D19: 1 | E19: 1 | F19: 1 | G19: 1 | H19: 1 | I19: 1 | J19: 1 | K19: 1 | L19: 1 | M19: 1 | N19: 1
B20: 2 | C20: 1 | D20: 1 | E20: 1 | F20: 1 | G20: 1 | H20: 1 | I20: 1 | J20: 1 | K20: 1 | L20: 1 | M20: 1 | N20: 1
B21: 2 | C21: 1 | D21: 1 | E21: 1 | F21: 1 | G21: 1 | H21: 1 | I21: 1 | J21: 1 | K21: 1 | L21: 1 | M21: 1 | N21: 1
B22: 2 | C22: 1 | D22: 1 | E22: 1 | F22: 1 | G22: 1 | H22: 1 | I22: 1 | J22: 1 | K22: 1 | L22: 1 | M22: 1 | N22: 1
B24: Custom KPI labels are unlocked — pick from the dropdown list (maintained on Config) or type your own; enter values by month.

Sheet Checks
B2: CHECKS — TIE-OUTS
B3: All differences should be ~0. Status flags flip to ERROR on any break.
B5: Check | C5: Difference | D5: Status
B6: (a) Total Revenue = sum of revenue streams (Actual + Budget) | C6: {=SUMPRODUCT(ABS(Monthly_Flash!C10:AA10-(Monthly_Flash!C7:AA7+Monthly_Flash!C8:AA8+Monthly_Flash!C9:AA9)))} -> 3 | D6: =IF(ABS(C6)<0.001,"OK","ERROR") -> ERROR
B7: (b) Balance Sheet balances (Total Assets = Total Liabilities & Equity) | C7: {=SUMPRODUCT(ABS(Balance_Sheet!C11:N11-Balance_Sheet!C21:N21))} -> 24 | D7: =IF(ABS(C7)<0.001,"OK","ERROR") -> ERROR
B8: (c) Adjusted EBITDA (Flash) = LTM building block (Covenants) | C8: =SUM(Monthly_Flash!C31:N31)-Covenants!C6 -> 0 | D8: =IF(ABS(C8)<0.001,"OK","ERROR") -> OK
B9: (d) Net Debt (Balance Sheet) = Net Debt (Covenants) | C9: =Balance_Sheet!N24-Covenants!C8 -> 0 | D9: =IF(ABS(C9)<0.001,"OK","ERROR") -> OK
B10: (e) Headcount (Flash) = Headcount (KPI Dashboard) | C10: {=SUMPRODUCT(ABS(Monthly_Flash!C41:N41-KPI_Dashboard!C9:N9))} -> 0 | D10: =IF(ABS(C10)<0.001,"OK","ERROR") -> OK
B12: ALL CHECKS PASS | C12: =AND(D6="OK",D7="OK",D8="OK",D9="OK",D10="OK") -> FALSE

Sheet Config
B2: CONFIG — Lists & Drivers
B5: MONTH DRIVER
B6: First actual month | C6: =EDATE(DATE(YEAR(AsOfDate),MONTH(AsOfDate),1),-11) -> 45839
B7: As-of month (last actual) | C7: =EDATE(C6,11) -> 46174
B10: ENTITY LIST
B11: Group (Consolidated)
B12: HoldCo
B13: OpCo — Germany
B14: OpCo — France
B15: OpCo — UK
B18: SCENARIO LIST
B19: Actual
B20: Budget
B21: Forecast
B24: CURRENCY LIST
B25: €m
... B30: COVENANT THRESHOLDS
B31: Max Net Leverage | C31: 4.5
B32: Min Interest Cover | C32: 3
B35: CUSTOM KPI LIST
B36: Custom KPI 1
B37: Custom KPI 2
B38: Custom KPI 3
B39: Custom KPI 4
B40: Custom KPI 5
B41: Custom KPI 6
B42: Gross Margin %
B43: Logo Churn %
B44: Bookings (€m)
B45: Pipeline Coverage (x)
B46: NPS
B47: Other…
