Workbook
Name array_displayUnit: tbl_displayUnit[UnitName]
Name array_timeline: _xlfn.ANCHORARRAY(Developer!$B$97)
Name array_typeIAdj: _xlfn.ANCHORARRAY(Developer!$B$164)
Name COMPANY_ENTITY_ID: PM_Support[COMPANY_ENTITY_ID]
Name Company_selector: _xlfn.ANCHORARRAY(Developer!$J$410)
Name CVC.PACK: _xlfn.LAMBDA(_xlpm.Array,_xlfn.TEXTJOIN("¶",FALSE,_xlfn.BYROW(_xlpm.Array,_xlfn.LAMBDA(_xlpm.row,_xlfn.TEXTJOIN("|",FALSE,_xlpm.row)))))
Name CX_ENTITY: Developer!$A$7
Name debt_ouput_replay_schedule: _xlfn.ANCHORARRAY(DebtOverview!$BZ$64)
Name debt_output_db: _xlfn.ANCHORARRAY(DebtOverview!$BK$67)
Name DebtRatio_Normal: DebtOverview!$C$8
Name fx_attrConverter: _xlfn.LAMBDA(_xlpm.Input,_xlop.EnablePOC,_xlpm.Input)
Name fx_getLTM: _xlfn.LAMBDA(_xlpm.Array,_xlpm.endDate,_xlpm.Periods,_xlfn.TAKE(_xlfn.DROP(_xlpm.Array,,_xlfn.XMATCH(_xlpm.endDate,array_timeline,0)-_xlpm.Periods),1,_xlpm.Periods))
Name fx_hasCX: _xlfn.LAMBDA(_xlpm.x,SEARCH("CX.",_xlfn.FORMULATEXT(_xlpm.x))>0)
Name fx_ProtectPush: TRUE
Name fx_trailingPeriods: _xlfn.LAMBDA(_xlpm.Periods,_xlpm.EndMonth,EOMONTH(_xlpm.EndMonth,_xlfn.SEQUENCE(1,_xlpm.Periods,-_xlpm.Periods+1,1)))
Name fxVal_normal: DebtOverview!$C$8
Name fxVal_normal: _xlfn.XLOOKUP(val_displayUnit,tbl_displayUnit[UnitName],tbl_displayUnit[Number],1)
Name fxVal_sign: _xlfn.LAMBDA(_xlpm.ID,1)
Name icon_lock: fx_getIcon("lock")
Name icon_unlock: fx_getIcon("unlock")
Name IFBLANK: _xlfn.LAMBDA(_xlpm.Primary,_xlpm.Alternative,IF(_xlpm.Primary="",_xlpm.Alternative,_xlpm.Primary))
Name img_cvc: Developer!$E$158
Name IQ_CH: 110000
Name IQ_CQ: 5000
Name IQ_CY: 10000
Name IQ_DAILY: 500000
Name IQ_FH: 100000
Name IQ_FQ: 500
Name IQ_FY: 1000
Name IQ_LTM: 2000
Name IQ_MONTH: 15000
Name IQ_NTM: 6000
Name IQ_WEEK: 50000
Name IQ_YTD: 3000
Name ISBLANKTAB: _xlfn.LAMBDA(_xlpm.tableStr,TRIM(SUBSTITUTE(SUBSTITUTE(_xlpm.tableStr,"|",""),"¶",""))="")
Name loc_adjExample: AdjustmtType!$C$4
Name LTM: fx_trailingPeriods(12,val_asOfDate)
Name PACK: _xlfn.LAMBDA(_xlpm.tbl,_xlfn.TEXTJOIN("¶",FALSE,_xlfn.BYROW(_xlpm.tbl,_xlfn.LAMBDA(_xlpm.row,_xlfn.TEXTJOIN("|",FALSE,_xlpm.row)))))
Name pqToday: pquery_today[Date]
Name protectStatus: "!$O$4"
Name reportingdate: Developer!$R$2
Name TODECIMAL: _xlfn.LAMBDA(_xlpm.Input,_xlop.NormaliseFactor,_xlfn.LET(_xlpm.Norm,IF(_xlfn.ISOMITTED(_xlpm.NormaliseFactor),1,_xlpm.NormaliseFactor),IF(ISNUMBER(_xlpm.Input),_xlpm.Input/_xlpm.Norm,_xlpm.Input)))
Name UNPACK: _xlfn.LAMBDA(_xlpm.CXReturn,_xlfn.LET(_xlpm.Res,IF(_xlpm.CXReturn="","",_xlfn.TEXTSPLIT(_xlpm.CXReturn,"|","¶",FALSE)),IFERROR(_xlfn.NUMBERVALUE(_xlpm.Res),_xlpm.Res)))
Name UNPACK_ROW: _xlfn.LAMBDA(_xlpm.PackedString,_xlpm.Nth,IF(_xlpm.PackedString="","",IF(ISNUMBER(SEARCH("|",_xlpm.PackedString)),INDEX(_xlfn.TEXTSPLIT(_xlpm.PackedString,"|",,FALSE),_xlpm.Nth),_xlpm.PackedString)))
Name val_asOfDate: PL!$AG$6
Name val_blankRefText: _PL!$S$12
Name val_company: Developer!$A$8
Name val_currentFYE: _PL!$AK$6
Name val_displayUnit: PL!$AL$6
Name val_enablePOC: Developer!$A$11
Name val_priorQtrEnd: _xlfn.LET(_xlpm.GetQtr,_xlfn.LAMBDA(_xlpm.date,EOMONTH(_xlpm.date,3-ROUNDUP(MONTH(_xlpm.date)/3,0)+1)),EOMONTH(_xlpm.GetQtr(val_asOfDate),-3))
Name val_reportingCurrency: _PL!$AM$6

Sheet EVAL LEGEND
B1: Classification eval — Flash Collection_MasterTemplate_2.1.6_PROD
B2: Every cell you marked (1/2) is coloured by what the system did with it:
B4: GREEN | C4: agreement — system fills this marked cell | E4: 5826
B5: RED | C5: MISSED — invisible to the system (no fact, no region) | E5: 90
B6: ORANGE | C6: marked but holds a FORMULA — system never writes formulas | E6: 2158
B7: BLUE | C7: recognized as extensible-region slot (add-line path) | E7: 5
B8: PURPLE | C8: seen but classified config/staging (control/placeholder) | E8: 0
B9: YELLOW | C9: NOT marked by you, but the system would fill it | E9: 1201
B10: PALE GREEN | C10: system FILLS it — your marking is indistinguishable from the template's own value (collision), so unverifiable | E10: 53
B11: PALE PINK | C11: system does NOT fill it — marking/value collision, unverifiable | E11: 1138
B13: Note: YELLOW skips cells whose marking collides with a placeholder value (CLASSIFIED == NORMAL == 1/2) — ground truth is ambiguous there.
B14: Marked cells scored: 8079

Sheet Introduction
A1: unprotected | B1: 2025-12-23T03:33:24.755Z
G3: =_xlfn.IMAGE(INDEX(PM_Support[COMPANY_LOGO_URL],MATCH(val_company,PM_Support[COMPANY_NAME],0))) -> #VALUE!
G6: Introduction to the Monthly Flash Sheets
G10: Introduction
G19: Core Financial Data Collection
G42: Key Performance Indicators (KPIs)
G49: Debt Analysis Section

Sheet AdjustmentReview
A1: unprotected | B1: 2025-12-23T03:33:24.755Z
K3: DO NOT SKIP
F4: Flash Data
F5: Like-for-Like Adjustments Review
F9: Perimeter changes distort year-over-year comparisons. LFL adjustments hold the perimeter constant so you compare the same businesses across periods—either by: > Excluding acquired/disposed contributions in the comparison window, or > Restating the base period on a pro-forma basis to simulate today’s perimeter.
F15: Example. If we bought a business in May, we will add last year’s May–Dec sales as if we’d owned it then. Either way, we’re comparing the same footprint across both years.
AR19: Past FY | AS19: =AU19-1 -> #NAME? | AU19: =YEAR(AU20) -> #NAME?
AR20: FY Ending | AS20: {=EOMONTH(val_currentFYE,-12)} -> #NAME? | AU20: {=val_currentFYE} -> #NAME?
AR21: FY Starting | AS21: =EOMONTH(AS20,-12)+1 -> #NAME? | AU21: =EOMONTH(AU20,-12)+1 -> #NAME?
AQ32: ="AS OF "&UPPER(TEXT(val_asOfDate,"mmm-yy"))&" ("&val_reportingCurrency&" M)" -> #NAME?
AQ33: Branch | AR33: Metric | AS33: =PL!$CE$12 -> #NAME? | AT33: =PL!CN12 -> #NAME? | AU33: =PL!CQ12 -> #NAME?
AQ34: NO | AR34: Top Line | AT34: {=_xlfn.LET(_xlpm.Res,IFBLANK(PL!$CN$148,PL!$CM$148),IF(_xlpm.Res="","-",_xlpm.Res*fxVal_normal/1000000))} -> 1 | AU34: {=_xlfn.LET(_xlpm.Res,IFBLANK(PL!$CQ$148,PL!$CP$148),IF(_xlpm.Res="","-",_xlpm.Res*fxVal_normal/1000000))} -> 1
AQ35: NO | AR35: Earning | AT35: {=_xlfn.LET(_xlpm.Res,IFBLANK(PL!$CN$162,PL!$CM$162),IF(_xlpm.Res="","-",_xlpm.Res*fxVal_normal/1000000))} -> 1 | AU35: {=_xlfn.LET(_xlpm.Res,IFBLANK(PL!$CQ$162,PL!$CP$162),IF(_xlpm.Res="","-",_xlpm.Res*fxVal_normal/1000000))} -> 1
AQ36: NO | AR36: Valuation | AT36: {=_xlfn.LET(_xlpm.Res,IFBLANK(PL!$CN$176,PL!$CM$176),IF(_xlpm.Res="","-",_xlpm.Res*fxVal_normal/1000000))} -> 1 | AU36: {=_xlfn.LET(_xlpm.Res,IFBLANK(PL!$CQ$176,PL!$CP$176),IF(_xlpm.Res="","-",_xlpm.Res*fxVal_normal/1000000))} -> 1
AQ37: YES | AR37: Top Line | AS37: {=IF(OR(_xlfn.VSTACK(PL!$CE$154,PL!$CE$147)=""),"-",IFERROR((PL!$CE$154-PL!$CE$147)*fxVal_normal/1000000,"-"))} -> #NAME? | AT37: {=_xlfn.LET(_xlpm.Res,IFBLANK(PL!$CN$149,PL!$CM$149),IF(_xlpm.Res="","-",_xlpm.Res*fxVal_normal/1000000))} -> 1 | AU37: {=_xlfn.LET(_xlpm.Res,IFBLANK(PL!$CQ$149,PL!$CP$149),IF(_xlpm.Res="","-",_xlpm.Res*fxVal_normal/1000000))} -> 1
AQ38: YES | AR38: Earning | AS38: {=IF(OR(_xlfn.VSTACK(PL!$CE$168,PL!$CE$161)=""),"-",IFERROR((PL!$CE$168-PL!$CE$161)*fxVal_normal/1000000,"-"))} -> #NAME? | AT38: {=_xlfn.LET(_xlpm.Res,IFBLANK(PL!$CN$163,PL!$CM$163),IF(_xlpm.Res="","-",_xlpm.Res*fxVal_normal/1000000))} -> 1 | AU38: {=_xlfn.LET(_xlpm.Res,IFBLANK(PL!$CQ$163,PL!$CP$163),IF(_xlpm.Res="","-",_xlpm.Res*fxVal_normal/1000000))} -> 1
AQ39: YES | AR39: Valuation | AS39: {=IF(OR(_xlfn.VSTACK(PL!$CE$182,PL!$CE$175)=""),"-",(PL!$CE$182-PL!$CE$175)*fxVal_normal/1000000)} -> #NAME? | AT39: {=_xlfn.LET(_xlpm.Res,IFBLANK(PL!$CN$177,PL!$CM$177),IF(_xlpm.Res="","-",_xlpm.Res*fxVal_normal/1000000))} -> 1 | AU39: {=_xlfn.LET(_xlpm.Res,IFBLANK(PL!$CQ$177,PL!$CP$177),IF(_xlpm.Res="","-",_xlpm.Res*fxVal_normal/1000000))} -> 1
F52: Example 1: Deal closed in May 2025, not reflected in the FY2025 Budget.
F89: Example 2: Portfolio company budgeting a perimeter change for an add-on expected to happen during the year, not yet closed.

Sheet PL
A1: unprotected | B1: 2025-12-23T03:33:24.755Z
N3: USER GUIDE
O4: {=IF(LEFT($A$1,3)="unp",icon_unlock,icon_lock)} -> #VALUE! | S4: #VALUE! | Y4: =_xlfn.IMAGE(INDEX(PM_Support[COMPANY_LOGO_URL],MATCH(val_company,PM_Support[COMPANY_NAME],0))) -> #VALUE!
S5: Worksheet Completion Guidance | Y5: Profit and Loss (OpCo) | AE5: =CX_ENTITY -> W06f9Irq7 | AG5: As of Date | AJ5: Fiscal Year End | AK5: Current FYE | AL5: Unit | AM5: Currency | DD5: =HYPERLINK(DD6,"Check CX") -> Check CX
S6: Hide grouping to minimise | AE6: =_PL!AE6 -> Therme Horizon | AG6: 46022 | AJ6: =_PL!AJ6 -> #NAME? | AK6: {=val_currentFYE} -> #NAME? | AL6: Millions | AM6: =val_reportingCurrency -> #NAME? | DD6: ="https://cvc.chronograph.pe/company-show/"&CX_ENTITY&"/analytics" -> https://cvc.chronograph.pe/company-show/W06f9Irq7/analytics
AK7: 46022 | CD7: Annual Summary | CM7: Forward Looking Data Collection
E9: Date | F9: Push | Y9: =IF(SUBTOTAL(103,W16:W124)=2,"Reported Actual & Budget","") | CJ9: {=DATEDIFF(PL!CJ$11,val_asOfDate,"M")} -> 1 | CK9: {=DATEDIFF(PL!CK$11,val_asOfDate,"M")} -> 0
B10: Developer Console | C10: Template Version Push | E10: =val_asOfDate -> 46022 | F10: {=_xldudf_CX_PUSH(pqToday,CX_ENTITY,"Flash Latest Version Date",val_asOfDate,"As of",W20)} -> #NAME? | H10: Colour | I10: Format | J10: Unpivot | K10: Push? | CD10: Full Financial Year | CG10: Financial Year To Date | CJ10: Last 12 Months | CM10: Current FY | CP10: Next FY
B11: PUSH NOTICE | C11: Flash Task Date Push | E11: =EOMONTH(val_asOfDate,1) -> 46053 | F11: {=_xldudf_CX_PUSH(pqToday,CX_ENTITY,"Flash Task Date",EOMONTH(val_asOfDate,1),"As of",W20)} -> #NAME? | X11: =IF(SUBTOTAL(103,$W$12:$W$14)>0,"Assistance","Summary") -> Assistance | Z11: =IF(SUBTOTAL(103,$W$12:$W$14)>0,"Completion","Requirement") -> Completion | AB11: Financial Period Ending | AD11: {=array_timeline} -> 44926 | AE11: 44957 | AF11: 44985 | AG11: 45016 | AH11: 45046 | AI11: 45077 | AJ11: 45107 | AK11: 45138 | AL11: 45169 | AM11: 45199 | AN11: 45230 | AO11: 45260 | AP11: 45291 | AQ11: 45322 | AR11: 45351 | AS11: 45382 | AT11: 45412 | AU11: 45443 | AV11: 45473 | AW11: 45504 | AX11: 45535 | AY11: 45565 | AZ11: 45596 | BA11: 45626 | BB11: 45657 | BC11: 45688 | BD11: 45716 | BE11: 45747 | BF11: 45777 | BG11: 45808 | BH11: 45838 | BI11: 45869 | BJ11: 45900 | BK11: 45930 | BL11: 45961 | BM11: 45991 | BN11: 46022 | CD11: {=EOMONTH(val_currentFYE,-24)} -> #NAME? | CE11: {=EOMONTH(val_currentFYE,-12)} -> #NAME? | CG11: =EOMONTH(val_asOfDate,-1) -> 45991 | CH11: =EOMONTH(val_asOfDate,0) -> 46022 | CJ11: =EOMONTH(val_asOfDate,-1) -> 45991 | CK11: =EOMONTH(val_asOfDate,0) -> 46022 | CM11: {=val_currentFYE} -> #NAME? | CN11: {=val_currentFYE} -> #NAME? | CP11: {=EOMONTH(val_currentFYE,12)} -> #NAME? | CQ11: {=EOMONTH(val_currentFYE,12)} -> #NAME?
B12: As part of process, the push operation should push Field values to CX against the folloiwng parameters Task month (as of date) and the month following. | S12: Input (White shading, black font) | T12: Refer to the definitions in columns X–Y for all mandatory fields. | W12: Dropdown | X12: {=fx_getIcon("select")} -> #VALUE! | Y12: Required | Z12: {=_xlfn.SWITCH(TRUE,_BS!$L31=TRUE,1,_BS!$L31=FALSE,-1,_BS!$L31=-1,0,"")} -> 1 | AB12: Financial Period | AD12: =EOMONTH(AD11,12-MONTH(val_currentFYE)) -> #NAME? | AE12: {=EOMONTH(AE11,12-MONTH(val_currentFYE))} -> #NAME? | AF12: {=EOMONTH(AF11,12-MONTH(val_currentFYE))} -> #NAME? | AG12: {=EOMONTH(AG11,12-MONTH(val_currentFYE))} -> #NAME? | AH12: {=EOMONTH(AH11,12-MONTH(val_currentFYE))} -> #NAME? | AI12: {=EOMONTH(AI11,12-MONTH(val_currentFYE))} -> #NAME? | AJ12: {=EOMONTH(AJ11,12-MONTH(val_currentFYE))} -> #NAME? | AK12: {=EOMONTH(AK11,12-MONTH(val_currentFYE))} -> #NAME? | AL12: {=EOMONTH(AL11,12-MONTH(val_currentFYE))} -> #NAME? | ... BN12: {=EOMONTH(BN11,12-MONTH(val_currentFYE))} -> #NAME? | CD12: {=YEAR(val_currentFYE)-2} -> #NAME? | CE12: {=YEAR(val_currentFYE)-1} -> #NAME? | CG12: =YEAR(EOMONTH(CG$11,12-MONTH(val_currentFYE))) -> #NAME? | CH12: =YEAR(EOMONTH(CH$11,12-MONTH(val_currentFYE))) -> #NAME? | CJ12: LTM | CK12: LTM | CM12: {=YEAR(val_currentFYE)} -> #NAME? | CN12: {=YEAR(val_currentFYE)} -> #NAME? | CP12: {=YEAR(val_currentFYE)+1} -> #NAME? | CQ12: {=YEAR(val_currentFYE)+1} -> #NAME?
B13: As | H13: 2-blue | I13: 1 num | J13: 1 Req, 0 Opt, -1 Auto | S13: Formula (Off-blue shading, blue font) | T13: Summary type of formula | W13: Sign | X13: a | Y13: Optional | Z13: -1 | AB13: Months prior | AD13: {=_xlfn.SEQUENCE(1,37,-36,1)} -> -36 | AE13: -35 | AF13: -34 | AG13: -33 | AH13: -32 | AI13: -31 | AJ13: -30 | AK13: -29 | AL13: -28 | AM13: -27 | AN13: -26 | AO13: -25 | AP13: -24 | AQ13: -23 | AR13: -22 | AS13: -21 | AT13: -20 | AU13: -19 | AV13: -18 | AW13: -17 | AX13: -16 | AY13: -15 | AZ13: -14 | BA13: -13 | BB13: -12 | BC13: -11 | BD13: -10 | BE13: -9 | BF13: -8 | BG13: -7 | BH13: -6 | BI13: -5 | BJ13: -4 | BK13: -3 | BL13: -2 | BM13: -1 | BN13: 0
A14: FALSE | B14: Show Unprotected Cell | D14: Modify with caution! | I14: 2 pct | J14: Blank - not upload | S14: Formula (Grey shading, black font) | T14: Prefilled formula | W14: Total/Ref | X14: 0 | Y14: Calculated | Z14: 0 | AB14: Period Type | AD14: Month | AE14: =$AD$14 -> Month | AF14: =$AD$14 -> Month | AG14: =$AD$14 -> Month | AH14: =$AD$14 -> Month | AI14: =$AD$14 -> Month | AJ14: =$AD$14 -> Month | AK14: =$AD$14 -> Month | AL14: =$AD$14 -> Month | ... BN14: =$AD$14 -> Month | CD14: FY | CE14: FY | CG14: FYTD | CH14: FYTD | CJ14: LTM | CK14: LTM | CM14: LTM | CN14: LTM | CP14: LTM | CQ14: LTM
D15: Column below used for filtering dropdown in segments | I15: 3 date | S15: {=fx_getIcon("find")} -> #VALUE! | T15: (Icon Only) Suggesting Definition for the term is available | AB15: Conditional formatting | AD15: {=IF(MONTH(AD11)=MONTH(val_currentFYE),1,IF(MOD(MONTH(AD$11)-MONTH(val_currentFYE),3)=0,2,0))} -> #NAME? | AE15: {=IF(MONTH(AE11)=MONTH(val_currentFYE),1,IF(MOD(MONTH(AE$11)-MONTH(val_currentFYE),3)=0,2,0))} -> #NAME? | AF15: {=IF(MONTH(AF11)=MONTH(val_currentFYE),1,IF(MOD(MONTH(AF$11)-MONTH(val_currentFYE),3)=0,2,0))} -> #NAME? | AG15: {=IF(MONTH(AG11)=MONTH(val_currentFYE),1,IF(MOD(MONTH(AG$11)-MONTH(val_currentFYE),3)=0,2,0))} -> #NAME? | AH15: {=IF(MONTH(AH11)=MONTH(val_currentFYE),1,IF(MOD(MONTH(AH$11)-MONTH(val_currentFYE),3)=0,2,0))} -> #NAME? | AI15: {=IF(MONTH(AI11)=MONTH(val_currentFYE),1,IF(MOD(MONTH(AI$11)-MONTH(val_currentFYE),3)=0,2,0))} -> #NAME? | AJ15: {=IF(MONTH(AJ11)=MONTH(val_currentFYE),1,IF(MOD(MONTH(AJ$11)-MONTH(val_currentFYE),3)=0,2,0))} -> #NAME? | AK15: {=IF(MONTH(AK11)=MONTH(val_currentFYE),1,IF(MOD(MONTH(AK$11)-MONTH(val_currentFYE),3)=0,2,0))} -> #NAME? | ... BN15: {=IF(MONTH(BN11)=MONTH(val_currentFYE),1,IF(MOD(MONTH(BN$11)-MONTH(val_currentFYE),3)=0,2,0))} -> #NAME?
W17: =_PL!W17 -> Actual | Y17: Monthly P&L | Z17: [Required] | AB17: Completion Indicator | AD17: {=fx_checkComp(AD20:AD41)} -> 100 | AE17: {=fx_checkComp(AE20:AE41)} -> 100 | AF17: {=fx_checkComp(AF20:AF41)} -> 100 | AG17: {=fx_checkComp(AG20:AG41)} -> 100 | AH17: {=fx_checkComp(AH20:AH41)} -> 100 | AI17: {=fx_checkComp(AI20:AI41)} -> 100 | AJ17: {=fx_checkComp(AJ20:AJ41)} -> 100 | AK17: {=fx_checkComp(AK20:AK41)} -> 100 | ... BN17: {=fx_checkComp(BN20:BN41)} -> 100 | CM17: {=fx_checkComp(CM20:CM41)} -> 100 | CN17: {=fx_checkComp(CN20:CN41)} -> 100 | CP17: {=fx_checkComp(CP20:CP41)} -> 100 | CQ17: {=fx_checkComp(CQ20:CQ41)} -> 100
AB18: Type: Completed / Total | AD18: O: 6 / 6 | AE18: O: 6 / 6 | AF18: O: 6 / 6 | AG18: O: 6 / 6 | AH18: O: 6 / 6 | AI18: O: 6 / 6 | AJ18: O: 6 / 6 | AK18: O: 6 / 6 | AL18: O: 6 / 6 | AM18: O: 6 / 6 | AN18: O: 6 / 6 | AO18: O: 6 / 6 | AP18: O: 6 / 6 | AQ18: O: 6 / 6 | AR18: O: 6 / 6 | AS18: O: 6 / 6 | AT18: O: 6 / 6 | AU18: O: 6 / 6 | AV18: O: 6 / 6 | AW18: O: 6 / 6 | AX18: O: 6 / 6 | AY18: O: 6 / 6 | AZ18: O: 6 / 6 | BA18: O: 6 / 6 | BB18: O: 6 / 6 | BC18: O: 6 / 6 | BD18: O: 6 / 6 | BE18: O: 6 / 6 | BF18: O: 6 / 6 | BG18: O: 6 / 6 | BH18: O: 6 / 6 | BI18: O: 6 / 6 | BJ18: O: 6 / 6 | BK18: O: 6 / 6 | BL18: O: 6 / 6 | BM18: O: 6 / 6 | BN18: O: 6 / 6 | CM18: O: 6 / 6 | CN18: O: 6 / 6 | CP18: O: 6 / 6 | CQ18: O: 6 / 6
B19: Metric Attribute | C19: Field Attribute | D19: Utility Column (Prefilled Text) - Please ignore | E19: TOTAL | F19: NOT BLANK | G19: TYPE | H19: BgFill | I19: Fmt | J19: Required | K19: To Push | W19: Scenario | X19: =_PL!X19 -> a | Y19: =val_company&" P&L Accounts" -> Therme Horizon P&L Accounts | AB19: CVC Standard P&L A/C | AD19: =$W$17 -> Actual | AE19: =$W$17 -> Actual | AF19: =$W$17 -> Actual | AG19: =$W$17 -> Actual | AH19: =$W$17 -> Actual | AI19: =$W$17 -> Actual | AJ19: =$W$17 -> Actual | AK19: =$W$17 -> Actual | ... BN19: =$W$17 -> Actual | CD19: =$W$17 -> Actual | CE19: =$W$17 -> Actual | CG19: {=fx_scenarioConverter($W17)} -> Actual | CH19: {=fx_scenarioConverter($W17)} -> Actual | CJ19: {=fx_scenarioConverter($W17)} -> Actual | CK19: {=fx_scenarioConverter($W17)} -> Actual | CM19: {=fx_scenarioConverter("Original Budget")} -> Original Budget | CN19: {=fx_scenarioConverter("LE")} -> LE | CP19: {=fx_scenarioConverter("Original Budget")} -> Original Budget | CQ19: {=fx_scenarioConverter("LE")} -> LE | CT19: {=RIGHT(CELL("filename",A1),LEN(CELL("filename",A1))-FIND("]",CELL("filename",A1)))&" "&"Label PUSH"&TEXT(val_asOfDate," MMm-YY")} -> PL Label PUSH Dec-25 | CU19: {=RIGHT(CELL("filename",A1),LEN(CELL("filename",A1))-FIND("]",CELL("filename",A1)))&" "&"Label PUSH"&TEXT(EOMONTH(val_asOfDate,1)," MMMM-YY")} -> PL Label PUSH January-26 | CV19: {=RIGHT(CELL("filename",B1),LEN(CELL("filename",B1))-FIND("]",CELL("filename",B1)))&" "&"Label PUSH"&TEXT(EOMONTH(val_asOfDate,2)," MMMM-YY")} -> PL Label PUSH February-26 | CW19: {=RIGHT(CELL("filename",B1),LEN(CELL("filename",B1))-FIND("]",CELL("filename",B1)))&" "&"Label PUSH"&TEXT(EOMONTH(val_asOfDate,2)," MMMM-YY")} -> PL Label PUSH February-26 | CY19: {=RIGHT(CELL("filename",A1),LEN(CELL("filename",A1))-FIND("]",CELL("filename",A1)))&" "&$CM$10&" PUSH"} -> PL Current FY PUSH | CZ19: {=RIGHT(CELL("filename",A1),LEN(CELL("filename",A1))-FIND("]",CELL("filename",A1)))&" "&$CM$10&" PUSH"} -> PL Current FY PUSH | DA19: {=RIGHT(CELL("filename",C1),LEN(CELL("filename",C1))-FIND("]",CELL("filename",C1)))&" "&$CP$10&" PUSH"} -> PL Next FY PUSH | DB19: {=RIGHT(CELL("filename",C1),LEN(CELL("filename",C1))-FIND("]",CELL("filename",C1)))&" "&$CP$10&" PUSH"} -> PL Next FY PUSH | DD19: {=RIGHT(CELL("filename",$A$1),LEN(CELL("filename",$A$1))-FIND("]",CELL("filename",$A$1)))&" PUSH"} -> PL PUSH | DE19: {=RIGHT(CELL("filename",$A$1),LEN(CELL("filename",$A$1))-FIND("]",CELL("filename",$A$1)))&" PUSH"} -> PL PUSH | DF19: {=RIGHT(CELL("filename",$A$1),LEN(CELL("filename",$A$1))-FIND("]",CELL("filename",$A$1)))&" PUSH"} -> PL PUSH | DG19: {=RIGHT(CELL("filename",$A$1),LEN(CELL("filename",$A$1))-FIND("]",CELL("filename",$A$1)))&" PUSH"} -> PL PUSH | DH19: {=RIGHT(CELL("filename",$A$1),LEN(CELL("filename",$A$1))-FIND("]",CELL("filename",$A$1)))&" PUSH"} -> PL PUSH | DI19: {=RIGHT(CELL("filename",$A$1),LEN(CELL("filename",$A$1))-FIND("]",CELL("filename",$A$1)))&" PUSH"} -> PL PUSH | DJ19: {=RIGHT(CELL("filename",$A$1),LEN(CELL("filename",$A$1))-FIND("]",CELL("filename",$A$1)))&" PUSH"} -> PL PUSH | DK19: {=RIGHT(CELL("filename",$A$1),LEN(CELL("filename",$A$1))-FIND("]",CELL("filename",$A$1)))&" PUSH"} -> PL PUSH | ... EN19: {=RIGHT(CELL("filename",$A$1),LEN(CELL("filename",$A$1))-FIND("]",CELL("filename",$A$1)))&" PUSH"} -> PL PUSH
A20: F | B20: =_xlfn.LET(_xlpm.IsNotAttrDynamic,D20="",_xlpm.Attr,_PL!F20,_xlpm.NotInUse,Y20=D20,_xlpm.RESULT,IF(_xlpm.IsNotAttrDynamic,_xlpm.Attr,IF(_xlpm.NotInUse,"",Y20)),IF(_xlpm.RESULT="","",_xlpm.RESULT)) -> Net Revenue | C20: {=IFBLANK(_PL!C20,"")} -> Net Revenue (Company View) | E20: {=_xlfn.LAMBDA(_xlpm.Array,_xlop.Type,_xlfn.LET(_xlpm._type,IF(_xlfn.ISOMITTED(_xlpm.Type),0,_xlpm.Type),_xlpm.R,ROWS(_xlpm.Array),_xlpm.C,COLUMNS(_xlpm.Array),_xlpm.Unlocked,_xlfn.MAKEARRAY(_xlpm.R,_xlpm.C,_xlfn.LAMBDA(_xlpm.i,_xlpm.j,--(CELL("protect",INDEX(_xlpm.Array,_xlpm.i,_xlpm.j))=0))),_xlpm.IsUnlocked,_xlfn.MAKEARRAY(_xlpm.R,_xlpm.C,_xlfn.LAMBDA(_xlpm.i,_xlpm.j,CELL("protect",INDEX(_xlpm.Array,_xlpm.i,_xlpm.j))=0)),_xlpm.HasData,_xlpm.Array<>"",_xlpm.Total,SUM(_xlpm.Unlocked),_xlpm.Completed,SUM(--(_xlpm.IsUnlocked*_xlpm.HasData)),_xlpm.type_display,_xlfn.SWITCH(_xlpm._type,1,"R",-1,"O",0,"A",""),_xlfn.HSTACK(_xlpm.Total,_xlpm.Completed,_xlpm.type_display)))($AD20:$CQ20,Z20)} -> #NAME? | H20: 0 | I20: 1 | J20: =IF(OR(ISNUMBER(SEARCH("required",Z20)),ISNUMBER(SEARCH("optional",Z20))),"",Z20) -> 1 | K20: =IFERROR(IF(LEN(AB20)=0,"No",IF(LEN(J20)>0,"Yes","No")),"") -> Yes | W20: {=fx_scenarioConverter($W$17)} -> Actual | X20: =_PL!X20 -> 1 | Y20: 2 | Z20: {=_xlfn.SWITCH(TRUE,_PL!$L20=TRUE,1,_PL!$L20=FALSE,-1,_PL!$L20=-1,0,"")} -> 1 | AB20: =_PL!AB20 -> Net Revenue | AC20: {=_xlfn.LET(_xlpm._termname,$AB20,_xlpm._iconname,"find",_xlpm._icon,fx_getIcon(_xlpm._iconname),_xlpm._location,_xlfn.XLOOKUP(LOWER(_xlpm._termname),LOWER(tbl_acctDef[Term]),tbl_acctDef[Term]),_xlpm._hyperlink,HYPERLINK("#"&CELL("address",_xlpm._location),_xlpm._icon),IFERROR(_xlpm._hyperlink,""))} -> #VALUE! | AD20: 1 | AE20: 1 | AF20: 1 | AG20: 1 | AH20: 1 | AI20: 1 | AJ20: 1 | AK20: 1 | AL20: 1 | AM20: 1 | AN20: 1 | AO20: 1 | AP20: 1 | AQ20: 1 | AR20: 1 | AS20: 1 | AT20: 1 | AU20: 1 | AV20: 1 | AW20: 1 | AX20: 1 | AY20: 1 | AZ20: 1 | BA20: 1 | BB20: 1 | BC20: 1 | BD20: 1 | BE20: 1 | BF20: 1 | BG20: 1 | BH20: 1 | BI20: 1 | BJ20: 1 | BK20: 1 | BL20: 1 | BM20: 1 | BN20: 1 | CD20: {=_xlfn.LET(_xlpm.CheckBlank,SUM(PL!$AD20:$BN20)=0,IF(_xlpm.CheckBlank,"",SUM(_xlfn._xlws.FILTER(PL!$AD20:$BN20,(YEAR(PL!$AD$12:$BN$12)=PL!CD$12)*(array_timeline<=PL!CD$11)))))} -> #NAME? | CE20: {=_xlfn.LET(_xlpm.CheckBlank,SUM(PL!$AD20:$BN20)=0,IF(_xlpm.CheckBlank,"",SUM(_xlfn._xlws.FILTER(PL!$AD20:$BN20,(YEAR(PL!$AD$12:$BN$12)=PL!CE$12)*(array_timeline<=PL!CE$11)))))} -> #NAME? | CG20: {=IFERROR(_xlfn.LET(_xlpm.CheckBlank,SUM(PL!$AD20:$BN20)=0,IF(_xlpm.CheckBlank,"",SUM(_xlfn._xlws.FILTER(PL!$AD20:$BN20,(YEAR(PL!$AD$12:$BN$12)=PL!CG$12)*(array_timeline<=PL!CG$11))))),"n/a")} -> n/a | CH20: {=_xlfn.LET(_xlpm.CheckBlank,SUM(PL!$AD20:$BN20)=0,IF(_xlpm.CheckBlank,"",SUM(_xlfn._xlws.FILTER(PL!$AD20:$BN20,(YEAR(PL!$AD$12:$BN$12)=PL!CH$12)*(array_timeline<=PL!CH$11)))))} -> #NAME? | CJ20: {=_xlfn.LET(_xlpm.CheckBlank,SUM(PL!$AD20:$BN20)=0,IF(_xlpm.CheckBlank,"",SUM(_xlfn.TAKE(_xlfn.DROP(PL!$AD20:$BN20,,-DATEDIFF(PL!CJ$11,val_asOfDate,"M")),1,-12))))} -> 12 | CK20: {=_xlfn.LET(_xlpm.CheckBlank,SUM(PL!$AD20:$BN20)=0,IF(_xlpm.CheckBlank,"",SUM(_xlfn.TAKE(_xlfn.DROP(PL!$AD20:$BN20,,-DATEDIFF(PL!CK$11,val_asOfDate,"M")),1,-12))))} -> 12 | CM20: 1 | CN20: 1 | CP20: 1 | CQ20: 1 | CT20: {=IF(K20<>"Yes","",IF(OR(Y20="Select, enter text or leave as blank.",Y20="Set from Actual section above!",Y20="Please select or type in or leave as blank",Y20="Select, enter text or leave as blank",Y20="Please select your Top Line Metric",Y20="Check Sum",Y20="Please name your Like-for-Like Revenue",Y20="Please name your Like-for-like Earning Metric",Y20="Valuation Metric",Y20="Please name your Like-for-like Valuation Metric",Y20="Please select your Valuation Metric",Y20="Please select the metric for segmentation",Y20="Untitled Segmentation II",Y20="Untitled Segmentation III"),"",IF(OR(Y20<>AB20,AND(LEN(B20)=0,NOT(OR(Y20="Select, enter text or leave as blank.",Y20="Set from Actual section above!",Y20="Please select or type in or leave as blank",Y20="Select, enter text or leave as blank",Y20="Please select your Top Line Metric",Y20="Check Sum",Y20="Please name your Like-for-Like Revenue",Y20="Please name your Like-for-like Earning Metric",Y20="Valuation Metric",Y20="Please name your Like-for-like Valuation Metric",Y20="Please select your Valuation Metric",Y20="Please select the metric for segmentation",Y20="Untitled Segmentation II",Y20="Untitled Segmentation III")))),_xldudf_CX_PUSH(Y20,CX_ENTITY,C20,EOMONTH(val_asOfDate,0)),"")))} -> #NAME? | CU20: {=IF(K20<>"Yes","",IF(OR(Y20="Select, enter text or leave as blank.",Y20="Set from Actual section above!",Y20="Please select or type in or leave as blank",Y20="Select, enter text or leave as blank",Y20="Please select your Top Line Metric",Y20="Check Sum",Y20="Please name your Like-for-Like Revenue",Y20="Please name your Like-for-like Earning Metric",Y20="Valuation Metric",Y20="Please name your Like-for-like Valuation Metric",Y20="Please select your Valuation Metric",Y20="Please select the metric for segmentation",Y20="Untitled Segmentation II",Y20="Untitled Segmentation III"),"",IF(OR(Y20<>AB20,AND(LEN(B20)=0,NOT(OR(Y20="Select, enter text or leave as blank.",Y20="Set from Actual section above!",Y20="Please select or type in or leave as blank",Y20="Select, enter text or leave as blank",Y20="Please select your Top Line Metric",Y20="Check Sum",Y20="Please name your Like-for-Like Revenue",Y20="Please name your Like-for-like Earning Metric",Y20="Valuation Metric",Y20="Please name your Like-for-like Valuation Metric",Y20="Please select your Valuation Metric",Y20="Please select the metric for segmentation",Y20="Untitled Segmentation II",Y20="Untitled Segmentation III")))),_xldudf_CX_PUSH(Y20,CX_ENTITY,C20,EOMONTH(val_asOfDate,1)),"")))} -> #NAME? | CV20: {=IF(K20<>"Yes","",IF(OR(Y20="Select, enter text or leave as blank.",Y20="Set from Actual section above!",Y20="Please select or type in or leave as blank",Y20="Select, enter text or leave as blank",Y20="Please select your Top Line Metric",Y20="Check Sum",Y20="Please name your Like-for-Like Revenue",Y20="Please name your Like-for-like Earning Metric",Y20="Valuation Metric",Y20="Please name your Like-for-like Valuation Metric",Y20="Please select your Valuation Metric",Y20="Please select the metric for segmentation",Y20="Untitled Segmentation II",Y20="Untitled Segmentation III"),"",IF(OR(Y20<>AB20,AND(LEN(B20)=0,NOT(OR(Y20="Select, enter text or leave as blank.",Y20="Set from Actual section above!",Y20="Please select or type in or leave as blank",Y20="Select, enter text or leave as blank",Y20="Please select your Top Line Metric",Y20="Check Sum",Y20="Please name your Like-for-Like Revenue",Y20="Please name your Like-for-like Earning Metric",Y20="Valuation Metric",Y20="Please name your Like-for-like Valuation Metric",Y20="Please select your Valuation Metric",Y20="Please select the metric for segmentation",Y20="Untitled Segmentation II",Y20="Untitled Segmentation III")))),_xldudf_CX_PUSH(Y20,CX_ENTITY,C20,EOMONTH(val_asOfDate,2)),"")))} -> #NAME? | CW20: {=IF(K20<>"Yes","",IF(OR(Y20="Select, enter text or leave as blank.",Y20="Set from Actual section above!",Y20="Please select or type in or leave as blank",Y20="Select, enter text or leave as blank",Y20="Please select your Top Line Metric",Y20="Check Sum",Y20="Please name your Like-for-Like Revenue",Y20="Please name your Like-for-like Earning Metric",Y20="Valuation Metric",Y20="Please name your Like-for-like Valuation Metric",Y20="Please select your Valuation Metric",Y20="Please select the metric for segmentation",Y20="Untitled Segmentation II",Y20="Untitled Segmentation III"),"",IF(OR(Y20<>AB20,AND(LEN(B20)=0,NOT(OR(Y20="Select, enter text or leave as blank.",Y20="Set from Actual section above!",Y20="Please select or type in or leave as blank",Y20="Select, enter text or leave as blank",Y20="Please select your Top Line Metric",Y20="Check Sum",Y20="Please name your Like-for-Like Revenue",Y20="Please name your Like-for-like Earning Metric",Y20="Valuation Metric",Y20="Please name your Like-for-like Valuation Metric",Y20="Please select your Valuation Metric",Y20="Please select the metric for segmentation",Y20="Untitled Segmentation II",Y20="Untitled Segmentation III")))),_xldudf_CX_PUSH(Y20,CX_ENTITY,C20,EOMONTH(val_asOfDate,3)),"")))} -> #NAME? | CY20: {=IFERROR(IF(CM20*fxVal_normal=_PL!CM20,"",IF(OR($CM20="",$CM20=0,NOT(ISNUMBER($CM20)),ISERROR($CM20),$B20=""),"",IF($I20=1,IFBLANK(_xldudf_CX_PUSH($CM20*fxVal_normal,CX_ENTITY,$B20,$CM$11,$CM$14,$CM$19,),""),IF($I20=2,IFBLANK(_xldudf_CX_PUSH($CM20,CX_ENTITY,$B20,$CM$11,$CM$14,$CM$19,),""),IF($I20=3,"",IFBLANK(_xldudf_CX_PUSH($CM20,CX_ENTITY,$B20,$CM$11,$CM$14,$CM$19,),"")))))),"")} | CZ20: {=IFERROR(IF(CN20*fxVal_normal=_PL!CN20,"",IF(OR($CN20="",$CN20=0,NOT(ISNUMBER($CN20)),ISERROR($CN20),$B20=""),"",IF($I20=1,IFBLANK(_xldudf_CX_PUSH($CN20*fxVal_normal,CX_ENTITY,$B20,$CN$11,$CN$14,$CN$19,),""),IF($I20=2,IFBLANK(_xldudf_CX_PUSH($CN20,CX_ENTITY,$B20,$CN$11,$CN$14,$CN$19,),""),IF($I20=3,"",IFBLANK(_xldudf_CX_PUSH($CN20,CX_ENTITY,$B20,$CN$11,$CN$14,$CN$19,),"")))))),"")} | DA20: {=IFERROR(IF(CP20*fxVal_normal=_PL!CP20,"",IF(OR($CP20="",$CP20=0,NOT(ISNUMBER($CP20)),ISERROR($CP20),$B20=""),"",IF($I20=1,IFBLANK(_xldudf_CX_PUSH($CP20*fxVal_normal,CX_ENTITY,$B20,$CP$11,$CP$14,$CP$19,),""),IF($I20=2,IFBLANK(_xldudf_CX_PUSH($CP20,CX_ENTITY,$B20,$CP$11,$CP$14,$CP$19,),""),IF($I20=3,"",IFBLANK(_xldudf_CX_PUSH($CP20,CX_ENTITY,$B20,$CP$11,$CP$14,$CP$19,),"")))))),"")} | DB20: {=IFERROR(IF(CQ20*fxVal_normal=_PL!CQ20,"",IF(OR($CQ20="",$CQ20=0,NOT(ISNUMBER($CQ20)),ISERROR($CQ20),$B20=""),"",IF($I20=1,IFBLANK(_xldudf_CX_PUSH($CQ20*fxVal_normal,CX_ENTITY,$B20,$CQ$11,$CQ$14,$CQ$19,),""),IF($I20=2,IFBLANK(_xldudf_CX_PUSH($CQ20,CX_ENTITY,$B20,$CQ$11,$CQ$14,$CQ$19,),""),IF($I20=3,"",IFBLANK(_xldudf_CX_PUSH($CQ20,CX_ENTITY,$B20,$CQ$11,$CQ$14,$CQ$19,),"")))))),"")} | DD20: {=IFERROR(IF(AD20*fxVal_normal=_PL!AD20,"",IF(OR(AD20="",NOT(ISNUMBER(AD20)),ISERROR(AD20),$B20=""),"",IF($I20=1,IFBLANK(_xldudf_CX_PUSH(AD20*fxVal_normal,CX_ENTITY,$B20,AD$11,AD$14,AD$19,),""),IF($I20=2,IFBLANK(_xldudf_CX_PUSH(AD20,CX_ENTITY,$B20,AD$11,AD$14,AD$19,),""),IF($I20=3,"",IFBLANK(_xldudf_CX_PUSH(AD20,CX_ENTITY,$B20,AD$11,AD$14,AD$19,),"")))))),"")} | DE20: {=IFERROR(IF(AE20*fxVal_normal=_PL!AE20,"",IF(OR(AE20="",NOT(ISNUMBER(AE20)),ISERROR(AE20),$B20=""),"",IF($I20=1,IFBLANK(_xldudf_CX_PUSH(AE20*fxVal_normal,CX_ENTITY,$B20,AE$11,AE$14,AE$19,),""),IF($I20=2,IFBLANK(_xldudf_CX_PUSH(AE20,CX_ENTITY,$B20,AE$11,AE$14,AE$19,),""),IF($I20=3,"",IFBLANK(_xldudf_CX_PUSH(AE20,CX_ENTITY,$B20,AE$11,AE$14,AE$19,),"")))))),"")} | DF20: {=IFERROR(IF(AF20*fxVal_normal=_PL!AF20,"",IF(OR(AF20="",NOT(ISNUMBER(AF20)),ISERROR(AF20),$B20=""),"",IF($I20=1,IFBLANK(_xldudf_CX_PUSH(AF20*fxVal_normal,CX_ENTITY,$B20,AF$11,AF$14,AF$19,),""),IF($I20=2,IFBLANK(_xldudf_CX_PUSH(AF20,CX_ENTITY,$B20,AF$11,AF$14,AF$19,),""),IF($I20=3,"",IFBLANK(_xldudf_CX_PUSH(AF20,CX_ENTITY,$B20,AF$11,AF$14,AF$19,),"")))))),"")} | DG20: {=IFERROR(IF(AG20*fxVal_normal=_PL!AG20,"",IF(OR(AG20="",NOT(ISNUMBER(AG20)),ISERROR(AG20),$B20=""),"",IF($I20=1,IFBLANK(_xldudf_CX_PUSH(AG20*fxVal_normal,CX_ENTITY,$B20,AG$11,AG$14,AG$19,),""),IF($I20=2,IFBLANK(_xldudf_CX_PUSH(AG20,CX_ENTITY,$B20,AG$11,AG$14,AG$19,),""),IF($I20=3,"",IFBLANK(_xldudf_CX_PUSH(AG20,CX_ENTITY,$B20,AG$11,AG$14,AG$19,),"")))))),"")} | DH20: {=IFERROR(IF(AH20*fxVal_normal=_PL!AH20,"",IF(OR(AH20="",NOT(ISNUMBER(AH20)),ISERROR(AH20),$B20=""),"",IF($I20=1,IFBLANK(_xldudf_CX_PUSH(AH20*fxVal_normal,CX_ENTITY,$B20,AH$11,AH$14,AH$19,),""),IF($I20=2,IFBLANK(_xldudf_CX_PUSH(AH20,CX_ENTITY,$B20,AH$11,AH$14,AH$19,),""),IF($I20=3,"",IFBLANK(_xldudf_CX_PUSH(AH20,CX_ENTITY,$B20,AH$11,AH$14,AH$19,),"")))))),"")} | DI20: {=IFERROR(IF(AI20*fxVal_normal=_PL!AI20,"",IF(OR(AI20="",NOT(ISNUMBER(AI20)),ISERROR(AI20),$B20=""),"",IF($I20=1,IFBLANK(_xldudf_CX_PUSH(AI20*fxVal_normal,CX_ENTITY,$B20,AI$11,AI$14,AI$19,),""),IF($I20=2,IFBLANK(_xldudf_CX_PUSH(AI20,CX_ENTITY,$B20,AI$11,AI$14,AI$19,),""),IF($I20=3,"",IFBLANK(_xldudf_CX_PUSH(AI20,CX_ENTITY,$B20,AI$11,AI$14,AI$19,),"")))))),"")} | DJ20: {=IFERROR(IF(AJ20*fxVal_normal=_PL!AJ20,"",IF(OR(AJ20="",NOT(ISNUMBER(AJ20)),ISERROR(AJ20),$B20=""),"",IF($I20=1,IFBLANK(_xldudf_CX_PUSH(AJ20*fxVal_normal,CX_ENTITY,$B20,AJ$11,AJ$14,AJ$19,),""),IF($I20=2,IFBLANK(_xldudf_CX_PUSH(AJ20,CX_ENTITY,$B20,AJ$11,AJ$14,AJ$19,),""),IF($I20=3,"",IFBLANK(_xldudf_CX_PUSH(AJ20,CX_ENTITY,$B20,AJ$11,AJ$14,AJ$19,),"")))))),"")} | DK20: {=IFERROR(IF(AK20*fxVal_normal=_PL!AK20,"",IF(OR(AK20="",NOT(ISNUMBER(AK20)),ISERROR(AK20),$B20=""),"",IF($I20=1,IFBLANK(_xldudf_CX_PUSH(AK20*fxVal_normal,CX_ENTITY,$B20,AK$11,AK$14,AK$19,),""),IF($I20=2,IFBLANK(_xldudf_CX_PUSH(AK20,CX_ENTITY,$B20,AK$11,AK$14,AK$19,),""),IF($I20=3,"",IFBLANK(_xldudf_CX_PUSH(AK20,CX_ENTITY,$B20,AK$11,AK$14,AK$19,),"")))))),"")} | ... EN20: {=IFERROR(IF(BN20*fxVal_normal=_PL!BN20,"",IF(OR(BN20="",NOT(ISNUMBER(BN20)),ISERROR(BN20),$B20=""),"",IF($I20=1,IFBLANK(_xldudf_CX_PUSH(BN20*fxVal_normal,CX_ENTITY,$B20,BN$11,BN$14,BN$19,),""),IF($I20=2,IFBLANK(_xldudf_CX_PUSH(BN20,CX_ENTITY,$B20,BN$11,BN$14,BN$19,),""),IF($I20=3,"",IFBLANK(_xldudf_CX_PUSH(BN20,CX_ENTITY,$B20,BN$11,BN$14,BN$19,),"")))))),"")}
B21: =_xlfn.LET(_xlpm.IsNotAttrDynamic,D21="",_xlpm.Attr,_PL!F21,_xlpm.NotInUse,Y21=D21,_xlpm.RESULT,IF(_xlpm.IsNotAttrDynamic,_xlpm.Attr,IF(_xlpm.NotInUse,"",Y21)),IF(_xlpm.RESULT="","",_xlpm.RESULT)) -> Cost of Sales | C21: {=IFBLANK(_PL!C21,"")} -> Cost of Sales (Company View) | E21: {=_xlfn.LAMBDA(_xlpm.Array,_xlop.Type,_xlfn.LET(_xlpm._type,IF(_xlfn.ISOMITTED(_xlpm.Type),0,_xlpm.Type),_xlpm.R,ROWS(_xlpm.Array),_xlpm.C,COLUMNS(_xlpm.Array),_xlpm.Unlocked,_xlfn.MAKEARRAY(_xlpm.R,_xlpm.C,_xlfn.LAMBDA(_xlpm.i,_xlpm.j,--(CELL("protect",INDEX(_xlpm.Array,_xlpm.i,_xlpm.j))=0))),_xlpm.IsUnlocked,_xlfn.MAKEARRAY(_xlpm.R,_xlpm.C,_xlfn.LAMBDA(_xlpm.i,_xlpm.j,CELL("protect",INDEX(_xlpm.Array,_xlpm.i,_xlpm.j))=0)),_xlpm.HasData,_xlpm.Array<>"",_xlpm.Total,SUM(_xlpm.Unlocked),_xlpm.Completed,SUM(--(_xlpm.IsUnlocked*_xlpm.HasData)),_xlpm.type_display,_xlfn.SWITCH(_xlpm._type,1,"R",-1,"O",0,"A",""),_xlfn.HSTACK(_xlpm.Total,_xlpm.Completed,_xlpm.type_display)))($AD21:$CQ21,Z21)} -> #NAME? | H21: 0 | I21: 1 | J21: {=IFBLANK(Z21,"")} -> 1 | K21: =IFERROR(IF(LEN(AB21)=0,"No",IF(LEN(J21)>0,"Yes","No")),"") -> Yes | W21: =$W$20 -> Actual | X21: =_PL!X21 -> -1 | Y21: 2 | Z21: {=_xlfn.SWITCH(TRUE,_PL!$L21=TRUE,1,_PL!$L21=FALSE,-1,_PL!$L21=-1,0,"")} -> 1 | AB21: =_PL!AB21 -> Cost of Sales | AC21: {=_xlfn.LET(_xlpm._termname,$AB21,_xlpm._iconname,"find",_xlpm._icon,fx_getIcon(_xlpm._iconname),_xlpm._location,_xlfn.XLOOKUP(LOWER(_xlpm._termname),LOWER(tbl_acctDef[Term]),tbl_acctDef[Term]),_xlpm._hyperlink,HYPERLINK("#"&CELL("address",_xlpm._location),_xlpm._icon),IFERROR(_xlpm._hyperlink,""))} -> #VALUE! | AD21: 1 | AE21: 1 | AF21: 1 | AG21: 1 | AH21: 1 | AI21: 1 | AJ21: 1 | AK21: 1 | AL21: 1 | AM21: 1 | AN21: 1 | AO21: 1 | AP21: 1 | AQ21: 1 | AR21: 1 | AS21: 1 | AT21: 1 | AU21: 1 | AV21: 1 | AW21: 1 | AX21: 1 | AY21: 1 | AZ21: 1 | BA21: 1 | BB21: 1 | BC21: 1 | BD21: 1 | BE21: 1 | BF21: 1 | BG21: 1 | BH21: 1 | BI21: 1 | BJ21: 1 | BK21: 1 | BL21: 1 | BM21: 1 | BN21: 1 | CD21: {=_xlfn.LET(_xlpm.CheckBlank,SUM(PL!$AD21:$BN21)=0,IF(_xlpm.CheckBlank,"",SUM(_xlfn._xlws.FILTER(PL!$AD21:$BN21,(YEAR(PL!$AD$12:$BN$12)=PL!CD$12)*(array_timeline<=PL!CD$11)))))} -> #NAME? | CE21: {=_xlfn.LET(_xlpm.CheckBlank,SUM(PL!$AD21:$BN21)=0,IF(_xlpm.CheckBlank,"",SUM(_xlfn._xlws.FILTER(PL!$AD21:$BN21,(YEAR(PL!$AD$12:$BN$12)=PL!CE$12)*(array_timeline<=PL!CE$11)))))} -> #NAME? | CG21: {=IFERROR(_xlfn.LET(_xlpm.CheckBlank,SUM(PL!$AD21:$BN21)=0,IF(_xlpm.CheckBlank,"",SUM(_xlfn._xlws.FILTER(PL!$AD21:$BN21,(YEAR(PL!$AD$12:$BN$12)=PL!CG$12)*(array_timeline<=PL!CG$11))))),"n/a")} -> n/a | CH21: {=_xlfn.LET(_xlpm.CheckBlank,SUM(PL!$AD21:$BN21)=0,IF(_xlpm.CheckBlank,"",SUM(_xlfn._xlws.FILTER(PL!$AD21:$BN21,(YEAR(PL!$AD$12:$BN$12)=PL!CH$12)*(array_timeline<=PL!CH$11)))))} -> #NAME? | CJ21: {=_xlfn.LET(_xlpm.CheckBlank,SUM(PL!$AD21:$BN21)=0,IF(_xlpm.CheckBlank,"",SUM(_xlfn.TAKE(_xlfn.DROP(PL!$AD21:$BN21,,-DATEDIFF(PL!CJ$11,val_asOfDate,"M")),1,-12))))} -> 12 | CK21: {=_xlfn.LET(_xlpm.CheckBlank,SUM(PL!$AD21:$BN21)=0,IF(_xlpm.CheckBlank,"",SUM(_xlfn.TAKE(_xlfn.DROP(PL!$AD21:$BN21,,-DATEDIFF(PL!CK$11,val_asOfDate,"M")),1,-12))))} -> 12 | CM21: 1 | CN21: 1 | CP21: 1 | CQ21: 1 | CT21: {=IF(K21<>"Yes","",IF(OR(Y21="Select, enter text or leave as blank.",Y21="Set from Actual section above!",Y21="Please select or type in or leave as blank",Y21="Select, enter text or leave as blank",Y21="Please select your Top Line Metric",Y21="Check Sum",Y21="Please name your Like-for-Like Revenue",Y21="Please name your Like-for-like Earning Metric",Y21="Valuation Metric",Y21="Please name your Like-for-like Valuation Metric",Y21="Please select your Valuation Metric",Y21="Please select the metric for segmentation",Y21="Untitled Segmentation II",Y21="Untitled Segmentation III"),"",IF(OR(Y21<>AB21,AND(LEN(B21)=0,NOT(OR(Y21="Select, enter text or leave as blank.",Y21="Set from Actual section above!",Y21="Please select or type in or leave as blank",Y21="Select, enter text or leave as blank",Y21="Please select your Top Line Metric",Y21="Check Sum",Y21="Please name your Like-for-Like Revenue",Y21="Please name your Like-for-like Earning Metric",Y21="Valuation Metric",Y21="Please name your Like-for-like Valuation Metric",Y21="Please select your Valuation Metric",Y21="Please select the metric for segmentation",Y21="Untitled Segmentation II",Y21="Untitled Segmentation III")))),_xldudf_CX_PUSH(Y21,CX_ENTITY,C21,EOMONTH(val_asOfDate,0)),"")))} -> #NAME? | CU21: {=IF(K21<>"Yes","",IF(OR(Y21="Select, enter text or leave as blank.",Y21="Set from Actual section above!",Y21="Please select or type in or leave as blank",Y21="Select, enter text or leave as blank",Y21="Please select your Top Line Metric",Y21="Check Sum",Y21="Please name your Like-for-Like Revenue",Y21="Please name your Like-for-like Earning Metric",Y21="Valuation Metric",Y21="Please name your Like-for-like Valuation Metric",Y21="Please select your Valuation Metric",Y21="Please select the metric for segmentation",Y21="Untitled Segmentation II",Y21="Untitled Segmentation III"),"",IF(OR(Y21<>AB21,AND(LEN(B21)=0,NOT(OR(Y21="Select, enter text or leave as blank.",Y21="Set from Actual section above!",Y21="Please select or type in or leave as blank",Y21="Select, enter text or leave as blank",Y21="Please select your Top Line Metric",Y21="Check Sum",Y21="Please name your Like-for-Like Revenue",Y21="Please name your Like-for-like Earning Metric",Y21="Valuation Metric",Y21="Please name your Like-for-like Valuation Metric",Y21="Please select your Valuation Metric",Y21="Please select the metric for segmentation",Y21="Untitled Segmentation II",Y21="Untitled Segmentation III")))),_xldudf_CX_PUSH(Y21,CX_ENTITY,C21,EOMONTH(val_asOfDate,1)),"")))} -> #NAME? | CV21: {=IF(K21<>"Yes","",IF(OR(Y21="Select, enter text or leave as blank.",Y21="Set from Actual section above!",Y21="Please select or type in or leave as blank",Y21="Select, enter text or leave as blank",Y21="Please select your Top Line Metric",Y21="Check Sum",Y21="Please name your Like-for-Like Revenue",Y21="Please name your Like-for-like Earning Metric",Y21="Valuation Metric",Y21="Please name your Like-for-like Valuation Metric",Y21="Please select your Valuation Metric",Y21="Please select the metric for segmentation",Y21="Untitled Segmentation II",Y21="Untitled Segmentation III"),"",IF(OR(Y21<>AB21,AND(LEN(B21)=0,NOT(OR(Y21="Select, enter text or leave as blank.",Y21="Set from Actual section above!",Y21="Please select or type in or leave as blank",Y21="Select, enter text or leave as blank",Y21="Please select your Top Line Metric",Y21="Check Sum",Y21="Please name your Like-for-Like Revenue",Y21="Please name your Like-for-like Earning Metric",Y21="Valuation Metric",Y21="Please name your Like-for-like Valuation Metric",Y21="Please select your Valuation Metric",Y21="Please select the metric for segmentation",Y21="Untitled Segmentation II",Y21="Untitled Segmentation III")))),_xldudf_CX_PUSH(Y21,CX_ENTITY,C21,EOMONTH(val_asOfDate,2)),"")))} -> #NAME? | CW21: {=IF(K21<>"Yes","",IF(OR(Y21="Select, enter text or leave as blank.",Y21="Set from Actual section above!",Y21="Please select or type in or leave as blank",Y21="Select, enter text or leave as blank",Y21="Please select your Top Line Metric",Y21="Check Sum",Y21="Please name your Like-for-Like Revenue",Y21="Please name your Like-for-like Earning Metric",Y21="Valuation Metric",Y21="Please name your Like-for-like Valuation Metric",Y21="Please select your Valuation Metric",Y21="Please select the metric for segmentation",Y21="Untitled Segmentation II",Y21="Untitled Segmentation III"),"",IF(OR(Y21<>AB21,AND(LEN(B21)=0,NOT(OR(Y21="Select, enter text or leave as blank.",Y21="Set from Actual section above!",Y21="Please select or type in or leave as blank",Y21="Select, enter text or leave as blank",Y21="Please select your Top Line Metric",Y21="Check Sum",Y21="Please name your Like-for-Like Revenue",Y21="Please name your Like-for-like Earning Metric",Y21="Valuation Metric",Y21="Please name your Like-for-like Valuation Metric",Y21="Please select your Valuation Metric",Y21="Please select the metric for segmentation",Y21="Untitled Segmentation II",Y21="Untitled Segmentation III")))),_xldudf_CX_PUSH(Y21,CX_ENTITY,C21,EOMONTH(val_asOfDate,3)),"")))} -> #NAME? | CY21: {=IFERROR(IF(CM21*fxVal_normal=_PL!CM21,"",IF(OR($CM21="",$CM21=0,NOT(ISNUMBER($CM21)),ISERROR($CM21),$B21=""),"",IF($I21=1,IFBLANK(_xldudf_CX_PUSH($CM21*fxVal_normal,CX_ENTITY,$B21,$CM$11,$CM$14,$CM$19,),""),IF($I21=2,IFBLANK(_xldudf_CX_PUSH($CM21,CX_ENTITY,$B21,$CM$11,$CM$14,$CM$19,),""),IF($I21=3,"",IFBLANK(_xldudf_CX_PUSH($CM21,CX_ENTITY,$B21,$CM$11,$CM$14,$CM$19,),"")))))),"")} | CZ21: {=IFERROR(IF(CN21*fxVal_normal=_PL!CN21,"",IF(OR($CN21="",$CN21=0,NOT(ISNUMBER($CN21)),ISERROR($CN21),$B21=""),"",IF($I21=1,IFBLANK(_xldudf_CX_PUSH($CN21*fxVal_normal,CX_ENTITY,$B21,$CN$11,$CN$14,$CN$19,),""),IF($I21=2,IFBLANK(_xldudf_CX_PUSH($CN21,CX_ENTITY,$B21,$CN$11,$CN$14,$CN$19,),""),IF($I21=3,"",IFBLANK(_xldudf_CX_PUSH($CN21,CX_ENTITY,$B21,$CN$11,$CN$14,$CN$19,),"")))))),"")} | DA21: {=IFERROR(IF(CP21*fxVal_normal=_PL!CP21,"",IF(OR($CP21="",$CP21=0,NOT(ISNUMBER($CP21)),ISERROR($CP21),$B21=""),"",IF($I21=1,IFBLANK(_xldudf_CX_PUSH($CP21*fxVal_normal,CX_ENTITY,$B21,$CP$11,$CP$14,$CP$19,),""),IF($I21=2,IFBLANK(_xldudf_CX_PUSH($CP21,CX_ENTITY,$B21,$CP$11,$CP$14,$CP$19,),""),IF($I21=3,"",IFBLANK(_xldudf_CX_PUSH($CP21,CX_ENTITY,$B21,$CP$11,$CP$14,$CP$19,),"")))))),"")} | DB21: {=IFERROR(IF(CQ21*fxVal_normal=_PL!CQ21,"",IF(OR($CQ21="",$CQ21=0,NOT(ISNUMBER($CQ21)),ISERROR($CQ21),$B21=""),"",IF($I21=1,IFBLANK(_xldudf_CX_PUSH($CQ21*fxVal_normal,CX_ENTITY,$B21,$CQ$11,$CQ$14,$CQ$19,),""),IF($I21=2,IFBLANK(_xldudf_CX_PUSH($CQ21,CX_ENTITY,$B21,$CQ$11,$CQ$14,$CQ$19,),""),IF($I21=3,"",IFBLANK(_xldudf_CX_PUSH($CQ21,CX_ENTITY,$B21,$CQ$11,$CQ$14,$CQ$19,),"")))))),"")} | DD21: {=IFERROR(IF(AD21*fxVal_normal=_PL!AD21,"",IF(OR(AD21="",NOT(ISNUMBER(AD21)),ISERROR(AD21),$B21=""),"",IF($I21=1,IFBLANK(_xldudf_CX_PUSH(AD21*fxVal_normal,CX_ENTITY,$B21,AD$11,AD$14,AD$19,),""),IF($I21=2,IFBLANK(_xldudf_CX_PUSH(AD21,CX_ENTITY,$B21,AD$11,AD$14,AD$19,),""),IF($I21=3,"",IFBLANK(_xldudf_CX_PUSH(AD21,CX_ENTITY,$B21,AD$11,AD$14,AD$19,),"")))))),"")} | DE21: {=IFERROR(IF(AE21*fxVal_normal=_PL!AE21,"",IF(OR(AE21="",NOT(ISNUMBER(AE21)),ISERROR(AE21),$B21=""),"",IF($I21=1,IFBLANK(_xldudf_CX_PUSH(AE21*fxVal_normal,CX_ENTITY,$B21,AE$11,AE$14,AE$19,),""),IF($I21=2,IFBLANK(_xldudf_CX_PUSH(AE21,CX_ENTITY,$B21,AE$11,AE$14,AE$19,),""),IF($I21=3,"",IFBLANK(_xldudf_CX_PUSH(AE21,CX_ENTITY,$B21,AE$11,AE$14,AE$19,),"")))))),"")} | DF21: {=IFERROR(IF(AF21*fxVal_normal=_PL!AF21,"",IF(OR(AF21="",NOT(ISNUMBER(AF21)),ISERROR(AF21),$B21=""),"",IF($I21=1,IFBLANK(_xldudf_CX_PUSH(AF21*fxVal_normal,CX_ENTITY,$B21,AF$11,AF$14,AF$19,),""),IF($I21=2,IFBLANK(_xldudf_CX_PUSH(AF21,CX_ENTITY,$B21,AF$11,AF$14,AF$19,),""),IF($I21=3,"",IFBLANK(_xldudf_CX_PUSH(AF21,CX_ENTITY,$B21,AF$11,AF$14,AF$19,),"")))))),"")} | DG21: {=IFERROR(IF(AG21*fxVal_normal=_PL!AG21,"",IF(OR(AG21="",NOT(ISNUMBER(AG21)),ISERROR(AG21),$B21=""),"",IF($I21=1,IFBLANK(_xldudf_CX_PUSH(AG21*fxVal_normal,CX_ENTITY,$B21,AG$11,AG$14,AG$19,),""),IF($I21=2,IFBLANK(_xldudf_CX_PUSH(AG21,CX_ENTITY,$B21,AG$11,AG$14,AG$19,),""),IF($I21=3,"",IFBLANK(_xldudf_CX_PUSH(AG21,CX_ENTITY,$B21,AG$11,AG$14,AG$19,),"")))))),"")} | DH21: {=IFERROR(IF(AH21*fxVal_normal=_PL!AH21,"",IF(OR(AH21="",NOT(ISNUMBER(AH21)),ISERROR(AH21),$B21=""),"",IF($I21=1,IFBLANK(_xldudf_CX_PUSH(AH21*fxVal_normal,CX_ENTITY,$B21,AH$11,AH$14,AH$19,),""),IF($I21=2,IFBLANK(_xldudf_CX_PUSH(AH21,CX_ENTITY,$B21,AH$11,AH$14,AH$19,),""),IF($I21=3,"",IFBLANK(_xldudf_CX_PUSH(AH21,CX_ENTITY,$B21,AH$11,AH$14,AH$19,),"")))))),"")} | DI21: {=IFERROR(IF(AI21*fxVal_normal=_PL!AI21,"",IF(OR(AI21="",NOT(ISNUMBER(AI21)),ISERROR(AI21),$B21=""),"",IF($I21=1,IFBLANK(_xldudf_CX_PUSH(AI21*fxVal_normal,CX_ENTITY,$B21,AI$11,AI$14,AI$19,),""),IF($I21=2,IFBLANK(_xldudf_CX_PUSH(AI21,CX_ENTITY,$B21,AI$11,AI$14,AI$19,),""),IF($I21=3,"",IFBLANK(_xldudf_CX_PUSH(AI21,CX_ENTITY,$B21,AI$11,AI$14,AI$19,),"")))))),"")} | DJ21: {=IFERROR(IF(AJ21*fxVal_normal=_PL!AJ21,"",IF(OR(AJ21="",NOT(ISNUMBER(AJ21)),ISERROR(AJ21),$B21=""),"",IF($I21=1,IFBLANK(_xldudf_CX_PUSH(AJ21*fxVal_normal,CX_ENTITY,$B21,AJ$11,AJ$14,AJ$19,),""),IF($I21=2,IFBLANK(_xldudf_CX_PUSH(AJ21,CX_ENTITY,$B21,AJ$11,AJ$14,AJ$19,),""),IF($I21=3,"",IFBLANK(_xldudf_CX_PUSH(AJ21,CX_ENTITY,$B21,AJ$11,AJ$14,AJ$19,),"")))))),"")} | DK21: {=IFERROR(IF(AK21*fxVal_normal=_PL!AK21,"",IF(OR(AK21="",NOT(ISNUMBER(AK21)),ISERROR(AK21),$B21=""),"",IF($I21=1,IFBLANK(_xldudf_CX_PUSH(AK21*fxVal_normal,CX_ENTITY,$B21,AK$11,AK$14,AK$19,),""),IF($I21=2,IFBLANK(_xldudf_CX_PUSH(AK21,CX_ENTITY,$B21,AK$11,AK$14,AK$19,),""),IF($I21=3,"",IFBLANK(_xldudf_CX_PUSH(AK21,CX_ENTITY,$B21,AK$11,AK$14,AK$19,),"")))))),"")} | ... EN21: {=IFERROR(IF(BN21*fxVal_normal=_PL!BN21,"",IF(OR(BN21="",NOT(ISNUMBER(BN21)),ISERROR(BN21),$B21=""),"",IF($I21=1,IFBLANK(_xldudf_CX_PUSH(BN21*fxVal_normal,CX_ENTITY,$B21,BN$11,BN$14,BN$19,),""),IF($I21=2,IFBLANK(_xldudf_CX_PUSH(BN21,CX_ENTITY,$B21,BN$11,BN$14,BN$19,),""),IF($I21=3,"",IFBLANK(_xldudf_CX_PUSH(BN21,CX_ENTITY,$B21,BN$11,BN$14,BN$19,),"")))))),"")}
B22: =_xlfn.LET(_xlpm.IsNotAttrDynamic,D22="",_xlpm.Attr,_PL!F22,_xlpm.NotInUse,Y22=D22,_xlpm.RESULT,IF(_xlpm.IsNotAttrDynamic,_xlpm.Attr,IF(_xlpm.NotInUse,"",Y22)),IF(_xlpm.RESULT="","",_xlpm.RESULT)) -> Gross Profit | C22: {=IFBLANK(_PL!C22,"")} -> Gross Profit (Company View) | E22: {=_xlfn.LAMBDA(_xlpm.Array,_xlop.Type,_xlfn.LET(_xlpm._type,IF(_xlfn.ISOMITTED(_xlpm.Type),0,_xlpm.Type),_xlpm.R,ROWS(_xlpm.Array),_xlpm.C,COLUMNS(_xlpm.Array),_xlpm.Unlocked,_xlfn.MAKEARRAY(_xlpm.R,_xlpm.C,_xlfn.LAMBDA(_xlpm.i,_xlpm.j,--(CELL("protect",INDEX(_xlpm.Array,_xlpm.i,_xlpm.j))=0))),_xlpm.IsUnlocked,_xlfn.MAKEARRAY(_xlpm.R,_xlpm.C,_xlfn.LAMBDA(_xlpm.i,_xlpm.j,CELL("protect",INDEX(_xlpm.Array,_xlpm.i,_xlpm.j))=0)),_xlpm.HasData,_xlpm.Array<>"",_xlpm.Total,SUM(_xlpm.Unlocked),_xlpm.Completed,SUM(--(_xlpm.IsUnlocked*_xlpm.HasData)),_xlpm.type_display,_xlfn.SWITCH(_xlpm._type,1,"R",-1,"O",0,"A",""),_xlfn.HSTACK(_xlpm.Total,_xlpm.Completed,_xlpm.type_display)))($AD22:$CQ22,Z22)} -> #NAME? | H22: 2 | I22: 1 | J22: {=IFBLANK(Z22,"")} -> 0 | K22: =IFERROR(IF(LEN(AB22)=0,"No",IF(LEN(J22)>0,"Yes","No")),"") -> Yes | W22: =$W$20 -> Actual | X22: =_PL!X22 -> 0 | Y22: =IF(_PL!Y22="Error","",_PL!Y22) -> #NAME? | Z22: {=_xlfn.SWITCH(TRUE,_PL!$L22=TRUE,1,_PL!$L22=FALSE,-1,_PL!$L22=-1,0,"")} -> 0 | AB22: =_PL!AB22 -> Gross Profit | AC22: {=_xlfn.LET(_xlpm._termname,$AB22,_xlpm._iconname,"find",_xlpm._icon,fx_getIcon(_xlpm._iconname),_xlpm._location,_xlfn.XLOOKUP(LOWER(_xlpm._termname),LOWER(tbl_acctDef[Term]),tbl_acctDef[Term]),_xlpm._hyperlink,HYPERLINK("#"&CELL("address",_xlpm._location),_xlpm._icon),IFERROR(_xlpm._hyperlink,""))} -> #VALUE! | AD22: =SUBTOTAL(9,AD20:AD21) -> 2 | AE22: =SUBTOTAL(9,AE20:AE21) -> 2 | AF22: =SUBTOTAL(9,AF20:AF21) -> 2 | AG22: =SUBTOTAL(9,AG20:AG21) -> 2 | AH22: =SUBTOTAL(9,AH20:AH21) -> 2 | AI22: =SUBTOTAL(9,AI20:AI21) -> 2 | AJ22: =SUBTOTAL(9,AJ20:AJ21) -> 2 | AK22: =SUBTOTAL(9,AK20:AK21) -> 2 | ... BN22: =SUBTOTAL(9,BN20:BN21) -> 2 | CD22: {=_xlfn.LET(_xlpm.CheckBlank,SUM(PL!$AD22:$BN22)=0,IF(_xlpm.CheckBlank,"",SUM(_xlfn._xlws.FILTER(PL!$AD22:$BN22,(YEAR(PL!$AD$12:$BN$12)=PL!CD$12)*(array_timeline<=PL!CD$11)))))} -> #NAME? | CE22: {=_xlfn.LET(_xlpm.CheckBlank,SUM(PL!$AD22:$BN22)=0,IF(_xlpm.CheckBlank,"",SUM(_xlfn._xlws.FILTER(PL!$AD22:$BN22,(YEAR(PL!$AD$12:$BN$12)=PL!CE$12)*(array_timeline<=PL!CE$11)))))} -> #NAME? | CG22: {=IFERROR(_xlfn.LET(_xlpm.CheckBlank,SUM(PL!$AD22:$BN22)=0,IF(_xlpm.CheckBlank,"",SUM(_xlfn._xlws.FILTER(PL!$AD22:$BN22,(YEAR(PL!$AD$12:$BN$12)=PL!CG$12)*(array_timeline<=PL!CG$11))))),"n/a")} -> n/a | CH22: {=_xlfn.LET(_xlpm.CheckBlank,SUM(PL!$AD22:$BN22)=0,IF(_xlpm.CheckBlank,"",SUM(_xlfn._xlws.FILTER(PL!$AD22:$BN22,(YEAR(PL!$AD$12:$BN$12)=PL!CH$12)*(array_timeline<=PL!CH$11)))))} -> #NAME? | CJ22: {=_xlfn.LET(_xlpm.CheckBlank,SUM(PL!$AD22:$BN22)=0,IF(_xlpm.CheckBlank,"",SUM(_xlfn.TAKE(_xlfn.DROP(PL!$AD22:$BN22,,-DATEDIFF(PL!CJ$11,val_asOfDate,"M")),1,-12))))} -> 24 | CK22: {=_xlfn.LET(_xlpm.CheckBlank,SUM(PL!$AD22:$BN22)=0,IF(_xlpm.CheckBlank,"",SUM(_xlfn.TAKE(_xlfn.DROP(PL!$AD22:$BN22,,-DATEDIFF(PL!CK$11,val_asOfDate,"M")),1,-12))))} -> 24 | CM22: =SUBTOTAL(9,CM20:CM21) -> 2 | CN22: =SUBTOTAL(9,CN20:CN21) -> 2 | CP22: =SUBTOTAL(9,CP20:CP21) -> 2 | CQ22: =SUBTOTAL(9,CQ20:CQ21) -> 2 | CT22: {=IF(K22<>"Yes","",IF(OR(Y22="Select, enter text or leave as blank.",Y22="Set from Actual section above!",Y22="Please select or type in or leave as blank",Y22="Select, enter text or leave as blank",Y22="Please select your Top Line Metric",Y22="Check Sum",Y22="Please name your Like-for-Like Revenue",Y22="Please name your Like-for-like Earning Metric",Y22="Valuation Metric",Y22="Please name your Like-for-like Valuation Metric",Y22="Please select your Valuation Metric",Y22="Please select the metric for segmentation",Y22="Untitled Segmentation II",Y22="Untitled Segmentation III"),"",IF(OR(Y22<>AB22,AND(LEN(B22)=0,NOT(OR(Y22="Select, enter text or leave as blank.",Y22="Set from Actual section above!",Y22="Please select or type in or leave as blank",Y22="Select, enter text or leave as blank",Y22="Please select your Top Line Metric",Y22="Check Sum",Y22="Please name your Like-for-Like Revenue",Y22="Please name your Like-for-like Earning Metric",Y22="Valuation Metric",Y22="Please name your Like-for-like Valuation Metric",Y22="Please select your Valuation Metric",Y22="Please select the metric for segmentation",Y22="Untitled Segmentation II",Y22="Untitled Segmentation III")))),_xldudf_CX_PUSH(Y22,CX_ENTITY,C22,EOMONTH(val_asOfDate,0)),"")))} -> #NAME? | CU22: {=IF(K22<>"Yes","",IF(OR(Y22="Select, enter text or leave as blank.",Y22="Set from Actual section above!",Y22="Please select or type in or leave as blank",Y22="Select, enter text or leave as blank",Y22="Please select your Top Line Metric",Y22="Check Sum",Y22="Please name your Like-for-Like Revenue",Y22="Please name your Like-for-like Earning Metric",Y22="Valuation Metric",Y22="Please name your Like-for-like Valuation Metric",Y22="Please select your Valuation Metric",Y22="Please select the metric for segmentation",Y22="Untitled Segmentation II",Y22="Untitled Segmentation III"),"",IF(OR(Y22<>AB22,AND(LEN(B22)=0,NOT(OR(Y22="Select, enter text or leave as blank.",Y22="Set from Actual section above!",Y22="Please select or type in or leave as blank",Y22="Select, enter text or leave as blank",Y22="Please select your Top Line Metric",Y22="Check Sum",Y22="Please name your Like-for-Like Revenue",Y22="Please name your Like-for-like Earning Metric",Y22="Valuation Metric",Y22="Please name your Like-for-like Valuation Metric",Y22="Please select your Valuation Metric",Y22="Please select the metric for segmentation",Y22="Untitled Segmentation II",Y22="Untitled Segmentation III")))),_xldudf_CX_PUSH(Y22,CX_ENTITY,C22,EOMONTH(val_asOfDate,1)),"")))} -> #NAME? | CV22: {=IF(K22<>"Yes","",IF(OR(Y22="Select, enter text or leave as blank.",Y22="Set from Actual section above!",Y22="Please select or type in or leave as blank",Y22="Select, enter text or leave as blank",Y22="Please select your Top Line Metric",Y22="Check Sum",Y22="Please name your Like-for-Like Revenue",Y22="Please name your Like-for-like Earning Metric",Y22="Valuation Metric",Y22="Please name your Like-for-like Valuation Metric",Y22="Please select your Valuation Metric",Y22="Please select the metric for segmentation",Y22="Untitled Segmentation II",Y22="Untitled Segmentation III"),"",IF(OR(Y22<>AB22,AND(LEN(B22)=0,NOT(OR(Y22="Select, enter text or leave as blank.",Y22="Set from Actual section above!",Y22="Please select or type in or leave as blank",Y22="Select, enter text or leave as blank",Y22="Please select your Top Line Metric",Y22="Check Sum",Y22="Please name your Like-for-Like Revenue",Y22="Please name your Like-for-like Earning Metric",Y22="Valuation Metric",Y22="Please name your Like-for-like Valuation Metric",Y22="Please select your Valuation Metric",Y22="Please select the metric for segmentation",Y22="Untitled Segmentation II",Y22="Untitled Segmentation III")))),_xldudf_CX_PUSH(Y22,CX_ENTITY,C22,EOMONTH(val_asOfDate,2)),"")))} -> #NAME? | CW22: {=IF(K22<>"Yes","",IF(OR(Y22="Select, enter text or leave as blank.",Y22="Set from Actual section above!",Y22="Please select or type in or leave as blank",Y22="Select, enter text or leave as blank",Y22="Please select your Top Line Metric",Y22="Check Sum",Y22="Please name your Like-for-Like Revenue",Y22="Please name your Like-for-like Earning Metric",Y22="Valuation Metric",Y22="Please name your Like-for-like Valuation Metric",Y22="Please select your Valuation Metric",Y22="Please select the metric for segmentation",Y22="Untitled Segmentation II",Y22="Untitled Segmentation III"),"",IF(OR(Y22<>AB22,AND(LEN(B22)=0,NOT(OR(Y22="Select, enter text or leave as blank.",Y22="Set from Actual section above!",Y22="Please select or type in or leave as blank",Y22="Select, enter text or leave as blank",Y22="Please select your Top Line Metric",Y22="Check Sum",Y22="Please name your Like-for-Like Revenue",Y22="Please name your Like-for-like Earning Metric",Y22="Valuation Metric",Y22="Please name your Like-for-like Valuation Metric",Y22="Please select your Valuation Metric",Y22="Please select the metric for segmentation",Y22="Untitled Segmentation II",Y22="Untitled Segmentation III")))),_xldudf_CX_PUSH(Y22,CX_ENTITY,C22,EOMONTH(val_asOfDate,3)),"")))} -> #NAME? | CY22: {=IFERROR(IF(CM22*fxVal_normal=_PL!CM22,"",IF(OR($CM22="",$CM22=0,NOT(ISNUMBER($CM22)),ISERROR($CM22),$B22=""),"",IF($I22=1,IFBLANK(_xldudf_CX_PUSH($CM22*fxVal_normal,CX_ENTITY,$B22,$CM$11,$CM$14,$CM$19,),""),IF($I22=2,IFBLANK(_xldudf_CX_PUSH($CM22,CX_ENTITY,$B22,$CM$11,$CM$14,$CM$19,),""),IF($I22=3,"",IFBLANK(_xldudf_CX_PUSH($CM22,CX_ENTITY,$B22,$CM$11,$CM$14,$CM$19,),"")))))),"")} | CZ22: {=IFERROR(IF(CN22*fxVal_normal=_PL!CN22,"",IF(OR($CN22="",$CN22=0,NOT(ISNUMBER($CN22)),ISERROR($CN22),$B22=""),"",IF($I22=1,IFBLANK(_xldudf_CX_PUSH($CN22*fxVal_normal,CX_ENTITY,$B22,$CN$11,$CN$14,$CN$19,),""),IF($I22=2,IFBLANK(_xldudf_CX_PUSH($CN22,CX_ENTITY,$B22,$CN$11,$CN$14,$CN$19,),""),IF($I22=3,"",IFBLANK(_xldudf_CX_PUSH($CN22,CX_ENTITY,$B22,$CN$11,$CN$14,$CN$19,),"")))))),"")} | DA22: {=IFERROR(IF(CP22*fxVal_normal=_PL!CP22,"",IF(OR($CP22="",$CP22=0,NOT(ISNUMBER($CP22)),ISERROR($CP22),$B22=""),"",IF($I22=1,IFBLANK(_xldudf_CX_PUSH($CP22*fxVal_normal,CX_ENTITY,$B22,$CP$11,$CP$14,$CP$19,),""),IF($I22=2,IFBLANK(_xldudf_CX_PUSH($CP22,CX_ENTITY,$B22,$CP$11,$CP$14,$CP$19,),""),IF($I22=3,"",IFBLANK(_xldudf_CX_PUSH($CP22,CX_ENTITY,$B22,$CP$11,$CP$14,$CP$19,),"")))))),"")} | DB22: {=IFERROR(IF(CQ22*fxVal_normal=_PL!CQ22,"",IF(OR($CQ22="",$CQ22=0,NOT(ISNUMBER($CQ22)),ISERROR($CQ22),$B22=""),"",IF($I22=1,IFBLANK(_xldudf_CX_PUSH($CQ22*fxVal_normal,CX_ENTITY,$B22,$CQ$11,$CQ$14,$CQ$19,),""),IF($I22=2,IFBLANK(_xldudf_CX_PUSH($CQ22,CX_ENTITY,$B22,$CQ$11,$CQ$14,$CQ$19,),""),IF($I22=3,"",IFBLANK(_xldudf_CX_PUSH($CQ22,CX_ENTITY,$B22,$CQ$11,$CQ$14,$CQ$19,),"")))))),"")} | DD22: {=IFERROR(IF(AD22*fxVal_normal=_PL!AD22,"",IF(OR(AD22="",NOT(ISNUMBER(AD22)),ISERROR(AD22),$B22=""),"",IF($I22=1,IFBLANK(_xldudf_CX_PUSH(AD22*fxVal_normal,CX_ENTITY,$B22,AD$11,AD$14,AD$19,),""),IF($I22=2,IFBLANK(_xldudf_CX_PUSH(AD22,CX_ENTITY,$B22,AD$11,AD$14,AD$19,),""),IF($I22=3,"",IFBLANK(_xldudf_CX_PUSH(AD22,CX_ENTITY,$B22,AD$11,AD$14,AD$19,),"")))))),"")} | DE22: {=IFERROR(IF(AE22*fxVal_normal=_PL!AE22,"",IF(OR(AE22="",NOT(ISNUMBER(AE22)),ISERROR(AE22),$B22=""),"",IF($I22=1,IFBLANK(_xldudf_CX_PUSH(AE22*fxVal_normal,CX_ENTITY,$B22,AE$11,AE$14,AE$19,),""),IF($I22=2,IFBLANK(_xldudf_CX_PUSH(AE22,CX_ENTITY,$B22,AE$11,AE$14,AE$19,),""),IF($I22=3,"",IFBLANK(_xldudf_CX_PUSH(AE22,CX_ENTITY,$B22,AE$11,AE$14,AE$19,),"")))))),"")} | DF22: {=IFERROR(IF(AF22*fxVal_normal=_PL!AF22,"",IF(OR(AF22="",NOT(ISNUMBER(AF22)),ISERROR(AF22),$B22=""),"",IF($I22=1,IFBLANK(_xldudf_CX_PUSH(AF22*fxVal_normal,CX_ENTITY,$B22,AF$11,AF$14,AF$19,),""),IF($I22=2,IFBLANK(_xldudf_CX_PUSH(AF22,CX_ENTITY,$B22,AF$11,AF$14,AF$19,),""),IF($I22=3,"",IFBLANK(_xldudf_CX_PUSH(AF22,CX_ENTITY,$B22,AF$11,AF$14,AF$19,),"")))))),"")} | DG22: {=IFERROR(IF(AG22*fxVal_normal=_PL!AG22,"",IF(OR(AG22="",NOT(ISNUMBER(AG22)),ISERROR(AG22),$B22=""),"",IF($I22=1,IFBLANK(_xldudf_CX_PUSH(AG22*fxVal_normal,CX_ENTITY,$B22,AG$11,AG$14,AG$19,),""),IF($I22=2,IFBLANK(_xldudf_CX_PUSH(AG22,CX_ENTITY,$B22,AG$11,AG$14,AG$19,),""),IF($I22=3,"",IFBLANK(_xldudf_CX_PUSH(AG22,CX_ENTITY,$B22,AG$11,AG$14,AG$19,),"")))))),"")} | DH22: {=IFERROR(IF(AH22*fxVal_normal=_PL!AH22,"",IF(OR(AH22="",NOT(ISNUMBER(AH22)),ISERROR(AH22),$B22=""),"",IF($I22=1,IFBLANK(_xldudf_CX_PUSH(AH22*fxVal_normal,CX_ENTITY,$B22,AH$11,AH$14,AH$19,),""),IF($I22=2,IFBLANK(_xldudf_CX_PUSH(AH22,CX_ENTITY,$B22,AH$11,AH$14,AH$19,),""),IF($I22=3,"",IFBLANK(_xldudf_CX_PUSH(AH22,CX_ENTITY,$B22,AH$11,AH$14,AH$19,),"")))))),"")} | DI22: {=IFERROR(IF(AI22*fxVal_normal=_PL!AI22,"",IF(OR(AI22="",NOT(ISNUMBER(AI22)),ISERROR(AI22),$B22=""),"",IF($I22=1,IFBLANK(_xldudf_CX_PUSH(AI22*fxVal_normal,CX_ENTITY,$B22,AI$11,AI$14,AI$19,),""),IF($I22=2,IFBLANK(_xldudf_CX_PUSH(AI22,CX_ENTITY,$B22,AI$11,AI$14,AI$19,),""),IF($I22=3,"",IFBLANK(_xldudf_CX_PUSH(AI22,CX_ENTITY,$B22,AI$11,AI$14,AI$19,),"")))))),"")} | DJ22: {=IFERROR(IF(AJ22*fxVal_normal=_PL!AJ22,"",IF(OR(AJ22="",NOT(ISNUMBER(AJ22)),ISERROR(AJ22),$B22=""),"",IF($I22=1,IFBLANK(_xldudf_CX_PUSH(AJ22*fxVal_normal,CX_ENTITY,$B22,AJ$11,AJ$14,AJ$19,),""),IF($I22=2,IFBLANK(_xldudf_CX_PUSH(AJ22,CX_ENTITY,$B22,AJ$11,AJ$14,AJ$19,),""),IF($I22=3,"",IFBLANK(_xldudf_CX_PUSH(AJ22,CX_ENTITY,$B22,AJ$11,AJ$14,AJ$19,),"")))))),"")} | DK22: {=IFERROR(IF(AK22*fxVal_normal=_PL!AK22,"",IF(OR(AK22="",NOT(ISNUMBER(AK22)),ISERROR(AK22),$B22=""),"",IF($I22=1,IFBLANK(_xldudf_CX_PUSH(AK22*fxVal_normal,CX_ENTITY,$B22,AK$11,AK$14,AK$19,),""),IF($I22=2,IFBLANK(_xldudf_CX_PUSH(AK22,CX_ENTITY,$B22,AK$11,AK$14,AK$19,),""),IF($I22=3,"",IFBLANK(_xldudf_CX_PUSH(AK22,CX_ENTITY,$B22,AK$11,AK$14,AK$19,),"")))))),"")} | ... EN22: {=IFERROR(IF(BN22*fxVal_normal=_PL!BN22,"",IF(OR(BN22="",NOT(ISNUMBER(BN22)),ISERROR(BN22),$B22=""),"",IF($I22=1,IFBLANK(_xldudf_CX_PUSH(BN22*fxVal_normal,CX_ENTITY,$B22,BN$11,BN$14,BN$19,),""),IF($I22=2,IFBLANK(_xldudf_CX_PUSH(BN22,CX_ENTITY,$B22,BN$11,BN$14,BN$19,),""),IF($I22=3,"",IFBLANK(_xldudf_CX_PUSH(BN22,CX_ENTITY,$B22,BN$11,BN$14,BN$19,),"")))))),"")}
B23: =_xlfn.LET(_xlpm.IsNotAttrDynamic,D23="",_xlpm.Attr,_PL!F23,_xlpm.NotInUse,Y23=D23,_xlpm.RESULT,IF(_xlpm.IsNotAttrDynamic,_xlpm.Attr,IF(_xlpm.NotInUse,"",Y23)),IF(_xlpm.RESULT="","",_xlpm.RESULT)) -> Gross Margin % | C23: {=IFBLANK(_PL!C23,"")} -> Gross Margin % (Company View) | E23: {=_xlfn.LAMBDA(_xlpm.Array,_xlop.Type,_xlfn.LET(_xlpm._type,IF(_xlfn.ISOMITTED(_xlpm.Type),0,_xlpm.Type),_xlpm.R,ROWS(_xlpm.Array),_xlpm.C,COLUMNS(_xlpm.Array),_xlpm.Unlocked,_xlfn.MAKEARRAY(_xlpm.R,_xlpm.C,_xlfn.LAMBDA(_xlpm.i,_xlpm.j,--(CELL("protect",INDEX(_xlpm.Array,_xlpm.i,_xlpm.j))=0))),_xlpm.IsUnlocked,_xlfn.MAKEARRAY(_xlpm.R,_xlpm.C,_xlfn.LAMBDA(_xlpm.i,_xlpm.j,CELL("protect",INDEX(_xlpm.Array,_xlpm.i,_xlpm.j))=0)),_xlpm.HasData,_xlpm.Array<>"",_xlpm.Total,SUM(_xlpm.Unlocked),_xlpm.Completed,SUM(--(_xlpm.IsUnlocked*_xlpm.HasData)),_xlpm.type_display,_xlfn.SWITCH(_xlpm._type,1,"R",-1,"O",0,"A",""),_xlfn.HSTACK(_xlpm.Total,_xlpm.Completed,_xlpm.type_display)))($AD23:$CQ23,Z23)} -> #NAME? | H23: 2 | I23: 2 | J23: {=IFBLANK(Z23,"")} -> 0 | K23: =IFERROR(IF(LEN(AB23)=0,"No",IF(LEN(J23)>0,"Yes","No")),"") -> Yes | W23: =$W$20 -> Actual | X23: =_PL!X23 -> 0 | Y23: =IF(_PL!Y23="Error","",_PL!Y23) -> #NAME? | Z23: {=_xlfn.SWITCH(TRUE,_PL!$L23=TRUE,1,_PL!$L23=FALSE,-1,_PL!$L23=-1,0,"")} -> 0 | AB23: =_PL!AB23 -> Gross Margin % | AC23: {=_xlfn.LET(_xlpm._termname,$AB23,_xlpm._iconname,"find",_xlpm._icon,fx_getIcon(_xlpm._iconname),_xlpm._location,_xlfn.XLOOKUP(LOWER(_xlpm._termname),LOWER(tbl_acctDef[Term]),tbl_acctDef[Term]),_xlpm._hyperlink,HYPERLINK("#"&CELL("address",_xlpm._location),_xlpm._icon),IFERROR(_xlpm._hyperlink,""))} | AD23: =IF(N(AD20)<>0,N(AD22)/N(AD20),"n/a") -> 2 | AE23: =IF(N(AE20)<>0,N(AE22)/N(AE20),"n/a") -> 2 | AF23: =IF(N(AF20)<>0,N(AF22)/N(AF20),"n/a") -> 2 | AG23: =IF(N(AG20)<>0,N(AG22)/N(AG20),"n/a") -> 2 | AH23: =IF(N(AH20)<>0,N(AH22)/N(AH20),"n/a") -> 2 | AI23: =IF(N(AI20)<>0,N(AI22)/N(AI20),"n/a") -> 2 | AJ23: =IF(N(AJ20)<>0,N(AJ22)/N(AJ20),"n/a") -> 2 | AK23: =IF(N(AK20)<>0,N(AK22)/N(AK20),"n/a") -> 2 | ... BN23: =IF(N(BN20)<>0,N(BN22)/N(BN20),"n/a") -> 2 | CD23: =IF(N(CD20)<>0,N(CD22)/N(CD20),"n/a") -> #NAME? | CE23: =IF(N(CE20)<>0,N(CE22)/N(CE20),"n/a") -> #NAME? | CG23: =IF(N(CG20)<>0,N(CG22)/N(CG20),"n/a") -> n/a | CH23: =IF(N(CH20)<>0,N(CH22)/N(CH20),"n/a") -> #NAME? | CJ23: =IF(N(CJ20)<>0,N(CJ22)/N(CJ20),"n/a") -> 2 | CK23: =IF(N(CK20)<>0,N(CK22)/N(CK20),"n/a") -> 2 | CM23: =IF(N(CM20)<>0,N(CM22)/N(CM20),"n/a") -> 2 | CN23: =IF(N(CN20)<>0,N(CN22)/N(CN20),"n/a") -> 2 | CP23: =IF(N(CP20)<>0,N(CP22)/N(CP20),"n/a") -> 2 | CQ23: =IF(N(CQ20)<>0,N(CQ22)/N(CQ20),"n/a") -> 2 | CT23: {=IF(K23<>"Yes","",IF(OR(Y23="Select, enter text or leave as blank.",Y23="Set from Actual section above!",Y23="Please select or type in or leave as blank",Y23="Select, enter text or leave as blank",Y23="Please select your Top Line Metric",Y23="Check Sum",Y23="Please name your Like-for-Like Revenue",Y23="Please name your Like-for-like Earning Metric",Y23="Valuation Metric",Y23="Please name your Like-for-like Valuation Metric",Y23="Please select your Valuation Metric",Y23="Please select the metric for segmentation",Y23="Untitled Segmentation II",Y23="Untitled Segmentation III"),"",IF(OR(Y23<>AB23,AND(LEN(B23)=0,NOT(OR(Y23="Select, enter text or leave as blank.",Y23="Set from Actual section above!",Y23="Please select or type in or leave as blank",Y23="Select, enter text or leave as blank",Y23="Please select your Top Line Metric",Y23="Check Sum",Y23="Please name your Like-for-Like Revenue",Y23="Please name your Like-for-like Earning Metric",Y23="Valuation Metric",Y23="Please name your Like-for-like Valuation Metric",Y23="Please select your Valuation Metric",Y23="Please select the metric for segmentation",Y23="Untitled Segmentation II",Y23="Untitled Segmentation III")))),_xldudf_CX_PUSH(Y23,CX_ENTITY,C23,EOMONTH(val_asOfDate,0)),"")))} -> #NAME? | CU23: {=IF(K23<>"Yes","",IF(OR(Y23="Select, enter text or leave as blank.",Y23="Set from Actual section above!",Y23="Please select or type in or leave as blank",Y23="Select, enter text or leave as blank",Y23="Please select your Top Line Metric",Y23="Check Sum",Y23="Please name your Like-for-Like Revenue",Y23="Please name your Like-for-like Earning Metric",Y23="Valuation Metric",Y23="Please name your Like-for-like Valuation Metric",Y23="Please select your Valuation Metric",Y23="Please select the metric for segmentation",Y23="Untitled Segmentation II",Y23="Untitled Segmentation III"),"",IF(OR(Y23<>AB23,AND(LEN(B23)=0,NOT(OR(Y23="Select, enter text or leave as blank.",Y23="Set from Actual section above!",Y23="Please select or type in or leave as blank",Y23="Select, enter text or leave as blank",Y23="Please select your Top Line Metric",Y23="Check Sum",Y23="Please name your Like-for-Like Revenue",Y23="Please name your Like-for-like Earning Metric",Y23="Valuation Metric",Y23="Please name your Like-for-like Valuation Metric",Y23="Please select your Valuation Metric",Y23="Please select the metric for segmentation",Y23="Untitled Segmentation II",Y23="Untitled Segmentation III")))),_xldudf_CX_PUSH(Y23,CX_ENTITY,C23,EOMONTH(val_asOfDate,1)),"")))} -> #NAME? | CV23: {=IF(K23<>"Yes","",IF(OR(Y23="Select, enter text or leave as blank.",Y23="Set from Actual section above!",Y23="Please select or type in or leave as blank",Y23="Select, enter text or leave as blank",Y23="Please select your Top Line Metric",Y23="Check Sum",Y23="Please name your Like-for-Like Revenue",Y23="Please name your Like-for-like Earning Metric",Y23="Valuation Metric",Y23="Please name your Like-for-like Valuation Metric",Y23="Please select your Valuation Metric",Y23="Please select the metric for segmentation",Y23="Untitled Segmentation II",Y23="Untitled Segmentation III"),"",IF(OR(Y23<>AB23,AND(LEN(B23)=0,NOT(OR(Y23="Select, enter text or leave as blank.",Y23="Set from Actual section above!",Y23="Please select or type in or leave as blank",Y23="Select, enter text or leave as blank",Y23="Please select your Top Line Metric",Y23="Check Sum",Y23="Please name your Like-for-Like Revenue",Y23="Please name your Like-for-like Earning Metric",Y23="Valuation Metric",Y23="Please name your Like-for-like Valuation Metric",Y23="Please select your Valuation Metric",Y23="Please select the metric for segmentation",Y23="Untitled Segmentation II",Y23="Untitled Segmentation III")))),_xldudf_CX_PUSH(Y23,CX_ENTITY,C23,EOMONTH(val_asOfDate,2)),"")))} -> #NAME? | CW23: {=IF(K23<>"Yes","",IF(OR(Y23="Select, enter text or leave as blank.",Y23="Set from Actual section above!",Y23="Please select or type in or leave as blank",Y23="Select, enter text or leave as blank",Y23="Please select your Top Line Metric",Y23="Check Sum",Y23="Please name your Like-for-Like Revenue",Y23="Please name your Like-for-like Earning Metric",Y23="Valuation Metric",Y23="Please name your Like-for-like Valuation Metric",Y23="Please select your Valuation Metric",Y23="Please select the metric for segmentation",Y23="Untitled Segmentation II",Y23="Untitled Segmentation III"),"",IF(OR(Y23<>AB23,AND(LEN(B23)=0,NOT(OR(Y23="Select, enter text or leave as blank.",Y23="Set from Actual section above!",Y23="Please select or type in or leave as blank",Y23="Select, enter text or leave as blank",Y23="Please select your Top Line Metric",Y23="Check Sum",Y23="Please name your Like-for-Like Revenue",Y23="Please name your Like-for-like Earning Metric",Y23="Valuation Metric",Y23="Please name your Like-for-like Valuation Metric",Y23="Please select your Valuation Metric",Y23="Please select the metric for segmentation",Y23="Untitled Segmentation II",Y23="Untitled Segmentation III")))),_xldudf_CX_PUSH(Y23,CX_ENTITY,C23,EOMONTH(val_asOfDate,3)),"")))} -> #NAME? | CY23: {=IF(CM23=_PL!CM23,"",IF(OR($CM23="",$CM23=0,NOT(ISNUMBER($CM23)),ISERROR($CM23),$B23=""),"",IF($I23=1,IFBLANK(_xldudf_CX_PUSH($CM23*fxVal_normal,CX_ENTITY,$B23,$CM$11,$CM$14,$CM$19,),""),IF($I23=2,IFBLANK(_xldudf_CX_PUSH($CM23,CX_ENTITY,$B23,$CM$11,$CM$14,$CM$19,),""),IF($I23=3,"",IFBLANK(_xldudf_CX_PUSH($CM23,CX_ENTITY,$B23,$CM$11,$CM$14,$CM$19,),""))))))} -> #NAME? | CZ23: {=IF(CN23=_PL!CN23,"",IF(OR($CN23="",$CN23=0,NOT(ISNUMBER($CN23)),ISERROR($CN23),$B23=""),"",IF($I23=1,IFBLANK(_xldudf_CX_PUSH($CN23*fxVal_normal,CX_ENTITY,$B23,$CN$11,$CN$14,$CN$19,),""),IF($I23=2,IFBLANK(_xldudf_CX_PUSH($CN23,CX_ENTITY,$B23,$CN$11,$CN$14,$CN$19,),""),IF($I23=3,"",IFBLANK(_xldudf_CX_PUSH($CN23,CX_ENTITY,$B23,$CN$11,$CN$14,$CN$19,),""))))))} -> #NAME? | DA23: {=IF(CP23=_PL!CP23,"",IF(OR($CP23="",$CP23=0,NOT(ISNUMBER($CP23)),ISERROR($CP23),$B23=""),"",IF($I23=1,IFBLANK(_xldudf_CX_PUSH($CP23*fxVal_normal,CX_ENTITY,$B23,$CP$11,$CP$14,$CP$19,),""),IF($I23=2,IFBLANK(_xldudf_CX_PUSH($CP23,CX_ENTITY,$B23,$CP$11,$CP$14,$CP$19,),""),IF($I23=3,"",IFBLANK(_xldudf_CX_PUSH($CP23,CX_ENTITY,$B23,$CP$11,$CP$14,$CP$19,),""))))))} -> #NAME? | DB23: {=IF(CQ23=_PL!CQ23,"",IF(OR($CQ23="",$CQ23=0,NOT(ISNUMBER($CQ23)),ISERROR($CQ23),$B23=""),"",IF($I23=1,IFBLANK(_xldudf_CX_PUSH($CQ23*fxVal_normal,CX_ENTITY,$B23,$CQ$11,$CQ$14,$CQ$19,),""),IF($I23=2,IFBLANK(_xldudf_CX_PUSH($CQ23,CX_ENTITY,$B23,$CQ$11,$CQ$14,$CQ$19,),""),IF($I23=3,"",IFBLANK(_xldudf_CX_PUSH($CQ23,CX_ENTITY,$B23,$CQ$11,$CQ$14,$CQ$19,),""))))))} -> #NAME? | DD23: {=IFERROR(IF(AD23=_PL!AD23,"",IF(OR(AD23="",NOT(ISNUMBER(AD23)),ISERROR(AD23),$B23=""),"",IF($I23=1,IFBLANK(_xldudf_CX_PUSH(AD23*fxVal_normal,CX_ENTITY,$B23,AD$11,AD$14,AD$19,),""),IF($I23=2,IFBLANK(_xldudf_CX_PUSH(AD23,CX_ENTITY,$B23,AD$11,AD$14,AD$19,),""),IF($I23=3,"",IFBLANK(_xldudf_CX_PUSH(AD23,CX_ENTITY,$B23,AD$11,AD$14,AD$19,),"")))))),"")} | DE23: {=IFERROR(IF(AE23=_PL!AE23,"",IF(OR(AE23="",NOT(ISNUMBER(AE23)),ISERROR(AE23),$B23=""),"",IF($I23=1,IFBLANK(_xldudf_CX_PUSH(AE23*fxVal_normal,CX_ENTITY,$B23,AE$11,AE$14,AE$19,),""),IF($I23=2,IFBLANK(_xldudf_CX_PUSH(AE23,CX_ENTITY,$B23,AE$11,AE$14,AE$19,),""),IF($I23=3,"",IFBLANK(_xldudf_CX_PUSH(AE23,CX_ENTITY,$B23,AE$11,AE$14,AE$19,),"")))))),"")} | DF23: {=IFERROR(IF(AF23=_PL!AF23,"",IF(OR(AF23="",NOT(ISNUMBER(AF23)),ISERROR(AF23),$B23=""),"",IF($I23=1,IFBLANK(_xldudf_CX_PUSH(AF23*fxVal_normal,CX_ENTITY,$B23,AF$11,AF$14,AF$19,),""),IF($I23=2,IFBLANK(_xldudf_CX_PUSH(AF23,CX_ENTITY,$B23,AF$11,AF$14,AF$19,),""),IF($I23=3,"",IFBLANK(_xldudf_CX_PUSH(AF23,CX_ENTITY,$B23,AF$11,AF$14,AF$19,),"")))))),"")} | DG23: {=IFERROR(IF(AG23=_PL!AG23,"",IF(OR(AG23="",NOT(ISNUMBER(AG23)),ISERROR(AG23),$B23=""),"",IF($I23=1,IFBLANK(_xldudf_CX_PUSH(AG23*fxVal_normal,CX_ENTITY,$B23,AG$11,AG$14,AG$19,),""),IF($I23=2,IFBLANK(_xldudf_CX_PUSH(AG23,CX_ENTITY,$B23,AG$11,AG$14,AG$19,),""),IF($I23=3,"",IFBLANK(_xldudf_CX_PUSH(AG23,CX_ENTITY,$B23,AG$11,AG$14,AG$19,),"")))))),"")} | DH23: {=IFERROR(IF(AH23=_PL!AH23,"",IF(OR(AH23="",NOT(ISNUMBER(AH23)),ISERROR(AH23),$B23=""),"",IF($I23=1,IFBLANK(_xldudf_CX_PUSH(AH23*fxVal_normal,CX_ENTITY,$B23,AH$11,AH$14,AH$19,),""),IF($I23=2,IFBLANK(_xldudf_CX_PUSH(AH23,CX_ENTITY,$B23,AH$11,AH$14,AH$19,),""),IF($I23=3,"",IFBLANK(_xldudf_CX_PUSH(AH23,CX_ENTITY,$B23,AH$11,AH$14,AH$19,),"")))))),"")} | DI23: {=IFERROR(IF(AI23=_PL!AI23,"",IF(OR(AI23="",NOT(ISNUMBER(AI23)),ISERROR(AI23),$B23=""),"",IF($I23=1,IFBLANK(_xldudf_CX_PUSH(AI23*fxVal_normal,CX_ENTITY,$B23,AI$11,AI$14,AI$19,),""),IF($I23=2,IFBLANK(_xldudf_CX_PUSH(AI23,CX_ENTITY,$B23,AI$11,AI$14,AI$19,),""),IF($I23=3,"",IFBLANK(_xldudf_CX_PUSH(AI23,CX_ENTITY,$B23,AI$11,AI$14,AI$19,),"")))))),"")} | DJ23: {=IFERROR(IF(AJ23=_PL!AJ23,"",IF(OR(AJ23="",NOT(ISNUMBER(AJ23)),ISERROR(AJ23),$B23=""),"",IF($I23=1,IFBLANK(_xldudf_CX_PUSH(AJ23*fxVal_normal,CX_ENTITY,$B23,AJ$11,AJ$14,AJ$19,),""),IF($I23=2,IFBLANK(_xldudf_CX_PUSH(AJ23,CX_ENTITY,$B23,AJ$11,AJ$14,AJ$19,),""),IF($I23=3,"",IFBLANK(_xldudf_CX_PUSH(AJ23,CX_ENTITY,$B23,AJ$11,AJ$14,AJ$19,),"")))))),"")} | DK23: {=IFERROR(IF(AK23=_PL!AK23,"",IF(OR(AK23="",NOT(ISNUMBER(AK23)),ISERROR(AK23),$B23=""),"",IF($I23=1,IFBLANK(_xldudf_CX_PUSH(AK23*fxVal_normal,CX_ENTITY,$B23,AK$11,AK$14,AK$19,),""),IF($I23=2,IFBLANK(_xldudf_CX_PUSH(AK23,CX_ENTITY,$B23,AK$11,AK$14,AK$19,),""),IF($I23=3,"",IFBLANK(_xldudf_CX_PUSH(AK23,CX_ENTITY,$B23,AK$11,AK$14,AK$19,),"")))))),"")} | ... EN23: {=IFERROR(IF(BN23=_PL!BN23,"",IF(OR(BN23="",NOT(ISNUMBER(BN23)),ISERROR(BN23),$B23=""),"",IF($I23=1,IFBLANK(_xldudf_CX_PUSH(BN23*fxVal_normal,CX_ENTITY,$B23,BN$11,BN$14,BN$19,),""),IF($I23=2,IFBLANK(_xldudf_CX_PUSH(BN23,CX_ENTITY,$B23,BN$11,BN$14,BN$19,),""),IF($I23=3,"",IFBLANK(_xldudf_CX_PUSH(BN23,CX_ENTITY,$B23,BN$11,BN$14,BN$19,),"")))))),"")}
B24: =_xlfn.LET(_xlpm.IsNotAttrDynamic,D24="",_xlpm.Attr,_PL!F24,_xlpm.NotInUse,Y24=D24,_xlpm.RESULT,IF(_xlpm.IsNotAttrDynamic,_xlpm.Attr,IF(_xlpm.NotInUse,"",Y24)),IF(_xlpm.RESULT="","",_xlpm.RESULT)) -> Operating Costs | C24: {=IFBLANK(_PL!C24,"")} -> Operating Costs (Company View) | E24: {=_xlfn.LAMBDA(_xlpm.Array,_xlop.Type,_xlfn.LET(_xlpm._type,IF(_xlfn.ISOMITTED(_xlpm.Type),0,_xlpm.Type),_xlpm.R,ROWS(_xlpm.Array),_xlpm.C,COLUMNS(_xlpm.Array),_xlpm.Unlocked,_xlfn.MAKEARRAY(_xlpm.R,_xlpm.C,_xlfn.LAMBDA(_xlpm.i,_xlpm.j,--(CELL("protect",INDEX(_xlpm.Array,_xlpm.i,_xlpm.j))=0))),_xlpm.IsUnlocked,_xlfn.MAKEARRAY(_xlpm.R,_xlpm.C,_xlfn.LAMBDA(_xlpm.i,_xlpm.j,CELL("protect",INDEX(_xlpm.Array,_xlpm.i,_xlpm.j))=0)),_xlpm.HasData,_xlpm.Array<>"",_xlpm.Total,SUM(_xlpm.Unlocked),_xlpm.Completed,SUM(--(_xlpm.IsUnlocked*_xlpm.HasData)),_xlpm.type_display,_xlfn.SWITCH(_xlpm._type,1,"R",-1,"O",0,"A",""),_xlfn.HSTACK(_xlpm.Total,_xlpm.Completed,_xlpm.type_display)))($AD24:$CQ24,Z24)} -> #NAME? | H24: 0 | I24: 1 | J24: {=IFBLANK(Z24,"")} -> 1 | K24: =IFERROR(IF(LEN(AB24)=0,"No",IF(LEN(J24)>0,"Yes","No")),"") -> Yes | W24: =$W$20 -> Actual | X24: =_PL!X24 -> -1 | Y24: 2 | Z24: {=_xlfn.SWITCH(TRUE,_PL!$L24=TRUE,1,_PL!$L24=FALSE,-1,_PL!$L24=-1,0,"")} -> 1 | AB24: =_PL!AB24 -> Operating Costs | AC24: {=_xlfn.LET(_xlpm._termname,$AB24,_xlpm._iconname,"find",_xlpm._icon,fx_getIcon(_xlpm._iconname),_xlpm._location,_xlfn.XLOOKUP(LOWER(_xlpm._termname),LOWER(tbl_acctDef[Term]),tbl_acctDef[Term]),_xlpm._hyperlink,HYPERLINK("#"&CELL("address",_xlpm._location),_xlpm._icon),IFERROR(_xlpm._hyperlink,""))} | AD24: 1 | AE24: 1 | AF24: 1 | AG24: 1 | AH24: 1 | AI24: 1 | AJ24: 1 | AK24: 1 | AL24: 1 | AM24: 1 | AN24: 1 | AO24: 1 | AP24: 1 | AQ24: 1 | AR24: 1 | AS24: 1 | AT24: 1 | AU24: 1 | AV24: 1 | AW24: 1 | AX24: 1 | AY24: 1 | AZ24: 1 | BA24: 1 | BB24: 1 | BC24: 1 | BD24: 1 | BE24: 1 | BF24: 1 | BG24: 1 | BH24: 1 | BI24: 1 | BJ24: 1 | BK24: 1 | BL24: 1 | BM24: 1 | BN24: 1 | CD24: {=_xlfn.LET(_xlpm.CheckBlank,SUM(PL!$AD24:$BN24)=0,IF(_xlpm.CheckBlank,"",SUM(_xlfn._xlws.FILTER(PL!$AD24:$BN24,(YEAR(PL!$AD$12:$BN$12)=PL!CD$12)*(array_timeline<=PL!CD$11)))))} -> #NAME? | CE24: {=_xlfn.LET(_xlpm.CheckBlank,SUM(PL!$AD24:$BN24)=0,IF(_xlpm.CheckBlank,"",SUM(_xlfn._xlws.FILTER(PL!$AD24:$BN24,(YEAR(PL!$AD$12:$BN$12)=PL!CE$12)*(array_timeline<=PL!CE$11)))))} -> #NAME? | CG24: {=IFERROR(_xlfn.LET(_xlpm.CheckBlank,SUM(PL!$AD24:$BN24)=0,IF(_xlpm.CheckBlank,"",SUM(_xlfn._xlws.FILTER(PL!$AD24:$BN24,(YEAR(PL!$AD$12:$BN$12)=PL!CG$12)*(array_timeline<=PL!CG$11))))),"n/a")} -> n/a | CH24: {=_xlfn.LET(_xlpm.CheckBlank,SUM(PL!$AD24:$BN24)=0,IF(_xlpm.CheckBlank,"",SUM(_xlfn._xlws.FILTER(PL!$AD24:$BN24,(YEAR(PL!$AD$12:$BN$12)=PL!CH$12)*(array_timeline<=PL!CH$11)))))} -> #NAME? | CJ24: {=_xlfn.LET(_xlpm.CheckBlank,SUM(PL!$AD24:$BN24)=0,IF(_xlpm.CheckBlank,"",SUM(_xlfn.TAKE(_xlfn.DROP(PL!$AD24:$BN24,,-DATEDIFF(PL!CJ$11,val_asOfDate,"M")),1,-12))))} -> 12 | CK24: {=_xlfn.LET(_xlpm.CheckBlank,SUM(PL!$AD24:$BN24)=0,IF(_xlpm.CheckBlank,"",SUM(_xlfn.TAKE(_xlfn.DROP(PL!$AD24:$BN24,,-DATEDIFF(PL!CK$11,val_asOfDate,"M")),1,-12))))} -> 12 | CM24: 1 | CN24: 1 | CP24: 1 | CQ24: 1 | CT24: {=IF(K24<>"Yes","",IF(OR(Y24="Select, enter text or leave as blank.",Y24="Set from Actual section above!",Y24="Please select or type in or leave as blank",Y24="Select, enter text or leave as blank",Y24="Please select your Top Line Metric",Y24="Check Sum",Y24="Please name your Like-for-Like Revenue",Y24="Please name your Like-for-like Earning Metric",Y24="Valuation Metric",Y24="Please name your Like-for-like Valuation Metric",Y24="Please select your Valuation Metric",Y24="Please select the metric for segmentation",Y24="Untitled Segmentation II",Y24="Untitled Segmentation III"),"",IF(OR(Y24<>AB24,AND(LEN(B24)=0,NOT(OR(Y24="Select, enter text or leave as blank.",Y24="Set from Actual section above!",Y24="Please select or type in or leave as blank",Y24="Select, enter text or leave as blank",Y24="Please select your Top Line Metric",Y24="Check Sum",Y24="Please name your Like-for-Like Revenue",Y24="Please name your Like-for-like Earning Metric",Y24="Valuation Metric",Y24="Please name your Like-for-like Valuation Metric",Y24="Please select your Valuation Metric",Y24="Please select the metric for segmentation",Y24="Untitled Segmentation II",Y24="Untitled Segmentation III")))),_xldudf_CX_PUSH(Y24,CX_ENTITY,C24,EOMONTH(val_asOfDate,0)),"")))} -> #NAME? | CU24: {=IF(K24<>"Yes","",IF(OR(Y24="Select, enter text or leave as blank.",Y24="Set from Actual section above!",Y24="Please select or type in or leave as blank",Y24="Select, enter text or leave as blank",Y24="Please select your Top Line Metric",Y24="Check Sum",Y24="Please name your Like-for-Like Revenue",Y24="Please name your Like-for-like Earning Metric",Y24="Valuation Metric",Y24="Please name your Like-for-like Valuation Metric",Y24="Please select your Valuation Metric",Y24="Please select the metric for segmentation",Y24="Untitled Segmentation II",Y24="Untitled Segmentation III"),"",IF(OR(Y24<>AB24,AND(LEN(B24)=0,NOT(OR(Y24="Select, enter text or leave as blank.",Y24="Set from Actual section above!",Y24="Please select or type in or leave as blank",Y24="Select, enter text or leave as blank",Y24="Please select your Top Line Metric",Y24="Check Sum",Y24="Please name your Like-for-Like Revenue",Y24="Please name your Like-for-like Earning Metric",Y24="Valuation Metric",Y24="Please name your Like-for-like Valuation Metric",Y24="Please select your Valuation Metric",Y24="Please select the metric for segmentation",Y24="Untitled Segmentation II",Y24="Untitled Segmentation III")))),_xldudf_CX_PUSH(Y24,CX_ENTITY,C24,EOMONTH(val_asOfDate,1)),"")))} -> #NAME? | CV24: {=IF(K24<>"Yes","",IF(OR(Y24="Select, enter text or leave as blank.",Y24="Set from Actual section above!",Y24="Please select or type in or leave as blank",Y24="Select, enter text or leave as blank",Y24="Please select your Top Line Metric",Y24="Check Sum",Y24="Please name your Like-for-Like Revenue",Y24="Please name your Like-for-like Earning Metric",Y24="Valuation Metric",Y24="Please name your Like-for-like Valuation Metric",Y24="Please select your Valuation Metric",Y24="Please select the metric for segmentation",Y24="Untitled Segmentation II",Y24="Untitled Segmentation III"),"",IF(OR(Y24<>AB24,AND(LEN(B24)=0,NOT(OR(Y24="Select, enter text or leave as blank.",Y24="Set from Actual section above!",Y24="Please select or type in or leave as blank",Y24="Select, enter text or leave as blank",Y24="Please select your Top Line Metric",Y24="Check Sum",Y24="Please name your Like-for-Like Revenue",Y24="Please name your Like-for-like Earning Metric",Y24="Valuation Metric",Y24="Please name your Like-for-like Valuation Metric",Y24="Please select your Valuation Metric",Y24="Please select the metric for segmentation",Y24="Untitled Segmentation II",Y24="Untitled Segmentation III")))),_xldudf_CX_PUSH(Y24,CX_ENTITY,C24,EOMONTH(val_asOfDate,2)),"")))} -> #NAME? | CW24: {=IF(K24<>"Yes","",IF(OR(Y24="Select, enter text or leave as blank.",Y24="Set from Actual section above!",Y24="Please select or type in or leave as blank",Y24="Select, enter text or leave as blank",Y24="Please select your Top Line Metric",Y24="Check Sum",Y24="Please name your Like-for-Like Revenue",Y24="Please name your Like-for-like Earning Metric",Y24="Valuation Metric",Y24="Please name your Like-for-like Valuation Metric",Y24="Please select your Valuation Metric",Y24="Please select the metric for segmentation",Y24="Untitled Segmentation II",Y24="Untitled Segmentation III"),"",IF(OR(Y24<>AB24,AND(LEN(B24)=0,NOT(OR(Y24="Select, enter text or leave as blank.",Y24="Set from Actual section above!",Y24="Please select or type in or leave as blank",Y24="Select, enter text or leave as blank",Y24="Please select your Top Line Metric",Y24="Check Sum",Y24="Please name your Like-for-Like Revenue",Y24="Please name your Like-for-like Earning Metric",Y24="Valuation Metric",Y24="Please name your Like-for-like Valuation Metric",Y24="Please select your Valuation Metric",Y24="Please select the metric for segmentation",Y24="Untitled Segmentation II",Y24="Untitled Segmentation III")))),_xldudf_CX_PUSH(Y24,CX_ENTITY,C24,EOMONTH(val_asOfDate,3)),"")))} -> #NAME? | CY24: {=IFERROR(IF(CM24*fxVal_normal=_PL!CM24,"",IF(OR($CM24="",$CM24=0,NOT(ISNUMBER($CM24)),ISERROR($CM24),$B24=""),"",IF($I24=1,IFBLANK(_xldudf_CX_PUSH($CM24*fxVal_normal,CX_ENTITY,$B24,$CM$11,$CM$14,$CM$19,),""),IF($I24=2,IFBLANK(_xldudf_CX_PUSH($CM24,CX_ENTITY,$B24,$CM$11,$CM$14,$CM$19,),""),IF($I24=3,"",IFBLANK(_xldudf_CX_PUSH($CM24,CX_ENTITY,$B24,$CM$11,$CM$14,$CM$19,),"")))))),"")} | CZ24: {=IFERROR(IF(CN24*fxVal_normal=_PL!CN24,"",IF(OR($CN24="",$CN24=0,NOT(ISNUMBER($CN24)),ISERROR($CN24),$B24=""),"",IF($I24=1,IFBLANK(_xldudf_CX_PUSH($CN24*fxVal_normal,CX_ENTITY,$B24,$CN$11,$CN$14,$CN$19,),""),IF($I24=2,IFBLANK(_xldudf_CX_PUSH($CN24,CX_ENTITY,$B24,$CN$11,$CN$14,$CN$19,),""),IF($I24=3,"",IFBLANK(_xldudf_CX_PUSH($CN24,CX_ENTITY,$B24,$CN$11,$CN$14,$CN$19,),"")))))),"")} | DA24: {=IFERROR(IF(CP24*fxVal_normal=_PL!CP24,"",IF(OR($CP24="",$CP24=0,NOT(ISNUMBER($CP24)),ISERROR($CP24),$B24=""),"",IF($I24=1,IFBLANK(_xldudf_CX_PUSH($CP24*fxVal_normal,CX_ENTITY,$B24,$CP$11,$CP$14,$CP$19,),""),IF($I24=2,IFBLANK(_xldudf_CX_PUSH($CP24,CX_ENTITY,$B24,$CP$11,$CP$14,$CP$19,),""),IF($I24=3,"",IFBLANK(_xldudf_CX_PUSH($CP24,CX_ENTITY,$B24,$CP$11,$CP$14,$CP$19,),"")))))),"")} | DB24: {=IFERROR(IF(CQ24*fxVal_normal=_PL!CQ24,"",IF(OR($CQ24="",$CQ24=0,NOT(ISNUMBER($CQ24)),ISERROR($CQ24),$B24=""),"",IF($I24=1,IFBLANK(_xldudf_CX_PUSH($CQ24*fxVal_normal,CX_ENTITY,$B24,$CQ$11,$CQ$14,$CQ$19,),""),IF($I24=2,IFBLANK(_xldudf_CX_PUSH($CQ24,CX_ENTITY,$B24,$CQ$11,$CQ$14,$CQ$19,),""),IF($I24=3,"",IFBLANK(_xldudf_CX_PUSH($CQ24,CX_ENTITY,$B24,$CQ$11,$CQ$14,$CQ$19,),"")))))),"")} | DD24: {=IFERROR(IF(AD24*fxVal_normal=_PL!AD24,"",IF(OR(AD24="",NOT(ISNUMBER(AD24)),ISERROR(AD24),$B24=""),"",IF($I24=1,IFBLANK(_xldudf_CX_PUSH(AD24*fxVal_normal,CX_ENTITY,$B24,AD$11,AD$14,AD$19,),""),IF($I24=2,IFBLANK(_xldudf_CX_PUSH(AD24,CX_ENTITY,$B24,AD$11,AD$14,AD$19,),""),IF($I24=3,"",IFBLANK(_xldudf_CX_PUSH(AD24,CX_ENTITY,$B24,AD$11,AD$14,AD$19,),"")))))),"")} | DE24: {=IFERROR(IF(AE24*fxVal_normal=_PL!AE24,"",IF(OR(AE24="",NOT(ISNUMBER(AE24)),ISERROR(AE24),$B24=""),"",IF($I24=1,IFBLANK(_xldudf_CX_PUSH(AE24*fxVal_normal,CX_ENTITY,$B24,AE$11,AE$14,AE$19,),""),IF($I24=2,IFBLANK(_xldudf_CX_PUSH(AE24,CX_ENTITY,$B24,AE$11,AE$14,AE$19,),""),IF($I24=3,"",IFBLANK(_xldudf_CX_PUSH(AE24,CX_ENTITY,$B24,AE$11,AE$14,AE$19,),"")))))),"")} | DF24: {=IFERROR(IF(AF24*fxVal_normal=_PL!AF24,"",IF(OR(AF24="",NOT(ISNUMBER(AF24)),ISERROR(AF24),$B24=""),"",IF($I24=1,IFBLANK(_xldudf_CX_PUSH(AF24*fxVal_normal,CX_ENTITY,$B24,AF$11,AF$14,AF$19,),""),IF($I24=2,IFBLANK(_xldudf_CX_PUSH(AF24,CX_ENTITY,$B24,AF$11,AF$14,AF$19,),""),IF($I24=3,"",IFBLANK(_xldudf_CX_PUSH(AF24,CX_ENTITY,$B24,AF$11,AF$14,AF$19,),"")))))),"")} | DG24: {=IFERROR(IF(AG24*fxVal_normal=_PL!AG24,"",IF(OR(AG24="",NOT(ISNUMBER(AG24)),ISERROR(AG24),$B24=""),"",IF($I24=1,IFBLANK(_xldudf_CX_PUSH(AG24*fxVal_normal,CX_ENTITY,$B24,AG$11,AG$14,AG$19,),""),IF($I24=2,IFBLANK(_xldudf_CX_PUSH(AG24,CX_ENTITY,$B24,AG$11,AG$14,AG$19,),""),IF($I24=3,"",IFBLANK(_xldudf_CX_PUSH(AG24,CX_ENTITY,$B24,AG$11,AG$14,AG$19,),"")))))),"")} | DH24: {=IFERROR(IF(AH24*fxVal_normal=_PL!AH24,"",IF(OR(AH24="",NOT(ISNUMBER(AH24)),ISERROR(AH24),$B24=""),"",IF($I24=1,IFBLANK(_xldudf_CX_PUSH(AH24*fxVal_normal,CX_ENTITY,$B24,AH$11,AH$14,AH$19,),""),IF($I24=2,IFBLANK(_xldudf_CX_PUSH(AH24,CX_ENTITY,$B24,AH$11,AH$14,AH$19,),""),IF($I24=3,"",IFBLANK(_xldudf_CX_PUSH(AH24,CX_ENTITY,$B24,AH$11,AH$14,AH$19,),"")))))),"")} | DI24: {=IFERROR(IF(AI24*fxVal_normal=_PL!AI24,"",IF(OR(AI24="",NOT(ISNUMBER(AI24)),ISERROR(AI24),$B24=""),"",IF($I24=1,IFBLANK(_xldudf_CX_PUSH(AI24*fxVal_normal,CX_ENTITY,$B24,AI$11,AI$14,AI$19,),""),IF($I24=2,IFBLANK(_xldudf_CX_PUSH(AI24,CX_ENTITY,$B24,AI$11,AI$14,AI$19,),""),IF($I24=3,"",IFBLANK(_xldudf_CX_PUSH(AI24,CX_ENTITY,$B24,AI$11,AI$14,AI$19,),"")))))),"")} | DJ24: {=IFERROR(IF(AJ24*fxVal_normal=_PL!AJ24,"",IF(OR(AJ24="",NOT(ISNUMBER(AJ24)),ISERROR(AJ24),$B24=""),"",IF($I24=1,IFBLANK(_xldudf_CX_PUSH(AJ24*fxVal_normal,CX_ENTITY,$B24,AJ$11,AJ$14,AJ$19,),""),IF($I24=2,IFBLANK(_xldudf_CX_PUSH(AJ24,CX_ENTITY,$B24,AJ$11,AJ$14,AJ$19,),""),IF($I24=3,"",IFBLANK(_xldudf_CX_PUSH(AJ24,CX_ENTITY,$B24,AJ$11,AJ$14,AJ$19,),"")))))),"")} | DK24: {=IFERROR(IF(AK24*fxVal_normal=_PL!AK24,"",IF(OR(AK24="",NOT(ISNUMBER(AK24)),ISERROR(AK24),$B24=""),"",IF($I24=1,IFBLANK(_xldudf_CX_PUSH(AK24*fxVal_normal,CX_ENTITY,$B24,AK$11,AK$14,AK$19,),""),IF($I24=2,IFBLANK(_xldudf_CX_PUSH(AK24,CX_ENTITY,$B24,AK$11,AK$14,AK$19,),""),IF($I24=3,"",IFBLANK(_xldudf_CX_PUSH(AK24,CX_ENTITY,$B24,AK$11,AK$14,AK$19,),"")))))),"")} | ... EN24: {=IFERROR(IF(BN24*fxVal_normal=_PL!BN24,"",IF(OR(BN24="",NOT(ISNUMBER(BN24)),ISERROR(BN24),$B24=""),"",IF($I24=1,IFBLANK(_xldudf_CX_PUSH(BN24*fxVal_normal,CX_ENTITY,$B24,BN$11,BN$14,BN$19,),""),IF($I24=2,IFBLANK(_xldudf_CX_PUSH(BN24,CX_ENTITY,$B24,BN$11,BN$14,BN$19,),""),IF($I24=3,"",IFBLANK(_xldudf_CX_PUSH(BN24,CX_ENTITY,$B24,BN$11,BN$14,BN$19,),"")))))),"")}
B25: =_xlfn.LET(_xlpm.IsNotAttrDynamic,D25="",_xlpm.Attr,_PL!F25,_xlpm.NotInUse,Y25=D25,_xlpm.RESULT,IF(_xlpm.IsNotAttrDynamic,_xlpm.Attr,IF(_xlpm.NotInUse,"",Y25)),IF(_xlpm.RESULT="","",_xlpm.RESULT)) -> Reported EBITDA | C25: {=IFBLANK(_PL!C25,"")} -> Reported EBITDA (Company View) | E25: {=_xlfn.LAMBDA(_xlpm.Array,_xlop.Type,_xlfn.LET(_xlpm._type,IF(_xlfn.ISOMITTED(_xlpm.Type),0,_xlpm.Type),_xlpm.R,ROWS(_xlpm.Array),_xlpm.C,COLUMNS(_xlpm.Array),_xlpm.Unlocked,_xlfn.MAKEARRAY(_xlpm.R,_xlpm.C,_xlfn.LAMBDA(_xlpm.i,_xlpm.j,--(CELL("protect",INDEX(_xlpm.Array,_xlpm.i,_xlpm.j))=0))),_xlpm.IsUnlocked,_xlfn.MAKEARRAY(_xlpm.R,_xlpm.C,_xlfn.LAMBDA(_xlpm.i,_xlpm.j,CELL("protect",INDEX(_xlpm.Array,_xlpm.i,_xlpm.j))=0)),_xlpm.HasData,_xlpm.Array<>"",_xlpm.Total,SUM(_xlpm.Unlocked),_xlpm.Completed,SUM(--(_xlpm.IsUnlocked*_xlpm.HasData)),_xlpm.type_display,_xlfn.SWITCH(_xlpm._type,1,"R",-1,"O",0,"A",""),_xlfn.HSTACK(_xlpm.Total,_xlpm.Completed,_xlpm.type_display)))($AD25:$CQ25,Z25)} -> #NAME? | H25: 2 | I25: 1 | J25: {=IFBLANK(Z25,"")} -> 0 | K25: =IFERROR(IF(LEN(AB25)=0,"No",IF(LEN(J25)>0,"Yes","No")),"") -> Yes | W25: =$W$20 -> Actual | X25: =_PL!X25 -> 0 | Y25: =IF(_PL!Y25="Error","",_PL!Y25) -> #NAME? | Z25: {=_xlfn.SWITCH(TRUE,_PL!$L25=TRUE,1,_PL!$L25=FALSE,-1,_PL!$L25=-1,0,"")} -> 0 | AB25: =_PL!AB25 -> Reported EBITDA | AC25: {=_xlfn.LET(_xlpm._termname,$AB25,_xlpm._iconname,"find",_xlpm._icon,fx_getIcon(_xlpm._iconname),_xlpm._location,_xlfn.XLOOKUP(LOWER(_xlpm._termname),LOWER(tbl_acctDef[Term]),tbl_acctDef[Term]),_xlpm._hyperlink,HYPERLINK("#"&CELL("address",_xlpm._location),_xlpm._icon),IFERROR(_xlpm._hyperlink,""))} -> #VALUE! | AD25: =SUBTOTAL(9,AD20:AD24)-N(AD23) -> 3 | AE25: =SUBTOTAL(9,AE20:AE24)-N(AE23) -> 3 | AF25: =SUBTOTAL(9,AF20:AF24)-N(AF23) -> 3 | AG25: =SUBTOTAL(9,AG20:AG24)-N(AG23) -> 3 | AH25: =SUBTOTAL(9,AH20:AH24)-N(AH23) -> 3 | AI25: =SUBTOTAL(9,AI20:AI24)-N(AI23) -> 3 | AJ25: =SUBTOTAL(9,AJ20:AJ24)-N(AJ23) -> 3 | AK25: =SUBTOTAL(9,AK20:AK24)-N(AK23) -> 3 | ... BN25: =SUBTOTAL(9,BN20:BN24)-N(BN23) -> 3 | CD25: {=_xlfn.LET(_xlpm.CheckBlank,SUM(PL!$AD25:PL!$BN25)=0,IF(_xlpm.CheckBlank,"",SUM(_xlfn._xlws.FILTER(PL!$AD25:$BN25,(YEAR(PL!$AD$12:$BN$12)=PL!CD$12)*(array_timeline<=PL!CD$11)))))} -> #NAME? | CE25: {=_xlfn.LET(_xlpm.CheckBlank,SUM(PL!$AD25:PL!$BN25)=0,IF(_xlpm.CheckBlank,"",SUM(_xlfn._xlws.FILTER(PL!$AD25:$BN25,(YEAR(PL!$AD$12:$BN$12)=PL!CE$12)*(array_timeline<=PL!CE$11)))))} -> #NAME? | CG25: {=IFERROR(_xlfn.LET(_xlpm.CheckBlank,SUM(PL!$AD25:$BN25)=0,IF(_xlpm.CheckBlank,"",SUM(_xlfn._xlws.FILTER(PL!$AD25:$BN25,(YEAR(PL!$AD$12:$BN$12)=PL!CG$12)*(array_timeline<=PL!CG$11))))),"n/a")} -> n/a | CH25: {=_xlfn.LET(_xlpm.CheckBlank,SUM(PL!$AD25:$BN25)=0,IF(_xlpm.CheckBlank,"",SUM(_xlfn._xlws.FILTER(PL!$AD25:$BN25,(YEAR(PL!$AD$12:$BN$12)=PL!CH$12)*(array_timeline<=PL!CH$11)))))} -> #NAME? | CJ25: {=_xlfn.LET(_xlpm.CheckBlank,SUM(PL!$AD25:$BN25)=0,IF(_xlpm.CheckBlank,"",SUM(_xlfn.TAKE(_xlfn.DROP(PL!$AD25:$BN25,,-DATEDIFF(PL!CJ$11,val_asOfDate,"M")),1,-12))))} -> 36 | CK25: {=_xlfn.LET(_xlpm.CheckBlank,SUM(PL!$AD25:$BN25)=0,IF(_xlpm.CheckBlank,"",SUM(_xlfn.TAKE(_xlfn.DROP(PL!$AD25:$BN25,,-DATEDIFF(PL!CK$11,val_asOfDate,"M")),1,-12))))} -> 36 | CM25: =SUBTOTAL(9,CM20:CM24)-N(CM23) -> 3 | CN25: =SUBTOTAL(9,CN20:CN24)-N(CN23) -> 3 | CP25: =SUBTOTAL(9,CP20:CP24)-N(CP23) -> 3 | CQ25: =SUBTOTAL(9,CQ20:CQ24)-N(CQ23) -> 3 | CT25: {=IF(K25<>"Yes","",IF(OR(Y25="Select, enter text or leave as blank.",Y25="Set from Actual section above!",Y25="Please select or type in or leave as blank",Y25="Select, enter text or leave as blank",Y25="Please select your Top Line Metric",Y25="Check Sum",Y25="Please name your Like-for-Like Revenue",Y25="Please name your Like-for-like Earning Metric",Y25="Valuation Metric",Y25="Please name your Like-for-like Valuation Metric",Y25="Please select your Valuation Metric",Y25="Please select the metric for segmentation",Y25="Untitled Segmentation II",Y25="Untitled Segmentation III"),"",IF(OR(Y25<>AB25,AND(LEN(B25)=0,NOT(OR(Y25="Select, enter text or leave as blank.",Y25="Set from Actual section above!",Y25="Please select or type in or leave as blank",Y25="Select, enter text or leave as blank",Y25="Please select your Top Line Metric",Y25="Check Sum",Y25="Please name your Like-for-Like Revenue",Y25="Please name your Like-for-like Earning Metric",Y25="Valuation Metric",Y25="Please name your Like-for-like Valuation Metric",Y25="Please select your Valuation Metric",Y25="Please select the metric for segmentation",Y25="Untitled Segmentation II",Y25="Untitled Segmentation III")))),_xldudf_CX_PUSH(Y25,CX_ENTITY,C25,EOMONTH(val_asOfDate,0)),"")))} -> #NAME? | CU25: {=IF(K25<>"Yes","",IF(OR(Y25="Select, enter text or leave as blank.",Y25="Set from Actual section above!",Y25="Please select or type in or leave as blank",Y25="Select, enter text or leave as blank",Y25="Please select your Top Line Metric",Y25="Check Sum",Y25="Please name your Like-for-Like Revenue",Y25="Please name your Like-for-like Earning Metric",Y25="Valuation Metric",Y25="Please name your Like-for-like Valuation Metric",Y25="Please select your Valuation Metric",Y25="Please select the metric for segmentation",Y25="Untitled Segmentation II",Y25="Untitled Segmentation III"),"",IF(OR(Y25<>AB25,AND(LEN(B25)=0,NOT(OR(Y25="Select, enter text or leave as blank.",Y25="Set from Actual section above!",Y25="Please select or type in or leave as blank",Y25="Select, enter text or leave as blank",Y25="Please select your Top Line Metric",Y25="Check Sum",Y25="Please name your Like-for-Like Revenue",Y25="Please name your Like-for-like Earning Metric",Y25="Valuation Metric",Y25="Please name your Like-for-like Valuation Metric",Y25="Please select your Valuation Metric",Y25="Please select the metric for segmentation",Y25="Untitled Segmentation II",Y25="Untitled Segmentation III")))),_xldudf_CX_PUSH(Y25,CX_ENTITY,C25,EOMONTH(val_asOfDate,1)),"")))} -> #NAME? | CV25: {=IF(K25<>"Yes","",IF(OR(Y25="Select, enter text or leave as blank.",Y25="Set from Actual section above!",Y25="Please select or type in or leave as blank",Y25="Select, enter text or leave as blank",Y25="Please select your Top Line Metric",Y25="Check Sum",Y25="Please name your Like-for-Like Revenue",Y25="Please name your Like-for-like Earning Metric",Y25="Valuation Metric",Y25="Please name your Like-for-like Valuation Metric",Y25="Please select your Valuation Metric",Y25="Please select the metric for segmentation",Y25="Untitled Segmentation II",Y25="Untitled Segmentation III"),"",IF(OR(Y25<>AB25,AND(LEN(B25)=0,NOT(OR(Y25="Select, enter text or leave as blank.",Y25="Set from Actual section above!",Y25="Please select or type in or leave as blank",Y25="Select, enter text or leave as blank",Y25="Please select your Top Line Metric",Y25="Check Sum",Y25="Please name your Like-for-Like Revenue",Y25="Please name your Like-for-like Earning Metric",Y25="Valuation Metric",Y25="Please name your Like-for-like Valuation Metric",Y25="Please select your Valuation Metric",Y25="Please select the metric for segmentation",Y25="Untitled Segmentation II",Y25="Untitled Segmentation III")))),_xldudf_CX_PUSH(Y25,CX_ENTITY,C25,EOMONTH(val_asOfDate,2)),"")))} -> #NAME? | CW25: {=IF(K25<>"Yes","",IF(OR(Y25="Select, enter text or leave as blank.",Y25="Set from Actual section above!",Y25="Please select or type in or leave as blank",Y25="Select, enter text or leave as blank",Y25="Please select your Top Line Metric",Y25="Check Sum",Y25="Please name your Like-for-Like Revenue",Y25="Please name your Like-for-like Earning Metric",Y25="Valuation Metric",Y25="Please name your Like-for-like Valuation Metric",Y25="Please select your Valuation Metric",Y25="Please select the metric for segmentation",Y25="Untitled Segmentation II",Y25="Untitled Segmentation III"),"",IF(OR(Y25<>AB25,AND(LEN(B25)=0,NOT(OR(Y25="Select, enter text or leave as blank.",Y25="Set from Actual section above!",Y25="Please select or type in or leave as blank",Y25="Select, enter text or leave as blank",Y25="Please select your Top Line Metric",Y25="Check Sum",Y25="Please name your Like-for-Like Revenue",Y25="Please name your Like-for-like Earning Metric",Y25="Valuation Metric",Y25="Please name your Like-for-like Valuation Metric",Y25="Please select your Valuation Metric",Y25="Please select the metric for segmentation",Y25="Untitled Segmentation II",Y25="Untitled Segmentation III")))),_xldudf_CX_PUSH(Y25,CX_ENTITY,C25,EOMONTH(val_asOfDate,3)),"")))} -> #NAME? | CY25: {=IFERROR(IF(CM25*fxVal_normal=_PL!CM25,"",IF(OR($CM25="",$CM25=0,NOT(ISNUMBER($CM25)),ISERROR($CM25),$B25=""),"",IF($I25=1,IFBLANK(_xldudf_CX_PUSH($CM25*fxVal_normal,CX_ENTITY,$B25,$CM$11,$CM$14,$CM$19,),""),IF($I25=2,IFBLANK(_xldudf_CX_PUSH($CM25,CX_ENTITY,$B25,$CM$11,$CM$14,$CM$19,),""),IF($I25=3,"",IFBLANK(_xldudf_CX_PUSH($CM25,CX_ENTITY,$B25,$CM$11,$CM$14,$CM$19,),"")))))),"")} | CZ25: {=IFERROR(IF(CN25*fxVal_normal=_PL!CN25,"",IF(OR($CN25="",$CN25=0,NOT(ISNUMBER($CN25)),ISERROR($CN25),$B25=""),"",IF($I25=1,IFBLANK(_xldudf_CX_PUSH($CN25*fxVal_normal,CX_ENTITY,$B25,$CN$11,$CN$14,$CN$19,),""),IF($I25=2,IFBLANK(_xldudf_CX_PUSH($CN25,CX_ENTITY,$B25,$CN$11,$CN$14,$CN$19,),""),IF($I25=3,"",IFBLANK(_xldudf_CX_PUSH($CN25,CX_ENTITY,$B25,$CN$11,$CN$14,$CN$19,),"")))))),"")} | DA25: {=IFERROR(IF(CP25*fxVal_normal=_PL!CP25,"",IF(OR($CP25="",$CP25=0,NOT(ISNUMBER($CP25)),ISERROR($CP25),$B25=""),"",IF($I25=1,IFBLANK(_xldudf_CX_PUSH($CP25*fxVal_normal,CX_ENTITY,$B25,$CP$11,$CP$14,$CP$19,),""),IF($I25=2,IFBLANK(_xldudf_CX_PUSH($CP25,CX_ENTITY,$B25,$CP$11,$CP$14,$CP$19,),""),IF($I25=3,"",IFBLANK(_xldudf_CX_PUSH($CP25,CX_ENTITY,$B25,$CP$11,$CP$14,$CP$19,),"")))))),"")} | DB25: {=IFERROR(IF(CQ25*fxVal_normal=_PL!CQ25,"",IF(OR($CQ25="",$CQ25=0,NOT(ISNUMBER($CQ25)),ISERROR($CQ25),$B25=""),"",IF($I25=1,IFBLANK(_xldudf_CX_PUSH($CQ25*fxVal_normal,CX_ENTITY,$B25,$CQ$11,$CQ$14,$CQ$19,),""),IF($I25=2,IFBLANK(_xldudf_CX_PUSH($CQ25,CX_ENTITY,$B25,$CQ$11,$CQ$14,$CQ$19,),""),IF($I25=3,"",IFBLANK(_xldudf_CX_PUSH($CQ25,CX_ENTITY,$B25,$CQ$11,$CQ$14,$CQ$19,),"")))))),"")} | DD25: {=IFERROR(IF(AD25*fxVal_normal=_PL!AD25,"",IF(OR(AD25="",NOT(ISNUMBER(AD25)),ISERROR(AD25),$B25=""),"",IF($I25=1,IFBLANK(_xldudf_CX_PUSH(AD25*fxVal_normal,CX_ENTITY,$B25,AD$11,AD$14,AD$19,),""),IF($I25=2,IFBLANK(_xldudf_CX_PUSH(AD25,CX_ENTITY,$B25,AD$11,AD$14,AD$19,),""),IF($I25=3,"",IFBLANK(_xldudf_CX_PUSH(AD25,CX_ENTITY,$B25,AD$11,AD$14,AD$19,),"")))))),"")} | DE25: {=IFERROR(IF(AE25*fxVal_normal=_PL!AE25,"",IF(OR(AE25="",NOT(ISNUMBER(AE25)),ISERROR(AE25),$B25=""),"",IF($I25=1,IFBLANK(_xldudf_CX_PUSH(AE25*fxVal_normal,CX_ENTITY,$B25,AE$11,AE$14,AE$19,),""),IF($I25=2,IFBLANK(_xldudf_CX_PUSH(AE25,CX_ENTITY,$B25,AE$11,AE$14,AE$19,),""),IF($I25=3,"",IFBLANK(_xldudf_CX_PUSH(AE25,CX_ENTITY,$B25,AE$11,AE$14,AE$19,),"")))))),"")} | DF25: {=IFERROR(IF(AF25*fxVal_normal=_PL!AF25,"",IF(OR(AF25="",NOT(ISNUMBER(AF25)),ISERROR(AF25),$B25=""),"",IF($I25=1,IFBLANK(_xldudf_CX_PUSH(AF25*fxVal_normal,CX_ENTITY,$B25,AF$11,AF$14,AF$19,),""),IF($I25=2,IFBLANK(_xldudf_CX_PUSH(AF25,CX_ENTITY,$B25,AF$11,AF$14,AF$19,),""),IF($I25=3,"",IFBLANK(_xldudf_CX_PUSH(AF25,CX_ENTITY,$B25,AF$11,AF$14,AF$19,),"")))))),"")} | DG25: {=IFERROR(IF(AG25*fxVal_normal=_PL!AG25,"",IF(OR(AG25="",NOT(ISNUMBER(AG25)),ISERROR(AG25),$B25=""),"",IF($I25=1,IFBLANK(_xldudf_CX_PUSH(AG25*fxVal_normal,CX_ENTITY,$B25,AG$11,AG$14,AG$19,),""),IF($I25=2,IFBLANK(_xldudf_CX_PUSH(AG25,CX_ENTITY,$B25,AG$11,AG$14,AG$19,),""),IF($I25=3,"",IFBLANK(_xldudf_CX_PUSH(AG25,CX_ENTITY,$B25,AG$11,AG$14,AG$19,),"")))))),"")} | DH25: {=IFERROR(IF(AH25*fxVal_normal=_PL!AH25,"",IF(OR(AH25="",NOT(ISNUMBER(AH25)),ISERROR(AH25),$B25=""),"",IF($I25=1,IFBLANK(_xldudf_CX_PUSH(AH25*fxVal_normal,CX_ENTITY,$B25,AH$11,AH$14,AH$19,),""),IF($I25=2,IFBLANK(_xldudf_CX_PUSH(AH25,CX_ENTITY,$B25,AH$11,AH$14,AH$19,),""),IF($I25=3,"",IFBLANK(_xldudf_CX_PUSH(AH25,CX_ENTITY,$B25,AH$11,AH$14,AH$19,),"")))))),"")} | DI25: {=IFERROR(IF(AI25*fxVal_normal=_PL!AI25,"",IF(OR(AI25="",NOT(ISNUMBER(AI25)),ISERROR(AI25),$B25=""),"",IF($I25=1,IFBLANK(_xldudf_CX_PUSH(AI25*fxVal_normal,CX_ENTITY,$B25,AI$11,AI$14,AI$19,),""),IF($I25=2,IFBLANK(_xldudf_CX_PUSH(AI25,CX_ENTITY,$B25,AI$11,AI$14,AI$19,),""),IF($I25=3,"",IFBLANK(_xldudf_CX_PUSH(AI25,CX_ENTITY,$B25,AI$11,AI$14,AI$19,),"")))))),"")} | DJ25: {=IFERROR(IF(AJ25*fxVal_normal=_PL!AJ25,"",IF(OR(AJ25="",NOT(ISNUMBER(AJ25)),ISERROR(AJ25),$B25=""),"",IF($I25=1,IFBLANK(_xldudf_CX_PUSH(AJ25*fxVal_normal,CX_ENTITY,$B25,AJ$11,AJ$14,AJ$19,),""),IF($I25=2,IFBLANK(_xldudf_CX_PUSH(AJ25,CX_ENTITY,$B25,AJ$11,AJ$14,AJ$19,),""),IF($I25=3,"",IFBLANK(_xldudf_CX_PUSH(AJ25,CX_ENTITY,$B25,AJ$11,AJ$14,AJ$19,),"")))))),"")} | DK25: {=IFERROR(IF(AK25*fxVal_normal=_PL!AK25,"",IF(OR(AK25="",NOT(ISNUMBER(AK25)),ISERROR(AK25),$B25=""),"",IF($I25=1,IFBLANK(_xldudf_CX_PUSH(AK25*fxVal_normal,CX_ENTITY,$B25,AK$11,AK$14,AK$19,),""),IF($I25=2,IFBLANK(_xldudf_CX_PUSH(AK25,CX_ENTITY,$B25,AK$11,AK$14,AK$19,),""),IF($I25=3,"",IFBLANK(_xldudf_CX_PUSH(AK25,CX_ENTITY,$B25,AK$11,AK$14,AK$19,),"")))))),"")} | ... EN25: {=IFERROR(IF(BN25*fxVal_normal=_PL!BN25,"",IF(OR(BN25="",NOT(ISNUMBER(BN25)),ISERROR(BN25),$B25=""),"",IF($I25=1,IFBLANK(_xldudf_CX_PUSH(BN25*fxVal_normal,CX_ENTITY,$B25,BN$11,BN$14,BN$19,),""),IF($I25=2,IFBLANK(_xldudf_CX_PUSH(BN25,CX_ENTITY,$B25,BN$11,BN$14,BN$19,),""),IF($I25=3,"",IFBLANK(_xldudf_CX_PUSH(BN25,CX_ENTITY,$B25,BN$11,BN$14,BN$19,),"")))))),"")}
B26: =_xlfn.LET(_xlpm.IsNotAttrDynamic,D26="",_xlpm.Attr,_PL!F26,_xlpm.NotInUse,Y26=D26,_xlpm.RESULT,IF(_xlpm.IsNotAttrDynamic,_xlpm.Attr,IF(_xlpm.NotInUse,"",Y26)),IF(_xlpm.RESULT="","",_xlpm.RESULT)) -> 2 | C26: {=IFBLANK(_PL!C26,"")} -> EBITDA Adjustment Type I - Label 1 | D26: Please select or type in or leave as blank (1) | E26: {=_xlfn.LAMBDA(_xlpm.Array,_xlop.Type,_xlfn.LET(_xlpm._type,IF(_xlfn.ISOMITTED(_xlpm.Type),0,_xlpm.Type),_xlpm.R,ROWS(_xlpm.Array),_xlpm.C,COLUMNS(_xlpm.Array),_xlpm.Unlocked,_xlfn.MAKEARRAY(_xlpm.R,_xlpm.C,_xlfn.LAMBDA(_xlpm.i,_xlpm.j,--(CELL("protect",INDEX(_xlpm.Array,_xlpm.i,_xlpm.j))=0))),_xlpm.IsUnlocked,_xlfn.MAKEARRAY(_xlpm.R,_xlpm.C,_xlfn.LAMBDA(_xlpm.i,_xlpm.j,CELL("protect",INDEX(_xlpm.Array,_xlpm.i,_xlpm.j))=0)),_xlpm.HasData,_xlpm.Array<>"",_xlpm.Total,SUM(_xlpm.Unlocked),_xlpm.Completed,SUM(--(_xlpm.IsUnlocked*_xlpm.HasData)),_xlpm.type_display,_xlfn.SWITCH(_xlpm._type,1,"R",-1,"O",0,"A",""),_xlfn.HSTACK(_xlpm.Total,_xlpm.Completed,_xlpm.type_display)))($AD26:$CQ26,Z26)} -> #NAME? | H26: 0 | I26: 1 | J26: {=IFBLANK(Z26,"")} -> -1 | K26: =IFERROR(IF(LEN(AB26)=0,"No",IF(LEN(J26)>0,"Yes","No")),"") -> Yes | L26: 1 | W26: =$W$20 -> Actual | X26: =_PL!X26 -> a | Y26: 2 | Z26: {=_xlfn.SWITCH(TRUE,_PL!$L26=TRUE,1,_PL!$L26=FALSE,-1,_PL!$L26=-1,0,"")} -> -1 | AB26: =Y26 -> 2 | AC26: {=_xlfn.LET(_xlpm._termname,$AB26,_xlpm._iconname,"find",_xlpm._icon,fx_getIcon(_xlpm._iconname),_xlpm._location,_xlfn.XLOOKUP(LOWER(_xlpm._termname),LOWER(tbl_acctDef[Term]),tbl_acctDef[Term]),_xlpm._hyperlink,HYPERLINK("#"&CELL("address",_xlpm._location),_xlpm._icon),IFERROR(_xlpm._hyperlink,""))} | AD26: 1 | AE26: 1 | AF26: 1 | AG26: 1 | AH26: 1 | AI26: 1 | AJ26: 1 | AK26: 1 | AL26: 1 | AM26: 1 | AN26: 1 | AO26: 1 | AP26: 1 | AQ26: 1 | AR26: 1 | AS26: 1 | AT26: 1 | AU26: 1 | AV26: 1 | AW26: 1 | AX26: 1 | AY26: 1 | AZ26: 1 | BA26: 1 | BB26: 1 | BC26: 1 | BD26: 1 | BE26: 1 | BF26: 1 | BG26: 1 | BH26: 1 | BI26: 1 | BJ26: 1 | BK26: 1 | BL26: 1 | BM26: 1 | BN26: 1 | CD26: {=_xlfn.LET(_xlpm.CheckBlank,SUM(PL!$AD26:PL!$BN26)=0,IF(_xlpm.CheckBlank,"",SUM(_xlfn._xlws.FILTER(PL!$AD26:$BN26,(YEAR(PL!$AD$12:$BN$12)=PL!CD$12)*(array_timeline<=PL!CD$11)))))} -> #NAME? | CE26: {=_xlfn.LET(_xlpm.CheckBlank,SUM(PL!$AD26:PL!$BN26)=0,IF(_xlpm.CheckBlank,"",SUM(_xlfn._xlws.FILTER(PL!$AD26:$BN26,(YEAR(PL!$AD$12:$BN$12)=PL!CE$12)*(array_timeline<=PL!CE$11)))))} -> #NAME? | CG26: {=IFERROR(_xlfn.LET(_xlpm.CheckBlank,SUM(PL!$AD26:$BN26)=0,IF(_xlpm.CheckBlank,"",SUM(_xlfn._xlws.FILTER(PL!$AD26:$BN26,(YEAR(PL!$AD$12:$BN$12)=PL!CG$12)*(array_timeline<=PL!CG$11))))),"n/a")} -> n/a | CH26: {=_xlfn.LET(_xlpm.CheckBlank,SUM(PL!$AD26:$BN26)=0,IF(_xlpm.CheckBlank,"",SUM(_xlfn._xlws.FILTER(PL!$AD26:$BN26,(YEAR(PL!$AD$12:$BN$12)=PL!CH$12)*(array_timeline<=PL!CH$11)))))} -> #NAME? | CJ26: {=_xlfn.LET(_xlpm.CheckBlank,SUM(PL!$AD26:$BN26)=0,IF(_xlpm.CheckBlank,"",SUM(_xlfn.TAKE(_xlfn.DROP(PL!$AD26:$BN26,,-DATEDIFF(PL!CJ$11,val_asOfDate,"M")),1,-12))))} -> 12 | CK26: {=_xlfn.LET(_xlpm.CheckBlank,SUM(PL!$AD26:$BN26)=0,IF(_xlpm.CheckBlank,"",SUM(_xlfn.TAKE(_xlfn.DROP(PL!$AD26:$BN26,,-DATEDIFF(PL!CK$11,val_asOfDate,"M")),1,-12))))} -> 12 | CM26: 1 | CN26: 1 | CP26: 1 | CQ26: 1 | CT26: {=IF(ISNUMBER(SEARCH("Select",$Y26)),"",_xldudf_CX_PUSH($Y26,CX_ENTITY,C26,val_asOfDate))} -> #NAME? | CU26: {=IF(ISNUMBER(SEARCH("Select",$Y26)),"",_xldudf_CX_PUSH($Y26,CX_ENTITY,C26,EOMONTH(val_asOfDate,1)))} -> #NAME? | CV26: {=IF(ISNUMBER(SEARCH("Select",$Y26)),"",_xldudf_CX_PUSH($Y26,CX_ENTITY,C26,EOMONTH(val_asOfDate,2)))} -> #NAME? | CW26: {=IF(ISNUMBER(SEARCH("Select",$Y26)),"",_xldudf_CX_PUSH($Y26,CX_ENTITY,C26,EOMONTH(val_asOfDate,3)))} -> #NAME? | CY26: {=IFERROR(IF(CM26*fxVal_normal=_PL!CM26,"",IF(OR($CM26="",$CM26=0,NOT(ISNUMBER($CM26)),ISERROR($CM26),$B26=""),"",IF($I26=1,IFBLANK(_xldudf_CX_PUSH($CM26*fxVal_normal,CX_ENTITY,$B26,$CM$11,$CM$14,$CM$19,),""),IF($I26=2,IFBLANK(_xldudf_CX_PUSH($CM26,CX_ENTITY,$B26,$CM$11,$CM$14,$CM$19,),""),IF($I26=3,"",IFBLANK(_xldudf_CX_PUSH($CM26,CX_ENTITY,$B26,$CM$11,$CM$14,$CM$19,),"")))))),"")} | CZ26: {=IFERROR(IF(CN26*fxVal_normal=_PL!CN26,"",IF(OR($CN26="",$CN26=0,NOT(ISNUMBER($CN26)),ISERROR($CN26),$B26=""),"",IF($I26=1,IFBLANK(_xldudf_CX_PUSH($CN26*fxVal_normal,CX_ENTITY,$B26,$CN$11,$CN$14,$CN$19,),""),IF($I26=2,IFBLANK(_xldudf_CX_PUSH($CN26,CX_ENTITY,$B26,$CN$11,$CN$14,$CN$19,),""),IF($I26=3,"",IFBLANK(_xldudf_CX_PUSH($CN26,CX_ENTITY,$B26,$CN$11,$CN$14,$CN$19,),"")))))),"")} | DA26: {=IFERROR(IF(CP26*fxVal_normal=_PL!CP26,"",IF(OR($CP26="",$CP26=0,NOT(ISNUMBER($CP26)),ISERROR($CP26),$B26=""),"",IF($I26=1,IFBLANK(_xldudf_CX_PUSH($CP26*fxVal_normal,CX_ENTITY,$B26,$CP$11,$CP$14,$CP$19,),""),IF($I26=2,IFBLANK(_xldudf_CX_PUSH($CP26,CX_ENTITY,$B26,$CP$11,$CP$14,$CP$19,),""),IF($I26=3,"",IFBLANK(_xldudf_CX_PUSH($CP26,CX_ENTITY,$B26,$CP$11,$CP$14,$CP$19,),"")))))),"")} | DB26: {=IFERROR(IF(CQ26*fxVal_normal=_PL!CQ26,"",IF(OR($CQ26="",$CQ26=0,NOT(ISNUMBER($CQ26)),ISERROR($CQ26),$B26=""),"",IF($I26=1,IFBLANK(_xldudf_CX_PUSH($CQ26*fxVal_normal,CX_ENTITY,$B26,$CQ$11,$CQ$14,$CQ$19,),""),IF($I26=2,IFBLANK(_xldudf_CX_PUSH($CQ26,CX_ENTITY,$B26,$CQ$11,$CQ$14,$CQ$19,),""),IF($I26=3,"",IFBLANK(_xldudf_CX_PUSH($CQ26,CX_ENTITY,$B26,$CQ$11,$CQ$14,$CQ$19,),"")))))),"")} | DD26: {=IFERROR(IF(AD26*fxVal_normal=_PL!AD26,"",IF(OR(AD26="",NOT(ISNUMBER(AD26)),ISERROR(AD26),$B26=""),"",IF($I26=1,IFBLANK(_xldudf_CX_PUSH(AD26*fxVal_normal,CX_ENTITY,$B26,AD$11,AD$14,AD$19,),""),IF($I26=2,IFBLANK(_xldudf_CX_PUSH(AD26,CX_ENTITY,$B26,AD$11,AD$14,AD$19,),""),IF($I26=3,"",IFBLANK(_xldudf_CX_PUSH(AD26,CX_ENTITY,$B26,AD$11,AD$14,AD$19,),"")))))),"")} | DE26: {=IFERROR(IF(AE26*fxVal_normal=_PL!AE26,"",IF(OR(AE26="",NOT(ISNUMBER(AE26)),ISERROR(AE26),$B26=""),"",IF($I26=1,IFBLANK(_xldudf_CX_PUSH(AE26*fxVal_normal,CX_ENTITY,$B26,AE$11,AE$14,AE$19,),""),IF($I26=2,IFBLANK(_xldudf_CX_PUSH(AE26,CX_ENTITY,$B26,AE$11,AE$14,AE$19,),""),IF($I26=3,"",IFBLANK(_xldudf_CX_PUSH(AE26,CX_ENTITY,$B26,AE$11,AE$14,AE$19,),"")))))),"")} | DF26: {=IFERROR(IF(AF26*fxVal_normal=_PL!AF26,"",IF(OR(AF26="",NOT(ISNUMBER(AF26)),ISERROR(AF26),$B26=""),"",IF($I26=1,IFBLANK(_xldudf_CX_PUSH(AF26*fxVal_normal,CX_ENTITY,$B26,AF$11,AF$14,AF$19,),""),IF($I26=2,IFBLANK(_xldudf_CX_PUSH(AF26,CX_ENTITY,$B26,AF$11,AF$14,AF$19,),""),IF($I26=3,"",IFBLANK(_xldudf_CX_PUSH(AF26,CX_ENTITY,$B26,AF$11,AF$14,AF$19,),"")))))),"")} | DG26: {=IFERROR(IF(AG26*fxVal_normal=_PL!AG26,"",IF(OR(AG26="",NOT(ISNUMBER(AG26)),ISERROR(AG26),$B26=""),"",IF($I26=1,IFBLANK(_xldudf_CX_PUSH(AG26*fxVal_normal,CX_ENTITY,$B26,AG$11,AG$14,AG$19,),""),IF($I26=2,IFBLANK(_xldudf_CX_PUSH(AG26,CX_ENTITY,$B26,AG$11,AG$14,AG$19,),""),IF($I26=3,"",IFBLANK(_xldudf_CX_PUSH(AG26,CX_ENTITY,$B26,AG$11,AG$14,AG$19,),"")))))),"")} | DH26: {=IFERROR(IF(AH26*fxVal_normal=_PL!AH26,"",IF(OR(AH26="",NOT(ISNUMBER(AH26)),ISERROR(AH26),$B26=""),"",IF($I26=1,IFBLANK(_xldudf_CX_PUSH(AH26*fxVal_normal,CX_ENTITY,$B26,AH$11,AH$14,AH$19,),""),IF($I26=2,IFBLANK(_xldudf_CX_PUSH(AH26,CX_ENTITY,$B26,AH$11,AH$14,AH$19,),""),IF($I26=3,"",IFBLANK(_xldudf_CX_PUSH(AH26,CX_ENTITY,$B26,AH$11,AH$14,AH$19,),"")))))),"")} | DI26: {=IFERROR(IF(AI26*fxVal_normal=_PL!AI26,"",IF(OR(AI26="",NOT(ISNUMBER(AI26)),ISERROR(AI26),$B26=""),"",IF($I26=1,IFBLANK(_xldudf_CX_PUSH(AI26*fxVal_normal,CX_ENTITY,$B26,AI$11,AI$14,AI$19,),""),IF($I26=2,IFBLANK(_xldudf_CX_PUSH(AI26,CX_ENTITY,$B26,AI$11,AI$14,AI$19,),""),IF($I26=3,"",IFBLANK(_xldudf_CX_PUSH(AI26,CX_ENTITY,$B26,AI$11,AI$14,AI$19,),"")))))),"")} | DJ26: {=IFERROR(IF(AJ26*fxVal_normal=_PL!AJ26,"",IF(OR(AJ26="",NOT(ISNUMBER(AJ26)),ISERROR(AJ26),$B26=""),"",IF($I26=1,IFBLANK(_xldudf_CX_PUSH(AJ26*fxVal_normal,CX_ENTITY,$B26,AJ$11,AJ$14,AJ$19,),""),IF($I26=2,IFBLANK(_xldudf_CX_PUSH(AJ26,CX_ENTITY,$B26,AJ$11,AJ$14,AJ$19,),""),IF($I26=3,"",IFBLANK(_xldudf_CX_PUSH(AJ26,CX_ENTITY,$B26,AJ$11,AJ$14,AJ$19,),"")))))),"")} | DK26: {=IFERROR(IF(AK26*fxVal_normal=_PL!AK26,"",IF(OR(AK26="",NOT(ISNUMBER(AK26)),ISERROR(AK26),$B26=""),"",IF($I26=1,IFBLANK(_xldudf_CX_PUSH(AK26*fxVal_normal,CX_ENTITY,$B26,AK$11,AK$14,AK$19,),""),IF($I26=2,IFBLANK(_xldudf_CX_PUSH(AK26,CX_ENTITY,$B26,AK$11,AK$14,AK$19,),""),IF($I26=3,"",IFBLANK(_xldudf_CX_PUSH(AK26,CX_ENTITY,$B26,AK$11,AK$14,AK$19,),"")))))),"")} | ... EN26: {=IFERROR(IF(BN26*fxVal_normal=_PL!BN26,"",IF(OR(BN26="",NOT(ISNUMBER(BN26)),ISERROR(BN26),$B26=""),"",IF($I26=1,IFBLANK(_xldudf_CX_PUSH(BN26*fxVal_normal,CX_ENTITY,$B26,BN$11,BN$14,BN$19,),""),IF($I26=2,IFBLANK(_xldudf_CX_PUSH(BN26,CX_ENTITY,$B26,BN$11,BN$14,BN$19,),""),IF($I26=3,"",IFBLANK(_xldudf_CX_PUSH(BN26,CX_ENTITY,$B26,BN$11,BN$14,BN$19,),"")))))),"")}
B27: =_xlfn.LET(_xlpm.IsNotAttrDynamic,D27="",_xlpm.Attr,_PL!F27,_xlpm.NotInUse,Y27=D27,_xlpm.RESULT,IF(_xlpm.IsNotAttrDynamic,_xlpm.Attr,IF(_xlpm.NotInUse,"",Y27)),IF(_xlpm.RESULT="","",_xlpm.RESULT)) -> 2 | C27: {=IFBLANK(_PL!C27,"")} -> EBITDA Adjustment Type I - Label 2 | D27: Please select or type in or leave as blank (2) | E27: {=_xlfn.LAMBDA(_xlpm.Array,_xlop.Type,_xlfn.LET(_xlpm._type,IF(_xlfn.ISOMITTED(_xlpm.Type),0,_xlpm.Type),_xlpm.R,ROWS(_xlpm.Array),_xlpm.C,COLUMNS(_xlpm.Array),_xlpm.Unlocked,_xlfn.MAKEARRAY(_xlpm.R,_xlpm.C,_xlfn.LAMBDA(_xlpm.i,_xlpm.j,--(CELL("protect",INDEX(_xlpm.Array,_xlpm.i,_xlpm.j))=0))),_xlpm.IsUnlocked,_xlfn.MAKEARRAY(_xlpm.R,_xlpm.C,_xlfn.LAMBDA(_xlpm.i,_xlpm.j,CELL("protect",INDEX(_xlpm.Array,_xlpm.i,_xlpm.j))=0)),_xlpm.HasData,_xlpm.Array<>"",_xlpm.Total,SUM(_xlpm.Unlocked),_xlpm.Completed,SUM(--(_xlpm.IsUnlocked*_xlpm.HasData)),_xlpm.type_display,_xlfn.SWITCH(_xlpm._type,1,"R",-1,"O",0,"A",""),_xlfn.HSTACK(_xlpm.Total,_xlpm.Completed,_xlpm.type_display)))($AD27:$CQ27,Z27)} -> #NAME? | H27: 0 | I27: 1 | J27: {=IFBLANK(Z27,"")} -> -1 | K27: =IFERROR(IF(LEN(AB27)=0,"No",IF(LEN(J27)>0,"Yes","No")),"") -> Yes | L27: 2 | W27: =$W$20 -> Actual | X27: =_PL!X27 -> a | Y27: 2 | Z27: {=_xlfn.SWITCH(TRUE,_PL!$L27=TRUE,1,_PL!$L27=FALSE,-1,_PL!$L27=-1,0,"")} -> -1 | AB27: =Y27 -> 2 | AC27: {=_xlfn.LET(_xlpm._termname,$AB27,_xlpm._iconname,"find",_xlpm._icon,fx_getIcon(_xlpm._iconname),_xlpm._location,_xlfn.XLOOKUP(LOWER(_xlpm._termname),LOWER(tbl_acctDef[Term]),tbl_acctDef[Term]),_xlpm._hyperlink,HYPERLINK("#"&CELL("address",_xlpm._location),_xlpm._icon),IFERROR(_xlpm._hyperlink,""))} | AD27: 1 | AE27: 1 | AF27: 1 | AG27: 1 | AH27: 1 | AI27: 1 | AJ27: 1 | AK27: 1 | AL27: 1 | AM27: 1 | AN27: 1 | AO27: 1 | AP27: 1 | AQ27: 1 | AR27: 1 | AS27: 1 | AT27: 1 | AU27: 1 | AV27: 1 | AW27: 1 | AX27: 1 | AY27: 1 | AZ27: 1 | BA27: 1 | BB27: 1 | BC27: 1 | BD27: 1 | BE27: 1 | BF27: 1 | BG27: 1 | BH27: 1 | BI27: 1 | BJ27: 1 | BK27: 1 | BL27: 1 | BM27: 1 | BN27: 1 | CD27: {=_xlfn.LET(_xlpm.CheckBlank,SUM(PL!$AD27:PL!$BN27)=0,IF(_xlpm.CheckBlank,"",SUM(_xlfn._xlws.FILTER(PL!$AD27:$BN27,(YEAR(PL!$AD$12:$BN$12)=PL!CD$12)*(array_timeline<=PL!CD$11)))))} -> #NAME? | CE27: {=_xlfn.LET(_xlpm.CheckBlank,SUM(PL!$AD27:PL!$BN27)=0,IF(_xlpm.CheckBlank,"",SUM(_xlfn._xlws.FILTER(PL!$AD27:$BN27,(YEAR(PL!$AD$12:$BN$12)=PL!CE$12)*(array_timeline<=PL!CE$11)))))} -> #NAME? | CG27: {=IFERROR(_xlfn.LET(_xlpm.CheckBlank,SUM(PL!$AD27:$BN27)=0,IF(_xlpm.CheckBlank,"",SUM(_xlfn._xlws.FILTER(PL!$AD27:$BN27,(YEAR(PL!$AD$12:$BN$12)=PL!CG$12)*(array_timeline<=PL!CG$11))))),"n/a")} -> n/a | CH27: {=_xlfn.LET(_xlpm.CheckBlank,SUM(PL!$AD27:$BN27)=0,IF(_xlpm.CheckBlank,"",SUM(_xlfn._xlws.FILTER(PL!$AD27:$BN27,(YEAR(PL!$AD$12:$BN$12)=PL!CH$12)*(array_timeline<=PL!CH$11)))))} -> #NAME? | CJ27: {=_xlfn.LET(_xlpm.CheckBlank,SUM(PL!$AD27:$BN27)=0,IF(_xlpm.CheckBlank,"",SUM(_xlfn.TAKE(_xlfn.DROP(PL!$AD27:$BN27,,-DATEDIFF(PL!CJ$11,val_asOfDate,"M")),1,-12))))} -> 12 | CK27: {=_xlfn.LET(_xlpm.CheckBlank,SUM(PL!$AD27:$BN27)=0,IF(_xlpm.CheckBlank,"",SUM(_xlfn.TAKE(_xlfn.DROP(PL!$AD27:$BN27,,-DATEDIFF(PL!CK$11,val_asOfDate,"M")),1,-12))))} -> 12 | CM27: 1 | CN27: 1 | CP27: 1 | CQ27: 1 | CT27: {=IF(ISNUMBER(SEARCH("Select",$Y27)),"",_xldudf_CX_PUSH($Y27,CX_ENTITY,C27,val_asOfDate))} -> #NAME? | CU27: {=IF(ISNUMBER(SEARCH("Select",$Y27)),"",_xldudf_CX_PUSH($Y27,CX_ENTITY,C27,EOMONTH(val_asOfDate,1)))} -> #NAME? | CV27: {=IF(ISNUMBER(SEARCH("Select",$Y27)),"",_xldudf_CX_PUSH($Y27,CX_ENTITY,C27,EOMONTH(val_asOfDate,2)))} -> #NAME? | CW27: {=IF(ISNUMBER(SEARCH("Select",$Y27)),"",_xldudf_CX_PUSH($Y27,CX_ENTITY,C27,EOMONTH(val_asOfDate,3)))} -> #NAME? | CY27: {=IFERROR(IF(CM27*fxVal_normal=_PL!CM27,"",IF(OR($CM27="",$CM27=0,NOT(ISNUMBER($CM27)),ISERROR($CM27),$B27=""),"",IF($I27=1,IFBLANK(_xldudf_CX_PUSH($CM27*fxVal_normal,CX_ENTITY,$B27,$CM$11,$CM$14,$CM$19,),""),IF($I27=2,IFBLANK(_xldudf_CX_PUSH($CM27,CX_ENTITY,$B27,$CM$11,$CM$14,$CM$19,),""),IF($I27=3,"",IFBLANK(_xldudf_CX_PUSH($CM27,CX_ENTITY,$B27,$CM$11,$CM$14,$CM$19,),"")))))),"")} | CZ27: {=IFERROR(IF(CN27*fxVal_normal=_PL!CN27,"",IF(OR($CN27="",$CN27=0,NOT(ISNUMBER($CN27)),ISERROR($CN27),$B27=""),"",IF($I27=1,IFBLANK(_xldudf_CX_PUSH($CN27*fxVal_normal,CX_ENTITY,$B27,$CN$11,$CN$14,$CN$19,),""),IF($I27=2,IFBLANK(_xldudf_CX_PUSH($CN27,CX_ENTITY,$B27,$CN$11,$CN$14,$CN$19,),""),IF($I27=3,"",IFBLANK(_xldudf_CX_PUSH($CN27,CX_ENTITY,$B27,$CN$11,$CN$14,$CN$19,),"")))))),"")} | DA27: {=IFERROR(IF(CP27*fxVal_normal=_PL!CP27,"",IF(OR($CP27="",$CP27=0,NOT(ISNUMBER($CP27)),ISERROR($CP27),$B27=""),"",IF($I27=1,IFBLANK(_xldudf_CX_PUSH($CP27*fxVal_normal,CX_ENTITY,$B27,$CP$11,$CP$14,$CP$19,),""),IF($I27=2,IFBLANK(_xldudf_CX_PUSH($CP27,CX_ENTITY,$B27,$CP$11,$CP$14,$CP$19,),""),IF($I27=3,"",IFBLANK(_xldudf_CX_PUSH($CP27,CX_ENTITY,$B27,$CP$11,$CP$14,$CP$19,),"")))))),"")} | DB27: {=IFERROR(IF(CQ27*fxVal_normal=_PL!CQ27,"",IF(OR($CQ27="",$CQ27=0,NOT(ISNUMBER($CQ27)),ISERROR($CQ27),$B27=""),"",IF($I27=1,IFBLANK(_xldudf_CX_PUSH($CQ27*fxVal_normal,CX_ENTITY,$B27,$CQ$11,$CQ$14,$CQ$19,),""),IF($I27=2,IFBLANK(_xldudf_CX_PUSH($CQ27,CX_ENTITY,$B27,$CQ$11,$CQ$14,$CQ$19,),""),IF($I27=3,"",IFBLANK(_xldudf_CX_PUSH($CQ27,CX_ENTITY,$B27,$CQ$11,$CQ$14,$CQ$19,),"")))))),"")} | DD27: {=IFERROR(IF(AD27*fxVal_normal=_PL!AD27,"",IF(OR(AD27="",NOT(ISNUMBER(AD27)),ISERROR(AD27),$B27=""),"",IF($I27=1,IFBLANK(_xldudf_CX_PUSH(AD27*fxVal_normal,CX_ENTITY,$B27,AD$11,AD$14,AD$19,),""),IF($I27=2,IFBLANK(_xldudf_CX_PUSH(AD27,CX_ENTITY,$B27,AD$11,AD$14,AD$19,),""),IF($I27=3,"",IFBLANK(_xldudf_CX_PUSH(AD27,CX_ENTITY,$B27,AD$11,AD$14,AD$19,),"")))))),"")} | DE27: {=IFERROR(IF(AE27*fxVal_normal=_PL!AE27,"",IF(OR(AE27="",NOT(ISNUMBER(AE27)),ISERROR(AE27),$B27=""),"",IF($I27=1,IFBLANK(_xldudf_CX_PUSH(AE27*fxVal_normal,CX_ENTITY,$B27,AE$11,AE$14,AE$19,),""),IF($I27=2,IFBLANK(_xldudf_CX_PUSH(AE27,CX_ENTITY,$B27,AE$11,AE$14,AE$19,),""),IF($I27=3,"",IFBLANK(_xldudf_CX_PUSH(AE27,CX_ENTITY,$B27,AE$11,AE$14,AE$19,),"")))))),"")} | DF27: {=IFERROR(IF(AF27*fxVal_normal=_PL!AF27,"",IF(OR(AF27="",NOT(ISNUMBER(AF27)),ISERROR(AF27),$B27=""),"",IF($I27=1,IFBLANK(_xldudf_CX_PUSH(AF27*fxVal_normal,CX_ENTITY,$B27,AF$11,AF$14,AF$19,),""),IF($I27=2,IFBLANK(_xldudf_CX_PUSH(AF27,CX_ENTITY,$B27,AF$11,AF$14,AF$19,),""),IF($I27=3,"",IFBLANK(_xldudf_CX_PUSH(AF27,CX_ENTITY,$B27,AF$11,AF$14,AF$19,),"")))))),"")} | DG27: {=IFERROR(IF(AG27*fxVal_normal=_PL!AG27,"",IF(OR(AG27="",NOT(ISNUMBER(AG27)),ISERROR(AG27),$B27=""),"",IF($I27=1,IFBLANK(_xldudf_CX_PUSH(AG27*fxVal_normal,CX_ENTITY,$B27,AG$11,AG$14,AG$19,),""),IF($I27=2,IFBLANK(_xldudf_CX_PUSH(AG27,CX_ENTITY,$B27,AG$11,AG$14,AG$19,),""),IF($I27=3,"",IFBLANK(_xldudf_CX_PUSH(AG27,CX_ENTITY,$B27,AG$11,AG$14,AG$19,),"")))))),"")} | DH27: {=IFERROR(IF(AH27*fxVal_normal=_PL!AH27,"",IF(OR(AH27="",NOT(ISNUMBER(AH27)),ISERROR(AH27),$B27=""),"",IF($I27=1,IFBLANK(_xldudf_CX_PUSH(AH27*fxVal_normal,CX_ENTITY,$B27,AH$11,AH$14,AH$19,),""),IF($I27=2,IFBLANK(_xldudf_CX_PUSH(AH27,CX_ENTITY,$B27,AH$11,AH$14,AH$19,),""),IF($I27=3,"",IFBLANK(_xldudf_CX_PUSH(AH27,CX_ENTITY,$B27,AH$11,AH$14,AH$19,),"")))))),"")} | DI27: {=IFERROR(IF(AI27*fxVal_normal=_PL!AI27,"",IF(OR(AI27="",NOT(ISNUMBER(AI27)),ISERROR(AI27),$B27=""),"",IF($I27=1,IFBLANK(_xldudf_CX_PUSH(AI27*fxVal_normal,CX_ENTITY,$B27,AI$11,AI$14,AI$19,),""),IF($I27=2,IFBLANK(_xldudf_CX_PUSH(AI27,CX_ENTITY,$B27,AI$11,AI$14,AI$19,),""),IF($I27=3,"",IFBLANK(_xldudf_CX_PUSH(AI27,CX_ENTITY,$B27,AI$11,AI$14,AI$19,),"")))))),"")} | DJ27: {=IFERROR(IF(AJ27*fxVal_normal=_PL!AJ27,"",IF(OR(AJ27="",NOT(ISNUMBER(AJ27)),ISERROR(AJ27),$B27=""),"",IF($I27=1,IFBLANK(_xldudf_CX_PUSH(AJ27*fxVal_normal,CX_ENTITY,$B27,AJ$11,AJ$14,AJ$19,),""),IF($I27=2,IFBLANK(_xldudf_CX_PUSH(AJ27,CX_ENTITY,$B27,AJ$11,AJ$14,AJ$19,),""),IF($I27=3,"",IFBLANK(_xldudf_CX_PUSH(AJ27,CX_ENTITY,$B27,AJ$11,AJ$14,AJ$19,),"")))))),"")} | DK27: {=IFERROR(IF(AK27*fxVal_normal=_PL!AK27,"",IF(OR(AK27="",NOT(ISNUMBER(AK27)),ISERROR(AK27),$B27=""),"",IF($I27=1,IFBLANK(_xldudf_CX_PUSH(AK27*fxVal_normal,CX_ENTITY,$B27,AK$11,AK$14,AK$19,),""),IF($I27=2,IFBLANK(_xldudf_CX_PUSH(AK27,CX_ENTITY,$B27,AK$11,AK$14,AK$19,),""),IF($I27=3,"",IFBLANK(_xldudf_CX_PUSH(AK27,CX_ENTITY,$B27,AK$11,AK$14,AK$19,),"")))))),"")} | ... EN27: {=IFERROR(IF(BN27*fxVal_normal=_PL!BN27,"",IF(OR(BN27="",NOT(ISNUMBER(BN27)),ISERROR(BN27),$B27=""),"",IF($I27=1,IFBLANK(_xldudf_CX_PUSH(BN27*fxVal_normal,CX_ENTITY,$B27,BN$11,BN$14,BN$19,),""),IF($I27=2,IFBLANK(_xldudf_CX_PUSH(BN27,CX_ENTITY,$B27,BN$11,BN$14,BN$19,),""),IF($I27=3,"",IFBLANK(_xldudf_CX_PUSH(BN27,CX_ENTITY,$B27,BN$11,BN$14,BN$19,),"")))))),"")}
B28: =_xlfn.LET(_xlpm.IsNotAttrDynamic,D28="",_xlpm.Attr,_PL!F28,_xlpm.NotInUse,Y28=D28,_xlpm.RESULT,IF(_xlpm.IsNotAttrDynamic,_xlpm.Attr,IF(_xlpm.NotInUse,"",Y28)),IF(_xlpm.RESULT="","",_xlpm.RESULT)) -> 2 | C28: {=IFBLANK(_PL!C28,"")} -> EBITDA Adjustment Type I - Label 3 | D28: Please select or type in or leave as blank (3) | E28: {=_xlfn.LAMBDA(_xlpm.Array,_xlop.Type,_xlfn.LET(_xlpm._type,IF(_xlfn.ISOMITTED(_xlpm.Type),0,_xlpm.Type),_xlpm.R,ROWS(_xlpm.Array),_xlpm.C,COLUMNS(_xlpm.Array),_xlpm.Unlocked,_xlfn.MAKEARRAY(_xlpm.R,_xlpm.C,_xlfn.LAMBDA(_xlpm.i,_xlpm.j,--(CELL("protect",INDEX(_xlpm.Array,_xlpm.i,_xlpm.j))=0))),_xlpm.IsUnlocked,_xlfn.MAKEARRAY(_xlpm.R,_xlpm.C,_xlfn.LAMBDA(_xlpm.i,_xlpm.j,CELL("protect",INDEX(_xlpm.Array,_xlpm.i,_xlpm.j))=0)),_xlpm.HasData,_xlpm.Array<>"",_xlpm.Total,SUM(_xlpm.Unlocked),_xlpm.Completed,SUM(--(_xlpm.IsUnlocked*_xlpm.HasData)),_xlpm.type_display,_xlfn.SWITCH(_xlpm._type,1,"R",-1,"O",0,"A",""),_xlfn.HSTACK(_xlpm.Total,_xlpm.Completed,_xlpm.type_display)))($AD28:$CQ28,Z28)} -> #NAME? | H28: 0 | I28: 1 | J28: {=IFBLANK(Z28,"")} -> -1 | K28: =IFERROR(IF(LEN(AB28)=0,"No",IF(LEN(J28)>0,"Yes","No")),"") -> Yes | L28: 3 | W28: =$W$20 -> Actual | X28: =_PL!X28 -> a | Y28: 2 | Z28: {=_xlfn.SWITCH(TRUE,_PL!$L28=TRUE,1,_PL!$L28=FALSE,-1,_PL!$L28=-1,0,"")} -> -1 | AB28: =Y28 -> 2 | AC28: {=_xlfn.LET(_xlpm._termname,$AB28,_xlpm._iconname,"find",_xlpm._icon,fx_getIcon(_xlpm._iconname),_xlpm._location,_xlfn.XLOOKUP(LOWER(_xlpm._termname),LOWER(tbl_acctDef[Term]),tbl_acctDef[Term]),_xlpm._hyperlink,HYPERLINK("#"&CELL("address",_xlpm._location),_xlpm._icon),IFERROR(_xlpm._hyperlink,""))} | AD28: 1 | AE28: 1 | AF28: 1 | AG28: 1 | AH28: 1 | AI28: 1 | AJ28: 1 | AK28: 1 | AL28: 1 | AM28: 1 | AN28: 1 | AO28: 1 | AP28: 1 | AQ28: 1 | AR28: 1 | AS28: 1 | AT28: 1 | AU28: 1 | AV28: 1 | AW28: 1 | AX28: 1 | AY28: 1 | AZ28: 1 | BA28: 1 | BB28: 1 | BC28: 1 | BD28: 1 | BE28: 1 | BF28: 1 | BG28: 1 | BH28: 1 | BI28: 1 | BJ28: 1 | BK28: 1 | BL28: 1 | BM28: 1 | BN28: 1 | CD28: {=_xlfn.LET(_xlpm.CheckBlank,SUM(PL!$AD28:PL!$BN28)=0,IF(_xlpm.CheckBlank,"",SUM(_xlfn._xlws.FILTER(PL!$AD28:$BN28,(YEAR(PL!$AD$12:$BN$12)=PL!CD$12)*(array_timeline<=PL!CD$11)))))} -> #NAME? | CE28: {=_xlfn.LET(_xlpm.CheckBlank,SUM(PL!$AD28:PL!$BN28)=0,IF(_xlpm.CheckBlank,"",SUM(_xlfn._xlws.FILTER(PL!$AD28:$BN28,(YEAR(PL!$AD$12:$BN$12)=PL!CE$12)*(array_timeline<=PL!CE$11)))))} -> #NAME? | CG28: {=IFERROR(_xlfn.LET(_xlpm.CheckBlank,SUM(PL!$AD28:$BN28)=0,IF(_xlpm.CheckBlank,"",SUM(_xlfn._xlws.FILTER(PL!$AD28:$BN28,(YEAR(PL!$AD$12:$BN$12)=PL!CG$12)*(array_timeline<=PL!CG$11))))),"n/a")} -> n/a | CH28: {=_xlfn.LET(_xlpm.CheckBlank,SUM(PL!$AD28:$BN28)=0,IF(_xlpm.CheckBlank,"",SUM(_xlfn._xlws.FILTER(PL!$AD28:$BN28,(YEAR(PL!$AD$12:$BN$12)=PL!CH$12)*(array_timeline<=PL!CH$11)))))} -> #NAME? | CJ28: {=_xlfn.LET(_xlpm.CheckBlank,SUM(PL!$AD28:$BN28)=0,IF(_xlpm.CheckBlank,"",SUM(_xlfn.TAKE(_xlfn.DROP(PL!$AD28:$BN28,,-DATEDIFF(PL!CJ$11,val_asOfDate,"M")),1,-12))))} -> 12 | CK28: {=_xlfn.LET(_xlpm.CheckBlank,SUM(PL!$AD28:$BN28)=0,IF(_xlpm.CheckBlank,"",SUM(_xlfn.TAKE(_xlfn.DROP(PL!$AD28:$BN28,,-DATEDIFF(PL!CK$11,val_asOfDate,"M")),1,-12))))} -> 12 | CM28: 1 | CN28: 1 | CP28: 1 | CQ28: 1 | CT28: {=IF(ISNUMBER(SEARCH("Select",$Y28)),"",_xldudf_CX_PUSH($Y28,CX_ENTITY,C28,val_asOfDate))} -> #NAME? | CU28: {=IF(ISNUMBER(SEARCH("Select",$Y28)),"",_xldudf_CX_PUSH($Y28,CX_ENTITY,C28,EOMONTH(val_asOfDate,1)))} -> #NAME? | CV28: {=IF(ISNUMBER(SEARCH("Select",$Y28)),"",_xldudf_CX_PUSH($Y28,CX_ENTITY,C28,EOMONTH(val_asOfDate,2)))} -> #NAME? | CW28: {=IF(ISNUMBER(SEARCH("Select",$Y28)),"",_xldudf_CX_PUSH($Y28,CX_ENTITY,C28,EOMONTH(val_asOfDate,3)))} -> #NAME? | CY28: {=IFERROR(IF(CM28*fxVal_normal=_PL!CM28,"",IF(OR($CM28="",$CM28=0,NOT(ISNUMBER($CM28)),ISERROR($CM28),$B28=""),"",IF($I28=1,IFBLANK(_xldudf_CX_PUSH($CM28*fxVal_normal,CX_ENTITY,$B28,$CM$11,$CM$14,$CM$19,),""),IF($I28=2,IFBLANK(_xldudf_CX_PUSH($CM28,CX_ENTITY,$B28,$CM$11,$CM$14,$CM$19,),""),IF($I28=3,"",IFBLANK(_xldudf_CX_PUSH($CM28,CX_ENTITY,$B28,$CM$11,$CM$14,$CM$19,),"")))))),"")} | CZ28: {=IFERROR(IF(CN28*fxVal_normal=_PL!CN28,"",IF(OR($CN28="",$CN28=0,NOT(ISNUMBER($CN28)),ISERROR($CN28),$B28=""),"",IF($I28=1,IFBLANK(_xldudf_CX_PUSH($CN28*fxVal_normal,CX_ENTITY,$B28,$CN$11,$CN$14,$CN$19,),""),IF($I28=2,IFBLANK(_xldudf_CX_PUSH($CN28,CX_ENTITY,$B28,$CN$11,$CN$14,$CN$19,),""),IF($I28=3,"",IFBLANK(_xldudf_CX_PUSH($CN28,CX_ENTITY,$B28,$CN$11,$CN$14,$CN$19,),"")))))),"")} | DA28: {=IFERROR(IF(CP28*fxVal_normal=_PL!CP28,"",IF(OR($CP28="",$CP28=0,NOT(ISNUMBER($CP28)),ISERROR($CP28),$B28=""),"",IF($I28=1,IFBLANK(_xldudf_CX_PUSH($CP28*fxVal_normal,CX_ENTITY,$B28,$CP$11,$CP$14,$CP$19,),""),IF($I28=2,IFBLANK(_xldudf_CX_PUSH($CP28,CX_ENTITY,$B28,$CP$11,$CP$14,$CP$19,),""),IF($I28=3,"",IFBLANK(_xldudf_CX_PUSH($CP28,CX_ENTITY,$B28,$CP$11,$CP$14,$CP$19,),"")))))),"")} | DB28: {=IFERROR(IF(CQ28*fxVal_normal=_PL!CQ28,"",IF(OR($CQ28="",$CQ28=0,NOT(ISNUMBER($CQ28)),ISERROR($CQ28),$B28=""),"",IF($I28=1,IFBLANK(_xldudf_CX_PUSH($CQ28*fxVal_normal,CX_ENTITY,$B28,$CQ$11,$CQ$14,$CQ$19,),""),IF($I28=2,IFBLANK(_xldudf_CX_PUSH($CQ28,CX_ENTITY,$B28,$CQ$11,$CQ$14,$CQ$19,),""),IF($I28=3,"",IFBLANK(_xldudf_CX_PUSH($CQ28,CX_ENTITY,$B28,$CQ$11,$CQ$14,$CQ$19,),"")))))),"")} | DD28: {=IFERROR(IF(AD28*fxVal_normal=_PL!AD28,"",IF(OR(AD28="",NOT(ISNUMBER(AD28)),ISERROR(AD28),$B28=""),"",IF($I28=1,IFBLANK(_xldudf_CX_PUSH(AD28*fxVal_normal,CX_ENTITY,$B28,AD$11,AD$14,AD$19,),""),IF($I28=2,IFBLANK(_xldudf_CX_PUSH(AD28,CX_ENTITY,$B28,AD$11,AD$14,AD$19,),""),IF($I28=3,"",IFBLANK(_xldudf_CX_PUSH(AD28,CX_ENTITY,$B28,AD$11,AD$14,AD$19,),"")))))),"")} | DE28: {=IFERROR(IF(AE28*fxVal_normal=_PL!AE28,"",IF(OR(AE28="",NOT(ISNUMBER(AE28)),ISERROR(AE28),$B28=""),"",IF($I28=1,IFBLANK(_xldudf_CX_PUSH(AE28*fxVal_normal,CX_ENTITY,$B28,AE$11,AE$14,AE$19,),""),IF($I28=2,IFBLANK(_xldudf_CX_PUSH(AE28,CX_ENTITY,$B28,AE$11,AE$14,AE$19,),""),IF($I28=3,"",IFBLANK(_xldudf_CX_PUSH(AE28,CX_ENTITY,$B28,AE$11,AE$14,AE$19,),"")))))),"")} | DF28: {=IFERROR(IF(AF28*fxVal_normal=_PL!AF28,"",IF(OR(AF28="",NOT(ISNUMBER(AF28)),ISERROR(AF28),$B28=""),"",IF($I28=1,IFBLANK(_xldudf_CX_PUSH(AF28*fxVal_normal,CX_ENTITY,$B28,AF$11,AF$14,AF$19,),""),IF($I28=2,IFBLANK(_xldudf_CX_PUSH(AF28,CX_ENTITY,$B28,AF$11,AF$14,AF$19,),""),IF($I28=3,"",IFBLANK(_xldudf_CX_PUSH(AF28,CX_ENTITY,$B28,AF$11,AF$14,AF$19,),"")))))),"")} | DG28: {=IFERROR(IF(AG28*fxVal_normal=_PL!AG28,"",IF(OR(AG28="",NOT(ISNUMBER(AG28)),ISERROR(AG28),$B28=""),"",IF($I28=1,IFBLANK(_xldudf_CX_PUSH(AG28*fxVal_normal,CX_ENTITY,$B28,AG$11,AG$14,AG$19,),""),IF($I28=2,IFBLANK(_xldudf_CX_PUSH(AG28,CX_ENTITY,$B28,AG$11,AG$14,AG$19,),""),IF($I28=3,"",IFBLANK(_xldudf_CX_PUSH(AG28,CX_ENTITY,$B28,AG$11,AG$14,AG$19,),"")))))),"")} | DH28: {=IFERROR(IF(AH28*fxVal_normal=_PL!AH28,"",IF(OR(AH28="",NOT(ISNUMBER(AH28)),ISERROR(AH28),$B28=""),"",IF($I28=1,IFBLANK(_xldudf_CX_PUSH(AH28*fxVal_normal,CX_ENTITY,$B28,AH$11,AH$14,AH$19,),""),IF($I28=2,IFBLANK(_xldudf_CX_PUSH(AH28,CX_ENTITY,$B28,AH$11,AH$14,AH$19,),""),IF($I28=3,"",IFBLANK(_xldudf_CX_PUSH(AH28,CX_ENTITY,$B28,AH$11,AH$14,AH$19,),"")))))),"")} | DI28: {=IFERROR(IF(AI28*fxVal_normal=_PL!AI28,"",IF(OR(AI28="",NOT(ISNUMBER(AI28)),ISERROR(AI28),$B28=""),"",IF($I28=1,IFBLANK(_xldudf_CX_PUSH(AI28*fxVal_normal,CX_ENTITY,$B28,AI$11,AI$14,AI$19,),""),IF($I28=2,IFBLANK(_xldudf_CX_PUSH(AI28,CX_ENTITY,$B28,AI$11,AI$14,AI$19,),""),IF($I28=3,"",IFBLANK(_xldudf_CX_PUSH(AI28,CX_ENTITY,$B28,AI$11,AI$14,AI$19,),"")))))),"")} | DJ28: {=IFERROR(IF(AJ28*fxVal_normal=_PL!AJ28,"",IF(OR(AJ28="",NOT(ISNUMBER(AJ28)),ISERROR(AJ28),$B28=""),"",IF($I28=1,IFBLANK(_xldudf_CX_PUSH(AJ28*fxVal_normal,CX_ENTITY,$B28,AJ$11,AJ$14,AJ$19,),""),IF($I28=2,IFBLANK(_xldudf_CX_PUSH(AJ28,CX_ENTITY,$B28,AJ$11,AJ$14,AJ$19,),""),IF($I28=3,"",IFBLANK(_xldudf_CX_PUSH(AJ28,CX_ENTITY,$B28,AJ$11,AJ$14,AJ$19,),"")))))),"")} | DK28: {=IFERROR(IF(AK28*fxVal_normal=_PL!AK28,"",IF(OR(AK28="",NOT(ISNUMBER(AK28)),ISERROR(AK28),$B28=""),"",IF($I28=1,IFBLANK(_xldudf_CX_PUSH(AK28*fxVal_normal,CX_ENTITY,$B28,AK$11,AK$14,AK$19,),""),IF($I28=2,IFBLANK(_xldudf_CX_PUSH(AK28,CX_ENTITY,$B28,AK$11,AK$14,AK$19,),""),IF($I28=3,"",IFBLANK(_xldudf_CX_PUSH(AK28,CX_ENTITY,$B28,AK$11,AK$14,AK$19,),"")))))),"")} | ... EN28: {=IFERROR(IF(BN28*fxVal_normal=_PL!BN28,"",IF(OR(BN28="",NOT(ISNUMBER(BN28)),ISERROR(BN28),$B28=""),"",IF($I28=1,IFBLANK(_xldudf_CX_PUSH(BN28*fxVal_normal,CX_ENTITY,$B28,BN$11,BN$14,BN$19,),""),IF($I28=2,IFBLANK(_xldudf_CX_PUSH(BN28,CX_ENTITY,$B28,BN$11,BN$14,BN$19,),""),IF($I28=3,"",IFBLANK(_xldudf_CX_PUSH(BN28,CX_ENTITY,$B28,BN$11,BN$14,BN$19,),"")))))),"")}
B29: =_xlfn.LET(_xlpm.IsNotAttrDynamic,D29="",_xlpm.Attr,_PL!F29,_xlpm.NotInUse,Y29=D29,_xlpm.RESULT,IF(_xlpm.IsNotAttrDynamic,_xlpm.Attr,IF(_xlpm.NotInUse,"",Y29)),IF(_xlpm.RESULT="","",_xlpm.RESULT)) -> 2 | C29: {=IFBLANK(_PL!C29,"")} -> EBITDA Adjustment Type I - Label 4 | D29: Please select or type in or leave as blank (4) | E29: {=_xlfn.LAMBDA(_xlpm.Array,_xlop.Type,_xlfn.LET(_xlpm._type,IF(_xlfn.ISOMITTED(_xlpm.Type),0,_xlpm.Type),_xlpm.R,ROWS(_xlpm.Array),_xlpm.C,COLUMNS(_xlpm.Array),_xlpm.Unlocked,_xlfn.MAKEARRAY(_xlpm.R,_xlpm.C,_xlfn.LAMBDA(_xlpm.i,_xlpm.j,--(CELL("protect",INDEX(_xlpm.Array,_xlpm.i,_xlpm.j))=0))),_xlpm.IsUnlocked,_xlfn.MAKEARRAY(_xlpm.R,_xlpm.C,_xlfn.LAMBDA(_xlpm.i,_xlpm.j,CELL("protect",INDEX(_xlpm.Array,_xlpm.i,_xlpm.j))=0)),_xlpm.HasData,_xlpm.Array<>"",_xlpm.Total,SUM(_xlpm.Unlocked),_xlpm.Completed,SUM(--(_xlpm.IsUnlocked*_xlpm.HasData)),_xlpm.type_display,_xlfn.SWITCH(_xlpm._type,1,"R",-1,"O",0,"A",""),_xlfn.HSTACK(_xlpm.Total,_xlpm.Completed,_xlpm.type_display)))($AD29:$CQ29,Z29)} -> #NAME? | H29: 0 | I29: 1 | J29: {=IFBLANK(Z29,"")} -> -1 | K29: =IFERROR(IF(LEN(AB29)=0,"No",IF(LEN(J29)>0,"Yes","No")),"") -> Yes | L29: 4 | W29: =$W$20 -> Actual | X29: =_PL!X29 -> a | Y29: 2 | Z29: {=_xlfn.SWITCH(TRUE,_PL!$L29=TRUE,1,_PL!$L29=FALSE,-1,_PL!$L29=-1,0,"")} -> -1 | AB29: =Y29 -> 2 | AC29: {=_xlfn.LET(_xlpm._termname,$AB29,_xlpm._iconname,"find",_xlpm._icon,fx_getIcon(_xlpm._iconname),_xlpm._location,_xlfn.XLOOKUP(LOWER(_xlpm._termname),LOWER(tbl_acctDef[Term]),tbl_acctDef[Term]),_xlpm._hyperlink,HYPERLINK("#"&CELL("address",_xlpm._location),_xlpm._icon),IFERROR(_xlpm._hyperlink,""))} | AD29: 1 | AE29: 1 | AF29: 1 | AG29: 1 | AH29: 1 | AI29: 1 | AJ29: 1 | AK29: 1 | AL29: 1 | AM29: 1 | AN29: 1 | AO29: 1 | AP29: 1 | AQ29: 1 | AR29: 1 | AS29: 1 | AT29: 1 | AU29: 1 | AV29: 1 | AW29: 1 | AX29: 1 | AY29: 1 | AZ29: 1 | BA29: 1 | BB29: 1 | BC29: 1 | BD29: 1 | BE29: 1 | BF29: 1 | BG29: 1 | BH29: 1 | BI29: 1 | BJ29: 1 | BK29: 1 | BL29: 1 | BM29: 1 | BN29: 1 | CD29: {=_xlfn.LET(_xlpm.CheckBlank,SUM(PL!$AD29:PL!$BN29)=0,IF(_xlpm.CheckBlank,"",SUM(_xlfn._xlws.FILTER(PL!$AD29:$BN29,(YEAR(PL!$AD$12:$BN$12)=PL!CD$12)*(array_timeline<=PL!CD$11)))))} -> #NAME? | CE29: {=_xlfn.LET(_xlpm.CheckBlank,SUM(PL!$AD29:PL!$BN29)=0,IF(_xlpm.CheckBlank,"",SUM(_xlfn._xlws.FILTER(PL!$AD29:$BN29,(YEAR(PL!$AD$12:$BN$12)=PL!CE$12)*(array_timeline<=PL!CE$11)))))} -> #NAME? | CG29: {=IFERROR(_xlfn.LET(_xlpm.CheckBlank,SUM(PL!$AD29:$BN29)=0,IF(_xlpm.CheckBlank,"",SUM(_xlfn._xlws.FILTER(PL!$AD29:$BN29,(YEAR(PL!$AD$12:$BN$12)=PL!CG$12)*(array_timeline<=PL!CG$11))))),"n/a")} -> n/a | CH29: {=_xlfn.LET(_xlpm.CheckBlank,SUM(PL!$AD29:$BN29)=0,IF(_xlpm.CheckBlank,"",SUM(_xlfn._xlws.FILTER(PL!$AD29:$BN29,(YEAR(PL!$AD$12:$BN$12)=PL!CH$12)*(array_timeline<=PL!CH$11)))))} -> #NAME? | CJ29: {=_xlfn.LET(_xlpm.CheckBlank,SUM(PL!$AD29:$BN29)=0,IF(_xlpm.CheckBlank,"",SUM(_xlfn.TAKE(_xlfn.DROP(PL!$AD29:$BN29,,-DATEDIFF(PL!CJ$11,val_asOfDate,"M")),1,-12))))} -> 12 | CK29: {=_xlfn.LET(_xlpm.CheckBlank,SUM(PL!$AD29:$BN29)=0,IF(_xlpm.CheckBlank,"",SUM(_xlfn.TAKE(_xlfn.DROP(PL!$AD29:$BN29,,-DATEDIFF(PL!CK$11,val_asOfDate,"M")),1,-12))))} -> 12 | CM29: 1 | CN29: 1 | CP29: 1 | CQ29: 1 | CT29: {=IF(ISNUMBER(SEARCH("Select",$Y29)),"",_xldudf_CX_PUSH($Y29,CX_ENTITY,C29,val_asOfDate))} -> #NAME? | CU29: {=IF(ISNUMBER(SEARCH("Select",$Y29)),"",_xldudf_CX_PUSH($Y29,CX_ENTITY,C29,EOMONTH(val_asOfDate,1)))} -> #NAME? | CV29: {=IF(ISNUMBER(SEARCH("Select",$Y29)),"",_xldudf_CX_PUSH($Y29,CX_ENTITY,C29,EOMONTH(val_asOfDate,2)))} -> #NAME? | CW29: {=IF(ISNUMBER(SEARCH("Select",$Y29)),"",_xldudf_CX_PUSH($Y29,CX_ENTITY,C29,EOMONTH(val_asOfDate,3)))} -> #NAME? | CY29: {=IFERROR(IF(CM29*fxVal_normal=_PL!CM29,"",IF(OR($CM29="",$CM29=0,NOT(ISNUMBER($CM29)),ISERROR($CM29),$B29=""),"",IF($I29=1,IFBLANK(_xldudf_CX_PUSH($CM29*fxVal_normal,CX_ENTITY,$B29,$CM$11,$CM$14,$CM$19,),""),IF($I29=2,IFBLANK(_xldudf_CX_PUSH($CM29,CX_ENTITY,$B29,$CM$11,$CM$14,$CM$19,),""),IF($I29=3,"",IFBLANK(_xldudf_CX_PUSH($CM29,CX_ENTITY,$B29,$CM$11,$CM$14,$CM$19,),"")))))),"")} | CZ29: {=IFERROR(IF(CN29*fxVal_normal=_PL!CN29,"",IF(OR($CN29="",$CN29=0,NOT(ISNUMBER($CN29)),ISERROR($CN29),$B29=""),"",IF($I29=1,IFBLANK(_xldudf_CX_PUSH($CN29*fxVal_normal,CX_ENTITY,$B29,$CN$11,$CN$14,$CN$19,),""),IF($I29=2,IFBLANK(_xldudf_CX_PUSH($CN29,CX_ENTITY,$B29,$CN$11,$CN$14,$CN$19,),""),IF($I29=3,"",IFBLANK(_xldudf_CX_PUSH($CN29,CX_ENTITY,$B29,$CN$11,$CN$14,$CN$19,),"")))))),"")} | DA29: {=IFERROR(IF(CP29*fxVal_normal=_PL!CP29,"",IF(OR($CP29="",$CP29=0,NOT(ISNUMBER($CP29)),ISERROR($CP29),$B29=""),"",IF($I29=1,IFBLANK(_xldudf_CX_PUSH($CP29*fxVal_normal,CX_ENTITY,$B29,$CP$11,$CP$14,$CP$19,),""),IF($I29=2,IFBLANK(_xldudf_CX_PUSH($CP29,CX_ENTITY,$B29,$CP$11,$CP$14,$CP$19,),""),IF($I29=3,"",IFBLANK(_xldudf_CX_PUSH($CP29,CX_ENTITY,$B29,$CP$11,$CP$14,$CP$19,),"")))))),"")} | DB29: {=IFERROR(IF(CQ29*fxVal_normal=_PL!CQ29,"",IF(OR($CQ29="",$CQ29=0,NOT(ISNUMBER($CQ29)),ISERROR($CQ29),$B29=""),"",IF($I29=1,IFBLANK(_xldudf_CX_PUSH($CQ29*fxVal_normal,CX_ENTITY,$B29,$CQ$11,$CQ$14,$CQ$19,),""),IF($I29=2,IFBLANK(_xldudf_CX_PUSH($CQ29,CX_ENTITY,$B29,$CQ$11,$CQ$14,$CQ$19,),""),IF($I29=3,"",IFBLANK(_xldudf_CX_PUSH($CQ29,CX_ENTITY,$B29,$CQ$11,$CQ$14,$CQ$19,),"")))))),"")} | DD29: {=IFERROR(IF(AD29*fxVal_normal=_PL!AD29,"",IF(OR(AD29="",NOT(ISNUMBER(AD29)),ISERROR(AD29),$B29=""),"",IF($I29=1,IFBLANK(_xldudf_CX_PUSH(AD29*fxVal_normal,CX_ENTITY,$B29,AD$11,AD$14,AD$19,),""),IF($I29=2,IFBLANK(_xldudf_CX_PUSH(AD29,CX_ENTITY,$B29,AD$11,AD$14,AD$19,),""),IF($I29=3,"",IFBLANK(_xldudf_CX_PUSH(AD29,CX_ENTITY,$B29,AD$11,AD$14,AD$19,),"")))))),"")} | DE29: {=IFERROR(IF(AE29*fxVal_normal=_PL!AE29,"",IF(OR(AE29="",NOT(ISNUMBER(AE29)),ISERROR(AE29),$B29=""),"",IF($I29=1,IFBLANK(_xldudf_CX_PUSH(AE29*fxVal_normal,CX_ENTITY,$B29,AE$11,AE$14,AE$19,),""),IF($I29=2,IFBLANK(_xldudf_CX_PUSH(AE29,CX_ENTITY,$B29,AE$11,AE$14,AE$19,),""),IF($I29=3,"",IFBLANK(_xldudf_CX_PUSH(AE29,CX_ENTITY,$B29,AE$11,AE$14,AE$19,),"")))))),"")} | DF29: {=IFERROR(IF(AF29*fxVal_normal=_PL!AF29,"",IF(OR(AF29="",NOT(ISNUMBER(AF29)),ISERROR(AF29),$B29=""),"",IF($I29=1,IFBLANK(_xldudf_CX_PUSH(AF29*fxVal_normal,CX_ENTITY,$B29,AF$11,AF$14,AF$19,),""),IF($I29=2,IFBLANK(_xldudf_CX_PUSH(AF29,CX_ENTITY,$B29,AF$11,AF$14,AF$19,),""),IF($I29=3,"",IFBLANK(_xldudf_CX_PUSH(AF29,CX_ENTITY,$B29,AF$11,AF$14,AF$19,),"")))))),"")} | DG29: {=IFERROR(IF(AG29*fxVal_normal=_PL!AG29,"",IF(OR(AG29="",NOT(ISNUMBER(AG29)),ISERROR(AG29),$B29=""),"",IF($I29=1,IFBLANK(_xldudf_CX_PUSH(AG29*fxVal_normal,CX_ENTITY,$B29,AG$11,AG$14,AG$19,),""),IF($I29=2,IFBLANK(_xldudf_CX_PUSH(AG29,CX_ENTITY,$B29,AG$11,AG$14,AG$19,),""),IF($I29=3,"",IFBLANK(_xldudf_CX_PUSH(AG29,CX_ENTITY,$B29,AG$11,AG$14,AG$19,),"")))))),"")} | DH29: {=IFERROR(IF(AH29*fxVal_normal=_PL!AH29,"",IF(OR(AH29="",NOT(ISNUMBER(AH29)),ISERROR(AH29),$B29=""),"",IF($I29=1,IFBLANK(_xldudf_CX_PUSH(AH29*fxVal_normal,CX_ENTITY,$B29,AH$11,AH$14,AH$19,),""),IF($I29=2,IFBLANK(_xldudf_CX_PUSH(AH29,CX_ENTITY,$B29,AH$11,AH$14,AH$19,),""),IF($I29=3,"",IFBLANK(_xldudf_CX_PUSH(AH29,CX_ENTITY,$B29,AH$11,AH$14,AH$19,),"")))))),"")} | DI29: {=IFERROR(IF(AI29*fxVal_normal=_PL!AI29,"",IF(OR(AI29="",NOT(ISNUMBER(AI29)),ISERROR(AI29),$B29=""),"",IF($I29=1,IFBLANK(_xldudf_CX_PUSH(AI29*fxVal_normal,CX_ENTITY,$B29,AI$11,AI$14,AI$19,),""),IF($I29=2,IFBLANK(_xldudf_CX_PUSH(AI29,CX_ENTITY,$B29,AI$11,AI$14,AI$19,),""),IF($I29=3,"",IFBLANK(_xldudf_CX_PUSH(AI29,CX_ENTITY,$B29,AI$11,AI$14,AI$19,),"")))))),"")} | DJ29: {=IFERROR(IF(AJ29*fxVal_normal=_PL!AJ29,"",IF(OR(AJ29="",NOT(ISNUMBER(AJ29)),ISERROR(AJ29),$B29=""),"",IF($I29=1,IFBLANK(_xldudf_CX_PUSH(AJ29*fxVal_normal,CX_ENTITY,$B29,AJ$11,AJ$14,AJ$19,),""),IF($I29=2,IFBLANK(_xldudf_CX_PUSH(AJ29,CX_ENTITY,$B29,AJ$11,AJ$14,AJ$19,),""),IF($I29=3,"",IFBLANK(_xldudf_CX_PUSH(AJ29,CX_ENTITY,$B29,AJ$11,AJ$14,AJ$19,),"")))))),"")} | DK29: {=IFERROR(IF(AK29*fxVal_normal=_PL!AK29,"",IF(OR(AK29="",NOT(ISNUMBER(AK29)),ISERROR(AK29),$B29=""),"",IF($I29=1,IFBLANK(_xldudf_CX_PUSH(AK29*fxVal_normal,CX_ENTITY,$B29,AK$11,AK$14,AK$19,),""),IF($I29=2,IFBLANK(_xldudf_CX_PUSH(AK29,CX_ENTITY,$B29,AK$11,AK$14,AK$19,),""),IF($I29=3,"",IFBLANK(_xldudf_CX_PUSH(AK29,CX_ENTITY,$B29,AK$11,AK$14,AK$19,),"")))))),"")} | ... EN29: {=IFERROR(IF(BN29*fxVal_normal=_PL!BN29,"",IF(OR(BN29="",NOT(ISNUMBER(BN29)),ISERROR(BN29),$B29=""),"",IF($I29=1,IFBLANK(_xldudf_CX_PUSH(BN29*fxVal_normal,CX_ENTITY,$B29,BN$11,BN$14,BN$19,),""),IF($I29=2,IFBLANK(_xldudf_CX_PUSH(BN29,CX_ENTITY,$B29,BN$11,BN$14,BN$19,),""),IF($I29=3,"",IFBLANK(_xldudf_CX_PUSH(BN29,CX_ENTITY,$B29,BN$11,BN$14,BN$19,),"")))))),"")}
B30: =_xlfn.LET(_xlpm.IsNotAttrDynamic,D30="",_xlpm.Attr,_PL!F30,_xlpm.NotInUse,Y30=D30,_xlpm.RESULT,IF(_xlpm.IsNotAttrDynamic,_xlpm.Attr,IF(_xlpm.NotInUse,"",Y30)),IF(_xlpm.RESULT="","",_xlpm.RESULT)) -> 2 | C30: {=IFBLANK(_PL!C30,"")} -> EBITDA Adjustment Type I - Label 5 | D30: Please select or type in or leave as blank (5) | E30: {=_xlfn.LAMBDA(_xlpm.Array,_xlop.Type,_xlfn.LET(_xlpm._type,IF(_xlfn.ISOMITTED(_xlpm.Type),0,_xlpm.Type),_xlpm.R,ROWS(_xlpm.Array),_xlpm.C,COLUMNS(_xlpm.Array),_xlpm.Unlocked,_xlfn.MAKEARRAY(_xlpm.R,_xlpm.C,_xlfn.LAMBDA(_xlpm.i,_xlpm.j,--(CELL("protect",INDEX(_xlpm.Array,_xlpm.i,_xlpm.j))=0))),_xlpm.IsUnlocked,_xlfn.MAKEARRAY(_xlpm.R,_xlpm.C,_xlfn.LAMBDA(_xlpm.i,_xlpm.j,CELL("protect",INDEX(_xlpm.Array,_xlpm.i,_xlpm.j))=0)),_xlpm.HasData,_xlpm.Array<>"",_xlpm.Total,SUM(_xlpm.Unlocked),_xlpm.Completed,SUM(--(_xlpm.IsUnlocked*_xlpm.HasData)),_xlpm.type_display,_xlfn.SWITCH(_xlpm._type,1,"R",-1,"O",0,"A",""),_xlfn.HSTACK(_xlpm.Total,_xlpm.Completed,_xlpm.type_display)))($AD30:$CQ30,Z30)} -> #NAME? | H30: 0 | I30: 1 | J30: {=IFBLANK(Z30,"")} -> -1 | K30: =IFERROR(IF(LEN(AB30)=0,"No",IF(LEN(J30)>0,"Yes","No")),"") -> Yes | L30: 5 | W30: =$W$20 -> Actual | X30: =_PL!X30 -> a | Y30: 2 | Z30: {=_xlfn.SWITCH(TRUE,_PL!$L30=TRUE,1,_PL!$L30=FALSE,-1,_PL!$L30=-1,0,"")} -> -1 | AB30: =Y30 -> 2 | AC30: {=_xlfn.LET(_xlpm._termname,$AB30,_xlpm._iconname,"find",_xlpm._icon,fx_getIcon(_xlpm._iconname),_xlpm._location,_xlfn.XLOOKUP(LOWER(_xlpm._termname),LOWER(tbl_acctDef[Term]),tbl_acctDef[Term]),_xlpm._hyperlink,HYPERLINK("#"&CELL("address",_xlpm._location),_xlpm._icon),IFERROR(_xlpm._hyperlink,""))} | AD30: 1 | AE30: 1 | AF30: 1 | AG30: 1 | AH30: 1 | AI30: 1 | AJ30: 1 | AK30: 1 | AL30: 1 | AM30: 1 | AN30: 1 | AO30: 1 | AP30: 1 | AQ30: 1 | AR30: 1 | AS30: 1 | AT30: 1 | AU30: 1 | AV30: 1 | AW30: 1 | AX30: 1 | AY30: 1 | AZ30: 1 | BA30: 1 | BB30: 1 | BC30: 1 | BD30: 1 | BE30: 1 | BF30: 1 | BG30: 1 | BH30: 1 | BI30: 1 | BJ30: 1 | BK30: 1 | BL30: 1 | BM30: 1 | BN30: 1 | CD30: {=_xlfn.LET(_xlpm.CheckBlank,SUM(PL!$AD30:PL!$BN30)=0,IF(_xlpm.CheckBlank,"",SUM(_xlfn._xlws.FILTER(PL!$AD30:$BN30,(YEAR(PL!$AD$12:$BN$12)=PL!CD$12)*(array_timeline<=PL!CD$11)))))} -> #NAME? | CE30: {=_xlfn.LET(_xlpm.CheckBlank,SUM(PL!$AD30:PL!$BN30)=0,IF(_xlpm.CheckBlank,"",SUM(_xlfn._xlws.FILTER(PL!$AD30:$BN30,(YEAR(PL!$AD$12:$BN$12)=PL!CE$12)*(array_timeline<=PL!CE$11)))))} -> #NAME? | CG30: {=IFERROR(_xlfn.LET(_xlpm.CheckBlank,SUM(PL!$AD30:$BN30)=0,IF(_xlpm.CheckBlank,"",SUM(_xlfn._xlws.FILTER(PL!$AD30:$BN30,(YEAR(PL!$AD$12:$BN$12)=PL!CG$12)*(array_timeline<=PL!CG$11))))),"n/a")} -> n/a | CH30: {=_xlfn.LET(_xlpm.CheckBlank,SUM(PL!$AD30:$BN30)=0,IF(_xlpm.CheckBlank,"",SUM(_xlfn._xlws.FILTER(PL!$AD30:$BN30,(YEAR(PL!$AD$12:$BN$12)=PL!CH$12)*(array_timeline<=PL!CH$11)))))} -> #NAME? | CJ30: {=_xlfn.LET(_xlpm.CheckBlank,SUM(PL!$AD30:$BN30)=0,IF(_xlpm.CheckBlank,"",SUM(_xlfn.TAKE(_xlfn.DROP(PL!$AD30:$BN30,,-DATEDIFF(PL!CJ$11,val_asOfDate,"M")),1,-12))))} -> 12 | CK30: {=_xlfn.LET(_xlpm.CheckBlank,SUM(PL!$AD30:$BN30)=0,IF(_xlpm.CheckBlank,"",SUM(_xlfn.TAKE(_xlfn.DROP(PL!$AD30:$BN30,,-DATEDIFF(PL!CK$11,val_asOfDate,"M")),1,-12))))} -> 12 | CM30: 1 | CN30: 1 | CP30: 1 | CQ30: 1 | CT30: {=IF(ISNUMBER(SEARCH("Select",$Y30)),"",_xldudf_CX_PUSH($Y30,CX_ENTITY,C30,val_asOfDate))} -> #NAME? | CU30: {=IF(ISNUMBER(SEARCH("Select",$Y30)),"",_xldudf_CX_PUSH($Y30,CX_ENTITY,C30,EOMONTH(val_asOfDate,1)))} -> #NAME? | CV30: {=IF(ISNUMBER(SEARCH("Select",$Y30)),"",_xldudf_CX_PUSH($Y30,CX_ENTITY,C30,EOMONTH(val_asOfDate,2)))} -> #NAME? | CW30: {=IF(ISNUMBER(SEARCH("Select",$Y30)),"",_xldudf_CX_PUSH($Y30,CX_ENTITY,C30,EOMONTH(val_asOfDate,3)))} -> #NAME? | CY30: {=IFERROR(IF(CM30*fxVal_normal=_PL!CM30,"",IF(OR($CM30="",$CM30=0,NOT(ISNUMBER($CM30)),ISERROR($CM30),$B30=""),"",IF($I30=1,IFBLANK(_xldudf_CX_PUSH($CM30*fxVal_normal,CX_ENTITY,$B30,$CM$11,$CM$14,$CM$19,),""),IF($I30=2,IFBLANK(_xldudf_CX_PUSH($CM30,CX_ENTITY,$B30,$CM$11,$CM$14,$CM$19,),""),IF($I30=3,"",IFBLANK(_xldudf_CX_PUSH($CM30,CX_ENTITY,$B30,$CM$11,$CM$14,$CM$19,),"")))))),"")} | CZ30: {=IFERROR(IF(CN30*fxVal_normal=_PL!CN30,"",IF(OR($CN30="",$CN30=0,NOT(ISNUMBER($CN30)),ISERROR($CN30),$B30=""),"",IF($I30=1,IFBLANK(_xldudf_CX_PUSH($CN30*fxVal_normal,CX_ENTITY,$B30,$CN$11,$CN$14,$CN$19,),""),IF($I30=2,IFBLANK(_xldudf_CX_PUSH($CN30,CX_ENTITY,$B30,$CN$11,$CN$14,$CN$19,),""),IF($I30=3,"",IFBLANK(_xldudf_CX_PUSH($CN30,CX_ENTITY,$B30,$CN$11,$CN$14,$CN$19,),"")))))),"")} | DA30: {=IFERROR(IF(CP30*fxVal_normal=_PL!CP30,"",IF(OR($CP30="",$CP30=0,NOT(ISNUMBER($CP30)),ISERROR($CP30),$B30=""),"",IF($I30=1,IFBLANK(_xldudf_CX_PUSH($CP30*fxVal_normal,CX_ENTITY,$B30,$CP$11,$CP$14,$CP$19,),""),IF($I30=2,IFBLANK(_xldudf_CX_PUSH($CP30,CX_ENTITY,$B30,$CP$11,$CP$14,$CP$19,),""),IF($I30=3,"",IFBLANK(_xldudf_CX_PUSH($CP30,CX_ENTITY,$B30,$CP$11,$CP$14,$CP$19,),"")))))),"")} | DB30: {=IFERROR(IF(CQ30*fxVal_normal=_PL!CQ30,"",IF(OR($CQ30="",$CQ30=0,NOT(ISNUMBER($CQ30)),ISERROR($CQ30),$B30=""),"",IF($I30=1,IFBLANK(_xldudf_CX_PUSH($CQ30*fxVal_normal,CX_ENTITY,$B30,$CQ$11,$CQ$14,$CQ$19,),""),IF($I30=2,IFBLANK(_xldudf_CX_PUSH($CQ30,CX_ENTITY,$B30,$CQ$11,$CQ$14,$CQ$19,),""),IF($I30=3,"",IFBLANK(_xldudf_CX_PUSH($CQ30,CX_ENTITY,$B30,$CQ$11,$CQ$14,$CQ$19,),"")))))),"")} | DD30: {=IFERROR(IF(AD30*fxVal_normal=_PL!AD30,"",IF(OR(AD30="",NOT(ISNUMBER(AD30)),ISERROR(AD30),$B30=""),"",IF($I30=1,IFBLANK(_xldudf_CX_PUSH(AD30*fxVal_normal,CX_ENTITY,$B30,AD$11,AD$14,AD$19,),""),IF($I30=2,IFBLANK(_xldudf_CX_PUSH(AD30,CX_ENTITY,$B30,AD$11,AD$14,AD$19,),""),IF($I30=3,"",IFBLANK(_xldudf_CX_PUSH(AD30,CX_ENTITY,$B30,AD$11,AD$14,AD$19,),"")))))),"")} | DE30: {=IFERROR(IF(AE30*fxVal_normal=_PL!AE30,"",IF(OR(AE30="",NOT(ISNUMBER(AE30)),ISERROR(AE30),$B30=""),"",IF($I30=1,IFBLANK(_xldudf_CX_PUSH(AE30*fxVal_normal,CX_ENTITY,$B30,AE$11,AE$14,AE$19,),""),IF($I30=2,IFBLANK(_xldudf_CX_PUSH(AE30,CX_ENTITY,$B30,AE$11,AE$14,AE$19,),""),IF($I30=3,"",IFBLANK(_xldudf_CX_PUSH(AE30,CX_ENTITY,$B30,AE$11,AE$14,AE$19,),"")))))),"")} | DF30: {=IFERROR(IF(AF30*fxVal_normal=_PL!AF30,"",IF(OR(AF30="",NOT(ISNUMBER(AF30)),ISERROR(AF30),$B30=""),"",IF($I30=1,IFBLANK(_xldudf_CX_PUSH(AF30*fxVal_normal,CX_ENTITY,$B30,AF$11,AF$14,AF$19,),""),IF($I30=2,IFBLANK(_xldudf_CX_PUSH(AF30,CX_ENTITY,$B30,AF$11,AF$14,AF$19,),""),IF($I30=3,"",IFBLANK(_xldudf_CX_PUSH(AF30,CX_ENTITY,$B30,AF$11,AF$14,AF$19,),"")))))),"")} | DG30: {=IFERROR(IF(AG30*fxVal_normal=_PL!AG30,"",IF(OR(AG30="",NOT(ISNUMBER(AG30)),ISERROR(AG30),$B30=""),"",IF($I30=1,IFBLANK(_xldudf_CX_PUSH(AG30*fxVal_normal,CX_ENTITY,$B30,AG$11,AG$14,AG$19,),""),IF($I30=2,IFBLANK(_xldudf_CX_PUSH(AG30,CX_ENTITY,$B30,AG$11,AG$14,AG$19,),""),IF($I30=3,"",IFBLANK(_xldudf_CX_PUSH(AG30,CX_ENTITY,$B30,AG$11,AG$14,AG$19,),"")))))),"")} | DH30: {=IFERROR(IF(AH30*fxVal_normal=_PL!AH30,"",IF(OR(AH30="",NOT(ISNUMBER(AH30)),ISERROR(AH30),$B30=""),"",IF($I30=1,IFBLANK(_xldudf_CX_PUSH(AH30*fxVal_normal,CX_ENTITY,$B30,AH$11,AH$14,AH$19,),""),IF($I30=2,IFBLANK(_xldudf_CX_PUSH(AH30,CX_ENTITY,$B30,AH$11,AH$14,AH$19,),""),IF($I30=3,"",IFBLANK(_xldudf_CX_PUSH(AH30,CX_ENTITY,$B30,AH$11,AH$14,AH$19,),"")))))),"")} | DI30: {=IFERROR(IF(AI30*fxVal_normal=_PL!AI30,"",IF(OR(AI30="",NOT(ISNUMBER(AI30)),ISERROR(AI30),$B30=""),"",IF($I30=1,IFBLANK(_xldudf_CX_PUSH(AI30*fxVal_normal,CX_ENTITY,$B30,AI$11,AI$14,AI$19,),""),IF($I30=2,IFBLANK(_xldudf_CX_PUSH(AI30,CX_ENTITY,$B30,AI$11,AI$14,AI$19,),""),IF($I30=3,"",IFBLANK(_xldudf_CX_PUSH(AI30,CX_ENTITY,$B30,AI$11,AI$14,AI$19,),"")))))),"")} | DJ30: {=IFERROR(IF(AJ30*fxVal_normal=_PL!AJ30,"",IF(OR(AJ30="",NOT(ISNUMBER(AJ30)),ISERROR(AJ30),$B30=""),"",IF($I30=1,IFBLANK(_xldudf_CX_PUSH(AJ30*fxVal_normal,CX_ENTITY,$B30,AJ$11,AJ$14,AJ$19,),""),IF($I30=2,IFBLANK(_xldudf_CX_PUSH(AJ30,CX_ENTITY,$B30,AJ$11,AJ$14,AJ$19,),""),IF($I30=3,"",IFBLANK(_xldudf_CX_PUSH(AJ30,CX_ENTITY,$B30,AJ$11,AJ$14,AJ$19,),"")))))),"")} | DK30: {=IFERROR(IF(AK30*fxVal_normal=_PL!AK30,"",IF(OR(AK30="",NOT(ISNUMBER(AK30)),ISERROR(AK30),$B30=""),"",IF($I30=1,IFBLANK(_xldudf_CX_PUSH(AK30*fxVal_normal,CX_ENTITY,$B30,AK$11,AK$14,AK$19,),""),IF($I30=2,IFBLANK(_xldudf_CX_PUSH(AK30,CX_ENTITY,$B30,AK$11,AK$14,AK$19,),""),IF($I30=3,"",IFBLANK(_xldudf_CX_PUSH(AK30,CX_ENTITY,$B30,AK$11,AK$14,AK$19,),"")))))),"")} | ... EN30: {=IFERROR(IF(BN30*fxVal_normal=_PL!BN30,"",IF(OR(BN30="",NOT(ISNUMBER(BN30)),ISERROR(BN30),$B30=""),"",IF($I30=1,IFBLANK(_xldudf_CX_PUSH(BN30*fxVal_normal,CX_ENTITY,$B30,BN$11,BN$14,BN$19,),""),IF($I30=2,IFBLANK(_xldudf_CX_PUSH(BN30,CX_ENTITY,$B30,BN$11,BN$14,BN$19,),""),IF($I30=3,"",IFBLANK(_xldudf_CX_PUSH(BN30,CX_ENTITY,$B30,BN$11,BN$14,BN$19,),"")))))),"")}
B31: =_xlfn.LET(_xlpm.IsNotAttrDynamic,D31="",_xlpm.Attr,_PL!F31,_xlpm.NotInUse,Y31=D31,_xlpm.RESULT,IF(_xlpm.IsNotAttrDynamic,_xlpm.Attr,IF(_xlpm.NotInUse,"",Y31)),IF(_xlpm.RESULT="","",_xlpm.RESULT)) -> 2 | C31: {=IFBLANK(_PL!C31,"")} -> EBITDA Adjustment Type I - Label 6 | D31: Please select or type in or leave as blank (6) | E31: {=_xlfn.LAMBDA(_xlpm.Array,_xlop.Type,_xlfn.LET(_xlpm._type,IF(_xlfn.ISOMITTED(_xlpm.Type),0,_xlpm.Type),_xlpm.R,ROWS(_xlpm.Array),_xlpm.C,COLUMNS(_xlpm.Array),_xlpm.Unlocked,_xlfn.MAKEARRAY(_xlpm.R,_xlpm.C,_xlfn.LAMBDA(_xlpm.i,_xlpm.j,--(CELL("protect",INDEX(_xlpm.Array,_xlpm.i,_xlpm.j))=0))),_xlpm.IsUnlocked,_xlfn.MAKEARRAY(_xlpm.R,_xlpm.C,_xlfn.LAMBDA(_xlpm.i,_xlpm.j,CELL("protect",INDEX(_xlpm.Array,_xlpm.i,_xlpm.j))=0)),_xlpm.HasData,_xlpm.Array<>"",_xlpm.Total,SUM(_xlpm.Unlocked),_xlpm.Completed,SUM(--(_xlpm.IsUnlocked*_xlpm.HasData)),_xlpm.type_display,_xlfn.SWITCH(_xlpm._type,1,"R",-1,"O",0,"A",""),_xlfn.HSTACK(_xlpm.Total,_xlpm.Completed,_xlpm.type_display)))($AD31:$CQ31,Z31)} -> #NAME? | H31: 0 | I31: 1 | J31: {=IFBLANK(Z31,"")} -> -1 | K31: =IFERROR(IF(LEN(AB31)=0,"No",IF(LEN(J31)>0,"Yes","No")),"") -> Yes | L31: 6 | W31: =$W$20 -> Actual | X31: =_PL!X31 -> a | Y31: 2 | Z31: {=_xlfn.SWITCH(TRUE,_PL!$L31=TRUE,1,_PL!$L31=FALSE,-1,_PL!$L31=-1,0,"")} -> -1 | AB31: =Y31 -> 2 | AC31: {=_xlfn.LET(_xlpm._termname,$AB31,_xlpm._iconname,"find",_xlpm._icon,fx_getIcon(_xlpm._iconname),_xlpm._location,_xlfn.XLOOKUP(LOWER(_xlpm._termname),LOWER(tbl_acctDef[Term]),tbl_acctDef[Term]),_xlpm._hyperlink,HYPERLINK("#"&CELL("address",_xlpm._location),_xlpm._icon),IFERROR(_xlpm._hyperlink,""))} | AD31: 1 | AE31: 1 | AF31: 1 | AG31: 1 | AH31: 1 | AI31: 1 | AJ31: 1 | AK31: 1 | AL31: 1 | AM31: 1 | AN31: 1 | AO31: 1 | AP31: 1 | AQ31: 1 | AR31: 1 | AS31: 1 | AT31: 1 | AU31: 1 | AV31: 1 | AW31: 1 | AX31: 1 | AY31: 1 | AZ31: 1 | BA31: 1 | BB31: 1 | BC31: 1 | BD31: 1 | BE31: 1 | BF31: 1 | BG31: 1 | BH31: 1 | BI31: 1 | BJ31: 1 | BK31: 1 | BL31: 1 | BM31: 1 | BN31: 1 | CD31: {=_xlfn.LET(_xlpm.CheckBlank,SUM(PL!$AD31:PL!$BN31)=0,IF(_xlpm.CheckBlank,"",SUM(_xlfn._xlws.FILTER(PL!$AD31:$BN31,(YEAR(PL!$AD$12:$BN$12)=PL!CD$12)*(array_timeline<=PL!CD$11)))))} -> #NAME? | CE31: {=_xlfn.LET(_xlpm.CheckBlank,SUM(PL!$AD31:PL!$BN31)=0,IF(_xlpm.CheckBlank,"",SUM(_xlfn._xlws.FILTER(PL!$AD31:$BN31,(YEAR(PL!$AD$12:$BN$12)=PL!CE$12)*(array_timeline<=PL!CE$11)))))} -> #NAME? | CG31: {=IFERROR(_xlfn.LET(_xlpm.CheckBlank,SUM(PL!$AD31:$BN31)=0,IF(_xlpm.CheckBlank,"",SUM(_xlfn._xlws.FILTER(PL!$AD31:$BN31,(YEAR(PL!$AD$12:$BN$12)=PL!CG$12)*(array_timeline<=PL!CG$11))))),"n/a")} -> n/a | CH31: {=_xlfn.LET(_xlpm.CheckBlank,SUM(PL!$AD31:$BN31)=0,IF(_xlpm.CheckBlank,"",SUM(_xlfn._xlws.FILTER(PL!$AD31:$BN31,(YEAR(PL!$AD$12:$BN$12)=PL!CH$12)*(array_timeline<=PL!CH$11)))))} -> #NAME? | CJ31: {=_xlfn.LET(_xlpm.CheckBlank,SUM(PL!$AD31:$BN31)=0,IF(_xlpm.CheckBlank,"",SUM(_xlfn.TAKE(_xlfn.DROP(PL!$AD31:$BN31,,-DATEDIFF(PL!CJ$11,val_asOfDate,"M")),1,-12))))} -> 12 | CK31: {=_xlfn.LET(_xlpm.CheckBlank,SUM(PL!$AD31:$BN31)=0,IF(_xlpm.CheckBlank,"",SUM(_xlfn.TAKE(_xlfn.DROP(PL!$AD31:$BN31,,-DATEDIFF(PL!CK$11,val_asOfDate,"M")),1,-12))))} -> 12 | CM31: 1 | CN31: 1 | CP31: 1 | CQ31: 1 | CT31: {=IF(ISNUMBER(SEARCH("Select",$Y31)),"",_xldudf_CX_PUSH($Y31,CX_ENTITY,C31,val_asOfDate))} -> #NAME? | CU31: {=IF(ISNUMBER(SEARCH("Select",$Y31)),"",_xldudf_CX_PUSH($Y31,CX_ENTITY,C31,EOMONTH(val_asOfDate,1)))} -> #NAME? | CV31: {=IF(ISNUMBER(SEARCH("Select",$Y31)),"",_xldudf_CX_PUSH($Y31,CX_ENTITY,C31,EOMONTH(val_asOfDate,2)))} -> #NAME? | CW31: {=IF(ISNUMBER(SEARCH("Select",$Y31)),"",_xldudf_CX_PUSH($Y31,CX_ENTITY,C31,EOMONTH(val_asOfDate,3)))} -> #NAME? | CY31: {=IFERROR(IF(CM31*fxVal_normal=_PL!CM31,"",IF(OR($CM31="",$CM31=0,NOT(ISNUMBER($CM31)),ISERROR($CM31),$B31=""),"",IF($I31=1,IFBLANK(_xldudf_CX_PUSH($CM31*fxVal_normal,CX_ENTITY,$B31,$CM$11,$CM$14,$CM$19,),""),IF($I31=2,IFBLANK(_xldudf_CX_PUSH($CM31,CX_ENTITY,$B31,$CM$11,$CM$14,$CM$19,),""),IF($I31=3,"",IFBLANK(_xldudf_CX_PUSH($CM31,CX_ENTITY,$B31,$CM$11,$CM$14,$CM$19,),"")))))),"")} | CZ31: {=IFERROR(IF(CN31*fxVal_normal=_PL!CN31,"",IF(OR($CN31="",$CN31=0,NOT(ISNUMBER($CN31)),ISERROR($CN31),$B31=""),"",IF($I31=1,IFBLANK(_xldudf_CX_PUSH($CN31*fxVal_normal,CX_ENTITY,$B31,$CN$11,$CN$14,$CN$19,),""),IF($I31=2,IFBLANK(_xldudf_CX_PUSH($CN31,CX_ENTITY,$B31,$CN$11,$CN$14,$CN$19,),""),IF($I31=3,"",IFBLANK(_xldudf_CX_PUSH($CN31,CX_ENTITY,$B31,$CN$11,$CN$14,$CN$19,),"")))))),"")} | DA31: {=IFERROR(IF(CP31*fxVal_normal=_PL!CP31,"",IF(OR($CP31="",$CP31=0,NOT(ISNUMBER($CP31)),ISERROR($CP31),$B31=""),"",IF($I31=1,IFBLANK(_xldudf_CX_PUSH($CP31*fxVal_normal,CX_ENTITY,$B31,$CP$11,$CP$14,$CP$19,),""),IF($I31=2,IFBLANK(_xldudf_CX_PUSH($CP31,CX_ENTITY,$B31,$CP$11,$CP$14,$CP$19,),""),IF($I31=3,"",IFBLANK(_xldudf_CX_PUSH($CP31,CX_ENTITY,$B31,$CP$11,$CP$14,$CP$19,),"")))))),"")} | DB31: {=IFERROR(IF(CQ31*fxVal_normal=_PL!CQ31,"",IF(OR($CQ31="",$CQ31=0,NOT(ISNUMBER($CQ31)),ISERROR($CQ31),$B31=""),"",IF($I31=1,IFBLANK(_xldudf_CX_PUSH($CQ31*fxVal_normal,CX_ENTITY,$B31,$CQ$11,$CQ$14,$CQ$19,),""),IF($I31=2,IFBLANK(_xldudf_CX_PUSH($CQ31,CX_ENTITY,$B31,$CQ$11,$CQ$14,$CQ$19,),""),IF($I31=3,"",IFBLANK(_xldudf_CX_PUSH($CQ31,CX_ENTITY,$B31,$CQ$11,$CQ$14,$CQ$19,),"")))))),"")} | DD31: {=IFERROR(IF(AD31*fxVal_normal=_PL!AD31,"",IF(OR(AD31="",NOT(ISNUMBER(AD31)),ISERROR(AD31),$B31=""),"",IF($I31=1,IFBLANK(_xldudf_CX_PUSH(AD31*fxVal_normal,CX_ENTITY,$B31,AD$11,AD$14,AD$19,),""),IF($I31=2,IFBLANK(_xldudf_CX_PUSH(AD31,CX_ENTITY,$B31,AD$11,AD$14,AD$19,),""),IF($I31=3,"",IFBLANK(_xldudf_CX_PUSH(AD31,CX_ENTITY,$B31,AD$11,AD$14,AD$19,),"")))))),"")} | DE31: {=IFERROR(IF(AE31*fxVal_normal=_PL!AE31,"",IF(OR(AE31="",NOT(ISNUMBER(AE31)),ISERROR(AE31),$B31=""),"",IF($I31=1,IFBLANK(_xldudf_CX_PUSH(AE31*fxVal_normal,CX_ENTITY,$B31,AE$11,AE$14,AE$19,),""),IF($I31=2,IFBLANK(_xldudf_CX_PUSH(AE31,CX_ENTITY,$B31,AE$11,AE$14,AE$19,),""),IF($I31=3,"",IFBLANK(_xldudf_CX_PUSH(AE31,CX_ENTITY,$B31,AE$11,AE$14,AE$19,),"")))))),"")} | DF31: {=IFERROR(IF(AF31*fxVal_normal=_PL!AF31,"",IF(OR(AF31="",NOT(ISNUMBER(AF31)),ISERROR(AF31),$B31=""),"",IF($I31=1,IFBLANK(_xldudf_CX_PUSH(AF31*fxVal_normal,CX_ENTITY,$B31,AF$11,AF$14,AF$19,),""),IF($I31=2,IFBLANK(_xldudf_CX_PUSH(AF31,CX_ENTITY,$B31,AF$11,AF$14,AF$19,),""),IF($I31=3,"",IFBLANK(_xldudf_CX_PUSH(AF31,CX_ENTITY,$B31,AF$11,AF$14,AF$19,),"")))))),"")} | DG31: {=IFERROR(IF(AG31*fxVal_normal=_PL!AG31,"",IF(OR(AG31="",NOT(ISNUMBER(AG31)),ISERROR(AG31),$B31=""),"",IF($I31=1,IFBLANK(_xldudf_CX_PUSH(AG31*fxVal_normal,CX_ENTITY,$B31,AG$11,AG$14,AG$19,),""),IF($I31=2,IFBLANK(_xldudf_CX_PUSH(AG31,CX_ENTITY,$B31,AG$11,AG$14,AG$19,),""),IF($I31=3,"",IFBLANK(_xldudf_CX_PUSH(AG31,CX_ENTITY,$B31,AG$11,AG$14,AG$19,),"")))))),"")} | DH31: {=IFERROR(IF(AH31*fxVal_normal=_PL!AH31,"",IF(OR(AH31="",NOT(ISNUMBER(AH31)),ISERROR(AH31),$B31=""),"",IF($I31=1,IFBLANK(_xldudf_CX_PUSH(AH31*fxVal_normal,CX_ENTITY,$B31,AH$11,AH$14,AH$19,),""),IF($I31=2,IFBLANK(_xldudf_CX_PUSH(AH31,CX_ENTITY,$B31,AH$11,AH$14,AH$19,),""),IF($I31=3,"",IFBLANK(_xldudf_CX_PUSH(AH31,CX_ENTITY,$B31,AH$11,AH$14,AH$19,),"")))))),"")} | DI31: {=IFERROR(IF(AI31*fxVal_normal=_PL!AI31,"",IF(OR(AI31="",NOT(ISNUMBER(AI31)),ISERROR(AI31),$B31=""),"",IF($I31=1,IFBLANK(_xldudf_CX_PUSH(AI31*fxVal_normal,CX_ENTITY,$B31,AI$11,AI$14,AI$19,),""),IF($I31=2,IFBLANK(_xldudf_CX_PUSH(AI31,CX_ENTITY,$B31,AI$11,AI$14,AI$19,),""),IF($I31=3,"",IFBLANK(_xldudf_CX_PUSH(AI31,CX_ENTITY,$B31,AI$11,AI$14,AI$19,),"")))))),"")} | DJ31: {=IFERROR(IF(AJ31*fxVal_normal=_PL!AJ31,"",IF(OR(AJ31="",NOT(ISNUMBER(AJ31)),ISERROR(AJ31),$B31=""),"",IF($I31=1,IFBLANK(_xldudf_CX_PUSH(AJ31*fxVal_normal,CX_ENTITY,$B31,AJ$11,AJ$14,AJ$19,),""),IF($I31=2,IFBLANK(_xldudf_CX_PUSH(AJ31,CX_ENTITY,$B31,AJ$11,AJ$14,AJ$19,),""),IF($I31=3,"",IFBLANK(_xldudf_CX_PUSH(AJ31,CX_ENTITY,$B31,AJ$11,AJ$14,AJ$19,),"")))))),"")} | DK31: {=IFERROR(IF(AK31*fxVal_normal=_PL!AK31,"",IF(OR(AK31="",NOT(ISNUMBER(AK31)),ISERROR(AK31),$B31=""),"",IF($I31=1,IFBLANK(_xldudf_CX_PUSH(AK31*fxVal_normal,CX_ENTITY,$B31,AK$11,AK$14,AK$19,),""),IF($I31=2,IFBLANK(_xldudf_CX_PUSH(AK31,CX_ENTITY,$B31,AK$11,AK$14,AK$19,),""),IF($I31=3,"",IFBLANK(_xldudf_CX_PUSH(AK31,CX_ENTITY,$B31,AK$11,AK$14,AK$19,),"")))))),"")} | ... EN31: {=IFERROR(IF(BN31*fxVal_normal=_PL!BN31,"",IF(OR(BN31="",NOT(ISNUMBER(BN31)),ISERROR(BN31),$B31=""),"",IF($I31=1,IFBLANK(_xldudf_CX_PUSH(BN31*fxVal_normal,CX_ENTITY,$B31,BN$11,BN$14,BN$19,),""),IF($I31=2,IFBLANK(_xldudf_CX_PUSH(BN31,CX_ENTITY,$B31,BN$11,BN$14,BN$19,),""),IF($I31=3,"",IFBLANK(_xldudf_CX_PUSH(BN31,CX_ENTITY,$B31,BN$11,BN$14,BN$19,),"")))))),"")}
B32: =_xlfn.LET(_xlpm.IsNotAttrDynamic,D32="",_xlpm.Attr,_PL!F32,_xlpm.NotInUse,Y32=D32,_xlpm.RESULT,IF(_xlpm.IsNotAttrDynamic,_xlpm.Attr,IF(_xlpm.NotInUse,"",Y32)),IF(_xlpm.RESULT="","",_xlpm.RESULT)) -> Adjusted EBITDA | C32: {=IFBLANK(_PL!C32,"")} -> Adjusted EBITDA (Company View) | E32: {=_xlfn.LAMBDA(_xlpm.Array,_xlop.Type,_xlfn.LET(_xlpm._type,IF(_xlfn.ISOMITTED(_xlpm.Type),0,_xlpm.Type),_xlpm.R,ROWS(_xlpm.Array),_xlpm.C,COLUMNS(_xlpm.Array),_xlpm.Unlocked,_xlfn.MAKEARRAY(_xlpm.R,_xlpm.C,_xlfn.LAMBDA(_xlpm.i,_xlpm.j,--(CELL("protect",INDEX(_xlpm.Array,_xlpm.i,_xlpm.j))=0))),_xlpm.IsUnlocked,_xlfn.MAKEARRAY(_xlpm.R,_xlpm.C,_xlfn.LAMBDA(_xlpm.i,_xlpm.j,CELL("protect",INDEX(_xlpm.Array,_xlpm.i,_xlpm.j))=0)),_xlpm.HasData,_xlpm.Array<>"",_xlpm.Total,SUM(_xlpm.Unlocked),_xlpm.Completed,SUM(--(_xlpm.IsUnlocked*_xlpm.HasData)),_xlpm.type_display,_xlfn.SWITCH(_xlpm._type,1,"R",-1,"O",0,"A",""),_xlfn.HSTACK(_xlpm.Total,_xlpm.Completed,_xlpm.type_display)))($AD32:$CQ32,Z32)} -> #NAME? | H32: 2 | I32: 1 | J32: {=IFBLANK(Z32,"")} -> 0 | K32: =IFERROR(IF(LEN(AB32)=0,"No",IF(LEN(J32)>0,"Yes","No")),"") -> Yes | W32: =$W$20 -> Actual | X32: =_PL!X32 -> 0 | Y32: =IF(_PL!Y32="Error","",_PL!Y32) -> #NAME? | Z32: {=_xlfn.SWITCH(TRUE,_PL!$L32=TRUE,1,_PL!$L32=FALSE,-1,_PL!$L32=-1,0,"")} -> 0 | AB32: =_PL!AB32 -> Adjusted EBITDA | AC32: {=_xlfn.LET(_xlpm._termname,$AB32,_xlpm._iconname,"find",_xlpm._icon,fx_getIcon(_xlpm._iconname),_xlpm._location,_xlfn.XLOOKUP(LOWER(_xlpm._termname),LOWER(tbl_acctDef[Term]),tbl_acctDef[Term]),_xlpm._hyperlink,HYPERLINK("#"&CELL("address",_xlpm._location),_xlpm._icon),IFERROR(_xlpm._hyperlink,""))} -> #VALUE! | AD32: =SUBTOTAL(9,AD20:AD31)-N(AD23) -> 9 | AE32: =SUBTOTAL(9,AE20:AE31)-N(AE23) -> 9 | AF32: =SUBTOTAL(9,AF20:AF31)-N(AF23) -> 9 | AG32: =SUBTOTAL(9,AG20:AG31)-N(AG23) -> 9 | AH32: =SUBTOTAL(9,AH20:AH31)-N(AH23) -> 9 | AI32: =SUBTOTAL(9,AI20:AI31)-N(AI23) -> 9 | AJ32: =SUBTOTAL(9,AJ20:AJ31)-N(AJ23) -> 9 | AK32: =SUBTOTAL(9,AK20:AK31)-N(AK23) -> 9 | ... BN32: =SUBTOTAL(9,BN20:BN31)-N(BN23) -> 9 | CD32: {=_xlfn.LET(_xlpm.CheckBlank,SUM(PL!$AD32:PL!$BN32)=0,IF(_xlpm.CheckBlank,"",SUM(_xlfn._xlws.FILTER(PL!$AD32:$BN32,(YEAR(PL!$AD$12:$BN$12)=PL!CD$12)*(array_timeline<=PL!CD$11)))))} -> #NAME? | CE32: {=_xlfn.LET(_xlpm.CheckBlank,SUM(PL!$AD32:PL!$BN32)=0,IF(_xlpm.CheckBlank,"",SUM(_xlfn._xlws.FILTER(PL!$AD32:$BN32,(YEAR(PL!$AD$12:$BN$12)=PL!CE$12)*(array_timeline<=PL!CE$11)))))} -> #NAME? | CG32: {=IFERROR(_xlfn.LET(_xlpm.CheckBlank,SUM(PL!$AD32:$BN32)=0,IF(_xlpm.CheckBlank,"",SUM(_xlfn._xlws.FILTER(PL!$AD32:$BN32,(YEAR(PL!$AD$12:$BN$12)=PL!CG$12)*(array_timeline<=PL!CG$11))))),"n/a")} -> n/a | CH32: {=_xlfn.LET(_xlpm.CheckBlank,SUM(PL!$AD32:$BN32)=0,IF(_xlpm.CheckBlank,"",SUM(_xlfn._xlws.FILTER(PL!$AD32:$BN32,(YEAR(PL!$AD$12:$BN$12)=PL!CH$12)*(array_timeline<=PL!CH$11)))))} -> #NAME? | CJ32: {=_xlfn.LET(_xlpm.CheckBlank,SUM(PL!$AD32:$BN32)=0,IF(_xlpm.CheckBlank,"",SUM(_xlfn.TAKE(_xlfn.DROP(PL!$AD32:$BN32,,-DATEDIFF(PL!CJ$11,val_asOfDate,"M")),1,-12))))} -> 108 | CK32: {=_xlfn.LET(_xlpm.CheckBlank,SUM(PL!$AD32:$BN32)=0,IF(_xlpm.CheckBlank,"",SUM(_xlfn.TAKE(_xlfn.DROP(PL!$AD32:$BN32,,-DATEDIFF(PL!CK$11,val_asOfDate,"M")),1,-12))))} -> 108 | CM32: =SUBTOTAL(9,CM20:CM31)-N(CM23) -> 9 | CN32: =SUBTOTAL(9,CN20:CN31)-N(CN23) -> 9 | CP32: =SUBTOTAL(9,CP20:CP31)-N(CP23) -> 9 | CQ32: =SUBTOTAL(9,CQ20:CQ31)-N(CQ23) -> 9 | CT32: {=IF(K32<>"Yes","",IF(OR(Y32="Select, enter text or leave as blank.",Y32="Set from Actual section above!",Y32="Please select or type in or leave as blank",Y32="Select, enter text or leave as blank",Y32="Please select your Top Line Metric",Y32="Check Sum",Y32="Please name your Like-for-Like Revenue",Y32="Please name your Like-for-like Earning Metric",Y32="Valuation Metric",Y32="Please name your Like-for-like Valuation Metric",Y32="Please select your Valuation Metric",Y32="Please select the metric for segmentation",Y32="Untitled Segmentation II",Y32="Untitled Segmentation III"),"",IF(OR(Y32<>AB32,AND(LEN(B32)=0,NOT(OR(Y32="Select, enter text or leave as blank.",Y32="Set from Actual section above!",Y32="Please select or type in or leave as blank",Y32="Select, enter text or leave as blank",Y32="Please select your Top Line Metric",Y32="Check Sum",Y32="Please name your Like-for-Like Revenue",Y32="Please name your Like-for-like Earning Metric",Y32="Valuation Metric",Y32="Please name your Like-for-like Valuation Metric",Y32="Please select your Valuation Metric",Y32="Please select the metric for segmentation",Y32="Untitled Segmentation II",Y32="Untitled Segmentation III")))),_xldudf_CX_PUSH(Y32,CX_ENTITY,C32,EOMONTH(val_asOfDate,0)),"")))} -> #NAME? | CU32: {=IF(K32<>"Yes","",IF(OR(Y32="Select, enter text or leave as blank.",Y32="Set from Actual section above!",Y32="Please select or type in or leave as blank",Y32="Select, enter text or leave as blank",Y32="Please select your Top Line Metric",Y32="Check Sum",Y32="Please name your Like-for-Like Revenue",Y32="Please name your Like-for-like Earning Metric",Y32="Valuation Metric",Y32="Please name your Like-for-like Valuation Metric",Y32="Please select your Valuation Metric",Y32="Please select the metric for segmentation",Y32="Untitled Segmentation II",Y32="Untitled Segmentation III"),"",IF(OR(Y32<>AB32,AND(LEN(B32)=0,NOT(OR(Y32="Select, enter text or leave as blank.",Y32="Set from Actual section above!",Y32="Please select or type in or leave as blank",Y32="Select, enter text or leave as blank",Y32="Please select your Top Line Metric",Y32="Check Sum",Y32="Please name your Like-for-Like Revenue",Y32="Please name your Like-for-like Earning Metric",Y32="Valuation Metric",Y32="Please name your Like-for-like Valuation Metric",Y32="Please select your Valuation Metric",Y32="Please select the metric for segmentation",Y32="Untitled Segmentation II",Y32="Untitled Segmentation III")))),_xldudf_CX_PUSH(Y32,CX_ENTITY,C32,EOMONTH(val_asOfDate,1)),"")))} -> #NAME? | CV32: {=IF(K32<>"Yes","",IF(OR(Y32="Select, enter text or leave as blank.",Y32="Set from Actual section above!",Y32="Please select or type in or leave as blank",Y32="Select, enter text or leave as blank",Y32="Please select your Top Line Metric",Y32="Check Sum",Y32="Please name your Like-for-Like Revenue",Y32="Please name your Like-for-like Earning Metric",Y32="Valuation Metric",Y32="Please name your Like-for-like Valuation Metric",Y32="Please select your Valuation Metric",Y32="Please select the metric for segmentation",Y32="Untitled Segmentation II",Y32="Untitled Segmentation III"),"",IF(OR(Y32<>AB32,AND(LEN(B32)=0,NOT(OR(Y32="Select, enter text or leave as blank.",Y32="Set from Actual section above!",Y32="Please select or type in or leave as blank",Y32="Select, enter text or leave as blank",Y32="Please select your Top Line Metric",Y32="Check Sum",Y32="Please name your Like-for-Like Revenue",Y32="Please name your Like-for-like Earning Metric",Y32="Valuation Metric",Y32="Please name your Like-for-like Valuation Metric",Y32="Please select your Valuation Metric",Y32="Please select the metric for segmentation",Y32="Untitled Segmentation II",Y32="Untitled Segmentation III")))),_xldudf_CX_PUSH(Y32,CX_ENTITY,C32,EOMONTH(val_asOfDate,2)),"")))} -> #NAME? | CW32: {=IF(K32<>"Yes","",IF(OR(Y32="Select, enter text or leave as blank.",Y32="Set from Actual section above!",Y32="Please select or type in or leave as blank",Y32="Select, enter text or leave as blank",Y32="Please select your Top Line Metric",Y32="Check Sum",Y32="Please name your Like-for-Like Revenue",Y32="Please name your Like-for-like Earning Metric",Y32="Valuation Metric",Y32="Please name your Like-for-like Valuation Metric",Y32="Please select your Valuation Metric",Y32="Please select the metric for segmentation",Y32="Untitled Segmentation II",Y32="Untitled Segmentation III"),"",IF(OR(Y32<>AB32,AND(LEN(B32)=0,NOT(OR(Y32="Select, enter text or leave as blank.",Y32="Set from Actual section above!",Y32="Please select or type in or leave as blank",Y32="Select, enter text or leave as blank",Y32="Please select your Top Line Metric",Y32="Check Sum",Y32="Please name your Like-for-Like Revenue",Y32="Please name your Like-for-like Earning Metric",Y32="Valuation Metric",Y32="Please name your Like-for-like Valuation Metric",Y32="Please select your Valuation Metric",Y32="Please select the metric for segmentation",Y32="Untitled Segmentation II",Y32="Untitled Segmentation III")))),_xldudf_CX_PUSH(Y32,CX_ENTITY,C32,EOMONTH(val_asOfDate,3)),"")))} -> #NAME? | CY32: {=IFERROR(IF(CM32*fxVal_normal=_PL!CM32,"",IF(OR($CM32="",$CM32=0,NOT(ISNUMBER($CM32)),ISERROR($CM32),$B32=""),"",IF($I32=1,IFBLANK(_xldudf_CX_PUSH($CM32*fxVal_normal,CX_ENTITY,$B32,$CM$11,$CM$14,$CM$19,),""),IF($I32=2,IFBLANK(_xldudf_CX_PUSH($CM32,CX_ENTITY,$B32,$CM$11,$CM$14,$CM$19,),""),IF($I32=3,"",IFBLANK(_xldudf_CX_PUSH($CM32,CX_ENTITY,$B32,$CM$11,$CM$14,$CM$19,),"")))))),"")} | CZ32: {=IFERROR(IF(CN32*fxVal_normal=_PL!CN32,"",IF(OR($CN32="",$CN32=0,NOT(ISNUMBER($CN32)),ISERROR($CN32),$B32=""),"",IF($I32=1,IFBLANK(_xldudf_CX_PUSH($CN32*fxVal_normal,CX_ENTITY,$B32,$CN$11,$CN$14,$CN$19,),""),IF($I32=2,IFBLANK(_xldudf_CX_PUSH($CN32,CX_ENTITY,$B32,$CN$11,$CN$14,$CN$19,),""),IF($I32=3,"",IFBLANK(_xldudf_CX_PUSH($CN32,CX_ENTITY,$B32,$CN$11,$CN$14,$CN$19,),"")))))),"")} | DA32: {=IFERROR(IF(CP32*fxVal_normal=_PL!CP32,"",IF(OR($CP32="",$CP32=0,NOT(ISNUMBER($CP32)),ISERROR($CP32),$B32=""),"",IF($I32=1,IFBLANK(_xldudf_CX_PUSH($CP32*fxVal_normal,CX_ENTITY,$B32,$CP$11,$CP$14,$CP$19,),""),IF($I32=2,IFBLANK(_xldudf_CX_PUSH($CP32,CX_ENTITY,$B32,$CP$11,$CP$14,$CP$19,),""),IF($I32=3,"",IFBLANK(_xldudf_CX_PUSH($CP32,CX_ENTITY,$B32,$CP$11,$CP$14,$CP$19,),"")))))),"")} | DB32: {=IFERROR(IF(CQ32*fxVal_normal=_PL!CQ32,"",IF(OR($CQ32="",$CQ32=0,NOT(ISNUMBER($CQ32)),ISERROR($CQ32),$B32=""),"",IF($I32=1,IFBLANK(_xldudf_CX_PUSH($CQ32*fxVal_normal,CX_ENTITY,$B32,$CQ$11,$CQ$14,$CQ$19,),""),IF($I32=2,IFBLANK(_xldudf_CX_PUSH($CQ32,CX_ENTITY,$B32,$CQ$11,$CQ$14,$CQ$19,),""),IF($I32=3,"",IFBLANK(_xldudf_CX_PUSH($CQ32,CX_ENTITY,$B32,$CQ$11,$CQ$14,$CQ$19,),"")))))),"")} | DD32: {=IFERROR(IF(AD32*fxVal_normal=_PL!AD32,"",IF(OR(AD32="",NOT(ISNUMBER(AD32)),ISERROR(AD32),$B32=""),"",IF($I32=1,IFBLANK(_xldudf_CX_PUSH(AD32*fxVal_normal,CX_ENTITY,$B32,AD$11,AD$14,AD$19,),""),IF($I32=2,IFBLANK(_xldudf_CX_PUSH(AD32,CX_ENTITY,$B32,AD$11,AD$14,AD$19,),""),IF($I32=3,"",IFBLANK(_xldudf_CX_PUSH(AD32,CX_ENTITY,$B32,AD$11,AD$14,AD$19,),"")))))),"")} | DE32: {=IFERROR(IF(AE32*fxVal_normal=_PL!AE32,"",IF(OR(AE32="",NOT(ISNUMBER(AE32)),ISERROR(AE32),$B32=""),"",IF($I32=1,IFBLANK(_xldudf_CX_PUSH(AE32*fxVal_normal,CX_ENTITY,$B32,AE$11,AE$14,AE$19,),""),IF($I32=2,IFBLANK(_xldudf_CX_PUSH(AE32,CX_ENTITY,$B32,AE$11,AE$14,AE$19,),""),IF($I32=3,"",IFBLANK(_xldudf_CX_PUSH(AE32,CX_ENTITY,$B32,AE$11,AE$14,AE$19,),"")))))),"")} | DF32: {=IFERROR(IF(AF32*fxVal_normal=_PL!AF32,"",IF(OR(AF32="",NOT(ISNUMBER(AF32)),ISERROR(AF32),$B32=""),"",IF($I32=1,IFBLANK(_xldudf_CX_PUSH(AF32*fxVal_normal,CX_ENTITY,$B32,AF$11,AF$14,AF$19,),""),IF($I32=2,IFBLANK(_xldudf_CX_PUSH(AF32,CX_ENTITY,$B32,AF$11,AF$14,AF$19,),""),IF($I32=3,"",IFBLANK(_xldudf_CX_PUSH(AF32,CX_ENTITY,$B32,AF$11,AF$14,AF$19,),"")))))),"")} | DG32: {=IFERROR(IF(AG32*fxVal_normal=_PL!AG32,"",IF(OR(AG32="",NOT(ISNUMBER(AG32)),ISERROR(AG32),$B32=""),"",IF($I32=1,IFBLANK(_xldudf_CX_PUSH(AG32*fxVal_normal,CX_ENTITY,$B32,AG$11,AG$14,AG$19,),""),IF($I32=2,IFBLANK(_xldudf_CX_PUSH(AG32,CX_ENTITY,$B32,AG$11,AG$14,AG$19,),""),IF($I32=3,"",IFBLANK(_xldudf_CX_PUSH(AG32,CX_ENTITY,$B32,AG$11,AG$14,AG$19,),"")))))),"")} | DH32: {=IFERROR(IF(AH32*fxVal_normal=_PL!AH32,"",IF(OR(AH32="",NOT(ISNUMBER(AH32)),ISERROR(AH32),$B32=""),"",IF($I32=1,IFBLANK(_xldudf_CX_PUSH(AH32*fxVal_normal,CX_ENTITY,$B32,AH$11,AH$14,AH$19,),""),IF($I32=2,IFBLANK(_xldudf_CX_PUSH(AH32,CX_ENTITY,$B32,AH$11,AH$14,AH$19,),""),IF($I32=3,"",IFBLANK(_xldudf_CX_PUSH(AH32,CX_ENTITY,$B32,AH$11,AH$14,AH$19,),"")))))),"")} | DI32: {=IFERROR(IF(AI32*fxVal_normal=_PL!AI32,"",IF(OR(AI32="",NOT(ISNUMBER(AI32)),ISERROR(AI32),$B32=""),"",IF($I32=1,IFBLANK(_xldudf_CX_PUSH(AI32*fxVal_normal,CX_ENTITY,$B32,AI$11,AI$14,AI$19,),""),IF($I32=2,IFBLANK(_xldudf_CX_PUSH(AI32,CX_ENTITY,$B32,AI$11,AI$14,AI$19,),""),IF($I32=3,"",IFBLANK(_xldudf_CX_PUSH(AI32,CX_ENTITY,$B32,AI$11,AI$14,AI$19,),"")))))),"")} | DJ32: {=IFERROR(IF(AJ32*fxVal_normal=_PL!AJ32,"",IF(OR(AJ32="",NOT(ISNUMBER(AJ32)),ISERROR(AJ32),$B32=""),"",IF($I32=1,IFBLANK(_xldudf_CX_PUSH(AJ32*fxVal_normal,CX_ENTITY,$B32,AJ$11,AJ$14,AJ$19,),""),IF($I32=2,IFBLANK(_xldudf_CX_PUSH(AJ32,CX_ENTITY,$B32,AJ$11,AJ$14,AJ$19,),""),IF($I32=3,"",IFBLANK(_xldudf_CX_PUSH(AJ32,CX_ENTITY,$B32,AJ$11,AJ$14,AJ$19,),"")))))),"")} | DK32: {=IFERROR(IF(AK32*fxVal_normal=_PL!AK32,"",IF(OR(AK32="",NOT(ISNUMBER(AK32)),ISERROR(AK32),$B32=""),"",IF($I32=1,IFBLANK(_xldudf_CX_PUSH(AK32*fxVal_normal,CX_ENTITY,$B32,AK$11,AK$14,AK$19,),""),IF($I32=2,IFBLANK(_xldudf_CX_PUSH(AK32,CX_ENTITY,$B32,AK$11,AK$14,AK$19,),""),IF($I32=3,"",IFBLANK(_xldudf_CX_PUSH(AK32,CX_ENTITY,$B32,AK$11,AK$14,AK$19,),"")))))),"")} | ... EN32: {=IFERROR(IF(BN32*fxVal_normal=_PL!BN32,"",IF(OR(BN32="",NOT(ISNUMBER(BN32)),ISERROR(BN32),$B32=""),"",IF($I32=1,IFBLANK(_xldudf_CX_PUSH(BN32*fxVal_normal,CX_ENTITY,$B32,BN$11,BN$14,BN$19,),""),IF($I32=2,IFBLANK(_xldudf_CX_PUSH(BN32,CX_ENTITY,$B32,BN$11,BN$14,BN$19,),""),IF($I32=3,"",IFBLANK(_xldudf_CX_PUSH(BN32,CX_ENTITY,$B32,BN$11,BN$14,BN$19,),"")))))),"")}
B33: =_xlfn.LET(_xlpm.IsNotAttrDynamic,D33="",_xlpm.Attr,_PL!F33,_xlpm.NotInUse,Y33=D33,_xlpm.RESULT,IF(_xlpm.IsNotAttrDynamic,_xlpm.Attr,IF(_xlpm.NotInUse,"",Y33)),IF(_xlpm.RESULT="","",_xlpm.RESULT)) -> Depreciation | C33: {=IFBLANK(_PL!C33,"")} -> Depreciation (Company View) | E33: {=_xlfn.LAMBDA(_xlpm.Array,_xlop.Type,_xlfn.LET(_xlpm._type,IF(_xlfn.ISOMITTED(_xlpm.Type),0,_xlpm.Type),_xlpm.R,ROWS(_xlpm.Array),_xlpm.C,COLUMNS(_xlpm.Array),_xlpm.Unlocked,_xlfn.MAKEARRAY(_xlpm.R,_xlpm.C,_xlfn.LAMBDA(_xlpm.i,_xlpm.j,--(CELL("protect",INDEX(_xlpm.Array,_xlpm.i,_xlpm.j))=0))),_xlpm.IsUnlocked,_xlfn.MAKEARRAY(_xlpm.R,_xlpm.C,_xlfn.LAMBDA(_xlpm.i,_xlpm.j,CELL("protect",INDEX(_xlpm.Array,_xlpm.i,_xlpm.j))=0)),_xlpm.HasData,_xlpm.Array<>"",_xlpm.Total,SUM(_xlpm.Unlocked),_xlpm.Completed,SUM(--(_xlpm.IsUnlocked*_xlpm.HasData)),_xlpm.type_display,_xlfn.SWITCH(_xlpm._type,1,"R",-1,"O",0,"A",""),_xlfn.HSTACK(_xlpm.Total,_xlpm.Completed,_xlpm.type_display)))($AD33:$CQ33,Z33)} -> #NAME? | H33: 0 | I33: 1 | J33: {=IFBLANK(Z33,"")} -> 1 | K33: =IFERROR(IF(LEN(AB33)=0,"No",IF(LEN(J33)>0,"Yes","No")),"") -> Yes | W33: =$W$20 -> Actual | X33: =_PL!X33 -> -1 | Y33: 2 | Z33: {=_xlfn.SWITCH(TRUE,_PL!$L33=TRUE,1,_PL!$L33=FALSE,-1,_PL!$L33=-1,0,"")} -> 1 | AB33: =_PL!AB33 -> Depreciation | AC33: {=_xlfn.LET(_xlpm._termname,$AB33,_xlpm._iconname,"find",_xlpm._icon,fx_getIcon(_xlpm._iconname),_xlpm._location,_xlfn.XLOOKUP(LOWER(_xlpm._termname),LOWER(tbl_acctDef[Term]),tbl_acctDef[Term]),_xlpm._hyperlink,HYPERLINK("#"&CELL("address",_xlpm._location),_xlpm._icon),IFERROR(_xlpm._hyperlink,""))} -> #VALUE! | AD33: 1 | AE33: 1 | AF33: 1 | AG33: 1 | AH33: 1 | AI33: 1 | AJ33: 1 | AK33: 1 | AL33: 1 | AM33: 1 | AN33: 1 | AO33: 1 | AP33: 1 | AQ33: 1 | AR33: 1 | AS33: 1 | AT33: 1 | AU33: 1 | AV33: 1 | AW33: 1 | AX33: 1 | AY33: 1 | AZ33: 1 | BA33: 1 | BB33: 1 | BC33: 1 | BD33: 1 | BE33: 1 | BF33: 1 | BG33: 1 | BH33: 1 | BI33: 1 | BJ33: 1 | BK33: 1 | BL33: 1 | BM33: 1 | BN33: 1 | CD33: {=_xlfn.LET(_xlpm.CheckBlank,SUM(PL!$AD33:PL!$BN33)=0,IF(_xlpm.CheckBlank,"",SUM(_xlfn._xlws.FILTER(PL!$AD33:$BN33,(YEAR(PL!$AD$12:$BN$12)=PL!CD$12)*(array_timeline<=PL!CD$11)))))} -> #NAME? | CE33: {=_xlfn.LET(_xlpm.CheckBlank,SUM(PL!$AD33:PL!$BN33)=0,IF(_xlpm.CheckBlank,"",SUM(_xlfn._xlws.FILTER(PL!$AD33:$BN33,(YEAR(PL!$AD$12:$BN$12)=PL!CE$12)*(array_timeline<=PL!CE$11)))))} -> #NAME? | CG33: {=IFERROR(_xlfn.LET(_xlpm.CheckBlank,SUM(PL!$AD33:$BN33)=0,IF(_xlpm.CheckBlank,"",SUM(_xlfn._xlws.FILTER(PL!$AD33:$BN33,(YEAR(PL!$AD$12:$BN$12)=PL!CG$12)*(array_timeline<=PL!CG$11))))),"n/a")} -> n/a | CH33: {=_xlfn.LET(_xlpm.CheckBlank,SUM(PL!$AD33:$BN33)=0,IF(_xlpm.CheckBlank,"",SUM(_xlfn._xlws.FILTER(PL!$AD33:$BN33,(YEAR(PL!$AD$12:$BN$12)=PL!CH$12)*(array_timeline<=PL!CH$11)))))} -> #NAME? | CJ33: {=_xlfn.LET(_xlpm.CheckBlank,SUM(PL!$AD33:$BN33)=0,IF(_xlpm.CheckBlank,"",SUM(_xlfn.TAKE(_xlfn.DROP(PL!$AD33:$BN33,,-DATEDIFF(PL!CJ$11,val_asOfDate,"M")),1,-12))))} -> 12 | CK33: {=_xlfn.LET(_xlpm.CheckBlank,SUM(PL!$AD33:$BN33)=0,IF(_xlpm.CheckBlank,"",SUM(_xlfn.TAKE(_xlfn.DROP(PL!$AD33:$BN33,,-DATEDIFF(PL!CK$11,val_asOfDate,"M")),1,-12))))} -> 12 | CM33: 1 | CN33: 1 | CP33: 1 | CQ33: 1 | CT33: {=IF(K33<>"Yes","",IF(OR(Y33="Select, enter text or leave as blank.",Y33="Set from Actual section above!",Y33="Please select or type in or leave as blank",Y33="Select, enter text or leave as blank",Y33="Please select your Top Line Metric",Y33="Check Sum",Y33="Please name your Like-for-Like Revenue",Y33="Please name your Like-for-like Earning Metric",Y33="Valuation Metric",Y33="Please name your Like-for-like Valuation Metric",Y33="Please select your Valuation Metric",Y33="Please select the metric for segmentation",Y33="Untitled Segmentation II",Y33="Untitled Segmentation III"),"",IF(OR(Y33<>AB33,AND(LEN(B33)=0,NOT(OR(Y33="Select, enter text or leave as blank.",Y33="Set from Actual section above!",Y33="Please select or type in or leave as blank",Y33="Select, enter text or leave as blank",Y33="Please select your Top Line Metric",Y33="Check Sum",Y33="Please name your Like-for-Like Revenue",Y33="Please name your Like-for-like Earning Metric",Y33="Valuation Metric",Y33="Please name your Like-for-like Valuation Metric",Y33="Please select your Valuation Metric",Y33="Please select the metric for segmentation",Y33="Untitled Segmentation II",Y33="Untitled Segmentation III")))),_xldudf_CX_PUSH(Y33,CX_ENTITY,C33,EOMONTH(val_asOfDate,0)),"")))} -> #NAME? | CU33: {=IF(K33<>"Yes","",IF(OR(Y33="Select, enter text or leave as blank.",Y33="Set from Actual section above!",Y33="Please select or type in or leave as blank",Y33="Select, enter text or leave as blank",Y33="Please select your Top Line Metric",Y33="Check Sum",Y33="Please name your Like-for-Like Revenue",Y33="Please name your Like-for-like Earning Metric",Y33="Valuation Metric",Y33="Please name your Like-for-like Valuation Metric",Y33="Please select your Valuation Metric",Y33="Please select the metric for segmentation",Y33="Untitled Segmentation II",Y33="Untitled Segmentation III"),"",IF(OR(Y33<>AB33,AND(LEN(B33)=0,NOT(OR(Y33="Select, enter text or leave as blank.",Y33="Set from Actual section above!",Y33="Please select or type in or leave as blank",Y33="Select, enter text or leave as blank",Y33="Please select your Top Line Metric",Y33="Check Sum",Y33="Please name your Like-for-Like Revenue",Y33="Please name your Like-for-like Earning Metric",Y33="Valuation Metric",Y33="Please name your Like-for-like Valuation Metric",Y33="Please select your Valuation Metric",Y33="Please select the metric for segmentation",Y33="Untitled Segmentation II",Y33="Untitled Segmentation III")))),_xldudf_CX_PUSH(Y33,CX_ENTITY,C33,EOMONTH(val_asOfDate,1)),"")))} -> #NAME? | CV33: {=IF(K33<>"Yes","",IF(OR(Y33="Select, enter text or leave as blank.",Y33="Set from Actual section above!",Y33="Please select or type in or leave as blank",Y33="Select, enter text or leave as blank",Y33="Please select your Top Line Metric",Y33="Check Sum",Y33="Please name your Like-for-Like Revenue",Y33="Please name your Like-for-like Earning Metric",Y33="Valuation Metric",Y33="Please name your Like-for-like Valuation Metric",Y33="Please select your Valuation Metric",Y33="Please select the metric for segmentation",Y33="Untitled Segmentation II",Y33="Untitled Segmentation III"),"",IF(OR(Y33<>AB33,AND(LEN(B33)=0,NOT(OR(Y33="Select, enter text or leave as blank.",Y33="Set from Actual section above!",Y33="Please select or type in or leave as blank",Y33="Select, enter text or leave as blank",Y33="Please select your Top Line Metric",Y33="Check Sum",Y33="Please name your Like-for-Like Revenue",Y33="Please name your Like-for-like Earning Metric",Y33="Valuation Metric",Y33="Please name your Like-for-like Valuation Metric",Y33="Please select your Valuation Metric",Y33="Please select the metric for segmentation",Y33="Untitled Segmentation II",Y33="Untitled Segmentation III")))),_xldudf_CX_PUSH(Y33,CX_ENTITY,C33,EOMONTH(val_asOfDate,2)),"")))} -> #NAME? | CW33: {=IF(K33<>"Yes","",IF(OR(Y33="Select, enter text or leave as blank.",Y33="Set from Actual section above!",Y33="Please select or type in or leave as blank",Y33="Select, enter text or leave as blank",Y33="Please select your Top Line Metric",Y33="Check Sum",Y33="Please name your Like-for-Like Revenue",Y33="Please name your Like-for-like Earning Metric",Y33="Valuation Metric",Y33="Please name your Like-for-like Valuation Metric",Y33="Please select your Valuation Metric",Y33="Please select the metric for segmentation",Y33="Untitled Segmentation II",Y33="Untitled Segmentation III"),"",IF(OR(Y33<>AB33,AND(LEN(B33)=0,NOT(OR(Y33="Select, enter text or leave as blank.",Y33="Set from Actual section above!",Y33="Please select or type in or leave as blank",Y33="Select, enter text or leave as blank",Y33="Please select your Top Line Metric",Y33="Check Sum",Y33="Please name your Like-for-Like Revenue",Y33="Please name your Like-for-like Earning Metric",Y33="Valuation Metric",Y33="Please name your Like-for-like Valuation Metric",Y33="Please select your Valuation Metric",Y33="Please select the metric for segmentation",Y33="Untitled Segmentation II",Y33="Untitled Segmentation III")))),_xldudf_CX_PUSH(Y33,CX_ENTITY,C33,EOMONTH(val_asOfDate,3)),"")))} -> #NAME? | CY33: {=IFERROR(IF(CM33*fxVal_normal=_PL!CM33,"",IF(OR($CM33="",$CM33=0,NOT(ISNUMBER($CM33)),ISERROR($CM33),$B33=""),"",IF($I33=1,IFBLANK(_xldudf_CX_PUSH($CM33*fxVal_normal,CX_ENTITY,$B33,$CM$11,$CM$14,$CM$19,),""),IF($I33=2,IFBLANK(_xldudf_CX_PUSH($CM33,CX_ENTITY,$B33,$CM$11,$CM$14,$CM$19,),""),IF($I33=3,"",IFBLANK(_xldudf_CX_PUSH($CM33,CX_ENTITY,$B33,$CM$11,$CM$14,$CM$19,),"")))))),"")} | CZ33: {=IFERROR(IF(CN33*fxVal_normal=_PL!CN33,"",IF(OR($CN33="",$CN33=0,NOT(ISNUMBER($CN33)),ISERROR($CN33),$B33=""),"",IF($I33=1,IFBLANK(_xldudf_CX_PUSH($CN33*fxVal_normal,CX_ENTITY,$B33,$CN$11,$CN$14,$CN$19,),""),IF($I33=2,IFBLANK(_xldudf_CX_PUSH($CN33,CX_ENTITY,$B33,$CN$11,$CN$14,$CN$19,),""),IF($I33=3,"",IFBLANK(_xldudf_CX_PUSH($CN33,CX_ENTITY,$B33,$CN$11,$CN$14,$CN$19,),"")))))),"")} | DA33: {=IFERROR(IF(CP33*fxVal_normal=_PL!CP33,"",IF(OR($CP33="",$CP33=0,NOT(ISNUMBER($CP33)),ISERROR($CP33),$B33=""),"",IF($I33=1,IFBLANK(_xldudf_CX_PUSH($CP33*fxVal_normal,CX_ENTITY,$B33,$CP$11,$CP$14,$CP$19,),""),IF($I33=2,IFBLANK(_xldudf_CX_PUSH($CP33,CX_ENTITY,$B33,$CP$11,$CP$14,$CP$19,),""),IF($I33=3,"",IFBLANK(_xldudf_CX_PUSH($CP33,CX_ENTITY,$B33,$CP$11,$CP$14,$CP$19,),"")))))),"")} | DB33: {=IFERROR(IF(CQ33*fxVal_normal=_PL!CQ33,"",IF(OR($CQ33="",$CQ33=0,NOT(ISNUMBER($CQ33)),ISERROR($CQ33),$B33=""),"",IF($I33=1,IFBLANK(_xldudf_CX_PUSH($CQ33*fxVal_normal,CX_ENTITY,$B33,$CQ$11,$CQ$14,$CQ$19,),""),IF($I33=2,IFBLANK(_xldudf_CX_PUSH($CQ33,CX_ENTITY,$B33,$CQ$11,$CQ$14,$CQ$19,),""),IF($I33=3,"",IFBLANK(_xldudf_CX_PUSH($CQ33,CX_ENTITY,$B33,$CQ$11,$CQ$14,$CQ$19,),"")))))),"")} | DD33: {=IFERROR(IF(AD33*fxVal_normal=_PL!AD33,"",IF(OR(AD33="",NOT(ISNUMBER(AD33)),ISERROR(AD33),$B33=""),"",IF($I33=1,IFBLANK(_xldudf_CX_PUSH(AD33*fxVal_normal,CX_ENTITY,$B33,AD$11,AD$14,AD$19,),""),IF($I33=2,IFBLANK(_xldudf_CX_PUSH(AD33,CX_ENTITY,$B33,AD$11,AD$14,AD$19,),""),IF($I33=3,"",IFBLANK(_xldudf_CX_PUSH(AD33,CX_ENTITY,$B33,AD$11,AD$14,AD$19,),"")))))),"")} | DE33: {=IFERROR(IF(AE33*fxVal_normal=_PL!AE33,"",IF(OR(AE33="",NOT(ISNUMBER(AE33)),ISERROR(AE33),$B33=""),"",IF($I33=1,IFBLANK(_xldudf_CX_PUSH(AE33*fxVal_normal,CX_ENTITY,$B33,AE$11,AE$14,AE$19,),""),IF($I33=2,IFBLANK(_xldudf_CX_PUSH(AE33,CX_ENTITY,$B33,AE$11,AE$14,AE$19,),""),IF($I33=3,"",IFBLANK(_xldudf_CX_PUSH(AE33,CX_ENTITY,$B33,AE$11,AE$14,AE$19,),"")))))),"")} | DF33: {=IFERROR(IF(AF33*fxVal_normal=_PL!AF33,"",IF(OR(AF33="",NOT(ISNUMBER(AF33)),ISERROR(AF33),$B33=""),"",IF($I33=1,IFBLANK(_xldudf_CX_PUSH(AF33*fxVal_normal,CX_ENTITY,$B33,AF$11,AF$14,AF$19,),""),IF($I33=2,IFBLANK(_xldudf_CX_PUSH(AF33,CX_ENTITY,$B33,AF$11,AF$14,AF$19,),""),IF($I33=3,"",IFBLANK(_xldudf_CX_PUSH(AF33,CX_ENTITY,$B33,AF$11,AF$14,AF$19,),"")))))),"")} | DG33: {=IFERROR(IF(AG33*fxVal_normal=_PL!AG33,"",IF(OR(AG33="",NOT(ISNUMBER(AG33)),ISERROR(AG33),$B33=""),"",IF($I33=1,IFBLANK(_xldudf_CX_PUSH(AG33*fxVal_normal,CX_ENTITY,$B33,AG$11,AG$14,AG$19,),""),IF($I33=2,IFBLANK(_xldudf_CX_PUSH(AG33,CX_ENTITY,$B33,AG$11,AG$14,AG$19,),""),IF($I33=3,"",IFBLANK(_xldudf_CX_PUSH(AG33,CX_ENTITY,$B33,AG$11,AG$14,AG$19,),"")))))),"")} | DH33: {=IFERROR(IF(AH33*fxVal_normal=_PL!AH33,"",IF(OR(AH33="",NOT(ISNUMBER(AH33)),ISERROR(AH33),$B33=""),"",IF($I33=1,IFBLANK(_xldudf_CX_PUSH(AH33*fxVal_normal,CX_ENTITY,$B33,AH$11,AH$14,AH$19,),""),IF($I33=2,IFBLANK(_xldudf_CX_PUSH(AH33,CX_ENTITY,$B33,AH$11,AH$14,AH$19,),""),IF($I33=3,"",IFBLANK(_xldudf_CX_PUSH(AH33,CX_ENTITY,$B33,AH$11,AH$14,AH$19,),"")))))),"")} | DI33: {=IFERROR(IF(AI33*fxVal_normal=_PL!AI33,"",IF(OR(AI33="",NOT(ISNUMBER(AI33)),ISERROR(AI33),$B33=""),"",IF($I33=1,IFBLANK(_xldudf_CX_PUSH(AI33*fxVal_normal,CX_ENTITY,$B33,AI$11,AI$14,AI$19,),""),IF($I33=2,IFBLANK(_xldudf_CX_PUSH(AI33,CX_ENTITY,$B33,AI$11,AI$14,AI$19,),""),IF($I33=3,"",IFBLANK(_xldudf_CX_PUSH(AI33,CX_ENTITY,$B33,AI$11,AI$14,AI$19,),"")))))),"")} | DJ33: {=IFERROR(IF(AJ33*fxVal_normal=_PL!AJ33,"",IF(OR(AJ33="",NOT(ISNUMBER(AJ33)),ISERROR(AJ33),$B33=""),"",IF($I33=1,IFBLANK(_xldudf_CX_PUSH(AJ33*fxVal_normal,CX_ENTITY,$B33,AJ$11,AJ$14,AJ$19,),""),IF($I33=2,IFBLANK(_xldudf_CX_PUSH(AJ33,CX_ENTITY,$B33,AJ$11,AJ$14,AJ$19,),""),IF($I33=3,"",IFBLANK(_xldudf_CX_PUSH(AJ33,CX_ENTITY,$B33,AJ$11,AJ$14,AJ$19,),"")))))),"")} | DK33: {=IFERROR(IF(AK33*fxVal_normal=_PL!AK33,"",IF(OR(AK33="",NOT(ISNUMBER(AK33)),ISERROR(AK33),$B33=""),"",IF($I33=1,IFBLANK(_xldudf_CX_PUSH(AK33*fxVal_normal,CX_ENTITY,$B33,AK$11,AK$14,AK$19,),""),IF($I33=2,IFBLANK(_xldudf_CX_PUSH(AK33,CX_ENTITY,$B33,AK$11,AK$14,AK$19,),""),IF($I33=3,"",IFBLANK(_xldudf_CX_PUSH(AK33,CX_ENTITY,$B33,AK$11,AK$14,AK$19,),"")))))),"")} | ... EN33: {=IFERROR(IF(BN33*fxVal_normal=_PL!BN33,"",IF(OR(BN33="",NOT(ISNUMBER(BN33)),ISERROR(BN33),$B33=""),"",IF($I33=1,IFBLANK(_xldudf_CX_PUSH(BN33*fxVal_normal,CX_ENTITY,$B33,BN$11,BN$14,BN$19,),""),IF($I33=2,IFBLANK(_xldudf_CX_PUSH(BN33,CX_ENTITY,$B33,BN$11,BN$14,BN$19,),""),IF($I33=3,"",IFBLANK(_xldudf_CX_PUSH(BN33,CX_ENTITY,$B33,BN$11,BN$14,BN$19,),"")))))),"")}
B34: =_xlfn.LET(_xlpm.IsNotAttrDynamic,D34="",_xlpm.Attr,_PL!F34,_xlpm.NotInUse,Y34=D34,_xlpm.RESULT,IF(_xlpm.IsNotAttrDynamic,_xlpm.Attr,IF(_xlpm.NotInUse,"",Y34)),IF(_xlpm.RESULT="","",_xlpm.RESULT)) -> Reported EBITA | C34: {=IFBLANK(_PL!C34,"")} -> Reported EBITA (Company View) | E34: {=_xlfn.LAMBDA(_xlpm.Array,_xlop.Type,_xlfn.LET(_xlpm._type,IF(_xlfn.ISOMITTED(_xlpm.Type),0,_xlpm.Type),_xlpm.R,ROWS(_xlpm.Array),_xlpm.C,COLUMNS(_xlpm.Array),_xlpm.Unlocked,_xlfn.MAKEARRAY(_xlpm.R,_xlpm.C,_xlfn.LAMBDA(_xlpm.i,_xlpm.j,--(CELL("protect",INDEX(_xlpm.Array,_xlpm.i,_xlpm.j))=0))),_xlpm.IsUnlocked,_xlfn.MAKEARRAY(_xlpm.R,_xlpm.C,_xlfn.LAMBDA(_xlpm.i,_xlpm.j,CELL("protect",INDEX(_xlpm.Array,_xlpm.i,_xlpm.j))=0)),_xlpm.HasData,_xlpm.Array<>"",_xlpm.Total,SUM(_xlpm.Unlocked),_xlpm.Completed,SUM(--(_xlpm.IsUnlocked*_xlpm.HasData)),_xlpm.type_display,_xlfn.SWITCH(_xlpm._type,1,"R",-1,"O",0,"A",""),_xlfn.HSTACK(_xlpm.Total,_xlpm.Completed,_xlpm.type_display)))($AD34:$CQ34,Z34)} -> #NAME? | H34: 2 | I34: 1 | J34: {=IFBLANK(Z34,"")} -> 0 | K34: =IFERROR(IF(LEN(AB34)=0,"No",IF(LEN(J34)>0,"Yes","No")),"") -> Yes | W34: =$W$20 -> Actual | X34: =_PL!X34 -> 0 | Y34: =IF(_PL!Y34="Error","",_PL!Y34) -> #NAME? | Z34: {=_xlfn.SWITCH(TRUE,_PL!$L34=TRUE,1,_PL!$L34=FALSE,-1,_PL!$L34=-1,0,"")} -> 0 | AB34: =_PL!AB34 -> Reported EBITA | AC34: {=_xlfn.LET(_xlpm._termname,$AB34,_xlpm._iconname,"find",_xlpm._icon,fx_getIcon(_xlpm._iconname),_xlpm._location,_xlfn.XLOOKUP(LOWER(_xlpm._termname),LOWER(tbl_acctDef[Term]),tbl_acctDef[Term]),_xlpm._hyperlink,HYPERLINK("#"&CELL("address",_xlpm._location),_xlpm._icon),IFERROR(_xlpm._hyperlink,""))} | AD34: =SUBTOTAL(9,AD20:AD33)-SUBTOTAL(9,AD26:AD31)-N(AD23) -> 4 | AE34: =SUBTOTAL(9,AE20:AE33)-SUBTOTAL(9,AE26:AE31)-N(AE23) -> 4 | AF34: =SUBTOTAL(9,AF20:AF33)-SUBTOTAL(9,AF26:AF31)-N(AF23) -> 4 | AG34: =SUBTOTAL(9,AG20:AG33)-SUBTOTAL(9,AG26:AG31)-N(AG23) -> 4 | AH34: =SUBTOTAL(9,AH20:AH33)-SUBTOTAL(9,AH26:AH31)-N(AH23) -> 4 | AI34: =SUBTOTAL(9,AI20:AI33)-SUBTOTAL(9,AI26:AI31)-N(AI23) -> 4 | AJ34: =SUBTOTAL(9,AJ20:AJ33)-SUBTOTAL(9,AJ26:AJ31)-N(AJ23) -> 4 | AK34: =SUBTOTAL(9,AK20:AK33)-SUBTOTAL(9,AK26:AK31)-N(AK23) -> 4 | ... BN34: =SUBTOTAL(9,BN20:BN33)-SUBTOTAL(9,BN26:BN31)-N(BN23) -> 4 | CD34: {=_xlfn.LET(_xlpm.CheckBlank,SUM(PL!$AD34:PL!$BN34)=0,IF(_xlpm.CheckBlank,"",SUM(_xlfn._xlws.FILTER(PL!$AD34:$BN34,(YEAR(PL!$AD$12:$BN$12)=PL!CD$12)*(array_timeline<=PL!CD$11)))))} -> #NAME? | CE34: {=_xlfn.LET(_xlpm.CheckBlank,SUM(PL!$AD34:PL!$BN34)=0,IF(_xlpm.CheckBlank,"",SUM(_xlfn._xlws.FILTER(PL!$AD34:$BN34,(YEAR(PL!$AD$12:$BN$12)=PL!CE$12)*(array_timeline<=PL!CE$11)))))} -> #NAME? | CG34: {=IFERROR(_xlfn.LET(_xlpm.CheckBlank,SUM(PL!$AD34:$BN34)=0,IF(_xlpm.CheckBlank,"",SUM(_xlfn._xlws.FILTER(PL!$AD34:$BN34,(YEAR(PL!$AD$12:$BN$12)=PL!CG$12)*(array_timeline<=PL!CG$11))))),"n/a")} -> n/a | CH34: {=_xlfn.LET(_xlpm.CheckBlank,SUM(PL!$AD34:$BN34)=0,IF(_xlpm.CheckBlank,"",SUM(_xlfn._xlws.FILTER(PL!$AD34:$BN34,(YEAR(PL!$AD$12:$BN$12)=PL!CH$12)*(array_timeline<=PL!CH$11)))))} -> #NAME? | CJ34: {=_xlfn.LET(_xlpm.CheckBlank,SUM(PL!$AD34:$BN34)=0,IF(_xlpm.CheckBlank,"",SUM(_xlfn.TAKE(_xlfn.DROP(PL!$AD34:$BN34,,-DATEDIFF(PL!CJ$11,val_asOfDate,"M")),1,-12))))} -> 48 | CK34: {=_xlfn.LET(_xlpm.CheckBlank,SUM(PL!$AD34:$BN34)=0,IF(_xlpm.CheckBlank,"",SUM(_xlfn.TAKE(_xlfn.DROP(PL!$AD34:$BN34,,-DATEDIFF(PL!CK$11,val_asOfDate,"M")),1,-12))))} -> 48 | CM34: =SUBTOTAL(9,CM20:CM33)-SUBTOTAL(9,CM26:CM31)-N(CM23) -> 4 | CN34: =SUBTOTAL(9,CN20:CN33)-SUBTOTAL(9,CN26:CN31)-N(CN23) -> 4 | CP34: =SUBTOTAL(9,CP20:CP33)-SUBTOTAL(9,CP26:CP31)-N(CP23) -> 4 | CQ34: =SUBTOTAL(9,CQ20:CQ33)-SUBTOTAL(9,CQ26:CQ31)-N(CQ23) -> 4 | CT34: {=IF(K34<>"Yes","",IF(OR(Y34="Select, enter text or leave as blank.",Y34="Set from Actual section above!",Y34="Please select or type in or leave as blank",Y34="Select, enter text or leave as blank",Y34="Please select your Top Line Metric",Y34="Check Sum",Y34="Please name your Like-for-Like Revenue",Y34="Please name your Like-for-like Earning Metric",Y34="Valuation Metric",Y34="Please name your Like-for-like Valuation Metric",Y34="Please select your Valuation Metric",Y34="Please select the metric for segmentation",Y34="Untitled Segmentation II",Y34="Untitled Segmentation III"),"",IF(OR(Y34<>AB34,AND(LEN(B34)=0,NOT(OR(Y34="Select, enter text or leave as blank.",Y34="Set from Actual section above!",Y34="Please select or type in or leave as blank",Y34="Select, enter text or leave as blank",Y34="Please select your Top Line Metric",Y34="Check Sum",Y34="Please name your Like-for-Like Revenue",Y34="Please name your Like-for-like Earning Metric",Y34="Valuation Metric",Y34="Please name your Like-for-like Valuation Metric",Y34="Please select your Valuation Metric",Y34="Please select the metric for segmentation",Y34="Untitled Segmentation II",Y34="Untitled Segmentation III")))),_xldudf_CX_PUSH(Y34,CX_ENTITY,C34,EOMONTH(val_asOfDate,0)),"")))} -> #NAME? | CU34: {=IF(K34<>"Yes","",IF(OR(Y34="Select, enter text or leave as blank.",Y34="Set from Actual section above!",Y34="Please select or type in or leave as blank",Y34="Select, enter text or leave as blank",Y34="Please select your Top Line Metric",Y34="Check Sum",Y34="Please name your Like-for-Like Revenue",Y34="Please name your Like-for-like Earning Metric",Y34="Valuation Metric",Y34="Please name your Like-for-like Valuation Metric",Y34="Please select your Valuation Metric",Y34="Please select the metric for segmentation",Y34="Untitled Segmentation II",Y34="Untitled Segmentation III"),"",IF(OR(Y34<>AB34,AND(LEN(B34)=0,NOT(OR(Y34="Select, enter text or leave as blank.",Y34="Set from Actual section above!",Y34="Please select or type in or leave as blank",Y34="Select, enter text or leave as blank",Y34="Please select your Top Line Metric",Y34="Check Sum",Y34="Please name your Like-for-Like Revenue",Y34="Please name your Like-for-like Earning Metric",Y34="Valuation Metric",Y34="Please name your Like-for-like Valuation Metric",Y34="Please select your Valuation Metric",Y34="Please select the metric for segmentation",Y34="Untitled Segmentation II",Y34="Untitled Segmentation III")))),_xldudf_CX_PUSH(Y34,CX_ENTITY,C34,EOMONTH(val_asOfDate,1)),"")))} -> #NAME? | CV34: {=IF(K34<>"Yes","",IF(OR(Y34="Select, enter text or leave as blank.",Y34="Set from Actual section above!",Y34="Please select or type in or leave as blank",Y34="Select, enter text or leave as blank",Y34="Please select your Top Line Metric",Y34="Check Sum",Y34="Please name your Like-for-Like Revenue",Y34="Please name your Like-for-like Earning Metric",Y34="Valuation Metric",Y34="Please name your Like-for-like Valuation Metric",Y34="Please select your Valuation Metric",Y34="Please select the metric for segmentation",Y34="Untitled Segmentation II",Y34="Untitled Segmentation III"),"",IF(OR(Y34<>AB34,AND(LEN(B34)=0,NOT(OR(Y34="Select, enter text or leave as blank.",Y34="Set from Actual section above!",Y34="Please select or type in or leave as blank",Y34="Select, enter text or leave as blank",Y34="Please select your Top Line Metric",Y34="Check Sum",Y34="Please name your Like-for-Like Revenue",Y34="Please name your Like-for-like Earning Metric",Y34="Valuation Metric",Y34="Please name your Like-for-like Valuation Metric",Y34="Please select your Valuation Metric",Y34="Please select the metric for segmentation",Y34="Untitled Segmentation II",Y34="Untitled Segmentation III")))),_xldudf_CX_PUSH(Y34,CX_ENTITY,C34,EOMONTH(val_asOfDate,2)),"")))} -> #NAME? | CW34: {=IF(K34<>"Yes","",IF(OR(Y34="Select, enter text or leave as blank.",Y34="Set from Actual section above!",Y34="Please select or type in or leave as blank",Y34="Select, enter text or leave as blank",Y34="Please select your Top Line Metric",Y34="Check Sum",Y34="Please name your Like-for-Like Revenue",Y34="Please name your Like-for-like Earning Metric",Y34="Valuation Metric",Y34="Please name your Like-for-like Valuation Metric",Y34="Please select your Valuation Metric",Y34="Please select the metric for segmentation",Y34="Untitled Segmentation II",Y34="Untitled Segmentation III"),"",IF(OR(Y34<>AB34,AND(LEN(B34)=0,NOT(OR(Y34="Select, enter text or leave as blank.",Y34="Set from Actual section above!",Y34="Please select or type in or leave as blank",Y34="Select, enter text or leave as blank",Y34="Please select your Top Line Metric",Y34="Check Sum",Y34="Please name your Like-for-Like Revenue",Y34="Please name your Like-for-like Earning Metric",Y34="Valuation Metric",Y34="Please name your Like-for-like Valuation Metric",Y34="Please select your Valuation Metric",Y34="Please select the metric for segmentation",Y34="Untitled Segmentation II",Y34="Untitled Segmentation III")))),_xldudf_CX_PUSH(Y34,CX_ENTITY,C34,EOMONTH(val_asOfDate,3)),"")))} -> #NAME? | CY34: {=IFERROR(IF(CM34*fxVal_normal=_PL!CM34,"",IF(OR($CM34="",$CM34=0,NOT(ISNUMBER($CM34)),ISERROR($CM34),$B34=""),"",IF($I34=1,IFBLANK(_xldudf_CX_PUSH($CM34*fxVal_normal,CX_ENTITY,$B34,$CM$11,$CM$14,$CM$19,),""),IF($I34=2,IFBLANK(_xldudf_CX_PUSH($CM34,CX_ENTITY,$B34,$CM$11,$CM$14,$CM$19,),""),IF($I34=3,"",IFBLANK(_xldudf_CX_PUSH($CM34,CX_ENTITY,$B34,$CM$11,$CM$14,$CM$19,),"")))))),"")} | CZ34: {=IFERROR(IF(CN34*fxVal_normal=_PL!CN34,"",IF(OR($CN34="",$CN34=0,NOT(ISNUMBER($CN34)),ISERROR($CN34),$B34=""),"",IF($I34=1,IFBLANK(_xldudf_CX_PUSH($CN34*fxVal_normal,CX_ENTITY,$B34,$CN$11,$CN$14,$CN$19,),""),IF($I34=2,IFBLANK(_xldudf_CX_PUSH($CN34,CX_ENTITY,$B34,$CN$11,$CN$14,$CN$19,),""),IF($I34=3,"",IFBLANK(_xldudf_CX_PUSH($CN34,CX_ENTITY,$B34,$CN$11,$CN$14,$CN$19,),"")))))),"")} | DA34: {=IFERROR(IF(CP34*fxVal_normal=_PL!CP34,"",IF(OR($CP34="",$CP34=0,NOT(ISNUMBER($CP34)),ISERROR($CP34),$B34=""),"",IF($I34=1,IFBLANK(_xldudf_CX_PUSH($CP34*fxVal_normal,CX_ENTITY,$B34,$CP$11,$CP$14,$CP$19,),""),IF($I34=2,IFBLANK(_xldudf_CX_PUSH($CP34,CX_ENTITY,$B34,$CP$11,$CP$14,$CP$19,),""),IF($I34=3,"",IFBLANK(_xldudf_CX_PUSH($CP34,CX_ENTITY,$B34,$CP$11,$CP$14,$CP$19,),"")))))),"")} | DB34: {=IFERROR(IF(CQ34*fxVal_normal=_PL!CQ34,"",IF(OR($CQ34="",$CQ34=0,NOT(ISNUMBER($CQ34)),ISERROR($CQ34),$B34=""),"",IF($I34=1,IFBLANK(_xldudf_CX_PUSH($CQ34*fxVal_normal,CX_ENTITY,$B34,$CQ$11,$CQ$14,$CQ$19,),""),IF($I34=2,IFBLANK(_xldudf_CX_PUSH($CQ34,CX_ENTITY,$B34,$CQ$11,$CQ$14,$CQ$19,),""),IF($I34=3,"",IFBLANK(_xldudf_CX_PUSH($CQ34,CX_ENTITY,$B34,$CQ$11,$CQ$14,$CQ$19,),"")))))),"")} | DD34: {=IFERROR(IF(AD34*fxVal_normal=_PL!AD34,"",IF(OR(AD34="",NOT(ISNUMBER(AD34)),ISERROR(AD34),$B34=""),"",IF($I34=1,IFBLANK(_xldudf_CX_PUSH(AD34*fxVal_normal,CX_ENTITY,$B34,AD$11,AD$14,AD$19,),""),IF($I34=2,IFBLANK(_xldudf_CX_PUSH(AD34,CX_ENTITY,$B34,AD$11,AD$14,AD$19,),""),IF($I34=3,"",IFBLANK(_xldudf_CX_PUSH(AD34,CX_ENTITY,$B34,AD$11,AD$14,AD$19,),"")))))),"")} | DE34: {=IFERROR(IF(AE34*fxVal_normal=_PL!AE34,"",IF(OR(AE34="",NOT(ISNUMBER(AE34)),ISERROR(AE34),$B34=""),"",IF($I34=1,IFBLANK(_xldudf_CX_PUSH(AE34*fxVal_normal,CX_ENTITY,$B34,AE$11,AE$14,AE$19,),""),IF($I34=2,IFBLANK(_xldudf_CX_PUSH(AE34,CX_ENTITY,$B34,AE$11,AE$14,AE$19,),""),IF($I34=3,"",IFBLANK(_xldudf_CX_PUSH(AE34,CX_ENTITY,$B34,AE$11,AE$14,AE$19,),"")))))),"")} | DF34: {=IFERROR(IF(AF34*fxVal_normal=_PL!AF34,"",IF(OR(AF34="",NOT(ISNUMBER(AF34)),ISERROR(AF34),$B34=""),"",IF($I34=1,IFBLANK(_xldudf_CX_PUSH(AF34*fxVal_normal,CX_ENTITY,$B34,AF$11,AF$14,AF$19,),""),IF($I34=2,IFBLANK(_xldudf_CX_PUSH(AF34,CX_ENTITY,$B34,AF$11,AF$14,AF$19,),""),IF($I34=3,"",IFBLANK(_xldudf_CX_PUSH(AF34,CX_ENTITY,$B34,AF$11,AF$14,AF$19,),"")))))),"")} | DG34: {=IFERROR(IF(AG34*fxVal_normal=_PL!AG34,"",IF(OR(AG34="",NOT(ISNUMBER(AG34)),ISERROR(AG34),$B34=""),"",IF($I34=1,IFBLANK(_xldudf_CX_PUSH(AG34*fxVal_normal,CX_ENTITY,$B34,AG$11,AG$14,AG$19,),""),IF($I34=2,IFBLANK(_xldudf_CX_PUSH(AG34,CX_ENTITY,$B34,AG$11,AG$14,AG$19,),""),IF($I34=3,"",IFBLANK(_xldudf_CX_PUSH(AG34,CX_ENTITY,$B34,AG$11,AG$14,AG$19,),"")))))),"")} | DH34: {=IFERROR(IF(AH34*fxVal_normal=_PL!AH34,"",IF(OR(AH34="",NOT(ISNUMBER(AH34)),ISERROR(AH34),$B34=""),"",IF($I34=1,IFBLANK(_xldudf_CX_PUSH(AH34*fxVal_normal,CX_ENTITY,$B34,AH$11,AH$14,AH$19,),""),IF($I34=2,IFBLANK(_xldudf_CX_PUSH(AH34,CX_ENTITY,$B34,AH$11,AH$14,AH$19,),""),IF($I34=3,"",IFBLANK(_xldudf_CX_PUSH(AH34,CX_ENTITY,$B34,AH$11,AH$14,AH$19,),"")))))),"")} | DI34: {=IFERROR(IF(AI34*fxVal_normal=_PL!AI34,"",IF(OR(AI34="",NOT(ISNUMBER(AI34)),ISERROR(AI34),$B34=""),"",IF($I34=1,IFBLANK(_xldudf_CX_PUSH(AI34*fxVal_normal,CX_ENTITY,$B34,AI$11,AI$14,AI$19,),""),IF($I34=2,IFBLANK(_xldudf_CX_PUSH(AI34,CX_ENTITY,$B34,AI$11,AI$14,AI$19,),""),IF($I34=3,"",IFBLANK(_xldudf_CX_PUSH(AI34,CX_ENTITY,$B34,AI$11,AI$14,AI$19,),"")))))),"")} | DJ34: {=IFERROR(IF(AJ34*fxVal_normal=_PL!AJ34,"",IF(OR(AJ34="",NOT(ISNUMBER(AJ34)),ISERROR(AJ34),$B34=""),"",IF($I34=1,IFBLANK(_xldudf_CX_PUSH(AJ34*fxVal_normal,CX_ENTITY,$B34,AJ$11,AJ$14,AJ$19,),""),IF($I34=2,IFBLANK(_xldudf_CX_PUSH(AJ34,CX_ENTITY,$B34,AJ$11,AJ$14,AJ$19,),""),IF($I34=3,"",IFBLANK(_xldudf_CX_PUSH(AJ34,CX_ENTITY,$B34,AJ$11,AJ$14,AJ$19,),"")))))),"")} | DK34: {=IFERROR(IF(AK34*fxVal_normal=_PL!AK34,"",IF(OR(AK34="",NOT(ISNUMBER(AK34)),ISERROR(AK34),$B34=""),"",IF($I34=1,IFBLANK(_xldudf_CX_PUSH(AK34*fxVal_normal,CX_ENTITY,$B34,AK$11,AK$14,AK$19,),""),IF($I34=2,IFBLANK(_xldudf_CX_PUSH(AK34,CX_ENTITY,$B34,AK$11,AK$14,AK$19,),""),IF($I34=3,"",IFBLANK(_xldudf_CX_PUSH(AK34,CX_ENTITY,$B34,AK$11,AK$14,AK$19,),"")))))),"")} | ... EN34: {=IFERROR(IF(BN34*fxVal_normal=_PL!BN34,"",IF(OR(BN34="",NOT(ISNUMBER(BN34)),ISERROR(BN34),$B34=""),"",IF($I34=1,IFBLANK(_xldudf_CX_PUSH(BN34*fxVal_normal,CX_ENTITY,$B34,BN$11,BN$14,BN$19,),""),IF($I34=2,IFBLANK(_xldudf_CX_PUSH(BN34,CX_ENTITY,$B34,BN$11,BN$14,BN$19,),""),IF($I34=3,"",IFBLANK(_xldudf_CX_PUSH(BN34,CX_ENTITY,$B34,BN$11,BN$14,BN$19,),"")))))),"")}
